Workbook

Sheet Inputs
A1: Zoom Communications (ZM) - Take-Private LBO: Inputs
A2: USD millions except per-share. Blue = hard-coded input; black = formula; purple = same-tab link; green = cross-tab link.
A3: Item | B3: Value | C3: Units | D3: Source / note
A5: TRANSACTION
A6: Current share price (close 2026-10-15) | B6: 98.51 | C6: $/sh | D6: stockanalysis.com / finance.yahoo.com, close 2026-10-15
A7: Offer premium to current price | B7: 0.3 | C7: % | D7: User assumption
A8: Offer price per share | B8: =B6*(1+B7) -> 128.063 | C8: $/sh | D8: Formula
A9: Basic shares outstanding (Class A + B) | B9: 291.78371 | C9: m sh | D9: 10-Q Q2 FY27 cover: 263.233m A + 28.551m B as of 2026-08-14
A10: Dilutive securities (RSUs/options, est.) | B10: 6.867104 | C10: m sh | D10: Est.: Q2 FY27 diluted WASO 299.746m less basic WASO 292.879m (8-K 2026-08-25)
A11: Fully diluted shares | B11: =B9+B10 -> 298.65082 | C11: m sh | D11: Formula
A12: Cash & cash equivalents (2026-07-31) | B12: 931.992 | C12: $m | D12: 8-K Ex.99.1 filed 2026-08-25
A13: Marketable securities (2026-07-31) | B13: 6317.729 | C13: $m | D13: 8-K Ex.99.1 filed 2026-08-25
A14: Existing debt | B14: 0 | C14: $m | D14: No borrowings on balance sheet (8-K 2026-08-25)
A15: Minimum operating cash left in business | B15: 500 | C15: $m | D15: Assumption (~10% of LTM revenue)
A16: M&A / transaction fees (% of entry EV) | B16: 0.015 | C16: % | D16: Assumption
A17: Financing fees (% of debt raised) | B17: 0.0225 | C17: % | D17: Assumption
A18: Assumed closing date | B18: 46326 | C18: date | D18: Assumption
A19: Holding period | B19: 5 | C19: years | D19: User assumption
A21: LTM FINANCIALS (LTM to 2026-07-31 = FY26 + 6M FY27 - 6M FY26)
A22: Columns: FY26 (8-K 2026-02-25) | 6M FY27 | 6M FY26 (8-K 2026-08-25) | LTM | E22: FY2026 | F22: 6M FY27 | G22: 6M FY26 | H22: LTM
A23: Revenue | B23: =H23 -> 4993.05 | C23: $m | D23: LTM formula in col H | E23: 4868.769 | F23: 2516.223 | G23: 2391.942 | H23: =E23+F23-G23 -> 4993.05
A24: GAAP income from operations | B24: =H24 -> 1185.095 | C24: $m | D24: LTM formula in col H | E24: 1123.633 | F24: 624.789 | G24: 563.327 | H24: =E24+F24-G24 -> 1185.095
A25: Depreciation & amortization | B25: =H25 -> 130.464 | C25: $m | D25: LTM formula in col H | E25: 132.831 | F25: 65.112 | G25: 67.479 | H25: =E25+F25-G25 -> 130.464
A26: Stock-based compensation expense | B26: =H26 -> 729.245 | C26: $m | D26: LTM formula in col H | E26: 760.776 | F26: 358.737 | G26: 390.268 | H26: =E26+F26-G26 -> 729.245
A27: Capex (purchases of PP&E) | B27: =H27 -> 74.551 | C27: $m | D27: LTM formula in col H | E27: 64.961 | F27: 43.466 | G27: 33.876 | H27: =E27+F27-G27 -> 74.551
A28: LTM EBITDA (GAAP op. income + D&A) | B28: =B24+B25 -> 1315.559 | C28: $m | D28: Formula; SBC treated as expense
A29: LTM Adj. EBITDA (op. income + D&A + SBC) | B29: =B28+B26 -> 2044.804 | C29: $m | D29: Formula; SBC added back (sponsor/lender convention). Basis for valuation & leverage
A30: LTM Adj. EBITDA margin | B30: =B29/B23 -> 0.40953005 | C30: % | D30: Formula
A32: OPERATING ASSUMPTIONS (Year 1-5 = columns C..G of the LBO tab)
A33: Revenue growth Y1 | B33: 0.04 | C33: % | D33: Assumption; FY27 guide $5.085-5.095bn implies ~4.5%; Q2 grew 4.9%
A34: Revenue growth Y2 | B34: 0.04 | C34: % | D34: Assumption
A35: Revenue growth Y3 | B35: 0.035 | C35: % | D35: Assumption
A36: Revenue growth Y4 | B36: 0.035 | C36: % | D36: Assumption
A37: Revenue growth Y5 | B37: 0.03 | C37: % | D37: Assumption
A38: Adj. EBITDA margin Y1 | B38: 0.415 | C38: % | D38: Assumption; modest sponsor cost-out from 41.0% LTM
A39: Adj. EBITDA margin Y2 | B39: 0.42 | C39: % | D39: Assumption
A40: Adj. EBITDA margin Y3 | B40: 0.425 | C40: % | D40: Assumption
A41: Adj. EBITDA margin Y4 | B41: 0.43 | C41: % | D41: Assumption
A42: Adj. EBITDA margin Y5 | B42: 0.43 | C42: % | D42: Assumption
A43: Cash cost to replace SBC (% of revenue) | B43: 0.07 | C43: % | D43: Assumption: ~half of LTM SBC (14.6% of rev) replaced with cash comp post take-private
A44: D&A (% of revenue) | B44: 0.026 | C44: % | D44: LTM ~2.6%
... A47: Cash tax rate | B47: 0.23 | C47: % | D47: Assumption; 6M FY27 ETR ~22.1%
A49: FINANCING (market as of 2026-10-13/14)
A50: SOFR (2026-10-14) | B50: 0.0388 | C50: % | D50: FRED series SOFR, obs. 2026-10-14; held flat (no forward curve)
A51: Term Loan B spread over SOFR | B51: 0.0325 | C51: % | D51: Assumption: typical B+/BB- sponsor software TLB
A52: Term Loan B all-in rate | B52: =B50+B51 -> 0.0713 | C52: % | D52: Formula
A53: Term Loan B size (x LTM Adj. EBITDA) | B53: 4 | C53: x | D53: Assumption
A54: TLB mandatory amortization (% of original p.a.) | B54: 0.01 | C54: % | D54: Market standard
A55: Excess cash flow swept to TLB | B55: 1 | C55: % | D55: Assumption: 100% voluntary prepayment
A56: 7-yr US Treasury yield (2026-10-13) | B56: 0.0511 | C56: % | D56: FRED series DGS7, obs. 2026-10-13
A57: ICE BofA US High Yield OAS (2026-10-13) | B57: 0.0316 | C57: % | D57: FRED series BAMLH0A0HYM2, obs. 2026-10-13
A58: New-issue / LBO concession | B58: 0.005 | C58: % | D58: Assumption
A59: Senior notes coupon (fixed) | B59: =B56+B57+B58 -> 0.0877 | C59: % | D59: Formula: 7yr UST + HY OAS + concession
A60: Senior notes size (x LTM Adj. EBITDA) | B60: 2 | C60: x | D60: Assumption; non-call bullet, outstanding at exit

Sheet LBO
A1: Zoom Communications (ZM) - Take-Private LBO
A2: USD millions except per-share. Entry assumed 2026-10-31; Year 1 = 12 months to 2027-10-31 ... Year 5 exit 2031-10-31.
A4: SOURCES & USES
A5: Purchase price
A6: Current share price | B6: =Inputs!B6 -> 98.51
A7: Premium | B7: =Inputs!B7 -> 0.3
A8: Offer price per share | B8: =Inputs!B8 -> 128.063
A9: Fully diluted shares (m) | B9: =Inputs!B11 -> 298.65082
A10: Equity purchase price | B10: =B8*B9 -> 38246.119
A11: Plus: existing debt | B11: =Inputs!B14 -> 0
A12: Less: cash + marketable securities | B12: =-(Inputs!B12+Inputs!B13) -> -7249.721
A13: Entry enterprise value | B13: =B10+B11+B12 -> 30996.398
A14: LTM Adj. EBITDA (incl. SBC add-back) | B14: =Inputs!B29 -> 2044.804
A15: Entry EV / LTM Adj. EBITDA | B15: =B13/B14 -> 15.158616
A16: LTM EBITDA (SBC as expense) | B16: =Inputs!B28 -> 1315.559
A17: Entry EV / LTM EBITDA (SBC expensed) | B17: =B13/B16 -> 23.56139
A18: Implied premium to current market EV | B18: =B13/(B6*B9+B11+B12)-1 -> 0.39810013
A20: Sources | B20: $m | C20: % total | D20: x EBITDA | E20: Rate
A21: Term Loan B | B21: =Inputs!B53*B14 -> 8179.216 | C21: =B21/$B$25 -> 0.20979281 | D21: =B21/B14 -> 4 | E21: =Inputs!B52 -> 0.0713
A22: Senior Notes | B22: =Inputs!B60*B14 -> 4089.608 | C22: =B22/$B$25 -> 0.1048964 | D22: =B22/B14 -> 2 | E22: =Inputs!B59 -> 0.0877
A23: Existing balance sheet cash used | B23: =Inputs!B12+Inputs!B13-Inputs!B15 -> 6749.721 | C23: =B23/$B$25 -> 0.17312697
A24: Sponsor equity (plug) | B24: =B32-SUM(B21:B23) -> 19968.569 | C24: =B24/$B$25 -> 0.51218382
A25: Total sources | B25: =SUM(B21:B24) -> 38987.114 | C25: =B25/$B$25 -> 1
A27: Uses | B27: $m | C27: % total
A28: Purchase of equity | B28: =B10 -> 38246.119 | C28: =B28/$B$32 -> 0.98099386
A29: Refinance existing debt | B29: =B11 -> 0 | C29: =B29/$B$32 -> 0
A30: Transaction fees | B30: =Inputs!B16*B13 -> 464.94597 | C30: =B30/$B$32 -> 0.011925632
A31: Financing fees | B31: =Inputs!B17*(B21+B22) -> 276.04854 | C31: =B31/$B$32 -> 0.0070805072
A32: Total uses | B32: =SUM(B28:B31) -> 38987.114 | C32: =B32/$B$32 -> 1
A33: Check: sources - uses (should be 0) | B33: =B25-B32 -> 0
A34: Total debt / LTM Adj. EBITDA | B34: =(B21+B22)/B14 -> 6
A35: Sponsor equity % of total capitalization | B35: =B24/(B24+B21+B22) -> 0.61942257
A37: OPERATING MODEL
A38: Period | B38: LTM 2026-07 | C38: Year 1 | D38: Year 2 | E38: Year 3 | F38: Year 4 | G38: Year 5
A39: Period end (B = closing) | B39: =Inputs!B18 -> 46326 | C39: =EDATE(Inputs!B18,12) -> 46691 | D39: =EDATE(Inputs!B18,24) -> 47057 | E39: =EDATE(Inputs!B18,36) -> 47422 | F39: =EDATE(Inputs!B18,48) -> 47787 | G39: =EDATE(Inputs!B18,60) -> 48152
A40: Revenue growth | C40: =Inputs!B33 -> 0.04 | D40: =Inputs!B34 -> 0.04 | E40: =Inputs!B35 -> 0.035 | F40: =Inputs!B36 -> 0.035 | G40: =Inputs!B37 -> 0.03
A41: Revenue | B41: =Inputs!B23 -> 4993.05 | C41: =B41*(1+C40) -> 5192.772 | D41: =C41*(1+D40) -> 5400.4829 | E41: =D41*(1+E40) -> 5589.4998 | F41: =E41*(1+F40) -> 5785.1323 | G41: =F41*(1+G40) -> 5958.6862
A42: Adj. EBITDA margin | B42: =Inputs!B30 -> 0.40953005 | C42: =Inputs!B38 -> 0.415 | D42: =Inputs!B39 -> 0.42 | E42: =Inputs!B40 -> 0.425 | F42: =Inputs!B41 -> 0.43 | G42: =Inputs!B42 -> 0.43
A43: Adj. EBITDA (pre-SBC) | B43: =Inputs!B29 -> 2044.804 | C43: =C41*C42 -> 2155.0004 | D43: =D41*D42 -> 2268.2028 | E43: =E41*E42 -> 2375.5374 | F43: =F41*F42 -> 2487.6069 | G43: =G41*G42 -> 2562.2351
A44: Less: cash replacement of SBC | C44: =-C41*Inputs!B43 -> -363.49404 | D44: =-D41*Inputs!B43 -> -378.0338 | E44: =-E41*Inputs!B43 -> -391.26498 | F44: =-F41*Inputs!B43 -> -404.95926 | G44: =-G41*Inputs!B43 -> -417.10804
A45: Cash EBITDA | C45: =C43+C44 -> 1791.5063 | D45: =D43+D44 -> 1890.169 | E45: =E43+E44 -> 1984.2724 | F45: =F43+F44 -> 2082.6476 | G45: =G43+G44 -> 2145.127
A46: Less: D&A | C46: =-C41*Inputs!B44 -> -135.01207 | D46: =-D41*Inputs!B44 -> -140.41255 | E46: =-E41*Inputs!B44 -> -145.32699 | F46: =-F41*Inputs!B44 -> -150.41344 | G46: =-G41*Inputs!B44 -> -154.92584
A47: EBIT | C47: =C45+C46 -> 1656.4943 | D47: =D45+D46 -> 1749.7565 | E47: =E45+E46 -> 1838.9454 | F47: =F45+F46 -> 1932.2342 | G47: =G45+G46 -> 1990.2012
A48: Less: interest expense | C48: =-C82 -> -941.83672 | D48: =-D82 -> -895.68058 | E48: =-E82 -> -841.59341 | F48: =-F82 -> -779.75856 | G48: =-G82 -> -709.15949
A49: Pre-tax income | C49: =C47+C48 -> 714.65755 | D49: =D47+D48 -> 854.07587 | E49: =E47+E48 -> 997.35202 | F49: =F47+F48 -> 1152.4756 | G49: =G47+G48 -> 1281.0417
A50: Less: cash taxes | C50: =-MAX(0,C49)*Inputs!B47 -> -164.37124 | D50: =-MAX(0,D49)*Inputs!B47 -> -196.43745 | E50: =-MAX(0,E49)*Inputs!B47 -> -229.39096 | F50: =-MAX(0,F49)*Inputs!B47 -> -265.06939 | G50: =-MAX(0,G49)*Inputs!B47 -> -294.63959
A51: Net income | C51: =C49+C50 -> 550.28631 | D51: =D49+D50 -> 657.63842 | E51: =E49+E50 -> 767.96106 | F51: =F49+F50 -> 887.40623 | G51: =G49+G50 -> 986.40212
A53: Free cash flow
A54: Net working capital balance | B54: =Inputs!B46*B41 -> -998.61 | C54: =Inputs!B46*C41 -> -1038.5544 | D54: =Inputs!B46*D41 -> -1080.0966 | E54: =Inputs!B46*E41 -> -1117.9 | F54: =Inputs!B46*F41 -> -1157.0265 | G54: =Inputs!B46*G41 -> -1191.7372
A55: Plus: D&A | C55: =-C46 -> 135.01207 | D55: =-D46 -> 140.41255 | E55: =-E46 -> 145.32699 | F55: =-F46 -> 150.41344 | G55: =-G46 -> 154.92584
A56: Less: capex | C56: =-C41*Inputs!B45 -> -77.89158 | D56: =-D41*Inputs!B45 -> -81.007243 | E56: =-E41*Inputs!B45 -> -83.842497 | F56: =-F41*Inputs!B45 -> -86.776984 | G56: =-G41*Inputs!B45 -> -89.380294
A57: Less: increase in NWC | C57: =-(C54-B54) -> 39.9444 | D57: =-(D54-C54) -> 41.542176 | E57: =-(E54-D54) -> 37.80338 | F57: =-(F54-E54) -> 39.126498 | G57: =-(G54-F54) -> 34.710794
A58: Free cash flow available for debt repayment | C58: =C51+C55+C56+C57 -> 647.3512 | D58: =D51+D55+D56+D57 -> 758.58591 | E58: =E51+E55+E56+E57 -> 867.24893 | F58: =F51+F55+F56+F57 -> 990.16918 | G58: =G51+G55+G56+G57 -> 1086.6585
A60: DEBT SCHEDULE
B61: Closing | C61: Year 1 | D61: Year 2 | E61: Year 3 | F61: Year 4 | G61: Year 5
A62: Cash
A63: Beginning cash | C63: =B67 -> 500 | D63: =C67 -> 500 | E63: =D67 -> 500 | F63: =E67 -> 500 | G63: =F67 -> 500
A64: Plus: free cash flow | C64: =C58 -> 647.3512 | D64: =D58 -> 758.58591 | E64: =E58 -> 867.24893 | F64: =F58 -> 990.16918 | G64: =G58 -> 1086.6585
A65: Less: TLB mandatory amortization | C65: =C72 -> -81.79216 | D65: =D72 -> -81.79216 | E65: =E72 -> -81.79216 | F65: =F72 -> -81.79216 | G65: =G72 -> -81.79216
A66: Less: TLB voluntary prepayment (sweep) | C66: =C73 -> -565.55904 | D66: =D73 -> -676.79375 | E66: =E73 -> -785.45677 | F66: =F73 -> -908.37702 | G66: =G73 -> -1004.8663
A67: Ending cash | B67: =Inputs!B15 -> 500 | C67: =SUM(C63:C66) -> 500 | D67: =SUM(D63:D66) -> 500 | E67: =SUM(E63:E66) -> 500 | F67: =SUM(F63:F66) -> 500 | G67: =SUM(G63:G66) -> 500
A68: Cash available for sweep (above minimum) | C68: =C63+C64+C65-Inputs!B15 -> 565.55904 | D68: =D63+D64+D65-Inputs!B15 -> 676.79375 | E68: =E63+E64+E65-Inputs!B15 -> 785.45677 | F68: =F63+F64+F65-Inputs!B15 -> 908.37702 | G68: =G63+G64+G65-Inputs!B15 -> 1004.8663
A70: Term Loan B
A71: Beginning balance | C71: =B74 -> 8179.216 | D71: =C74 -> 7531.8648 | E71: =D74 -> 6773.2789 | F71: =E74 -> 5906.03 | G71: =F74 -> 4915.8608
A72: Mandatory amortization | C72: =-MIN(C71,Inputs!B54*$B$74) -> -81.79216 | D72: =-MIN(D71,Inputs!B54*$B$74) -> -81.79216 | E72: =-MIN(E71,Inputs!B54*$B$74) -> -81.79216 | F72: =-MIN(F71,Inputs!B54*$B$74) -> -81.79216 | G72: =-MIN(G71,Inputs!B54*$B$74) -> -81.79216
A73: Voluntary prepayment (cash sweep) | C73: =-MIN(C71+C72,MAX(0,C68)*Inputs!B55) -> -565.55904 | D73: =-MIN(D71+D72,MAX(0,D68)*Inputs!B55) -> -676.79375 | E73: =-MIN(E71+E72,MAX(0,E68)*Inputs!B55) -> -785.45677 | F73: =-MIN(F71+F72,MAX(0,F68)*Inputs!B55) -> -908.37702 | G73: =-MIN(G71+G72,MAX(0,G68)*Inputs!B55) -> -1004.8663
A74: Ending balance | B74: =B21 -> 8179.216 | C74: =SUM(C71:C73) -> 7531.8648 | D74: =SUM(D71:D73) -> 6773.2789 | E74: =SUM(E71:E73) -> 5906.03 | F74: =SUM(F71:F73) -> 4915.8608 | G74: =SUM(G71:G73) -> 3829.2023
A75: Interest expense (on beginning balance) | C75: =C71*Inputs!B52 -> 583.1781 | D75: =D71*Inputs!B52 -> 537.02196 | E75: =E71*Inputs!B52 -> 482.93478 | F75: =F71*Inputs!B52 -> 421.09994 | G75: =G71*Inputs!B52 -> 350.50087
A77: Senior Notes
A78: Beginning balance | C78: =B79 -> 4089.608 | D78: =C79 -> 4089.608 | E78: =D79 -> 4089.608 | F78: =E79 -> 4089.608 | G78: =F79 -> 4089.608
A79: Ending balance (bullet, non-call) | B79: =B22 -> 4089.608 | C79: =C78 -> 4089.608 | D79: =D78 -> 4089.608 | E79: =E78 -> 4089.608 | F79: =F78 -> 4089.608 | G79: =G78 -> 4089.608
A80: Interest expense | C80: =C78*Inputs!B59 -> 358.65862 | D80: =D78*Inputs!B59 -> 358.65862 | E80: =E78*Inputs!B59 -> 358.65862 | F80: =F78*Inputs!B59 -> 358.65862 | G80: =G78*Inputs!B59 -> 358.65862
A82: Total interest expense | C82: =C75+C80 -> 941.83672 | D82: =D75+D80 -> 895.68058 | E82: =E75+E80 -> 841.59341 | F82: =F75+F80 -> 779.75856 | G82: =G75+G80 -> 709.15949
A83: Total debt | B83: =B74+B79 -> 12268.824 | C83: =C74+C79 -> 11621.473 | D83: =D74+D79 -> 10862.887 | E83: =E74+E79 -> 9995.638 | F83: =F74+F79 -> 9005.4688 | G83: =G74+G79 -> 7918.8103
A84: Net debt | B84: =B83-B67 -> 11768.824 | C84: =C83-C67 -> 11121.473 | D84: =D83-D67 -> 10362.887 | E84: =E83-E67 -> 9495.638 | F84: =F83-F67 -> 8505.4688 | G84: =G83-G67 -> 7418.8103
A85: Total debt / Adj. EBITDA | B85: =B83/B43 -> 6 | C85: =C83/C43 -> 5.3927939 | D85: =D83/D43 -> 4.7892044 | E85: =E83/E43 -> 4.2077376 | F85: =F83/F43 -> 3.6201334 | G85: =G83/G43 -> 3.090587
A86: Cash EBITDA / interest | C86: =C45/C82 -> 1.9021411 | D86: =D45/D82 -> 2.1103159 | E86: =E45/E82 -> 2.3577566 | F86: =F45/F82 -> 2.6708878 | G86: =G45/G82 -> 3.0248866
A88: RETURNS ANALYSIS
A89: Exit EV / Adj. EBITDA (= entry multiple) | B89: =B15 -> 15.158616
A90: Year 5 Adj. EBITDA | B90: =G43 -> 2562.2351
A91: Exit enterprise value | B91: =B89*B90 -> 38839.937
A92: Less: total debt at exit | B92: =-G83 -> -7918.8103
A93: Plus: cash at exit | B93: =G67 -> 500
A94: Exit equity value | B94: =B91+B92+B93 -> 31421.127
A96: Sponsor cash flows | B96: Closing | C96: Year 1 | D96: Year 2 | E96: Year 3 | F96: Year 4 | G96: Year 5
A97: Equity (invested) / proceeds | B97: =-B24 -> -19968.569 | C97: 0 | D97: 0 | E97: 0 | F97: 0 | G97: =B94 -> 31421.127
A98: IRR | B98: =IRR(B97:G97) -> 0.094901281
A99: MOIC | B99: =B94/B24 -> 1.5735292
A100: Check: (MOIC)^(1/hold) - 1 | B100: =B99^(1/Inputs!B19)-1 -> 0.094901281
A102: Value creation bridge
A103: EBITDA growth (at entry multiple) | B103: =(B90-B14)*B15 -> 7843.539
A104: Multiple expansion | B104: =(B89-B15)*B90 -> 0
A105: Net debt paydown | B105: =(B84-G84) -> 4350.0137
A106: Less: fees & cash at entry (leakage) | B106: =B94-B24-B103-B104-B105 -> -740.99451
A107: Total equity gain | B107: =SUM(B103:B106) -> 11452.558
A109: SENSITIVITY: IRR (offer premium vs. exit multiple)
A110: Rows: offer premium | Columns: exit EV/Adj. EBITDA | B110: =B15+(-2) -> 13.158616 | C110: =B15+(-1) -> 14.158616 | D110: =B15 -> 15.158616 | E110: =B15+(1) -> 16.158616 | F110: =B15+(2) -> 17.158616
A111: =Inputs!B7+(-0.1) -> 0.2 | B111: =((B$110*B90+B92+B93)/((Inputs!B6*(1+$A111)*B9)+B11+Inputs!B16*((Inputs!B6*(1+$A111)*B9)+B11+B12)+B31-B21-B22-B23))^(1/Inputs!B19)-1 -> 0.091390436 | C111: =((C$110*B90+B92+B93)/((Inputs!B6*(1+$A111)*B9)+B11+Inputs!B16*((Inputs!B6*(1+$A111)*B9)+B11+B12)+B31-B21-B22-B23))^(1/Inputs!B19)-1 -> 0.111875 | D111: =((D$110*B90+B92+B93)/((Inputs!B6*(1+$A111)*B9)+B11+Inputs!B16*((Inputs!B6*(1+$A111)*B9)+B11+B12)+B31-B21-B22-B23))^(1/Inputs!B19)-1 -> 0.13095256 | E111: =((E$110*B90+B92+B93)/((Inputs!B6*(1+$A111)*B9)+B11+Inputs!B16*((Inputs!B6*(1+$A111)*B9)+B11+B12)+B31-B21-B22-B23))^(1/Inputs!B19)-1 -> 0.14882348 | F111: =((F$110*B90+B92+B93)/((Inputs!B6*(1+$A111)*B9)+B11+Inputs!B16*((Inputs!B6*(1+$A111)*B9)+B11+B12)+B31-B21-B22-B23))^(1/Inputs!B19)-1 -> 0.165647
A112: =Inputs!B7+(-0.05) -> 0.25 | B112: =((B$110*B90+B92+B93)/((Inputs!B6*(1+$A112)*B9)+B11+Inputs!B16*((Inputs!B6*(1+$A112)*B9)+B11+B12)+B31-B21-B22-B23))^(1/Inputs!B19)-1 -> 0.073151092 | C112: =((C$110*B90+B92+B93)/((Inputs!B6*(1+$A112)*B9)+B11+Inputs!B16*((Inputs!B6*(1+$A112)*B9)+B11+B12)+B31-B21-B22-B23))^(1/Inputs!B19)-1 -> 0.093293319 | D112: =((D$110*B90+B92+B93)/((Inputs!B6*(1+$A112)*B9)+B11+Inputs!B16*((Inputs!B6*(1+$A112)*B9)+B11+B12)+B31-B21-B22-B23))^(1/Inputs!B19)-1 -> 0.11205205 | E112: =((E$110*B90+B92+B93)/((Inputs!B6*(1+$A112)*B9)+B11+Inputs!B16*((Inputs!B6*(1+$A112)*B9)+B11+B12)+B31-B21-B22-B23))^(1/Inputs!B19)-1 -> 0.12962432 | F112: =((F$110*B90+B92+B93)/((Inputs!B6*(1+$A112)*B9)+B11+Inputs!B16*((Inputs!B6*(1+$A112)*B9)+B11+B12)+B31-B21-B22-B23))^(1/Inputs!B19)-1 -> 0.14616667
A113: =Inputs!B7 -> 0.3 | B113: =((B$110*B90+B92+B93)/((Inputs!B6*(1+$A113)*B9)+B11+Inputs!B16*((Inputs!B6*(1+$A113)*B9)+B11+B12)+B31-B21-B22-B23))^(1/Inputs!B19)-1 -> 0.056600276 | C113: =((C$110*B90+B92+B93)/((Inputs!B6*(1+$A113)*B9)+B11+Inputs!B16*((Inputs!B6*(1+$A113)*B9)+B11+B12)+B31-B21-B22-B23))^(1/Inputs!B19)-1 -> 0.076431858 | D113: =((D$110*B90+B92+B93)/((Inputs!B6*(1+$A113)*B9)+B11+Inputs!B16*((Inputs!B6*(1+$A113)*B9)+B11+B12)+B31-B21-B22-B23))^(1/Inputs!B19)-1 -> 0.094901281 | E113: =((E$110*B90+B92+B93)/((Inputs!B6*(1+$A113)*B9)+B11+Inputs!B16*((Inputs!B6*(1+$A113)*B9)+B11+B12)+B31-B21-B22-B23))^(1/Inputs!B19)-1 -> 0.11220254 | F113: =((F$110*B90+B92+B93)/((Inputs!B6*(1+$A113)*B9)+B11+Inputs!B16*((Inputs!B6*(1+$A113)*B9)+B11+B12)+B31-B21-B22-B23))^(1/Inputs!B19)-1 -> 0.12848977
...
