Workbook

Sheet Notes
A1: Advanced Micro Devices, Inc. (NASDAQ: AMD) - Financial Model
A3: Prepared 2026-10-14 (Initiating Coverage, Task 2). Units: USD millions except per-share (USD) and share counts (millions).
A4: Fiscal year ends on the last Saturday of December (FY2025 = 2025-12-27).
A6: COLOR CODE: blue = hardcoded input / historical data; black = formula; green = link to another sheet; grey italic = static scenario snapshot.
A7: SCENARIO SWITCH: Scenarios!C3 (1 Bull, 2 Base, 3 Bear). Named range: ScenarioSel.
A9: SOURCES
A10: - AMD Form 10-K FY2025 (filed 2026-02-04) and Form 10-K FY2024 (filed 2025-02-05), via SEC XBRL (stock-data get_financials).
A11: - AMD Form 10-Q Q2 FY2026 (filed 2026-08-05) and Q1 FY2026 (filed 2026-05-06), via XBRL and sec.gov.
A12: - AMD Q4/FY2025 earnings release (2026-02-03, ir.amd.com): full FY2025/FY2024 statements, segment data, FCF reconciliation.
A13: - AMD Q4/FY2024 earnings release EX-99.1 (2025-02-04) and Q4/FY2023 EX-99.1 (2024-01-30): FY2022-FY2023 statements and segments.
A14: - AMD Q2 FY2026 earnings release (2026-08-05): Q3 FY2026 guidance about USD 13.0bn +/- 0.3bn; non-GAAP GM about 56%.
A15: - Market data: stock-data get_quote, USD 605.53 at 2026-10-14 07:49 UTC.
... A27: TABS: Revenue Model | Income Statement | Cash Flow | Balance Sheet | Scenarios | DCF Inputs | Quarterly Hist | Checks

Sheet Revenue Model
A1: AMD - Revenue Model
A2: USD millions. Historical segment totals are reported (10-K / earnings releases); sub-product splits are analyst estimates (blue). Projections driven by Scenarios tab.
A4: Revenue by product | C4: FY2022A | D4: FY2023A | E4: FY2024A | F4: FY2025A | G4: FY2026E | H4: FY2027E | I4: FY2028E | J4: FY2029E | K4: FY2030E
A5: Data Center
A6: Server CPU (EPYC) | B6: hist split = estimate | C6: 5493 | D6: 5596 | E6: 7329 | F6: 9735 | G6: =F6*(1+G7) -> 13629 | H6: =G6*(1+H7) -> 17036.25 | I6: =H6*(1+I7) -> 19591.688 | J6: =I6*(1+J7) -> 21942.69 | K6: =J6*(1+K7) -> 24136.959
A7: YoY growth % | D7: =D6/C6-1 -> 0.018751138 | E7: =E6/D6-1 -> 0.30968549 | F7: =F6/E6-1 -> 0.3282849 | G7: =Scenarios!G9 -> 0.4 | H7: =Scenarios!H9 -> 0.25 | I7: =Scenarios!I9 -> 0.15 | J7: =Scenarios!J9 -> 0.12 | K7: =Scenarios!K9 -> 0.1
A8: Data Center GPU (Instinct MI-series) | B8: hist split = estimate | C8: 400 | D8: 700 | E8: 5000 | F8: 6500 | G8: =F8*(1+G9) -> 15600 | H8: =G8*(1+H9) -> 29640 | I8: =H8*(1+I9) -> 42978 | J8: =I8*(1+J9) -> 53722.5 | K8: =J8*(1+K9) -> 61780.875
A9: YoY growth % | D9: =D8/C8-1 -> 0.75 | E9: =E8/D8-1 -> 6.1428571 | F9: =F8/E8-1 -> 0.3 | G9: =Scenarios!G15 -> 1.4 | H9: =Scenarios!H15 -> 0.9 | I9: =Scenarios!I15 -> 0.45 | J9: =Scenarios!J15 -> 0.25 | K9: =Scenarios!K15 -> 0.15
A10: Networking (Pensando), rack-scale & other | B10: hist split = estimate | C10: 150 | D10: 200 | E10: 250 | F10: 400 | G10: =F10*(1+G11) -> 1000 | H10: =G10*(1+H11) -> 2000 | I10: =H10*(1+I11) -> 3000 | J10: =I10*(1+J11) -> 3900 | K10: =J10*(1+K11) -> 4680
A11: YoY growth % | D11: =D10/C10-1 -> 0.33333333 | E11: =E10/D10-1 -> 0.25 | F11: =F10/E10-1 -> 0.6 | G11: =Scenarios!G21 -> 1.5 | H11: =Scenarios!H21 -> 1 | I11: =Scenarios!I21 -> 0.5 | J11: =Scenarios!J21 -> 0.3 | K11: =Scenarios!K21 -> 0.2
A12: Data Center total | C12: =C6+C8+C10 -> 6043 | D12: =D6+D8+D10 -> 6496 | E12: =E6+E8+E10 -> 12579 | F12: =F6+F8+F10 -> 16635 | G12: =G6+G8+G10 -> 30229 | H12: =H6+H8+H10 -> 48676.25 | I12: =I6+I8+I10 -> 65569.688 | J12: =J6+J8+J10 -> 79565.19 | K12: =K6+K8+K10 -> 90597.834
A13: % of total revenue | C13: =C12/C47 -> 0.25604847 | D13: =D12/D47 -> 0.28641975 | E13: =E12/E47 -> 0.48784177 | F13: =F12/F47 -> 0.48023904 | G13: =G12/G47 -> 0.61098928 | H13: =H12/H47 -> 0.70425729 | I13: =I12/I47 -> 0.75007793 | J13: =J12/J47 -> 0.77489575 | K13: =K12/K47 -> 0.79116915
A14: YoY growth % | D14: =D12/C12-1 -> 0.074962767 | E14: =E12/D12-1 -> 0.93642241 | F14: =F12/E12-1 -> 0.32244217 | G14: =G12/F12-1 -> 0.81719267 | H14: =H12/G12-1 -> 0.61025009 | I14: =I12/H12-1 -> 0.34705709 | J14: =J12/I12-1 -> 0.2134447 | K14: =K12/J12-1 -> 0.13866169
A16: Client
A17: Desktop CPU (Ryzen, Threadripper) | B17: hist split = estimate | C17: 2790 | D17: 2093 | E17: 3174 | F17: 5320 | G17: =F17*(1+G18) -> 6118 | H17: =G17*(1+H18) -> 6485.08 | I17: =H17*(1+I18) -> 6809.334 | J17: =I17*(1+J18) -> 7149.8007 | K17: =J17*(1+K18) -> 7435.7927
A18: YoY growth % | D18: =D17/C17-1 -> -0.24982079 | E18: =E17/D17-1 -> 0.51648352 | F18: =F17/E17-1 -> 0.67611846 | G18: =Scenarios!G27 -> 0.15 | H18: =Scenarios!H27 -> 0.06 | I18: =Scenarios!I27 -> 0.05 | J18: =Scenarios!J27 -> 0.05 | K18: =Scenarios!K27 -> 0.04
A19: Notebook CPU (Ryzen AI / Mobile) | B19: hist split = estimate | C19: 3411 | D19: 2558 | E19: 3880 | F19: 5320 | G19: =F19*(1+G20) -> 6118 | H19: =G19*(1+H20) -> 6485.08 | I19: =H19*(1+I20) -> 6809.334 | J19: =I19*(1+J20) -> 7149.8007 | K19: =J19*(1+K20) -> 7435.7927
A20: YoY growth % | D20: =D19/C19-1 -> -0.25007329 | E20: =E19/D19-1 -> 0.51681001 | F20: =F19/E19-1 -> 0.37113402 | G20: =Scenarios!G33 -> 0.15 | H20: =Scenarios!H33 -> 0.06 | I20: =Scenarios!I33 -> 0.05 | J20: =Scenarios!J33 -> 0.05 | K20: =Scenarios!K33 -> 0.04
A21: Client total | C21: =C17+C19 -> 6201 | D21: =D17+D19 -> 4651 | E21: =E17+E19 -> 7054 | F21: =F17+F19 -> 10640 | G21: =G17+G19 -> 12236 | H21: =H17+H19 -> 12970.16 | I21: =I17+I19 -> 13618.668 | J21: =J17+J19 -> 14299.601 | K21: =K17+K19 -> 14871.585
A22: % of total revenue | C22: =C21/C47 -> 0.2627431 | D22: =D21/D47 -> 0.20507055 | E22: =E21/E47 -> 0.2735699 | F22: =F21/F47 -> 0.30716822 | G22: =G21/G47 -> 0.24731433 | H22: =H21/H47 -> 0.18765476 | I22: =I21/I47 -> 0.1557894 | J22: =J21/J47 -> 0.13926568 | K22: =K21/K47 -> 0.12986999
A23: YoY growth % | D23: =D21/C21-1 -> -0.24995968 | E23: =E21/D21-1 -> 0.51666308 | F23: =F21/E21-1 -> 0.50836405 | G23: =G21/F21-1 -> 0.15 | H23: =H21/G21-1 -> 0.06 | I23: =I21/H21-1 -> 0.05 | J23: =J21/I21-1 -> 0.05 | K23: =K21/J21-1 -> 0.04
A25: Gaming
A26: Semi-custom console SoCs | B26: hist split = estimate | C26: 5444 | D26: 5280 | E26: 1946 | F26: 2540 | G26: =F26*(1+G27) -> 1778 | H26: =G26*(1+H27) -> 1778 | I26: =H26*(1+I27) -> 2133.6 | J26: =I26*(1+J27) -> 2346.96 | K26: =J26*(1+K27) -> 2229.612
A27: YoY growth % | D27: =D26/C26-1 -> -0.030124908 | E27: =E26/D26-1 -> -0.63143939 | F27: =F26/E26-1 -> 0.30524152 | G27: =Scenarios!G39 -> -0.3 | H27: =Scenarios!H39 -> 0 | I27: =Scenarios!I39 -> 0.2 | J27: =Scenarios!J39 -> 0.1 | K27: =Scenarios!K39 -> -0.05
A28: Radeon discrete GPUs | B28: hist split = estimate | C28: 1361 | D28: 932 | E28: 649 | F28: 1370 | G28: =F28*(1+G29) -> 1260.4 | H28: =G28*(1+H29) -> 1323.42 | I28: =H28*(1+I29) -> 1376.3568 | J28: =I28*(1+J29) -> 1417.6475 | K28: =J28*(1+K29) -> 1460.1769
A29: YoY growth % | D29: =D28/C28-1 -> -0.3152094 | E29: =E28/D28-1 -> -0.30364807 | F29: =F28/E28-1 -> 1.1109399 | G29: =Scenarios!G45 -> -0.08 | H29: =Scenarios!H45 -> 0.05 | I29: =Scenarios!I45 -> 0.04 | J29: =Scenarios!J45 -> 0.03 | K29: =Scenarios!K45 -> 0.03
A30: Gaming total | C30: =C26+C28 -> 6805 | D30: =D26+D28 -> 6212 | E30: =E26+E28 -> 2595 | F30: =F26+F28 -> 3910 | G30: =G26+G28 -> 3038.4 | H30: =H26+H28 -> 3101.42 | I30: =I26+I28 -> 3509.9568 | J30: =J26+J28 -> 3764.6075 | K30: =K26+K28 -> 3689.7889
A31: % of total revenue | C31: =C30/C47 -> 0.28833524 | D31: =D30/D47 -> 0.27389771 | E31: =E30/E47 -> 0.10063991 | F31: =F30/F47 -> 0.11287855 | G31: =G30/G47 -> 0.061412214 | H31: =H30/H47 -> 0.044871938 | I31: =I30/I47 -> 0.040151802 | J31: =J30/J47 -> 0.036664003 | K31: =K30/K47 -> 0.032222041
A32: YoY growth % | D32: =D30/C30-1 -> -0.087141807 | E32: =E30/D30-1 -> -0.58226014 | F32: =F30/E30-1 -> 0.50674374 | G32: =G30/F30-1 -> -0.2229156 | H32: =H30/G30-1 -> 0.02074118 | I32: =I30/H30-1 -> 0.13172573 | J32: =J30/I30-1 -> 0.072550951 | K32: =K30/J30-1 -> -0.019874203
A34: Embedded
A35: FPGA & adaptive SoC (Xilinx) | B35: hist split = estimate | C35: 3869 | D35: 4523 | E35: 3023 | F35: 2936 | G35: =F35*(1+G36) -> 3376.4 | H35: =G35*(1+H36) -> 3714.04 | I35: =H35*(1+I36) -> 4011.1632 | J35: =I35*(1+J36) -> 4291.9446 | K35: =J35*(1+K36) -> 4549.4613
A36: YoY growth % | D36: =D35/C35-1 -> 0.16903593 | E36: =E35/D35-1 -> -0.33163829 | F36: =F35/E35-1 -> -0.028779358 | G36: =Scenarios!G51 -> 0.15 | H36: =Scenarios!H51 -> 0.1 | I36: =Scenarios!I51 -> 0.08 | J36: =Scenarios!J51 -> 0.07 | K36: =Scenarios!K51 -> 0.06
A37: Embedded x86 (EPYC/Ryzen Embedded) | B37: hist split = estimate | C37: 683 | D37: 798 | E37: 534 | F37: 518 | G37: =F37*(1+G38) -> 595.7 | H37: =G37*(1+H38) -> 655.27 | I37: =H37*(1+I38) -> 707.6916 | J37: =I37*(1+J38) -> 757.23001 | K37: =J37*(1+K38) -> 802.66381
A38: YoY growth % | D38: =D37/C37-1 -> 0.16837482 | E38: =E37/D37-1 -> -0.33082707 | F38: =F37/E37-1 -> -0.029962547 | G38: =Scenarios!G57 -> 0.15 | H38: =Scenarios!H57 -> 0.1 | I38: =Scenarios!I57 -> 0.08 | J38: =Scenarios!J57 -> 0.07 | K38: =Scenarios!K57 -> 0.06
A39: Embedded total | C39: =C35+C37 -> 4552 | D39: =D35+D37 -> 5321 | E39: =E35+E37 -> 3557 | F39: =F35+F37 -> 3454 | G39: =G35+G37 -> 3972.1 | H39: =H35+H37 -> 4369.31 | I39: =I35+I37 -> 4718.8548 | J39: =J35+J37 -> 5049.1746 | K39: =K35+K37 -> 5352.1251
A40: % of total revenue | C40: =C39/C47 -> 0.19287318 | D40: =D39/D47 -> 0.23461199 | E40: =E39/E47 -> 0.13794842 | F40: =F39/F47 -> 0.099714195 | G40: =G39/G47 -> 0.080284181 | H40: =H39/H47 -> 0.063216013 | I40: =I39/I47 -> 0.053980871 | J40: =J39/J47 -> 0.049174569 | K40: =K39/K47 -> 0.046738824
A41: YoY growth % | D41: =D39/C39-1 -> 0.16893673 | E41: =E39/D39-1 -> -0.33151663 | F41: =F39/E39-1 -> -0.028956986 | G41: =G39/F39-1 -> 0.15 | H41: =H39/G39-1 -> 0.1 | I41: =I39/H39-1 -> 0.08 | J41: =J39/I39-1 -> 0.07 | K41: =K39/J39-1 -> 0.06
A43: Reporting-segment view
A44: Client and Gaming segment (reported combined from FY2025) | C44: =C21+C30 -> 13006 | D44: =D21+D30 -> 10863 | E44: =E21+E30 -> 9649 | F44: =F21+F30 -> 14550 | G44: =G21+G30 -> 15274.4 | H44: =H21+H30 -> 16071.58 | I44: =I21+I30 -> 17128.625 | J44: =J21+J30 -> 18064.209 | K44: =K21+K30 -> 18561.374
A45: Data Center AI-related (GPU + networking) | C45: =C8+C10 -> 550 | D45: =D8+D10 -> 900 | E45: =E8+E10 -> 5250 | F45: =F8+F10 -> 6900 | G45: =G8+G10 -> 16600 | H45: =H8+H10 -> 31640 | I45: =I8+I10 -> 45978 | J45: =J8+J10 -> 57622.5 | K45: =K8+K10 -> 66460.875
A47: TOTAL REVENUE | C47: =C12+C21+C30+C39 -> 23601 | D47: =D12+D21+D30+D39 -> 22680 | E47: =E12+E21+E30+E39 -> 25785 | F47: =F12+F21+F30+F39 -> 34639 | G47: =G12+G21+G30+G39 -> 49475.5 | H47: =H12+H21+H30+H39 -> 69117.14 | I47: =I12+I21+I30+I39 -> 87417.167 | J47: =J12+J21+J30+J39 -> 102678.57 | K47: =K12+K21+K30+K39 -> 114511.33
A48: Total revenue growth % | D48: =D47/C47-1 -> -0.03902377 | E48: =E47/D47-1 -> 0.13690476 | F48: =F47/E47-1 -> 0.34337793 | G48: =G47/F47-1 -> 0.42831779 | H48: =H47/G47-1 -> 0.3969973 | I48: =I47/H47-1 -> 0.26476829 | J48: =J47/I47-1 -> 0.17458134 | K48: =K47/J47-1 -> 0.11524079
A51: Revenue by geography (billing location) | C51: FY2022A | D51: FY2023A | E51: FY2024A | F51: FY2025A | G51: FY2026E | H51: FY2027E | I51: FY2028E | J51: FY2029E | K51: FY2030E
A52: Geographic split is an analyst ESTIMATE (blue share inputs below); AMD's 10-K country table was not retrievable in this session.
A53: Americas
A54: United States | C54: =C$47*C78 -> 7080.3 | D54: =D$47*D78 -> 7030.8 | E54: =E$47*E78 -> 8251.2 | F54: =F$47*F78 -> 11430.87 | G54: =G$47*G78 -> 16821.67 | H54: =H$47*H78 -> 24190.999 | I54: =I$47*I78 -> 31470.18 | J54: =J$47*J78 -> 37991.072 | K54: =K$47*K78 -> 43514.307
A55: Other Americas | C55: =C$47*C79 -> 472.02 | D55: =D$47*D79 -> 453.6 | E55: =E$47*E79 -> 515.7 | F55: =F$47*F79 -> 692.78 | G55: =G$47*G79 -> 989.51 | H55: =H$47*H79 -> 1382.3428 | I55: =I$47*I79 -> 1748.3433 | J55: =J$47*J79 -> 2053.5715 | K55: =K$47*K79 -> 2290.2267
A56: Americas total | C56: =C54+C55 -> 7552.32 | D56: =D54+D55 -> 7484.4 | E56: =E54+E55 -> 8766.9 | F56: =F54+F55 -> 12123.65 | G56: =G54+G55 -> 17811.18 | H56: =H54+H55 -> 25573.342 | I56: =I54+I55 -> 33218.523 | J56: =J54+J55 -> 40044.644 | K56: =K54+K55 -> 45804.533
A57: % of total | C57: =C56/C$47 -> 0.32 | D57: =D56/D$47 -> 0.33 | E57: =E56/E$47 -> 0.34 | F57: =F56/F$47 -> 0.35 | G57: =G56/G$47 -> 0.36 | H57: =H56/H$47 -> 0.37 | I57: =I56/I$47 -> 0.38 | J57: =J56/J$47 -> 0.39 | K57: =K56/K$47 -> 0.4
A58: YoY growth % | D58: =D56/C56-1 -> -0.008993263 | E58: =E56/D56-1 -> 0.17135642 | F58: =F56/E56-1 -> 0.38288905 | G58: =G56/F56-1 -> 0.46912687 | H58: =H56/G56-1 -> 0.43580278 | I58: =I56/H56-1 -> 0.29895122 | J58: =J56/I56-1 -> 0.20549138 | K58: =K56/J56-1 -> 0.14383671
A59: Asia-Pacific
A60: China (incl. Hong Kong) | C60: =C$47*C80 -> 5664.24 | D60: =D$47*D80 -> 5216.4 | E60: =E$47*E80 -> 5672.7 | F60: =F$47*F80 -> 6927.8 | G60: =G$47*G80 -> 8905.59 | H60: =H$47*H80 -> 11749.914 | I60: =I$47*I80 -> 14860.918 | J60: =J$47*J80 -> 16428.572 | K60: =K$47*K80 -> 18321.813
A61: Taiwan | C61: =C$47*C81 -> 3776.16 | D61: =D$47*D81 -> 3628.8 | E61: =E$47*E81 -> 4125.6 | F61: =F$47*F81 -> 5542.24 | G61: =G$47*G81 -> 8410.835 | H61: =H$47*H81 -> 11749.914 | I61: =I$47*I81 -> 14860.918 | J61: =J$47*J81 -> 17455.358 | K61: =K$47*K81 -> 19466.927
A62: Japan | C62: =C$47*C82 -> 1416.06 | D62: =D$47*D82 -> 1360.8 | E62: =E$47*E82 -> 1547.1 | F62: =F$47*F82 -> 2078.34 | G62: =G$47*G82 -> 2968.53 | H62: =H$47*H82 -> 4147.0284 | I62: =I$47*I82 -> 5245.03 | J62: =J$47*J82 -> 6160.7144 | K62: =K$47*K82 -> 6870.68
A63: Singapore | C63: =C$47*C83 -> 2360.1 | D63: =D$47*D83 -> 2268 | E63: =E$47*E83 -> 2320.65 | F63: =F$47*F83 -> 3117.51 | G63: =G$47*G83 -> 4452.795 | H63: =H$47*H83 -> 6220.5426 | I63: =I$47*I83 -> 6993.3734 | J63: =J$47*J83 -> 8214.2859 | K63: =K$47*K83 -> 8015.7933
A64: Other Asia-Pacific | C64: =C$47*C84 -> 944.04 | D64: =D$47*D84 -> 907.2 | E64: =E$47*E84 -> 1031.4 | F64: =F$47*F84 -> 1385.56 | G64: =G$47*G84 -> 1979.02 | H64: =H$47*H84 -> 2764.6856 | I64: =I$47*I84 -> 3496.6867 | J64: =J$47*J84 -> 4107.1429 | K64: =K$47*K84 -> 4580.4533
A65: Asia-Pacific total | C65: =C60+C61+C62+C63+C64 -> 14160.6 | D65: =D60+D61+D62+D63+D64 -> 13381.2 | E65: =E60+E61+E62+E63+E64 -> 14697.45 | F65: =F60+F61+F62+F63+F64 -> 19051.45 | G65: =G60+G61+G62+G63+G64 -> 26716.77 | H65: =H60+H61+H62+H63+H64 -> 36632.084 | I65: =I60+I61+I62+I63+I64 -> 45456.927 | J65: =J60+J61+J62+J63+J64 -> 52366.073 | K65: =K60+K61+K62+K63+K64 -> 57255.667
A66: % of total | C66: =C65/C$47 -> 0.6 | D66: =D65/D$47 -> 0.59 | E66: =E65/E$47 -> 0.57 | F66: =F65/F$47 -> 0.55 | G66: =G65/G$47 -> 0.54 | H66: =H65/H$47 -> 0.53 | I66: =I65/I$47 -> 0.52 | J66: =J65/J$47 -> 0.51 | K66: =K65/K$47 -> 0.5
A67: YoY growth % | D67: =D65/C65-1 -> -0.055040041 | E67: =E65/D65-1 -> 0.098365617 | F67: =F65/E65-1 -> 0.29624187 | G67: =G65/F65-1 -> 0.40234838 | H67: =H65/G65-1 -> 0.37112698 | I67: =I65/H65-1 -> 0.24090474 | J67: =J65/I65-1 -> 0.15199324 | K67: =K65/J65-1 -> 0.093373324
A68: Europe, Middle East & Africa
A69: Europe | C69: =C$47*C85 -> 1416.06 | D69: =D$47*D85 -> 1360.8 | E69: =E$47*E85 -> 1804.95 | F69: =F$47*F85 -> 2771.12 | G69: =G$47*G85 -> 3958.04 | H69: =H$47*H85 -> 5529.3712 | I69: =I$47*I85 -> 6993.3734 | J69: =J$47*J85 -> 8214.2859 | K69: =K$47*K85 -> 9160.9067
A70: Other EMEA | C70: =C$47*C86 -> 472.02 | D70: =D$47*D86 -> 453.6 | E70: =E$47*E86 -> 515.7 | F70: =F$47*F86 -> 692.78 | G70: =G$47*G86 -> 989.51 | H70: =H$47*H86 -> 1382.3428 | I70: =I$47*I86 -> 1748.3433 | J70: =J$47*J86 -> 2053.5715 | K70: =K$47*K86 -> 2290.2267
A71: Europe, Middle East & Africa total | C71: =C69+C70 -> 1888.08 | D71: =D69+D70 -> 1814.4 | E71: =E69+E70 -> 2320.65 | F71: =F69+F70 -> 3463.9 | G71: =G69+G70 -> 4947.55 | H71: =H69+H70 -> 6911.714 | I71: =I69+I70 -> 8741.7167 | J71: =J69+J70 -> 10267.857 | K71: =K69+K70 -> 11451.133
A72: % of total | C72: =C71/C$47 -> 0.08 | D72: =D71/D$47 -> 0.08 | E72: =E71/E$47 -> 0.09 | F72: =F71/F$47 -> 0.1 | G72: =G71/G$47 -> 0.1 | H72: =H71/H$47 -> 0.1 | I72: =I71/I$47 -> 0.1 | J72: =J71/J$47 -> 0.1 | K72: =K71/K$47 -> 0.1
A73: YoY growth % | D73: =D71/C71-1 -> -0.03902377 | E73: =E71/D71-1 -> 0.27901786 | F73: =F71/E71-1 -> 0.49264215 | G73: =G71/F71-1 -> 0.42831779 | H73: =H71/G71-1 -> 0.3969973 | I73: =I71/H71-1 -> 0.26476829 | J73: =J71/I71-1 -> 0.17458134 | K73: =K71/J71-1 -> 0.11524079
A74: TOTAL REVENUE (geography) | C74: =C56+C65+C71 -> 23601 | D74: =D56+D65+D71 -> 22680 | E74: =E56+E65+E71 -> 25785 | F74: =F56+F65+F71 -> 34639 | G74: =G56+G65+G71 -> 49475.5 | H74: =H56+H65+H71 -> 69117.14 | I74: =I56+I65+I71 -> 87417.167 | J74: =J56+J65+J71 -> 102678.57 | K74: =K56+K65+K71 -> 114511.33
A75: Check vs product total (should be 0) | C75: =C74-C47 -> 0 | D75: =D74-D47 -> 0 | E75: =E74-E47 -> 0 | F75: =F74-F47 -> 0 | G75: =G74-G47 -> 0 | H75: =H74-H47 -> 0 | I75: =I74-I47 -> 0 | J75: =J74-J47 -> 0 | K75: =K74-K47 -> 0
A77: Geographic share inputs (estimates)
A78: United States share | C78: 0.3 | D78: 0.31 | E78: 0.32 | F78: 0.33 | G78: 0.34 | H78: 0.35 | I78: 0.36 | J78: 0.37 | K78: 0.38
A79: Other Americas share | C79: 0.02 | D79: 0.02 | E79: 0.02 | F79: 0.02 | G79: 0.02 | H79: 0.02 | I79: 0.02 | J79: 0.02 | K79: 0.02
A80: China (incl. Hong Kong) share | C80: 0.24 | D80: 0.23 | E80: 0.22 | F80: 0.2 | G80: 0.18 | H80: 0.17 | I80: 0.17 | J80: 0.16 | K80: 0.16
A81: Taiwan share | C81: 0.16 | D81: 0.16 | E81: 0.16 | F81: 0.16 | G81: 0.17 | H81: 0.17 | I81: 0.17 | J81: 0.17 | K81: 0.17
A82: Japan share | C82: 0.06 | D82: 0.06 | E82: 0.06 | F82: 0.06 | G82: 0.06 | H82: 0.06 | I82: 0.06 | J82: 0.06 | K82: 0.06
A83: Singapore share | C83: 0.1 | D83: 0.1 | E83: 0.09 | F83: 0.09 | G83: 0.09 | H83: 0.09 | I83: 0.08 | J83: 0.08 | K83: 0.07
A84: Other Asia-Pacific share | C84: 0.04 | D84: 0.04 | E84: 0.04 | F84: 0.04 | G84: 0.04 | H84: 0.04 | I84: 0.04 | J84: 0.04 | K84: 0.04
A85: Europe share | C85: 0.06 | D85: 0.06 | E85: 0.07 | F85: 0.08 | G85: 0.08 | H85: 0.08 | I85: 0.08 | J85: 0.08 | K85: 0.08
A86: Other EMEA share | C86: 0.02 | D86: 0.02 | E86: 0.02 | F86: 0.02 | G86: 0.02 | H86: 0.02 | I86: 0.02 | J86: 0.02 | K86: 0.02
A87: Sum of shares (must = 100%) | C87: =SUM(C78:C86) -> 1 | D87: =SUM(D78:D86) -> 1 | E87: =SUM(E78:E86) -> 1 | F87: =SUM(F78:F86) -> 1 | G87: =SUM(G78:G86) -> 1 | H87: =SUM(H78:H86) -> 1 | I87: =SUM(I78:I86) -> 1 | J87: =SUM(J78:J86) -> 1 | K87: =SUM(K78:K86) -> 1

Sheet Income Statement
A1: AMD - Income Statement (GAAP)
A2: USD millions except per share. FY2022A-FY2025A from 10-K / Q4 earnings releases (FY2024 & FY2025 MG&A shown net of licensing gains, as recast).
A4: USD millions | C4: FY2022A | D4: FY2023A | E4: FY2024A | F4: FY2025A | G4: FY2026E | H4: FY2027E | I4: FY2028E | J4: FY2029E | K4: FY2030E
A5: Revenue
A6: Data Center | C6: ='Revenue Model'!C12 -> 6043 | D6: ='Revenue Model'!D12 -> 6496 | E6: ='Revenue Model'!E12 -> 12579 | F6: ='Revenue Model'!F12 -> 16635 | G6: ='Revenue Model'!G12 -> 30229 | H6: ='Revenue Model'!H12 -> 48676.25 | I6: ='Revenue Model'!I12 -> 65569.688 | J6: ='Revenue Model'!J12 -> 79565.19 | K6: ='Revenue Model'!K12 -> 90597.834
A7: Client | C7: ='Revenue Model'!C21 -> 6201 | D7: ='Revenue Model'!D21 -> 4651 | E7: ='Revenue Model'!E21 -> 7054 | F7: ='Revenue Model'!F21 -> 10640 | G7: ='Revenue Model'!G21 -> 12236 | H7: ='Revenue Model'!H21 -> 12970.16 | I7: ='Revenue Model'!I21 -> 13618.668 | J7: ='Revenue Model'!J21 -> 14299.601 | K7: ='Revenue Model'!K21 -> 14871.585
A8: Gaming | C8: ='Revenue Model'!C30 -> 6805 | D8: ='Revenue Model'!D30 -> 6212 | E8: ='Revenue Model'!E30 -> 2595 | F8: ='Revenue Model'!F30 -> 3910 | G8: ='Revenue Model'!G30 -> 3038.4 | H8: ='Revenue Model'!H30 -> 3101.42 | I8: ='Revenue Model'!I30 -> 3509.9568 | J8: ='Revenue Model'!J30 -> 3764.6075 | K8: ='Revenue Model'!K30 -> 3689.7889
A9: Embedded | C9: ='Revenue Model'!C39 -> 4552 | D9: ='Revenue Model'!D39 -> 5321 | E9: ='Revenue Model'!E39 -> 3557 | F9: ='Revenue Model'!F39 -> 3454 | G9: ='Revenue Model'!G39 -> 3972.1 | H9: ='Revenue Model'!H39 -> 4369.31 | I9: ='Revenue Model'!I39 -> 4718.8548 | J9: ='Revenue Model'!J39 -> 5049.1746 | K9: ='Revenue Model'!K39 -> 5352.1251
A10: Total net revenue | C10: =C6+C7+C8+C9 -> 23601 | D10: =D6+D7+D8+D9 -> 22680 | E10: =E6+E7+E8+E9 -> 25785 | F10: =F6+F7+F8+F9 -> 34639 | G10: =G6+G7+G8+G9 -> 49475.5 | H10: =H6+H7+H8+H9 -> 69117.14 | I10: =I6+I7+I8+I9 -> 87417.167 | J10: =J6+J7+J8+J9 -> 102678.57 | K10: =K6+K7+K8+K9 -> 114511.33
A11: YoY growth % | D11: =D10/C10-1 -> -0.03902377 | E11: =E10/D10-1 -> 0.13690476 | F11: =F10/E10-1 -> 0.34337793 | G11: =G10/F10-1 -> 0.42831779 | H11: =H10/G10-1 -> 0.3969973 | I11: =I10/H10-1 -> 0.26476829 | J11: =J10/I10-1 -> 0.17458134 | K11: =K10/J10-1 -> 0.11524079
A13: Cost of sales
A14: Cost of sales ex-amortization % of revenue (driver) | C14: =C15/C10 -> 0.48938604 | D14: =D15/D10 -> 0.49726631 | E14: =E15/E10 -> 0.46980803 | F14: =F15/F10 -> 0.47507145 | G14: =Scenarios!G63 -> 0.455 | H14: =Scenarios!H63 -> 0.45 | I14: =Scenarios!I63 -> 0.445 | J14: =Scenarios!J63 -> 0.44 | K14: =Scenarios!K63 -> 0.44
A15: Cost of sales (ex-amortization) | C15: 11550 | D15: 11278 | E15: 12114 | F15: 16456 | G15: =G10*G14 -> 22511.353 | H15: =H10*H14 -> 31102.713 | I15: =I10*I14 -> 38900.639 | J15: =J10*J14 -> 45178.572 | K15: =K10*K14 -> 50384.987
A16: Amortization of acquisition-related intangibles (COGS) | C16: 1448 | D16: 942 | E16: 946 | F16: 1031 | G16: =G70*G71 -> 945 | H16: =H70*H71 -> 855 | I16: =I70*I71 -> 765 | J16: =J70*J71 -> 675 | K16: =K70*K71 -> 585
A17: Total cost of sales | C17: =C15+C16 -> 12998 | D17: =D15+D16 -> 12220 | E17: =E15+E16 -> 13060 | F17: =F15+F16 -> 17487 | G17: =G15+G16 -> 23456.353 | H17: =H15+H16 -> 31957.713 | I17: =I15+I16 -> 39665.639 | J17: =J15+J16 -> 45853.572 | K17: =K15+K16 -> 50969.987
A18: Gross profit | C18: =C10-C17 -> 10603 | D18: =D10-D17 -> 10460 | E18: =E10-E17 -> 12725 | F18: =F10-F17 -> 17152 | G18: =G10-G17 -> 26019.147 | H18: =H10-H17 -> 37159.427 | I18: =I10-I17 -> 47751.528 | J18: =J10-J17 -> 56825.001 | K18: =K10-K17 -> 63541.347
A19: Gross margin % (GAAP) | C19: =C18/C10 -> 0.44926062 | D19: =D18/D10 -> 0.46119929 | E19: =E18/E10 -> 0.49350398 | F19: =F18/F10 -> 0.49516441 | G19: =G18/G10 -> 0.52589964 | H19: =H18/H10 -> 0.5376297 | I19: =I18/I10 -> 0.54624886 | J19: =J18/J10 -> 0.55342609 | K19: =K18/K10 -> 0.55489134
A20: Gross margin % ex-amortization | C20: =1-C15/C10 -> 0.51061396 | D20: =1-D15/D10 -> 0.50273369 | E20: =1-E15/E10 -> 0.53019197 | F20: =1-F15/F10 -> 0.52492855 | G20: =1-G15/G10 -> 0.545 | H20: =1-H15/H10 -> 0.55 | I20: =1-I15/I10 -> 0.555 | J20: =1-J15/J10 -> 0.56 | K20: =1-K15/K10 -> 0.56
A22: Operating expenses
A23: R&D % of revenue (driver) | C23: =C24/C10 -> 0.21206729 | D23: =D24/D10 -> 0.25890653 | E23: =E24/E10 -> 0.25037813 | F23: =F24/F10 -> 0.23358065 | G23: =Scenarios!G69 -> 0.215 | H23: =Scenarios!H69 -> 0.185 | I23: =Scenarios!I69 -> 0.17 | J23: =Scenarios!J69 -> 0.16 | K23: =Scenarios!K69 -> 0.155
A24: Research and development | C24: 5005 | D24: 5872 | E24: 6456 | F24: 8091 | G24: =G10*G23 -> 10637.233 | H24: =H10*H23 -> 12786.671 | I24: =I10*I23 -> 14860.918 | J24: =J10*J23 -> 16428.572 | K24: =K10*K23 -> 17749.257
A25: MG&A % of revenue (driver) | C25: =C26/C10 -> 0.094657006 | D25: =D26/D10 -> 0.10220459 | E25: =E26/E10 -> 0.10606942 | F25: =F26/F10 -> 0.11963394 | G25: =Scenarios!G75 -> 0.115 | H25: =Scenarios!H75 -> 0.1 | I25: =Scenarios!I75 -> 0.09 | J25: =Scenarios!J75 -> 0.085 | K25: =Scenarios!K75 -> 0.08
A26: Marketing, general & administrative (net of licensing gain) | B26: FY22/23 net of 102/34 licensing gain | C26: 2234 | D26: 2318 | E26: 2735 | F26: 4144 | G26: =G10*G25 -> 5689.6825 | H26: =H10*H25 -> 6911.714 | I26: =I10*I25 -> 7867.545 | J26: =J10*J25 -> 8727.6788 | K26: =K10*K25 -> 9160.9067
A27: Amortization of acquisition-related intangibles (opex) | C27: 2100 | D27: 1869 | E27: 1448 | F27: 1223 | G27: =G70-G16 -> 1155 | H27: =H70-H16 -> 1045 | I27: =I70-I16 -> 935 | J27: =J70-J16 -> 825 | K27: =K70-K16 -> 715
A28: Restructuring charges | C28: 0 | D28: 0 | E28: 186 | F28: 0 | G28: 0 | H28: 0 | I28: 0 | J28: 0 | K28: 0
A29: Total operating expenses | C29: =C24+C26+C27+C28 -> 9339 | D29: =D24+D26+D27+D28 -> 10059 | E29: =E24+E26+E27+E28 -> 10825 | F29: =F24+F26+F27+F28 -> 13458 | G29: =G24+G26+G27+G28 -> 17481.915 | H29: =H24+H26+H27+H28 -> 20743.385 | I29: =I24+I26+I27+I28 -> 23663.463 | J29: =J24+J26+J27+J28 -> 25981.251 | K29: =K24+K26+K27+K28 -> 27625.163
A30: Opex % of revenue | C30: =C29/C10 -> 0.39570357 | D30: =D29/D10 -> 0.44351852 | E30: =E29/E10 -> 0.41981772 | F30: =F29/F10 -> 0.38852161 | G30: =G29/G10 -> 0.35334489 | H30: =H29/H10 -> 0.30011926 | I30: =I29/I10 -> 0.27069584 | J30: =J29/J10 -> 0.25303478 | K30: =K29/K10 -> 0.24124392
A32: Operating income (EBIT) | C32: =C18-C29 -> 1264 | D32: =D18-D29 -> 401 | E32: =E18-E29 -> 1900 | F32: =F18-F29 -> 3694 | G32: =G18-G29 -> 8537.2325 | H32: =H18-H29 -> 16416.042 | I32: =I18-I29 -> 24088.064 | J32: =J18-J29 -> 30843.751 | K32: =K18-K29 -> 35916.183
A33: Operating margin % | C33: =C32/C10 -> 0.053557053 | D33: =D32/D10 -> 0.017680776 | E33: =E32/E10 -> 0.073686252 | F33: =F32/F10 -> 0.1066428 | G33: =G32/G10 -> 0.17255475 | H33: =H32/H10 -> 0.23751044 | I33: =I32/I10 -> 0.27555302 | J33: =J32/J10 -> 0.3003913 | K33: =K32/K10 -> 0.31364741
A34: D&A (ex-acquired intangibles) % of revenue | C34: =C35/C10 -> 0.0265243 | D34: =D35/D10 -> 0.028306878 | E34: =E35/E10 -> 0.026022882 | F34: =F35/F10 -> 0.021651895 | G34: 0.02 | H34: 0.02 | I34: 0.02 | J34: 0.02 | K34: 0.02
A35: Depreciation & amortization (ex-acquired intangibles) | B35: FY22 = 4,174 total less 3,548 intangibles | C35: 626 | D35: 642 | E35: 671 | F35: 750 | G35: =G10*G34 -> 989.51 | H35: =H10*H34 -> 1382.3428 | I35: =I10*I34 -> 1748.3433 | J35: =J10*J34 -> 2053.5715 | K35: =K10*K34 -> 2290.2267
A36: Amortization of acquired intangibles (total) | C36: =C16+C27 -> 3548 | D36: =D16+D27 -> 2811 | E36: =E16+E27 -> 2394 | F36: =F16+F27 -> 2254 | G36: =G16+G27 -> 2100 | H36: =H16+H27 -> 1900 | I36: =I16+I27 -> 1700 | J36: =J16+J27 -> 1500 | K36: =K16+K27 -> 1300
A37: EBITDA | C37: =C32+C35+C36 -> 5438 | D37: =D32+D35+D36 -> 3854 | E37: =E32+E35+E36 -> 4965 | F37: =F32+F35+F36 -> 6698 | G37: =G32+G35+G36 -> 11626.743 | H37: =H32+H35+H36 -> 19698.385 | I37: =I32+I35+I36 -> 27536.408 | J37: =J32+J35+J36 -> 34397.322 | K37: =K32+K35+K36 -> 39506.41
A38: EBITDA margin % | C38: =C37/C10 -> 0.23041397 | D38: =D37/D10 -> 0.16992945 | E38: =E37/E10 -> 0.19255381 | F38: =F37/F10 -> 0.19336586 | G38: =G37/G10 -> 0.235 | H38: =H37/H10 -> 0.285 | I38: =I37/I10 -> 0.315 | J38: =J37/J10 -> 0.335 | K38: =K37/K10 -> 0.345
A39: Stock-based compensation % of revenue | C39: =C40/C10 -> 0.045803144 | D39: =D40/D10 -> 0.061022928 | E39: =E40/E10 -> 0.054566608 | F39: =F40/F10 -> 0.047287739 | G39: 0.04 | H39: 0.035 | I39: 0.032 | J39: 0.03 | K39: 0.03
A40: Stock-based compensation (memo) | C40: 1081 | D40: 1384 | E40: 1407 | F40: 1638 | G40: =G10*G39 -> 1979.02 | H40: =H10*H39 -> 2419.0999 | I40: =I10*I39 -> 2797.3493 | J40: =J10*J39 -> 3080.3572 | K40: =K10*K39 -> 3435.34
A41: Adjusted EBITDA (EBITDA + SBC + restructuring) | C41: =C37+C40+C28 -> 6519 | D41: =D37+D40+D28 -> 5238 | E41: =E37+E40+E28 -> 6558 | F41: =F37+F40+F28 -> 8336 | G41: =G37+G40+G28 -> 13605.763 | H41: =H37+H40+H28 -> 22117.485 | I41: =I37+I40+I28 -> 30333.757 | J41: =J37+J40+J28 -> 37477.679 | K41: =K37+K40+K28 -> 42941.75
A42: Approx. non-GAAP operating income (EBIT + amort + SBC + restr.) | B42: excl. inventory/acq. adj. | C42: =C32+C36+C40+C28 -> 5893 | D42: =D32+D36+D40+D28 -> 4596 | E42: =E32+E36+E40+E28 -> 5887 | F42: =F32+F36+F40+F28 -> 7586 | G42: =G32+G36+G40+G28 -> 12616.253 | H42: =H32+H36+H40+H28 -> 20735.142 | I42: =I32+I36+I40+I28 -> 28585.414 | J42: =J32+J36+J40+J28 -> 35424.108 | K42: =K32+K36+K40+K28 -> 40651.523
A43: Approx. non-GAAP operating margin % | C43: =C42/C10 -> 0.24969281 | D43: =D42/D10 -> 0.2026455 | E43: =E42/E10 -> 0.22831103 | F43: =F42/F10 -> 0.2190017 | G43: =G42/G10 -> 0.255 | H43: =H42/H10 -> 0.3 | I43: =I42/I10 -> 0.327 | J43: =J42/J10 -> 0.345 | K43: =K42/K10 -> 0.355
A45: Below the line
A46: Interest rate on average debt | D46: =D47/AVERAGE('Balance Sheet'!C52,'Balance Sheet'!D52) -> 0.04295846 | E46: =E47/AVERAGE('Balance Sheet'!D52,'Balance Sheet'!E52) -> 0.043924564 | F46: =F47/AVERAGE('Balance Sheet'!E52,'Balance Sheet'!F52) -> 0.053004248 | G46: 0.04 | H46: 0.04 | I46: 0.04 | J46: 0.04 | K46: 0.04
A47: Interest expense | C47: 88 | D47: 106 | E47: 92 | F47: 131 | G47: =G46*AVERAGE('Balance Sheet'!F52,'Balance Sheet'!G52) -> 128.88 | H47: =H46*AVERAGE('Balance Sheet'!G52,'Balance Sheet'!H52) -> 128.88 | I47: =I46*AVERAGE('Balance Sheet'!H52,'Balance Sheet'!I52) -> 128.88 | J47: =J46*AVERAGE('Balance Sheet'!I52,'Balance Sheet'!J52) -> 128.88 | K47: =K46*AVERAGE('Balance Sheet'!J52,'Balance Sheet'!K52) -> 128.88
A48: Yield on beginning cash + ST investments | D48: =D49/('Balance Sheet'!C14+'Balance Sheet'!C15) -> 0.033646456 | E48: =E49/('Balance Sheet'!D14+'Balance Sheet'!D15) -> 0.031352849 | F48: =F49/('Balance Sheet'!E14+'Balance Sheet'!E15) -> 0.1124318 | G48: 0.035 | H48: 0.035 | I48: 0.035 | J48: 0.035 | K48: 0.035
A49: Other income (expense), net (incl. interest income) | B49: FY25 incl. 341 inv. gains | C49: 8 | D49: 197 | E49: 181 | F49: 577 | G49: =G48*('Balance Sheet'!F14+'Balance Sheet'!F15) -> 369.32 | H49: =H48*('Balance Sheet'!G14+'Balance Sheet'!G15) -> 423.28612 | I49: =I48*('Balance Sheet'!H14+'Balance Sheet'!H15) -> 619.0633 | J49: =J48*('Balance Sheet'!I14+'Balance Sheet'!I15) -> 958.66341 | K49: =K48*('Balance Sheet'!J14+'Balance Sheet'!J15) -> 1412.4365
A50: Income before taxes and equity income | C50: =C32-C47+C49 -> 1184 | D50: =D32-D47+D49 -> 492 | E50: =E32-E47+E49 -> 1989 | F50: =F32-F47+F49 -> 4140 | G50: =G32-G47+G49 -> 8777.6725 | H50: =H32-H47+H49 -> 16710.448 | I50: =I32-I47+I49 -> 24578.248 | J50: =J32-J47+J49 -> 31673.534 | K50: =K32-K47+K49 -> 37199.74
A51: Effective tax rate % | C51: =C52/C50 -> -0.10304054 | D51: =D52/D50 -> -0.70325203 | E51: =E52/E50 -> 0.19155354 | F51: =F52/F50 -> -0.024879227 | G51: 0.13 | H51: 0.15 | I51: 0.15 | J51: 0.15 | K51: 0.15
A52: Income tax provision (benefit) | C52: -122 | D52: -346 | E52: 381 | F52: -103 | G52: =G50*G51 -> 1141.0974 | H52: =H50*H51 -> 2506.5672 | I52: =I50*I51 -> 3686.7371 | J52: =J50*J51 -> 4751.0301 | K52: =K50*K51 -> 5579.961
A53: Equity income in investee | C53: 14 | D53: 16 | E53: 33 | F53: 26 | G53: 30 | H53: 30 | I53: 30 | J53: 30 | K53: 30
A54: Income from continuing operations | C54: =C50-C52+C53 -> 1320 | D54: =D50-D52+D53 -> 854 | E54: =E50-E52+E53 -> 1641 | F54: =F50-F52+F53 -> 4269 | G54: =G50-G52+G53 -> 7666.5751 | H54: =H50-H52+H53 -> 14233.881 | I54: =I50-I52+I53 -> 20921.51 | J54: =J50-J52+J53 -> 26952.504 | K54: =K50-K52+K53 -> 31649.779
A55: Income (loss) from discontinued operations, net | B55: ZT manufacturing | C55: 0 | D55: 0 | E55: 0 | F55: 66 | G55: 0 | H55: 0 | I55: 0 | J55: 0 | K55: 0
A56: NET INCOME | C56: =C54+C55 -> 1320 | D56: =D54+D55 -> 854 | E56: =E54+E55 -> 1641 | F56: =F54+F55 -> 4335 | G56: =G54+G55 -> 7666.5751 | H56: =H54+H55 -> 14233.881 | I56: =I54+I55 -> 20921.51 | J56: =J54+J55 -> 26952.504 | K56: =K54+K55 -> 31649.779
A57: Net margin % | C57: =C56/C10 -> 0.055929833 | D57: =D56/D10 -> 0.037654321 | E57: =E56/E10 -> 0.063641652 | F57: =F56/F10 -> 0.12514795 | G57: =G56/G10 -> 0.154957 | H57: =H56/H10 -> 0.20593851 | I57: =I56/I10 -> 0.23932954 | J57: =J56/J10 -> 0.26249395 | K57: =K56/K10 -> 0.27638993
A58: Net income growth % | D58: =D56/C56-1 -> -0.3530303 | E58: =E56/D56-1 -> 0.92154567 | F58: =F56/E56-1 -> 1.6416819 | G58: =G56/F56-1 -> 0.76852943 | H58: =H56/G56-1 -> 0.85661535 | I58: =I56/H56-1 -> 0.46983879 | J58: =J56/I56-1 -> 0.2882676 | K58: =K56/J56-1 -> 0.17427972
A60: Per share
A61: Diluted share count growth % (projection input) | D61: =D63/C63-1 -> 0.034373011 | E61: =E63/D63-1 -> 0.0073846154 | F61: =F63/E63-1 -> -0.00061087355 | H61: 0.005 | I61: 0.005 | J61: 0.005 | K61: 0.005
A62: Weighted avg. basic shares (M) | B62: proj = 99% of diluted | C62: 1561 | D62: 1614 | E62: 1620 | F62: 1624 | G62: =G63*0.99 -> 1643.4 | H62: =H63*0.99 -> 1651.617 | I62: =I63*0.99 -> 1659.8751 | J62: =J63*0.99 -> 1668.1745 | K62: =K63*0.99 -> 1676.5153
A63: Weighted avg. diluted shares (M) | B63: FY26E: Q2'26 = 1,659; excl. OpenAI warrant | C63: 1571 | D63: 1625 | E63: 1637 | F63: 1636 | G63: 1660 | H63: =G63*(1+H61) -> 1668.3 | I63: =H63*(1+I61) -> 1676.6415 | J63: =I63*(1+J61) -> 1685.0247 | K63: =J63*(1+K61) -> 1693.4498
A64: EPS - basic (USD) | C64: =C56/C62 -> 0.84561179 | D64: =D56/D62 -> 0.5291202 | E64: =E56/E62 -> 1.012963 | F64: =F56/F62 -> 2.669335 | G64: =G56/G62 -> 4.6650694 | H64: =H56/H62 -> 8.6181488 | I64: =I56/I62 -> 12.604268 | J64: =J56/J62 -> 16.156886 | K64: =K56/K62 -> 18.878312
A65: EPS - diluted (USD) | C65: =C56/C63 -> 0.84022915 | D65: =D56/D63 -> 0.52553846 | E65: =E56/E63 -> 1.0024435 | F65: =F56/F63 -> 2.6497555 | G65: =G56/G63 -> 4.6184187 | H65: =H56/H63 -> 8.5319673 | I65: =I56/I63 -> 12.478225 | J65: =J56/J63 -> 15.995317 | K65: =K56/K63 -> 18.689529
A66: Diluted EPS growth % | D66: =D65/C65-1 -> -0.3745296 | E66: =E65/D65-1 -> 0.90745981 | F66: =F65/E65-1 -> 1.6432966 | G66: =G65/F65-1 -> 0.74296033 | H66: =H65/G65-1 -> 0.84737846 | I66: =I65/H65-1 -> 0.46252616 | J66: =J65/I65-1 -> 0.2818583 | K66: =K65/J65-1 -> 0.16843754
A67: Approx. non-GAAP diluted EPS (USD) | B67: 13% non-GAAP tax | C67: =(C42-C47+C49+C53)*(1-0.13)/C63 -> 3.2269192 | D67: =(D42-D47+D49+D53)*(1-0.13)/D63 -> 2.5179138 | E67: =(E42-E47+E49+E53)*(1-0.13)/E63 -> 3.1935431 | F67: =(F42-F47+F49+F53)*(1-0.13)/F63 -> 4.2851222 | G67: =(G42-G47+G49+G53)*(1-0.13)/G63 -> 6.753869 | H67: =(H42-H47+H49+H53)*(1-0.13)/H63 -> 10.982321 | I67: =(I42-I47+I49+I53)*(1-0.13)/I63 -> 15.102733 | J67: =(J42-J47+J49+J53)*(1-0.13)/J63 -> 18.733841 | K67: =(K42-K47+K49+K53)*(1-0.13)/K63 -> 21.559316
A69: Amortization schedule inputs
A70: Amortization of acquired intangibles - total (input) | C70: 3548 | D70: 2811 | E70: 2394 | F70: 2254 | G70: 2100 | H70: 1900 | I70: 1700 | J70: 1500 | K70: 1300
A71: Share recorded in cost of sales | C71: =C16/C36 -> 0.40811725 | D71: =D16/D36 -> 0.33511206 | E71: =E16/E36 -> 0.39515455 | F71: =F16/F36 -> 0.45740905 | G71: 0.45 | H71: 0.45 | I71: 0.45 | J71: 0.45 | K71: 0.45

Sheet Cash Flow
A1: AMD - Cash Flow Statement
A2: USD millions. Historical lines condensed from reported statements; projections derived from Income Statement and Balance Sheet.
A4: USD millions | C4: FY2022A | D4: FY2023A | E4: FY2024A | F4: FY2025A | G4: FY2026E | H4: FY2027E | I4: FY2028E | J4: FY2029E | K4: FY2030E
A5: OPERATING ACTIVITIES
A6: Net income | C6: ='Income Statement'!C56 -> 1320 | D6: ='Income Statement'!D56 -> 854 | E6: ='Income Statement'!E56 -> 1641 | F6: ='Income Statement'!F56 -> 4335 | G6: ='Income Statement'!G56 -> 7666.5751 | H6: ='Income Statement'!H56 -> 14233.881 | I6: ='Income Statement'!I56 -> 20921.51 | J6: ='Income Statement'!J56 -> 26952.504 | K6: ='Income Statement'!K56 -> 31649.779
A7: (Income) loss from discontinued operations | C7: =-'Income Statement'!C55 -> 0 | D7: =-'Income Statement'!D55 -> 0 | E7: =-'Income Statement'!E55 -> 0 | F7: =-'Income Statement'!F55 -> -66 | G7: =-'Income Statement'!G55 -> 0 | H7: =-'Income Statement'!H55 -> 0 | I7: =-'Income Statement'!I55 -> 0 | J7: =-'Income Statement'!J55 -> 0 | K7: =-'Income Statement'!K55 -> 0
A8: Depreciation & amortization (ex-intangibles) | C8: ='Income Statement'!C35 -> 626 | D8: ='Income Statement'!D35 -> 642 | E8: ='Income Statement'!E35 -> 671 | F8: ='Income Statement'!F35 -> 750 | G8: ='Income Statement'!G35 -> 989.51 | H8: ='Income Statement'!H35 -> 1382.3428 | I8: ='Income Statement'!I35 -> 1748.3433 | J8: ='Income Statement'!J35 -> 2053.5715 | K8: ='Income Statement'!K35 -> 2290.2267
A9: Amortization of acquisition-related intangibles | B9: FY24 CF shows 2,393 | C9: 3548 | D9: 2811 | E9: 2393 | F9: 2254 | G9: ='Income Statement'!G36 -> 2100 | H9: ='Income Statement'!H36 -> 1900 | I9: ='Income Statement'!I36 -> 1700 | J9: ='Income Statement'!J36 -> 1500 | K9: ='Income Statement'!K36 -> 1300
A10: Stock-based compensation | C10: ='Income Statement'!C40 -> 1081 | D10: ='Income Statement'!D40 -> 1384 | E10: ='Income Statement'!E40 -> 1407 | F10: ='Income Statement'!F40 -> 1638 | G10: ='Income Statement'!G40 -> 1979.02 | H10: ='Income Statement'!H40 -> 2419.0999 | I10: ='Income Statement'!I40 -> 2797.3493 | J10: ='Income Statement'!J40 -> 3080.3572 | K10: ='Income Statement'!K40 -> 3435.34
A11: Deferred income taxes | C11: -1505 | D11: -1019 | E11: -1163 | F11: 248 | G11: 0 | H11: 0 | I11: 0 | J11: 0 | K11: 0
A12: Other non-cash items | C12: 341 | D12: 44 | E12: 190 | F12: -288 | G12: 0 | H12: 0 | I12: 0 | J12: 0 | K12: 0
A13: Changes in working capital
A14: Accounts receivable | C14: -1091 | D14: -1339 | E14: -1865 | F14: -121 | G14: =-('Balance Sheet'!G16-'Balance Sheet'!F16) -> -2089.0575 | H14: =-('Balance Sheet'!H16-'Balance Sheet'!G16) -> -3336.3882 | I14: =-('Balance Sheet'!I16-'Balance Sheet'!H16) -> -3108.4978 | J14: =-('Balance Sheet'!J16-'Balance Sheet'!I16) -> -2592.3485 | K14: =-('Balance Sheet'!K16-'Balance Sheet'!J16) -> -2009.9483
A15: Inventories | C15: -1401 | D15: -580 | E15: -1458 | F15: -2189 | G15: =-('Balance Sheet'!G17-'Balance Sheet'!F17) -> -1331.2408 | H15: =-('Balance Sheet'!H17-'Balance Sheet'!G17) -> -2252.5024 | I15: =-('Balance Sheet'!I17-'Balance Sheet'!H17) -> -1818.3936 | J15: =-('Balance Sheet'!J17-'Balance Sheet'!I17) -> -1531.0925 | K15: =-('Balance Sheet'!K17-'Balance Sheet'!J17) -> -1021.4926
A16: Prepaid expenses & other assets | C16: -1210 | D16: -383 | E16: 339 | F16: -11 | G16: =-('Balance Sheet'!G18-'Balance Sheet'!F18) -> -561.1525 | H16: =-('Balance Sheet'!H18-'Balance Sheet'!G18) -> -1080.2902 | I16: =-('Balance Sheet'!I18-'Balance Sheet'!H18) -> -1006.5015 | J16: =-('Balance Sheet'!J18-'Balance Sheet'!I18) -> -839.37735 | K16: =-('Balance Sheet'!K18-'Balance Sheet'!J18) -> -650.8018
A17: Accounts payable (incl. related parties) | C17: 1310 | D17: -526 | E17: 3 | F17: 410 | G17: ='Balance Sheet'!G29-'Balance Sheet'!F29 -> 1388.2457 | H17: ='Balance Sheet'!H29-'Balance Sheet'!G29 -> 1647.6582 | I17: ='Balance Sheet'!I29-'Balance Sheet'!H29 -> 1495.4927 | J17: ='Balance Sheet'!J29-'Balance Sheet'!I29 -> 1203.9872 | K17: ='Balance Sheet'!K29-'Balance Sheet'!J29 -> 998.49043
A18: Accrued & other liabilities | C18: 546 | D18: -221 | E18: 883 | F18: -467 | G18: ='Balance Sheet'!G30-'Balance Sheet'!F30+'Balance Sheet'!G32-'Balance Sheet'!F32 -> 2115.6535 | H18: ='Balance Sheet'!H30-'Balance Sheet'!G30+'Balance Sheet'!H32-'Balance Sheet'!G32 -> 3083.7375 | I18: ='Balance Sheet'!I30-'Balance Sheet'!H30+'Balance Sheet'!I32-'Balance Sheet'!H32 -> 2873.1043 | J18: ='Balance Sheet'!J30-'Balance Sheet'!I30+'Balance Sheet'!J32-'Balance Sheet'!I32 -> 2396.0408 | K18: ='Balance Sheet'!K30-'Balance Sheet'!J30+'Balance Sheet'!K32-'Balance Sheet'!J32 -> 1857.7433
A19: Cash from operations - continuing | C19: =SUM(C6:C12)+SUM(C14:C18) -> 3565 | D19: =SUM(D6:D12)+SUM(D14:D18) -> 1667 | E19: =SUM(E6:E12)+SUM(E14:E18) -> 3041 | F19: =SUM(F6:F12)+SUM(F14:F18) -> 6493 | G19: =SUM(G6:G12)+SUM(G14:G18) -> 12257.553 | H19: =SUM(H6:H12)+SUM(H14:H18) -> 17997.539 | I19: =SUM(I6:I12)+SUM(I14:I18) -> 25602.407 | J19: =SUM(J6:J12)+SUM(J14:J18) -> 32223.642 | K19: =SUM(K6:K12)+SUM(K14:K18) -> 37849.337
A20: Cash from operations - discontinued | C20: 0 | D20: 0 | E20: 0 | F20: 1216 | G20: 0 | H20: 0 | I20: 0 | J20: 0 | K20: 0
A21: CASH FROM OPERATIONS | C21: =C19+C20 -> 3565 | D21: =D19+D20 -> 1667 | E21: =E19+E20 -> 3041 | F21: =F19+F20 -> 7709 | G21: =G19+G20 -> 12257.553 | H21: =H19+H20 -> 17997.539 | I21: =I19+I20 -> 25602.407 | J21: =J19+J20 -> 32223.642 | K21: =K19+K20 -> 37849.337
A23: INVESTING ACTIVITIES
A24: Capital expenditures | C24: -450 | D24: -546 | E24: -636 | F24: -974 | G24: =-'Income Statement'!G10*Scenarios!G81 -> -2473.775 | H24: =-'Income Statement'!H10*Scenarios!H81 -> -3110.2713 | I24: =-'Income Statement'!I10*Scenarios!I81 -> -3496.6867 | J24: =-'Income Statement'!J10*Scenarios!J81 -> -3593.7501 | K24: =-'Income Statement'!K10*Scenarios!K81 -> -4007.8967
A25: Net (purchases) / maturities of ST investments | C25: 1643 | D25: -735 | E25: 539 | F25: -3625 | G25: =-('Balance Sheet'!G15-'Balance Sheet'!F15) -> 0 | H25: =-('Balance Sheet'!H15-'Balance Sheet'!G15) -> 0 | I25: =-('Balance Sheet'!I15-'Balance Sheet'!H15) -> 0 | J25: =-('Balance Sheet'!J15-'Balance Sheet'!I15) -> 0 | K25: =-('Balance Sheet'!K15-'Balance Sheet'!J15) -> 0
A26: Acquisitions, net (FY22 incl. +2,366 Xilinx cash acquired) | C26: 822 | D26: -131 | E26: -548 | F26: -1760 | G26: 0 | H26: 0 | I26: 0 | J26: 0 | K26: 0
A27: Strategic / LT investments & other | B27: FY26E incl. post-Q2 commitments | C27: -16 | D27: -11 | E27: -456 | F27: -492 | G27: -3000 | H27: -1500 | I27: -1000 | J27: -1000 | K27: -1000
A28: Investing - discontinued ops (ZT divestiture) | C28: 0 | D28: 0 | E28: 0 | F28: 1318 | G28: 0 | H28: 0 | I28: 0 | J28: 0 | K28: 0
A29: CASH FROM INVESTING | C29: =SUM(C24:C28) -> 1999 | D29: =SUM(D24:D28) -> -1423 | E29: =SUM(E24:E28) -> -1101 | F29: =SUM(F24:F28) -> -5533 | G29: =SUM(G24:G28) -> -5473.775 | H29: =SUM(H24:H28) -> -4610.2713 | I29: =SUM(I24:I28) -> -4496.6867 | J29: =SUM(J24:J28) -> -4593.7501 | K29: =SUM(K24:K28) -> -5007.8967
A31: FREE CASH FLOW (CFO continuing + capex) | B31: AMD definition | C31: =C19+C24 -> 3115 | D31: =D19+D24 -> 1121 | E31: =E19+E24 -> 2405 | F31: =F19+F24 -> 5519 | G31: =G19+G24 -> 9783.7785 | H31: =H19+H24 -> 14887.267 | I31: =I19+I24 -> 22105.721 | J31: =J19+J24 -> 28629.892 | K31: =K19+K24 -> 33841.44
A32: FCF margin % | C32: =C31/'Income Statement'!C10 -> 0.13198593 | D32: =D31/'Income Statement'!D10 -> 0.049426808 | E32: =E31/'Income Statement'!E10 -> 0.093271282 | F32: =F31/'Income Statement'!F10 -> 0.15932908 | G32: =G31/'Income Statement'!G10 -> 0.19774997 | H32: =H31/'Income Statement'!H10 -> 0.21539183 | I32: =I31/'Income Statement'!I10 -> 0.2528762 | J32: =J31/'Income Statement'!J10 -> 0.27883025 | K32: =K31/'Income Statement'!K10 -> 0.29552918
A34: FINANCING ACTIVITIES
A35: Debt issuance | C35: 991 | D35: 0 | E35: 0 | F35: 2441 | G35: 0 | H35: 0 | I35: 0 | J35: 0 | K35: 0
A36: Debt repayment | C36: -312 | D36: 0 | E36: -750 | F36: -950 | G36: 0 | H36: 0 | I36: 0 | J36: 0 | K36: 0
A37: Proceeds from employee equity plans | C37: 167 | D37: 268 | E37: 279 | F37: 285 | G37: 300 | H37: 300 | I37: 300 | J37: 300 | K37: 300
A38: Repurchases of common stock | C38: -3702 | D38: -985 | E38: -862 | F38: -1316 | G38: =-MAX(0,G31)*G49 -> -4891.8892 | H38: =-MAX(0,H31)*H49 -> -7443.6336 | I38: =-MAX(0,I31)*I49 -> -11052.86 | J38: =-MAX(0,J31)*J49 -> -14314.946 | K38: =-MAX(0,K31)*K49 -> -16920.72
A39: Tax withholding on employee equity plans | C39: -406 | D39: -427 | E39: -728 | F39: -607 | G39: -650 | H39: -650 | I39: -650 | J39: -650 | K39: -650
A40: Other financing (FY25: contingent consideration) | C40: -2 | D40: -2 | E40: -1 | F40: -284 | G40: 0 | H40: 0 | I40: 0 | J40: 0 | K40: 0
A41: CASH FROM FINANCING | C41: =SUM(C35:C40) -> -3264 | D41: =SUM(D35:D40) -> -1146 | E41: =SUM(E35:E40) -> -2062 | F41: =SUM(F35:F40) -> -431 | G41: =SUM(G35:G40) -> -5241.8892 | H41: =SUM(H35:H40) -> -7793.6336 | I41: =SUM(I35:I40) -> -11402.86 | J41: =SUM(J35:J40) -> -14664.946 | K41: =SUM(K35:K40) -> -17270.72
A43: NET CHANGE IN CASH | C43: =C21+C29+C41 -> 2300 | D43: =D21+D29+D41 -> -902 | E43: =E21+E29+E41 -> -122 | F43: =F21+F29+F41 -> 1745 | G43: =G21+G29+G41 -> 1541.8892 | H43: =H21+H29+H41 -> 5593.6336 | I43: =I21+I29+I41 -> 9702.8603 | J43: =J21+J29+J41 -> 12964.946 | K43: =K21+K29+K41 -> 15570.72
A44: Beginning cash (incl. restricted, hist.) | B44: FY26E starts from BS cash | C44: 2535 | D44: =C45 -> 4835 | E44: =D45 -> 3933 | F44: =E45 -> 3811 | G44: ='Balance Sheet'!F14 -> 5539 | H44: =G45 -> 7080.8892 | I44: =H45 -> 12674.523 | J44: =I45 -> 22377.383 | K44: =J45 -> 35342.329
A45: Ending cash | C45: =C44+C43 -> 4835 | D45: =D44+D43 -> 3933 | E45: =E44+E43 -> 3811 | F45: =F44+F43 -> 5556 | G45: =G44+G43 -> 7080.8892 | H45: =H44+H43 -> 12674.523 | I45: =I44+I43 -> 22377.383 | J45: =J44+J43 -> 35342.329 | K45: =K44+K43 -> 50913.049
A46: Memo: restricted cash (CF ending - BS cash) | C46: =C45-'Balance Sheet'!C14 -> 0 | D46: =D45-'Balance Sheet'!D14 -> 0 | E46: =E45-'Balance Sheet'!E14 -> 24 | F46: =F45-'Balance Sheet'!F14 -> 17 | G46: =G45-'Balance Sheet'!G14 -> 0 | H46: =H45-'Balance Sheet'!H14 -> 0 | I46: =I45-'Balance Sheet'!I14 -> 0 | J46: =J45-'Balance Sheet'!J14 -> 0 | K46: =K45-'Balance Sheet'!K14 -> 0
A48: Projection inputs
A49: Buybacks as % of free cash flow | G49: 0.5 | H49: 0.5 | I49: 0.5 | J49: 0.5 | K49: 0.5

Sheet Balance Sheet
A1: AMD - Balance Sheet
A2: USD millions, fiscal year-end. FY2022-FY2023 related-party receivables/payables, ROU assets and equity-method investments folded into 'other' lines.
A4: USD millions | C4: FY2022A | D4: FY2023A | E4: FY2024A | F4: FY2025A | G4: FY2026E | H4: FY2027E | I4: FY2028E | J4: FY2029E | K4: FY2030E
A5: Working-capital drivers
A6: DSO (receivables / revenue x 365) | C6: =C16/'Income Statement'!C10*365 -> 63.810432 | D6: =D16/'Income Statement'!D10*365 -> 69.57209 | E6: =E16/'Income Statement'!E10*365 -> 87.65096 | F6: =F16/'Income Statement'!F10*365 -> 66.54277 | G6: 62 | H6: 62 | I6: 62 | J6: 62 | K6: 62
A7: DIO (inventory / cost of sales ex-amort. x 365) | C7: =C17/'Income Statement'!C15*365 -> 119.17013 | D7: =D17/'Income Statement'!D15*365 -> 140.8153 | E7: =E17/'Income Statement'!E15*365 -> 172.76787 | F7: =F17/'Income Statement'!F15*365 -> 175.66845 | G7: 150 | H7: 135 | I7: 125 | J7: 120 | K7: 115
A8: DPO (payables / cost of sales ex-amort. x 365) | C8: =C29/'Income Statement'!C15*365 -> 78.783117 | D8: =D29/'Income Statement'!D15*365 -> 66.507803 | E8: =E29/'Income Statement'!E15*365 -> 74.301634 | F8: =F29/'Income Statement'!F15*365 -> 64.966274 | G8: 70 | H8: 70 | I8: 70 | J8: 70 | K8: 70
A9: Prepaid & other current assets % revenue | C9: =C18/'Income Statement'!C10 -> 0.053684166 | D9: =D18/'Income Statement'!D10 -> 0.10233686 | E9: =E18/'Income Statement'!E10 -> 0.077215435 | F9: =F18/'Income Statement'!F10 -> 0.062357458 | G9: 0.055 | H9: 0.055 | I9: 0.055 | J9: 0.055 | K9: 0.055
A10: Accrued liabilities % revenue | C10: =C30/'Income Statement'!C10 -> 0.14999364 | D10: =D30/'Income Statement'!D10 -> 0.15189594 | E10: =E30/'Income Statement'!E10 -> 0.16521233 | F10: =F30/'Income Statement'!F10 -> 0.15156327 | G10: 0.145 | H10: 0.145 | I10: 0.145 | J10: 0.145 | K10: 0.145
A11: Other current liabilities % revenue | C11: =C32/'Income Statement'!C10 -> 0.014236685 | D11: =D32/'Income Statement'!D10 -> 0.019312169 | E11: =E32/'Income Statement'!E10 -> 0.021524142 | F11: =F32/'Income Statement'!F10 -> 0.011605416 | G11: 0.012 | H11: 0.012 | I11: 0.012 | J11: 0.012 | K11: 0.012
A13: ASSETS
A14: Cash and cash equivalents | C14: 4835 | D14: 3933 | E14: 3787 | F14: 5539 | G14: ='Cash Flow'!G45 -> 7080.8892 | H14: ='Cash Flow'!H45 -> 12674.523 | I14: ='Cash Flow'!I45 -> 22377.383 | J14: ='Cash Flow'!J45 -> 35342.329 | K14: ='Cash Flow'!K45 -> 50913.049
A15: Short-term investments | C15: 1020 | D15: 1840 | E15: 1345 | F15: 5013 | G15: =F15 -> 5013 | H15: =G15 -> 5013 | I15: =H15 -> 5013 | J15: =I15 -> 5013 | K15: =J15 -> 5013
A16: Accounts receivable, net | B16: FY23 as recast | C16: 4126 | D16: 4323 | E16: 6192 | F16: 6315 | G16: ='Income Statement'!G10*G6/365 -> 8404.0575 | H16: ='Income Statement'!H10*H6/365 -> 11740.446 | I16: ='Income Statement'!I10*I6/365 -> 14848.943 | J16: ='Income Statement'!J10*J6/365 -> 17441.292 | K16: ='Income Statement'!K10*K6/365 -> 19451.24
A17: Inventories | C17: 3771 | D17: 4351 | E17: 5734 | F17: 7920 | G17: ='Income Statement'!G15*G7/365 -> 9251.2408 | H17: ='Income Statement'!H15*H7/365 -> 11503.743 | I17: ='Income Statement'!I15*I7/365 -> 13322.137 | J17: ='Income Statement'!J15*J7/365 -> 14853.229 | K17: ='Income Statement'!K15*K7/365 -> 15874.722
A18: Prepaid expenses & other current assets | C18: 1267 | D18: 2321 | E18: 1991 | F18: 2160 | G18: ='Income Statement'!G10*G9 -> 2721.1525 | H18: ='Income Statement'!H10*H9 -> 3801.4427 | I18: ='Income Statement'!I10*I9 -> 4807.9442 | J18: ='Income Statement'!J10*J9 -> 5647.3215 | K18: ='Income Statement'!K10*K9 -> 6298.1233
A19: Total current assets | C19: =SUM(C14:C18) -> 15019 | D19: =SUM(D14:D18) -> 16768 | E19: =SUM(E14:E18) -> 19049 | F19: =SUM(F14:F18) -> 26947 | G19: =SUM(G14:G18) -> 32470.34 | H19: =SUM(H14:H18) -> 44733.154 | I19: =SUM(I14:I18) -> 60369.408 | J19: =SUM(J14:J18) -> 78297.172 | K19: =SUM(K14:K18) -> 97550.135
A20: Property and equipment, net | C20: 1513 | D20: 1589 | E20: 1802 | F20: 2312 | G20: =F20-'Cash Flow'!G24-'Income Statement'!G35 -> 3796.265 | H20: =G20-'Cash Flow'!H24-'Income Statement'!H35 -> 5524.1935 | I20: =H20-'Cash Flow'!I24-'Income Statement'!I35 -> 7272.5368 | J20: =I20-'Cash Flow'!J24-'Income Statement'!J35 -> 8812.7154 | K20: =J20-'Cash Flow'!K24-'Income Statement'!K35 -> 10530.385
A21: Goodwill | C21: 24177 | D21: 24262 | E21: 24839 | F21: 25126 | G21: =F21 -> 25126 | H21: =G21 -> 25126 | I21: =H21 -> 25126 | J21: =I21 -> 25126 | K21: =J21 -> 25126
A22: Acquisition-related intangibles, net | C22: 24118 | D22: 21363 | E22: 18930 | F22: 16705 | G22: =F22-'Income Statement'!G36 -> 14605 | H22: =G22-'Income Statement'!H36 -> 12705 | I22: =H22-'Income Statement'!I36 -> 11005 | J22: =I22-'Income Statement'!J36 -> 9505 | K22: =J22-'Income Statement'!K36 -> 8205
A23: Deferred tax assets | C23: 58 | D23: 366 | E23: 688 | F23: 384 | G23: =F23 -> 384 | H23: =G23 -> 384 | I23: =H23 -> 384 | J23: =I23 -> 384 | K23: =J23 -> 384
A24: Other non-current assets (incl. ROU, equity-method, LT investments) | C24: 2695 | D24: 3537 | E24: 3918 | F24: 5452 | G24: =F24-'Cash Flow'!G27 -> 8452 | H24: =G24-'Cash Flow'!H27 -> 9952 | I24: =H24-'Cash Flow'!I27 -> 10952 | J24: =I24-'Cash Flow'!J27 -> 11952 | K24: =J24-'Cash Flow'!K27 -> 12952
A25: Total non-current assets | C25: =SUM(C20:C24) -> 52561 | D25: =SUM(D20:D24) -> 51117 | E25: =SUM(E20:E24) -> 50177 | F25: =SUM(F20:F24) -> 49979 | G25: =SUM(G20:G24) -> 52363.265 | H25: =SUM(H20:H24) -> 53691.194 | I25: =SUM(I20:I24) -> 54739.537 | J25: =SUM(J20:J24) -> 55779.715 | K25: =SUM(K20:K24) -> 57197.385
A26: TOTAL ASSETS | C26: =C19+C25 -> 67580 | D26: =D19+D25 -> 67885 | E26: =E19+E25 -> 69226 | F26: =F19+F25 -> 76926 | G26: =G19+G25 -> 84833.605 | H26: =H19+H25 -> 98424.348 | I26: =I19+I25 -> 115108.94 | J26: =J19+J25 -> 134076.89 | K26: =K19+K25 -> 154747.52
A28: LIABILITIES
A29: Accounts payable | C29: 2493 | D29: 2055 | E29: 2466 | F29: 2929 | G29: ='Income Statement'!G15*G8/365 -> 4317.2457 | H29: ='Income Statement'!H15*H8/365 -> 5964.9039 | I29: ='Income Statement'!I15*I8/365 -> 7460.3966 | J29: ='Income Statement'!J15*J8/365 -> 8664.3837 | K29: ='Income Statement'!K15*K8/365 -> 9662.8742
A30: Accrued liabilities (incl. related-party payables) | C30: 3540 | D30: 3445 | E30: 4260 | F30: 5250 | G30: ='Income Statement'!G10*G10 -> 7173.9475 | H30: ='Income Statement'!H10*H10 -> 10021.985 | I30: ='Income Statement'!I10*I10 -> 12675.489 | J30: ='Income Statement'!J10*J10 -> 14888.393 | K30: ='Income Statement'!K10*K10 -> 16604.143
A31: Current portion of long-term debt | C31: 0 | D31: 751 | E31: 0 | F31: 874 | G31: =F31 -> 874 | H31: =G31 -> 874 | I31: =H31 -> 874 | J31: =I31 -> 874 | K31: =J31 -> 874
A32: Other current liabilities | C32: 336 | D32: 438 | E32: 555 | F32: 402 | G32: ='Income Statement'!G10*G11 -> 593.706 | H32: ='Income Statement'!H10*H11 -> 829.40568 | I32: ='Income Statement'!I10*I11 -> 1049.006 | J32: ='Income Statement'!J10*J11 -> 1232.1429 | K32: ='Income Statement'!K10*K11 -> 1374.136
A33: Total current liabilities | C33: =SUM(C29:C32) -> 6369 | D33: =SUM(D29:D32) -> 6689 | E33: =SUM(E29:E32) -> 7281 | F33: =SUM(F29:F32) -> 9455 | G33: =SUM(G29:G32) -> 12958.899 | H33: =SUM(H29:H32) -> 17690.295 | I33: =SUM(I29:I32) -> 22058.892 | J33: =SUM(J29:J32) -> 25658.92 | K33: =SUM(K29:K32) -> 28515.154
A34: Long-term debt, net of current portion | C34: 2467 | D34: 1717 | E34: 1721 | F34: 2348 | G34: =F34+'Cash Flow'!G35+'Cash Flow'!G36 -> 2348 | H34: =G34+'Cash Flow'!H35+'Cash Flow'!H36 -> 2348 | I34: =H34+'Cash Flow'!I35+'Cash Flow'!I36 -> 2348 | J34: =I34+'Cash Flow'!J35+'Cash Flow'!J36 -> 2348 | K34: =J34+'Cash Flow'!K35+'Cash Flow'!K36 -> 2348
A35: Long-term operating lease liabilities | C35: 396 | D35: 535 | E35: 491 | F35: 625 | G35: =F35 -> 625 | H35: =G35 -> 625 | I35: =H35 -> 625 | J35: =I35 -> 625 | K35: =J35 -> 625
A36: Deferred tax liabilities | C36: 1934 | D36: 1202 | E36: 349 | F36: 313 | G36: =F36 -> 313 | H36: =G36 -> 313 | I36: =H36 -> 313 | J36: =I36 -> 313 | K36: =J36 -> 313
A37: Other long-term liabilities | C37: 1664 | D37: 1850 | E37: 1816 | F37: 1186 | G37: =F37 -> 1186 | H37: =G37 -> 1186 | I37: =H37 -> 1186 | J37: =I37 -> 1186 | K37: =J37 -> 1186
A38: Total non-current liabilities | C38: =SUM(C34:C37) -> 6461 | D38: =SUM(D34:D37) -> 5304 | E38: =SUM(E34:E37) -> 4377 | F38: =SUM(F34:F37) -> 4472 | G38: =SUM(G34:G37) -> 4472 | H38: =SUM(H34:H37) -> 4472 | I38: =SUM(I34:I37) -> 4472 | J38: =SUM(J34:J37) -> 4472 | K38: =SUM(K34:K37) -> 4472
A39: TOTAL LIABILITIES | C39: =C33+C38 -> 12830 | D39: =D33+D38 -> 11993 | E39: =E33+E38 -> 11658 | F39: =F33+F38 -> 13927 | G39: =G33+G38 -> 17430.899 | H39: =H33+H38 -> 22162.295 | I39: =I33+I38 -> 26530.892 | J39: =J33+J38 -> 30130.92 | K39: =K33+K38 -> 32987.154
A41: STOCKHOLDERS' EQUITY
A42: Common stock, par value | C42: 16 | D42: 17 | E42: 17 | F42: 17 | G42: =F42 -> 17 | H42: =G42 -> 17 | I42: =H42 -> 17 | J42: =I42 -> 17 | K42: =J42 -> 17
A43: Additional paid-in capital | C43: 58005 | D43: 59676 | E43: 61362 | F43: 63365 | G43: =F43+'Income Statement'!G40+'Cash Flow'!G37+'Cash Flow'!G39 -> 64994.02 | H43: =G43+'Income Statement'!H40+'Cash Flow'!H37+'Cash Flow'!H39 -> 67063.12 | I43: =H43+'Income Statement'!I40+'Cash Flow'!I37+'Cash Flow'!I39 -> 69510.469 | J43: =I43+'Income Statement'!J40+'Cash Flow'!J37+'Cash Flow'!J39 -> 72240.826 | K43: =J43+'Income Statement'!K40+'Cash Flow'!K37+'Cash Flow'!K39 -> 75326.166
A44: Treasury stock, at cost | C44: -3099 | D44: -4514 | E44: -6106 | F44: -7079 | G44: =F44+'Cash Flow'!G38 -> -11970.889 | H44: =G44+'Cash Flow'!H38 -> -19414.523 | I44: =H44+'Cash Flow'!I38 -> -30467.383 | J44: =I44+'Cash Flow'!J38 -> -44782.329 | K44: =J44+'Cash Flow'!K38 -> -61703.049
A45: Retained earnings (accumulated deficit) | C45: -131 | D45: 723 | E45: 2364 | F45: 6699 | G45: =F45+'Income Statement'!G56 -> 14365.575 | H45: =G45+'Income Statement'!H56 -> 28599.456 | I45: =H45+'Income Statement'!I56 -> 49520.967 | J45: =I45+'Income Statement'!J56 -> 76473.47 | K45: =J45+'Income Statement'!K56 -> 108123.25
A46: Accumulated other comprehensive income (loss) | C46: -41 | D46: -10 | E46: -69 | F46: -3 | G46: =F46 -> -3 | H46: =G46 -> -3 | I46: =H46 -> -3 | J46: =I46 -> -3 | K46: =J46 -> -3
A47: TOTAL STOCKHOLDERS' EQUITY | C47: =SUM(C42:C46) -> 54750 | D47: =SUM(D42:D46) -> 55892 | E47: =SUM(E42:E46) -> 57568 | F47: =SUM(F42:F46) -> 62999 | G47: =SUM(G42:G46) -> 67402.706 | H47: =SUM(H42:H46) -> 76262.053 | I47: =SUM(I42:I46) -> 88578.053 | J47: =SUM(J42:J46) -> 103945.97 | K47: =SUM(K42:K46) -> 121760.37
A48: TOTAL LIABILITIES + EQUITY | C48: =C39+C47 -> 67580 | D48: =D39+D47 -> 67885 | E48: =E39+E47 -> 69226 | F48: =F39+F47 -> 76926 | G48: =G39+G47 -> 84833.605 | H48: =H39+H47 -> 98424.348 | I48: =I39+I47 -> 115108.94 | J48: =J39+J47 -> 134076.89 | K48: =K39+K47 -> 154747.52
A49: BALANCE CHECK (assets - liabilities - equity) | C49: =ROUND(C26-C48,3) -> 0 | D49: =ROUND(D26-D48,3) -> 0 | E49: =ROUND(E26-E48,3) -> 0 | F49: =ROUND(F26-F48,3) -> 0 | G49: =ROUND(G26-G48,3) -> 0 | H49: =ROUND(H26-H48,3) -> 0 | I49: =ROUND(I26-I48,3) -> 0 | J49: =ROUND(J26-J48,3) -> 0 | K49: =ROUND(K26-K48,3) -> 0
A51: Memo
A52: Total debt | C52: =C31+C34 -> 2467 | D52: =D31+D34 -> 2468 | E52: =E31+E34 -> 1721 | F52: =F31+F34 -> 3222 | G52: =G31+G34 -> 3222 | H52: =H31+H34 -> 3222 | I52: =I31+I34 -> 3222 | J52: =J31+J34 -> 3222 | K52: =K31+K34 -> 3222
A53: Net cash (cash + ST investments - debt) | C53: =C14+C15-C52 -> 3388 | D53: =D14+D15-D52 -> 3305 | E53: =E14+E15-E52 -> 3411 | F53: =F14+F15-F52 -> 7330 | G53: =G14+G15-G52 -> 8871.8892 | H53: =H14+H15-H52 -> 14465.523 | I53: =I14+I15-I52 -> 24168.383 | J53: =J14+J15-J52 -> 37133.329 | K53: =K14+K15-K52 -> 52704.049
A54: Operating NWC (AR + inv + prepaid - AP - accrued - OCL) | C54: =C16+C17+C18-C29-C30-C32 -> 2795 | D54: =D16+D17+D18-D29-D30-D32 -> 5057 | E54: =E16+E17+E18-E29-E30-E32 -> 6636 | F54: =F16+F17+F18-F29-F30-F32 -> 7814 | G54: =G16+G17+G18-G29-G30-G32 -> 8291.5516 | H54: =H16+H17+H18-H29-H30-H32 -> 10229.337 | I54: =I16+I17+I18-I29-I30-I32 -> 11794.133 | J54: =J16+J17+J18-J29-J30-J32 -> 13156.923 | K54: =K16+K17+K18-K29-K30-K32 -> 13982.932
A55: Debt / equity | C55: =C52/C47 -> 0.045059361 | D55: =D52/D47 -> 0.044156588 | E55: =E52/E47 -> 0.029895081 | F55: =F52/F47 -> 0.051143669 | G55: =G52/G47 -> 0.047802235 | H55: =H52/H47 -> 0.042249059 | I55: =I52/I47 -> 0.036374699 | J55: =J52/J47 -> 0.030996873 | K55: =K52/K47 -> 0.026461813
A56: Current ratio | C56: =C19/C33 -> 2.358141 | D56: =D19/D33 -> 2.5068022 | E56: =E19/E33 -> 2.6162615 | F56: =F19/F33 -> 2.8500264 | G56: =G19/G33 -> 2.5056403 | H56: =H19/H33 -> 2.5286834 | I56: =I19/I33 -> 2.736738 | J56: =J19/J33 -> 3.0514602 | K56: =K19/K33 -> 3.4209928
A57: ROIC (NOPAT / (equity + debt - cash - STI)) | C57: ='Income Statement'!C32*(1-0.15)/(C47+C52-C14-C15) -> 0.020918189 | D57: ='Income Statement'!D32*(1-0.15)/(D47+D52-D14-D15) -> 0.0064816399 | E57: ='Income Statement'!E32*(1-0.15)/(E47+E52-E14-E15) -> 0.029820706 | F57: ='Income Statement'!F32*(1-0.15)/(F47+F52-F14-F15) -> 0.056403025 | G57: ='Income Statement'!G32*(1-0.15)/(G47+G52-G14-G15) -> 0.12397995 | H57: ='Income Statement'!H32*(1-0.15)/(H47+H52-H14-H15) -> 0.22579966 | I57: ='Income Statement'!I32*(1-0.15)/(I47+I52-I14-I15) -> 0.3178848 | J57: ='Income Statement'!J32*(1-0.15)/(J47+J52-J14-J15) -> 0.39239863 | K57: ='Income Statement'!K32*(1-0.15)/(K47+K52-K14-K15) -> 0.44208491

Sheet Scenarios
A1: AMD - Scenario Drivers (Bull / Base / Bear)
A2: Change the selector in C3 to switch the whole model. Live rows feed the Revenue Model, Income Statement and Cash Flow.
A3: Scenario selector (1 = Bull, 2 = Base, 3 = Bear) | C3: 2 | D3: =CHOOSE($C$3,"Bull","Base","Bear") -> Base
A4: Driver / case | G4: FY2026E | H4: FY2027E | I4: FY2028E | J4: FY2029E | K4: FY2030E
A5: Server CPU (EPYC) revenue growth
A6: Bull | G6: 0.45 | H6: 0.3 | I6: 0.2 | J6: 0.15 | K6: 0.12
A7: Base | G7: 0.4 | H7: 0.25 | I7: 0.15 | J7: 0.12 | K7: 0.1
A8: Bear | G8: 0.35 | H8: 0.12 | I8: 0.06 | J8: 0.05 | K8: 0.04
A9: Live (selected) | G9: =CHOOSE($C$3,G6,G7,G8) -> 0.4 | H9: =CHOOSE($C$3,H6,H7,H8) -> 0.25 | I9: =CHOOSE($C$3,I6,I7,I8) -> 0.15 | J9: =CHOOSE($C$3,J6,J7,J8) -> 0.12 | K9: =CHOOSE($C$3,K6,K7,K8) -> 0.1
A11: Data Center GPU (Instinct) revenue growth
A12: Bull | G12: 1.55 | H12: 1.2 | I12: 0.6 | J12: 0.35 | K12: 0.2
A13: Base | G13: 1.4 | H13: 0.9 | I13: 0.45 | J13: 0.25 | K13: 0.15
A14: Bear | G14: 1.25 | H14: 0.4 | I14: 0.15 | J14: 0.08 | K14: 0.05
A15: Live (selected) | G15: =CHOOSE($C$3,G12,G13,G14) -> 1.4 | H15: =CHOOSE($C$3,H12,H13,H14) -> 0.9 | I15: =CHOOSE($C$3,I12,I13,I14) -> 0.45 | J15: =CHOOSE($C$3,J12,J13,J14) -> 0.25 | K15: =CHOOSE($C$3,K12,K13,K14) -> 0.15
A17: DC networking, rack-scale & other growth
A18: Bull | G18: 1.75 | H18: 1.2 | I18: 0.7 | J18: 0.4 | K18: 0.25
A19: Base | G19: 1.5 | H19: 1 | I19: 0.5 | J19: 0.3 | K19: 0.2
A20: Bear | G20: 1 | H20: 0.5 | I20: 0.2 | J20: 0.1 | K20: 0.05
A21: Live (selected) | G21: =CHOOSE($C$3,G18,G19,G20) -> 1.5 | H21: =CHOOSE($C$3,H18,H19,H20) -> 1 | I21: =CHOOSE($C$3,I18,I19,I20) -> 0.5 | J21: =CHOOSE($C$3,J18,J19,J20) -> 0.3 | K21: =CHOOSE($C$3,K18,K19,K20) -> 0.2
A23: Client desktop CPU growth
A24: Bull | G24: 0.17 | H24: 0.1 | I24: 0.08 | J24: 0.07 | K24: 0.06
A25: Base | G25: 0.15 | H25: 0.06 | I25: 0.05 | J25: 0.05 | K25: 0.04
A26: Bear | G26: 0.12 | H26: -0.02 | I26: 0.02 | J26: 0.03 | K26: 0.03
A27: Live (selected) | G27: =CHOOSE($C$3,G24,G25,G26) -> 0.15 | H27: =CHOOSE($C$3,H24,H25,H26) -> 0.06 | I27: =CHOOSE($C$3,I24,I25,I26) -> 0.05 | J27: =CHOOSE($C$3,J24,J25,J26) -> 0.05 | K27: =CHOOSE($C$3,K24,K25,K26) -> 0.04
A29: Client notebook CPU growth
A30: Bull | G30: 0.17 | H30: 0.1 | I30: 0.08 | J30: 0.07 | K30: 0.06
A31: Base | G31: 0.15 | H31: 0.06 | I31: 0.05 | J31: 0.05 | K31: 0.04
A32: Bear | G32: 0.12 | H32: -0.02 | I32: 0.02 | J32: 0.03 | K32: 0.03
A33: Live (selected) | G33: =CHOOSE($C$3,G30,G31,G32) -> 0.15 | H33: =CHOOSE($C$3,H30,H31,H32) -> 0.06 | I33: =CHOOSE($C$3,I30,I31,I32) -> 0.05 | J33: =CHOOSE($C$3,J30,J31,J32) -> 0.05 | K33: =CHOOSE($C$3,K30,K31,K32) -> 0.04
A35: Gaming semi-custom SoC growth
A36: Bull | G36: -0.28 | H36: 0.1 | I36: 0.25 | J36: 0.12 | K36: 0
A37: Base | G37: -0.3 | H37: 0 | I37: 0.2 | J37: 0.1 | K37: -0.05
A38: Bear | G38: -0.32 | H38: -0.1 | I38: 0.05 | J38: 0.05 | K38: -0.1
A39: Live (selected) | G39: =CHOOSE($C$3,G36,G37,G38) -> -0.3 | H39: =CHOOSE($C$3,H36,H37,H38) -> 0 | I39: =CHOOSE($C$3,I36,I37,I38) -> 0.2 | J39: =CHOOSE($C$3,J36,J37,J38) -> 0.1 | K39: =CHOOSE($C$3,K36,K37,K38) -> -0.05
A41: Gaming Radeon discrete GPU growth
A42: Bull | G42: -0.06 | H42: 0.1 | I42: 0.08 | J42: 0.06 | K42: 0.05
A43: Base | G43: -0.08 | H43: 0.05 | I43: 0.04 | J43: 0.03 | K43: 0.03
A44: Bear | G44: -0.12 | H44: 0 | I44: 0 | J44: 0.02 | K44: 0.02
A45: Live (selected) | G45: =CHOOSE($C$3,G42,G43,G44) -> -0.08 | H45: =CHOOSE($C$3,H42,H43,H44) -> 0.05 | I45: =CHOOSE($C$3,I42,I43,I44) -> 0.04 | J45: =CHOOSE($C$3,J42,J43,J44) -> 0.03 | K45: =CHOOSE($C$3,K42,K43,K44) -> 0.03
A47: Embedded FPGA / adaptive SoC growth
A48: Bull | G48: 0.17 | H48: 0.13 | I48: 0.1 | J48: 0.09 | K48: 0.08
A49: Base | G49: 0.15 | H49: 0.1 | I49: 0.08 | J49: 0.07 | K49: 0.06
A50: Bear | G50: 0.12 | H50: 0.05 | I50: 0.04 | J50: 0.04 | K50: 0.04
A51: Live (selected) | G51: =CHOOSE($C$3,G48,G49,G50) -> 0.15 | H51: =CHOOSE($C$3,H48,H49,H50) -> 0.1 | I51: =CHOOSE($C$3,I48,I49,I50) -> 0.08 | J51: =CHOOSE($C$3,J48,J49,J50) -> 0.07 | K51: =CHOOSE($C$3,K48,K49,K50) -> 0.06
A53: Embedded x86 growth
A54: Bull | G54: 0.17 | H54: 0.13 | I54: 0.1 | J54: 0.09 | K54: 0.08
A55: Base | G55: 0.15 | H55: 0.1 | I55: 0.08 | J55: 0.07 | K55: 0.06
A56: Bear | G56: 0.12 | H56: 0.05 | I56: 0.04 | J56: 0.04 | K56: 0.04
A57: Live (selected) | G57: =CHOOSE($C$3,G54,G55,G56) -> 0.15 | H57: =CHOOSE($C$3,H54,H55,H56) -> 0.1 | I57: =CHOOSE($C$3,I54,I55,I56) -> 0.08 | J57: =CHOOSE($C$3,J54,J55,J56) -> 0.07 | K57: =CHOOSE($C$3,K54,K55,K56) -> 0.06
A59: Cost of sales ex-amortization, % of revenue
A60: Bull | G60: 0.45 | H60: 0.44 | I60: 0.43 | J60: 0.425 | K60: 0.425
A61: Base | G61: 0.455 | H61: 0.45 | I61: 0.445 | J61: 0.44 | K61: 0.44
A62: Bear | G62: 0.465 | H62: 0.47 | I62: 0.475 | J62: 0.475 | K62: 0.475
A63: Live (selected) | G63: =CHOOSE($C$3,G60,G61,G62) -> 0.455 | H63: =CHOOSE($C$3,H60,H61,H62) -> 0.45 | I63: =CHOOSE($C$3,I60,I61,I62) -> 0.445 | J63: =CHOOSE($C$3,J60,J61,J62) -> 0.44 | K63: =CHOOSE($C$3,K60,K61,K62) -> 0.44
A65: R&D, % of revenue
A66: Bull | G66: 0.21 | H66: 0.17 | I66: 0.15 | J66: 0.14 | K66: 0.135
A67: Base | G67: 0.215 | H67: 0.185 | I67: 0.17 | J67: 0.16 | K67: 0.155
A68: Bear | G68: 0.225 | H68: 0.21 | I68: 0.2 | J68: 0.195 | K68: 0.19
A69: Live (selected) | G69: =CHOOSE($C$3,G66,G67,G68) -> 0.215 | H69: =CHOOSE($C$3,H66,H67,H68) -> 0.185 | I69: =CHOOSE($C$3,I66,I67,I68) -> 0.17 | J69: =CHOOSE($C$3,J66,J67,J68) -> 0.16 | K69: =CHOOSE($C$3,K66,K67,K68) -> 0.155
A71: MG&A (net of licensing gains), % of revenue
A72: Bull | G72: 0.112 | H72: 0.095 | I72: 0.085 | J72: 0.08 | K72: 0.075
A73: Base | G73: 0.115 | H73: 0.1 | I73: 0.09 | J73: 0.085 | K73: 0.08
A74: Bear | G74: 0.12 | H74: 0.115 | I74: 0.11 | J74: 0.105 | K74: 0.105
A75: Live (selected) | G75: =CHOOSE($C$3,G72,G73,G74) -> 0.115 | H75: =CHOOSE($C$3,H72,H73,H74) -> 0.1 | I75: =CHOOSE($C$3,I72,I73,I74) -> 0.09 | J75: =CHOOSE($C$3,J72,J73,J74) -> 0.085 | K75: =CHOOSE($C$3,K72,K73,K74) -> 0.08
A77: Capex, % of revenue
A78: Bull | G78: 0.05 | H78: 0.045 | I78: 0.04 | J78: 0.035 | K78: 0.035
A79: Base | G79: 0.05 | H79: 0.045 | I79: 0.04 | J79: 0.035 | K79: 0.035
A80: Bear | G80: 0.05 | H80: 0.045 | I80: 0.04 | J80: 0.04 | K80: 0.04
A81: Live (selected) | G81: =CHOOSE($C$3,G78,G79,G80) -> 0.05 | H81: =CHOOSE($C$3,H78,H79,H80) -> 0.045 | I81: =CHOOSE($C$3,I78,I79,I80) -> 0.04 | J81: =CHOOSE($C$3,J78,J79,J80) -> 0.035 | K81: =CHOOSE($C$3,K78,K79,K80) -> 0.035
A84: Scenario outputs - static snapshot from full-model recalculation under each case; 'Live' column follows the selector
A85: Metric | C85: Bull | D85: Base | E85: Bear | F85: Live
A86: FY2026E revenue | C86: 51397.33 | D86: 49475.5 | E86: 47285.33 | F86: ='Revenue Model'!G47 -> 49475.5
A87: FY2030E revenue | C87: 157285.59 | D87: 114511.33 | E87: 65405.859 | F87: ='Revenue Model'!K47 -> 114511.33
A88: Revenue CAGR FY2025A-FY2030E | C88: 0.35339547 | D88: 0.27015472 | E88: 0.13556046 | F88: =('Revenue Model'!K47/'Revenue Model'!F47)^(1/5)-1 -> 0.27015472
A89: FY2030E Data Center revenue | C89: 130079.27 | D89: 90597.834 | E89: 45402.555 | F89: ='Revenue Model'!K12 -> 90597.834
A90: FY2030E gross margin % (GAAP) | C90: 0.57128065 | D90: 0.55489134 | E90: 0.51605585 | F90: ='Income Statement'!K19 -> 0.55489134
A91: FY2026E operating margin % (GAAP) | C91: 0.18714185 | D91: 0.17255475 | E91: 0.14558876 | F91: ='Income Statement'!G33 -> 0.17255475
A92: FY2030E operating margin % (GAAP) | C92: 0.35673478 | D92: 0.31364741 | E92: 0.2101241 | F92: ='Income Statement'!K33 -> 0.31364741
A93: FY2030E EBITDA | C93: 60554.952 | D93: 39506.41 | E93: 16351.465 | F93: ='Income Statement'!K37 -> 39506.41
A94: FY2030E EBITDA margin % | C94: 0.385 | D94: 0.345 | E94: 0.25 | F94: ='Income Statement'!K38 -> 0.345
A95: FY2030E net income | C95: 49181.035 | D95: 31649.779 | E95: 12343.524 | F95: ='Income Statement'!K56 -> 31649.779
A96: FY2030E diluted EPS (USD) | C96: 29.041921 | D96: 18.689529 | E96: 7.2889812 | F96: ='Income Statement'!K65 -> 18.689529
A97: FY2030E approx. non-GAAP EPS (USD) | C97: 32.814544 | D97: 21.559316 | E97: 9.1336906 | F97: ='Income Statement'!K67 -> 21.559316
A98: FY2030E free cash flow | C98: 51020.015 | D98: 33841.44 | E98: 14403.73 | F98: ='Cash Flow'!K31 -> 33841.44
A99: FY2030E FCF margin % | C99: 0.32437819 | D99: 0.29552918 | E99: 0.22022079 | F99: ='Cash Flow'!K32 -> 0.29552918
A100: Cumulative FCF FY2026E-FY2030E | C100: 151109.59 | D100: 109248.1 | E100: 58930.079 | F100: =SUM('Cash Flow'!G31:K31) -> 109248.1
A101: FY2030E unlevered FCF | C101: 44813.266 | D101: 29285.077 | E101: 11779.876 | F101: ='DCF Inputs'!K16 -> 29285.077
A103: Bull: MI450/Helios ramps on schedule with OpenAI, Anthropic, Meta, Microsoft and Oracle; DC GPU revenue +155% in FY2026E and +120% in FY2027E; EPYC share gains continue toward management's >50% target; opex leverage drives GAAP operating margin toward the high-30s.
A104: Base: H1 FY2026 actuals plus Q3 guidance (about USD 13.0bn) anchor FY2026E; DC GPU growth decelerates from +140% to +15% by FY2030E; DC CAGR about 40% (below management's >60% target); cost of sales ex-amortization falls to 44% of revenue on mix.
A105: Bear: rack-scale deployment delays and customer pushouts (OpenAI or Anthropic milestones slip), custom ASIC substitution and export-control drag; DC GPU growth slows to +40% in FY2027E; rack pass-through content dilutes gross margin; opex stays elevated.

Sheet DCF Inputs
A1: AMD - DCF Inputs (for Task 3 valuation)
A2: Unlevered FCF built from GAAP EBIT; SBC is treated as a real expense (not added back). USD millions.
A4: USD millions | C4: FY2022A | D4: FY2023A | E4: FY2024A | F4: FY2025A | G4: FY2026E | H4: FY2027E | I4: FY2028E | J4: FY2029E | K4: FY2030E
A5: Revenue | C5: ='Income Statement'!C10 -> 23601 | D5: ='Income Statement'!D10 -> 22680 | E5: ='Income Statement'!E10 -> 25785 | F5: ='Income Statement'!F10 -> 34639 | G5: ='Income Statement'!G10 -> 49475.5 | H5: ='Income Statement'!H10 -> 69117.14 | I5: ='Income Statement'!I10 -> 87417.167 | J5: ='Income Statement'!J10 -> 102678.57 | K5: ='Income Statement'!K10 -> 114511.33
A6: Revenue growth % | D6: =D5/C5-1 -> -0.03902377 | E6: =E5/D5-1 -> 0.13690476 | F6: =F5/E5-1 -> 0.34337793 | G6: =G5/F5-1 -> 0.42831779 | H6: =H5/G5-1 -> 0.3969973 | I6: =I5/H5-1 -> 0.26476829 | J6: =J5/I5-1 -> 0.17458134 | K6: =K5/J5-1 -> 0.11524079
A7: EBITDA | C7: ='Income Statement'!C37 -> 5438 | D7: ='Income Statement'!D37 -> 3854 | E7: ='Income Statement'!E37 -> 4965 | F7: ='Income Statement'!F37 -> 6698 | G7: ='Income Statement'!G37 -> 11626.743 | H7: ='Income Statement'!H37 -> 19698.385 | I7: ='Income Statement'!I37 -> 27536.408 | J7: ='Income Statement'!J37 -> 34397.322 | K7: ='Income Statement'!K37 -> 39506.41
A8: EBIT (GAAP operating income) | C8: ='Income Statement'!C32 -> 1264 | D8: ='Income Statement'!D32 -> 401 | E8: ='Income Statement'!E32 -> 1900 | F8: ='Income Statement'!F32 -> 3694 | G8: ='Income Statement'!G32 -> 8537.2325 | H8: ='Income Statement'!H32 -> 16416.042 | I8: ='Income Statement'!I32 -> 24088.064 | J8: ='Income Statement'!J32 -> 30843.751 | K8: ='Income Statement'!K32 -> 35916.183
A9: EBIT margin % | C9: =C8/C5 -> 0.053557053 | D9: =D8/D5 -> 0.017680776 | E9: =E8/E5 -> 0.073686252 | F9: =F8/F5 -> 0.1066428 | G9: =G8/G5 -> 0.17255475 | H9: =H8/H5 -> 0.23751044 | I9: =I8/I5 -> 0.27555302 | J9: =J8/J5 -> 0.3003913 | K9: =K8/K5 -> 0.31364741
A10: Tax rate % (projection: model rate; hist: 15% normalized) | C10: 0.15 | D10: 0.15 | E10: 0.15 | F10: 0.15 | G10: ='Income Statement'!G51 -> 0.13 | H10: ='Income Statement'!H51 -> 0.15 | I10: ='Income Statement'!I51 -> 0.15 | J10: ='Income Statement'!J51 -> 0.15 | K10: ='Income Statement'!K51 -> 0.15
A11: NOPAT | C11: =C8*(1-C10) -> 1074.4 | D11: =D8*(1-D10) -> 340.85 | E11: =E8*(1-E10) -> 1615 | F11: =F8*(1-F10) -> 3139.9 | G11: =G8*(1-G10) -> 7427.3923 | H11: =H8*(1-H10) -> 13953.636 | I11: =I8*(1-I10) -> 20474.855 | J11: =J8*(1-J10) -> 26217.188 | K11: =K8*(1-K10) -> 30528.756
A12: Add: D&A (ex-intangibles) | C12: ='Income Statement'!C35 -> 626 | D12: ='Income Statement'!D35 -> 642 | E12: ='Income Statement'!E35 -> 671 | F12: ='Income Statement'!F35 -> 750 | G12: ='Income Statement'!G35 -> 989.51 | H12: ='Income Statement'!H35 -> 1382.3428 | I12: ='Income Statement'!I35 -> 1748.3433 | J12: ='Income Statement'!J35 -> 2053.5715 | K12: ='Income Statement'!K35 -> 2290.2267
A13: Add: amortization of acquired intangibles | C13: ='Income Statement'!C36 -> 3548 | D13: ='Income Statement'!D36 -> 2811 | E13: ='Income Statement'!E36 -> 2394 | F13: ='Income Statement'!F36 -> 2254 | G13: ='Income Statement'!G36 -> 2100 | H13: ='Income Statement'!H36 -> 1900 | I13: ='Income Statement'!I36 -> 1700 | J13: ='Income Statement'!J36 -> 1500 | K13: ='Income Statement'!K36 -> 1300
A14: Less: capital expenditures | C14: ='Cash Flow'!C24 -> -450 | D14: ='Cash Flow'!D24 -> -546 | E14: ='Cash Flow'!E24 -> -636 | F14: ='Cash Flow'!F24 -> -974 | G14: ='Cash Flow'!G24 -> -2473.775 | H14: ='Cash Flow'!H24 -> -3110.2713 | I14: ='Cash Flow'!I24 -> -3496.6867 | J14: ='Cash Flow'!J24 -> -3593.7501 | K14: ='Cash Flow'!K24 -> -4007.8967
A15: Less: increase in net working capital | C15: =SUM('Cash Flow'!C14:C18) -> -1846 | D15: =SUM('Cash Flow'!D14:D18) -> -3049 | E15: =SUM('Cash Flow'!E14:E18) -> -2098 | F15: =SUM('Cash Flow'!F14:F18) -> -2378 | G15: =SUM('Cash Flow'!G14:G18) -> -477.5516 | H15: =SUM('Cash Flow'!H14:H18) -> -1937.7851 | I15: =SUM('Cash Flow'!I14:I18) -> -1564.7959 | J15: =SUM('Cash Flow'!J14:J18) -> -1362.7904 | K15: =SUM('Cash Flow'!K14:K18) -> -826.0089
A16: UNLEVERED FREE CASH FLOW | C16: =C11+C12+C13+C14+C15 -> 2952.4 | D16: =D11+D12+D13+D14+D15 -> 198.85 | E16: =E11+E12+E13+E14+E15 -> 1946 | F16: =F11+F12+F13+F14+F15 -> 2791.9 | G16: =G11+G12+G13+G14+G15 -> 7565.5757 | H16: =H11+H12+H13+H14+H15 -> 12187.922 | I16: =I11+I12+I13+I14+I15 -> 18861.715 | J16: =J11+J12+J13+J14+J15 -> 24814.219 | K16: =K11+K12+K13+K14+K15 -> 29285.077
A17: UFCF margin % | C17: =C16/C5 -> 0.12509639 | D17: =D16/D5 -> 0.0087676367 | E17: =E16/E5 -> 0.075470235 | F17: =F16/F5 -> 0.080599902 | G17: =G16/G5 -> 0.1529156 | H17: =H16/H5 -> 0.17633719 | I17: =I16/I5 -> 0.21576672 | J17: =J16/J5 -> 0.24166891 | K17: =K16/K5 -> 0.25573955
A18: Memo: stock-based compensation (already deducted in EBIT) | C18: ='Income Statement'!C40 -> 1081 | D18: ='Income Statement'!D40 -> 1384 | E18: ='Income Statement'!E40 -> 1407 | F18: ='Income Statement'!F40 -> 1638 | G18: ='Income Statement'!G40 -> 1979.02 | H18: ='Income Statement'!H40 -> 2419.0999 | I18: ='Income Statement'!I40 -> 2797.3493 | J18: ='Income Statement'!J40 -> 3080.3572 | K18: ='Income Statement'!K40 -> 3435.34
A20: Terminal-year metrics (FY2030E)
A21: FY2030E revenue | C21: =K5 -> 114511.33
A22: FY2030E EBITDA | C22: =K7 -> 39506.41
A23: FY2030E EBIT | C23: =K8 -> 35916.183
A24: FY2030E unlevered FCF | C24: =K16 -> 29285.077
A25: FY2030E NOPAT | C25: =K11 -> 30528.756
A27: Capital structure & market inputs (latest)
A28: Share price (USD), 2026-10-14 | B28: stock-data get_quote | C28: 605.53
A29: Basic shares outstanding (M), 2026-06-27 | B29: 10-Q 2026-08-05 | C29: 1632
A30: Diluted weighted shares (M), Q2 FY2026 | B30: 10-Q 2026-08-05 | C30: 1659
A31: Market capitalization (price x basic shares) | C31: =C28*C29 -> 988224.96
A32: Cash and cash equivalents, 2026-06-27 | C32: 5086
A33: Short-term investments, 2026-06-27 | C33: 8025
A34: Total debt (carrying), 2026-06-27 | C34: 3226
A35: Enterprise value (market cap - cash - STI + debt) | C35: =C31-C32-C33+C34 -> 978339.96
A36: EV / FY2026E revenue | C36: =C35/G5 -> 19.774231
A37: EV / FY2027E EBITDA | C37: =C35/H7 -> 49.665999
A38: P/E FY2027E (diluted EPS) | C38: =C28/'Income Statement'!H65 -> 70.971908
A39: OpenAI warrant: up to 160M shares (not in share count; model knowledge) | B39: excluded | C39: 160

Sheet DCF
A1: AMD - Discounted Cash Flow (two-stage: explicit FY2026E-FY2030E + 5-year fade FY2031E-FY2035E + Gordon terminal value)
A2: USD millions except per share. Valuation date 2026-10-14; balance sheet as of 2026-06-27, so only H2 FY2026E cash flow is included. Mid-period discounting.
A4: WACC BUILD
A5: Risk-free rate: 10-year UST (FRED DGS10, 2026-10-09) | C5: 0.0524
A6: Equity risk premium (assumed) | C6: 0.05
A7: Peer median unlevered beta (Comps tab, Blume-adjusted 5y monthly) | C7: =Comps!V12 -> 1.5879639
A8: AMD debt / equity (market) | C8: ='DCF Inputs'!C34/'DCF Inputs'!C31 -> 0.0032644389
A9: Tax rate for levering / Kd shield | C9: 0.15
A10: Relevered beta applied to AMD | C10: =C7*(1+(1-C9)*C8) -> 1.5923702
A11: Memo: AMD own beta, Blume-adjusted (raw 2.52) | C11: =Comps!T17 -> 2.01505
A12: Cost of equity (CAPM) | C12: =C5+C10*C6 -> 0.13201851
A13: Pre-tax cost of debt (Rf + 0.6% A-rated spread, assumed) | C13: =C5+0.006 -> 0.0584
A14: After-tax cost of debt | C14: =C13*(1-C9) -> 0.04964
A15: Equity value (market cap) | C15: ='DCF Inputs'!C31 -> 988224.96
A16: Debt (carrying, 2026-06-27) | C16: ='DCF Inputs'!C34 -> 3226
A17: E / (D + E) | C17: =C15/(C15+C16) -> 0.99674618
A18: WACC | C18: =C17*C12+(1-C17)*C14 -> 0.13175046
A19: Terminal growth rate (nominal) | C19: 0.03
A20: Net cash: cash + ST investments - debt (2026-06-27) | C20: ='DCF Inputs'!C32+'DCF Inputs'!C33-'DCF Inputs'!C34 -> 9885
A21: Diluted shares (M), Q2 FY2026 | C21: ='DCF Inputs'!C30 -> 1659
A22: Current share price (USD), 2026-10-14 | C22: ='DCF Inputs'!C28 -> 605.53
A25: BASE DCF (linked live to the model; follows Scenarios!C3 selector - keep on 2 = Base)
A26: USD millions | C26: FY2026E (H2) | D26: FY2027E | E26: FY2028E | F26: FY2029E | G26: FY2030E | H26: FY2031E | I26: FY2032E | J26: FY2033E | K26: FY2034E | L26: FY2035E
A27: Stage | C27: Explicit (model) | D27: Explicit (model) | E27: Explicit (model) | F27: Explicit (model) | G27: Explicit (model) | H27: Fade | I27: Fade | J27: Fade | K27: Fade | L27: Fade
A28: Revenue | C28: ='DCF Inputs'!G5 -> 49475.5 | D28: ='DCF Inputs'!H5 -> 69117.14 | E28: ='DCF Inputs'!I5 -> 87417.167 | F28: ='DCF Inputs'!J5 -> 102678.57 | G28: ='DCF Inputs'!K5 -> 114511.33 | H28: =G28*(1+H29) -> 126080.87 | I28: =H28*(1+I29) -> 137028.12 | J28: =I28*(1+J29) -> 146979.15 | K28: =J28*(1+K29) -> 155564.74 | L28: =K28*(1+L29) -> 162441.75
A29: Revenue growth % | C29: =C28/'Revenue Model'!F47-1 -> 0.42831779 | D29: =D28/C28-1 -> 0.3969973 | E29: =E28/D28-1 -> 0.26476829 | F29: =F28/E28-1 -> 0.17458134 | G29: =G28/F28-1 -> 0.11524079 | H29: =$G29-($G29-$C$19)*1/6 -> 0.10103399 | I29: =$G29-($G29-$C$19)*2/6 -> 0.086827194 | J29: =$G29-($G29-$C$19)*3/6 -> 0.072620395 | K29: =$G29-($G29-$C$19)*4/6 -> 0.058413597 | L29: =$G29-($G29-$C$19)*5/6 -> 0.044206798
A30: Unlevered FCF (full year) | C30: ='DCF Inputs'!G16 -> 7565.5757 | D30: ='DCF Inputs'!H16 -> 12187.922 | E30: ='DCF Inputs'!I16 -> 18861.715 | F30: ='DCF Inputs'!J16 -> 24814.219 | G30: ='DCF Inputs'!K16 -> 29285.077 | H30: =H28*H31 -> 32243.865 | I30: =I28*I31 -> 35043.51 | J30: =J28*J31 -> 37588.383 | K30: =K28*K31 -> 39784.056 | L30: =L28*L31 -> 41542.781
A31: UFCF margin % | C31: =C30/C28 -> 0.1529156 | D31: =D30/D28 -> 0.17633719 | E31: =E30/E28 -> 0.21576672 | F31: =F30/F28 -> 0.24166891 | G31: =G30/G28 -> 0.25573955 | H31: =$G31 -> 0.25573955 | I31: =$G31 -> 0.25573955 | J31: =$G31 -> 0.25573955 | K31: =$G31 -> 0.25573955 | L31: =$G31 -> 0.25573955
A32: Fraction of year included | C32: 0.5 | D32: 1 | E32: 1 | F32: 1 | G32: 1 | H32: 1 | I32: 1 | J32: 1 | K32: 1 | L32: 1
A33: Cash flow discounted | C33: =C30*C32 -> 3782.7878 | D33: =D30*D32 -> 12187.922 | E33: =E30*E32 -> 18861.715 | F33: =F30*F32 -> 24814.219 | G33: =G30*G32 -> 29285.077 | H33: =H30*H32 -> 32243.865 | I33: =I30*I32 -> 35043.51 | J33: =J30*J32 -> 37588.383 | ... L33: =L30*L32 -> 41542.781
A34: Discount period (years, mid-period) | C34: 0 | D34: =(DATE(2027,7,2)-DATE(2026,10,14))/365.25 -> 0.71457906 | E34: =(DATE(2028,7,2)-DATE(2026,10,14))/365.25 -> 1.7166324 | F34: =(DATE(2029,7,2)-DATE(2026,10,14))/365.25 -> 2.715948 | G34: =(DATE(2030,7,2)-DATE(2026,10,14))/365.25 -> 3.7152635 | H34: =(DATE(2031,7,2)-DATE(2026,10,14))/365.25 -> 4.7145791 | I34: =(DATE(2032,7,2)-DATE(2026,10,14))/365.25 -> 5.7166324 | J34: =(DATE(2033,7,2)-DATE(2026,10,14))/365.25 -> 6.715948 | K34: =(DATE(2034,7,2)-DATE(2026,10,14))/365.25 -> 7.7152635 | L34: =(DATE(2035,7,2)-DATE(2026,10,14))/365.25 -> 8.7145791
A35: Discount factor | C35: =1/(1+$C$18)^C34 -> 1 | D35: =1/(1+$C$18)^D34 -> 0.91535781 | E35: =1/(1+$C$18)^E34 -> 0.80859274 | F35: =1/(1+$C$18)^F34 -> 0.71452256 | G35: =1/(1+$C$18)^G34 -> 0.63139633 | H35: =1/(1+$C$18)^H34 -> 0.55794086 | I35: =1/(1+$C$18)^I34 -> 0.49286402 | J35: =1/(1+$C$18)^J34 -> 0.43552513 | ... L35: =1/(1+$C$18)^L34 -> 0.3400834
A36: Present value | C36: =C33*C35 -> 3782.7878 | D36: =D33*D35 -> 11156.31 | E36: =E33*E35 -> 15251.446 | F36: =F33*F35 -> 17730.319 | G36: =G33*G35 -> 18490.49 | H36: =H33*H35 -> 17990.17 | I36: =I33*I35 -> 17271.685 | J36: =J33*J35 -> 16370.685 | ... L36: =L33*L35 -> 14128.011
A38: PV of explicit-period cash flows (H2 FY2026E-FY2030E) | C38: =SUM(C36:G36) -> 66411.353
A39: PV of fade-period cash flows (FY2031E-FY2035E) | C39: =SUM(H36:L36) -> 81071.721
A40: Terminal-year FCF (FY2036E = FY2035E x (1+g)) | C40: =L30*(1+$C$19) -> 42789.065
A41: Terminal value at end-FY2035E (Gordon growth) | C41: =C40/($C$18-$C$19) -> 420529.43
A42: Discount period to end-FY2035E (years) | C42: =(DATE(2035,12,31)-DATE(2026,10,14))/365.25 -> 9.2128679
A43: PV of terminal value | C43: =C41/(1+$C$18)^C42 -> 134461.66
A44: ENTERPRISE VALUE | C44: =C38+C39+C43 -> 281944.74
A45: Terminal value as % of EV | C45: =C43/C44 -> 0.47690786
A46: Plus: net cash | C46: =$C$20 -> 9885
A47: EQUITY VALUE | C47: =C44+C46 -> 291829.74
A48: DCF VALUE PER SHARE (USD) | C48: =C47/$C$21 -> 175.90701
A49: Implied upside / (downside) vs. current price | C49: =C48/$C$22-1 -> -0.70949909
A50: Implied EV / NTM revenue | C50: =C44/Comps!J17 -> 4.3912022
A51: Implied terminal EV / FY2035E UFCF (x) | C51: =C41/L30 -> 10.122804
A55: BULL SCENARIO DCF (static snapshot of model outputs for this case; same WACC and fade)
A56: USD millions | C56: FY2026E (H2) | D56: FY2027E | E56: FY2028E | F56: FY2029E | G56: FY2030E | H56: FY2031E | I56: FY2032E | J56: FY2033E | K56: FY2034E | L56: FY2035E
A57: Stage | C57: Explicit (model) | D57: Explicit (model) | E57: Explicit (model) | F57: Explicit (model) | G57: Explicit (model) | H57: Fade | I57: Fade | J57: Fade | K57: Fade | L57: Fade
A58: Revenue | C58: 51397.3 | D58: 78923.9 | E58: 108335.4 | F58: 135585.4 | G58: 157285.6 | H58: =G58*(1+H59) -> 179049.76 | I58: =H58*(1+I59) -> 199944.65 | J58: =I58*(1+J59) -> 218944.21 | K58: =J58*(1+K59) -> 235003.64 | L58: =K58*(1+L59) -> 247147.38
A59: Revenue growth % | C59: =C58/'Revenue Model'!F47-1 -> 0.48379861 | D59: =D58/C58-1 -> 0.5355651 | E59: =E58/D58-1 -> 0.37265645 | F59: =F58/E58-1 -> 0.25153366 | G59: =G58/F58-1 -> 0.16004821 | H59: =$G59-($G59-$C$19)*1/6 -> 0.1383735 | I59: =$G59-($G59-$C$19)*2/6 -> 0.1166988 | J59: =$G59-($G59-$C$19)*3/6 -> 0.095024103 | K59: =$G59-($G59-$C$19)*4/6 -> 0.073349402 | L59: =$G59-($G59-$C$19)*5/6 -> 0.051674701
A60: Unlevered FCF (full year) | C60: 8183 | D60: 15119.2 | E60: 26105.5 | F60: 36380.7 | G60: 44813.3 | H60: =H58*H61 -> 51014.273 | I60: =I58*I61 -> 56967.578 | J60: =J58*J61 -> 62380.871 | K60: =K58*K61 -> 66956.471 | L60: =L58*L61 -> 70416.426
A61: UFCF margin % | C61: =C60/C58 -> 0.1592107 | D61: =D60/D58 -> 0.19156681 | E61: =E60/E58 -> 0.24096925 | F61: =F60/F58 -> 0.26832314 | G61: =G60/G58 -> 0.28491674 | H61: =$G61 -> 0.28491674 | I61: =$G61 -> 0.28491674 | J61: =$G61 -> 0.28491674 | K61: =$G61 -> 0.28491674 | L61: =$G61 -> 0.28491674
A62: Fraction of year included | C62: 0.5 | D62: 1 | E62: 1 | F62: 1 | G62: 1 | H62: 1 | I62: 1 | J62: 1 | K62: 1 | L62: 1
A63: Cash flow discounted | C63: =C60*C62 -> 4091.5 | D63: =D60*D62 -> 15119.2 | E63: =E60*E62 -> 26105.5 | F63: =F60*F62 -> 36380.7 | G63: =G60*G62 -> 44813.3 | H63: =H60*H62 -> 51014.273 | I63: =I60*I62 -> 56967.578 | J63: =J60*J62 -> 62380.871 | ... L63: =L60*L62 -> 70416.426
A64: Discount period (years, mid-period) | C64: 0 | D64: =(DATE(2027,7,2)-DATE(2026,10,14))/365.25 -> 0.71457906 | E64: =(DATE(2028,7,2)-DATE(2026,10,14))/365.25 -> 1.7166324 | F64: =(DATE(2029,7,2)-DATE(2026,10,14))/365.25 -> 2.715948 | G64: =(DATE(2030,7,2)-DATE(2026,10,14))/365.25 -> 3.7152635 | H64: =(DATE(2031,7,2)-DATE(2026,10,14))/365.25 -> 4.7145791 | I64: =(DATE(2032,7,2)-DATE(2026,10,14))/365.25 -> 5.7166324 | J64: =(DATE(2033,7,2)-DATE(2026,10,14))/365.25 -> 6.715948 | K64: =(DATE(2034,7,2)-DATE(2026,10,14))/365.25 -> 7.7152635 | L64: =(DATE(2035,7,2)-DATE(2026,10,14))/365.25 -> 8.7145791
A65: Discount factor | C65: =1/(1+$C$18)^C64 -> 1 | D65: =1/(1+$C$18)^D64 -> 0.91535781 | E65: =1/(1+$C$18)^E64 -> 0.80859274 | F65: =1/(1+$C$18)^F64 -> 0.71452256 | G65: =1/(1+$C$18)^G64 -> 0.63139633 | H65: =1/(1+$C$18)^H64 -> 0.55794086 | I65: =1/(1+$C$18)^I64 -> 0.49286402 | J65: =1/(1+$C$18)^J64 -> 0.43552513 | ... L65: =1/(1+$C$18)^L64 -> 0.3400834
A66: Present value | C66: =C63*C65 -> 4091.5 | D66: =D63*D65 -> 13839.478 | E66: =E63*E65 -> 21108.718 | F66: =F63*F65 -> 25994.831 | G66: =G63*G65 -> 28294.953 | H66: =H63*H65 -> 28462.947 | I66: =I63*I65 -> 28077.269 | J66: =J63*J65 -> 27168.437 | ... L66: =L63*L65 -> 23947.458
A68: PV of explicit-period cash flows (H2 FY2026E-FY2030E) | C68: =SUM(C66:G66) -> 93329.48
A69: PV of fade-period cash flows (FY2031E-FY2035E) | C69: =SUM(H66:L66) -> 133424.77
A70: Terminal-year FCF (FY2036E = FY2035E x (1+g)) | C70: =L60*(1+$C$19) -> 72528.919
A71: Terminal value at end-FY2035E (Gordon growth) | C71: =C70/($C$18-$C$19) -> 712811.68
A72: Discount period to end-FY2035E (years) | C72: =(DATE(2035,12,31)-DATE(2026,10,14))/365.25 -> 9.2128679
A73: PV of terminal value | C73: =C71/(1+$C$18)^C72 -> 227917.08
A74: ENTERPRISE VALUE | C74: =C68+C69+C73 -> 454671.34
A75: Terminal value as % of EV | C75: =C73/C74 -> 0.50127876
A76: Plus: net cash | C76: =$C$20 -> 9885
A77: EQUITY VALUE | C77: =C74+C76 -> 464556.34
A78: DCF VALUE PER SHARE (USD) | C78: =C77/$C$21 -> 280.0219
A79: Implied upside / (downside) vs. current price | C79: =C78/$C$22-1 -> -0.53755899
A80: Implied EV / NTM revenue | C80: =C74/Comps!J17 -> 7.0813658
A81: Implied terminal EV / FY2035E UFCF (x) | C81: =C71/L60 -> 10.122804
A85: BASE (static) SCENARIO DCF (static snapshot of model outputs for this case; same WACC and fade)
A86: USD millions | C86: FY2026E (H2) | D86: FY2027E | E86: FY2028E | F86: FY2029E | G86: FY2030E | H86: FY2031E | I86: FY2032E | J86: FY2033E | K86: FY2034E | L86: FY2035E
A87: Stage | C87: Explicit (model) | D87: Explicit (model) | E87: Explicit (model) | F87: Explicit (model) | G87: Explicit (model) | H87: Fade | I87: Fade | J87: Fade | K87: Fade | L87: Fade
A88: Revenue | C88: 49475.5 | D88: 69117.1 | E88: 87417.2 | F88: 102678.6 | G88: 114511.3 | H88: =G88*(1+H89) -> 126080.78 | I88: =H88*(1+I89) -> 137027.96 | J88: =I88*(1+J89) -> 146978.95 | K88: =J88*(1+K89) -> 155564.49 | L88: =K88*(1+L89) -> 162441.48
A89: Revenue growth % | C89: =C88/'Revenue Model'!F47-1 -> 0.42831779 | D89: =D88/C88-1 -> 0.39699649 | E89: =E88/D88-1 -> 0.2647695 | F89: =F88/E88-1 -> 0.1745812 | G89: =G88/F88-1 -> 0.11524018 | H89: =$G89-($G89-$C$19)*1/6 -> 0.10103348 | I89: =$G89-($G89-$C$19)*2/6 -> 0.086826784 | J89: =$G89-($G89-$C$19)*3/6 -> 0.072620088 | K89: =$G89-($G89-$C$19)*4/6 -> 0.058413392 | L89: =$G89-($G89-$C$19)*5/6 -> 0.044206696
A90: Unlevered FCF (full year) | C90: 7565.6 | D90: 12187.9 | E90: 18861.7 | F90: 24814.2 | G90: 29285.1 | H90: =H88*H91 -> 32243.876 | I90: =I88*I91 -> 35043.508 | J90: =J88*J91 -> 37588.37 | K90: =K88*K91 -> 39784.034 | L90: =L88*L91 -> 41542.755
A91: UFCF margin % | C91: =C90/C88 -> 0.15291609 | D91: =D90/D88 -> 0.17633697 | E91: =E90/E88 -> 0.21576646 | F91: =F90/F88 -> 0.24166866 | G91: =G90/G88 -> 0.25573983 | H91: =$G91 -> 0.25573983 | I91: =$G91 -> 0.25573983 | J91: =$G91 -> 0.25573983 | K91: =$G91 -> 0.25573983 | L91: =$G91 -> 0.25573983
A92: Fraction of year included | C92: 0.5 | D92: 1 | E92: 1 | F92: 1 | G92: 1 | H92: 1 | I92: 1 | J92: 1 | K92: 1 | L92: 1
A93: Cash flow discounted | C93: =C90*C92 -> 3782.8 | D93: =D90*D92 -> 12187.9 | E93: =E90*E92 -> 18861.7 | F93: =F90*F92 -> 24814.2 | G93: =G90*G92 -> 29285.1 | H93: =H90*H92 -> 32243.876 | I93: =I90*I92 -> 35043.508 | J93: =J90*J92 -> 37588.37 | ... L93: =L90*L92 -> 41542.755
A94: Discount period (years, mid-period) | C94: 0 | D94: =(DATE(2027,7,2)-DATE(2026,10,14))/365.25 -> 0.71457906 | E94: =(DATE(2028,7,2)-DATE(2026,10,14))/365.25 -> 1.7166324 | F94: =(DATE(2029,7,2)-DATE(2026,10,14))/365.25 -> 2.715948 | G94: =(DATE(2030,7,2)-DATE(2026,10,14))/365.25 -> 3.7152635 | H94: =(DATE(2031,7,2)-DATE(2026,10,14))/365.25 -> 4.7145791 | I94: =(DATE(2032,7,2)-DATE(2026,10,14))/365.25 -> 5.7166324 | J94: =(DATE(2033,7,2)-DATE(2026,10,14))/365.25 -> 6.715948 | K94: =(DATE(2034,7,2)-DATE(2026,10,14))/365.25 -> 7.7152635 | L94: =(DATE(2035,7,2)-DATE(2026,10,14))/365.25 -> 8.7145791
A95: Discount factor | C95: =1/(1+$C$18)^C94 -> 1 | D95: =1/(1+$C$18)^D94 -> 0.91535781 | E95: =1/(1+$C$18)^E94 -> 0.80859274 | F95: =1/(1+$C$18)^F94 -> 0.71452256 | G95: =1/(1+$C$18)^G94 -> 0.63139633 | H95: =1/(1+$C$18)^H94 -> 0.55794086 | I95: =1/(1+$C$18)^I94 -> 0.49286402 | J95: =1/(1+$C$18)^J94 -> 0.43552513 | ... L95: =1/(1+$C$18)^L94 -> 0.3400834
A96: Present value | C96: =C93*C95 -> 3782.8 | D96: =D93*D95 -> 11156.289 | E96: =E93*E95 -> 15251.434 | F96: =F93*F95 -> 17730.306 | G96: =G93*G95 -> 18490.505 | H96: =H93*H95 -> 17990.176 | I96: =I93*I95 -> 17271.684 | J96: =J93*J95 -> 16370.68 | ... L96: =L93*L95 -> 14128.002
A98: PV of explicit-period cash flows (H2 FY2026E-FY2030E) | C98: =SUM(C96:G96) -> 66411.334
A99: PV of fade-period cash flows (FY2031E-FY2035E) | C99: =SUM(H96:L96) -> 81071.703
A100: Terminal-year FCF (FY2036E = FY2035E x (1+g)) | C100: =L90*(1+$C$19) -> 42789.038
A101: Terminal value at end-FY2035E (Gordon growth) | C101: =C100/($C$18-$C$19) -> 420529.17
A102: Discount period to end-FY2035E (years) | C102: =(DATE(2035,12,31)-DATE(2026,10,14))/365.25 -> 9.2128679
A103: PV of terminal value | C103: =C101/(1+$C$18)^C102 -> 134461.58
A104: ENTERPRISE VALUE | C104: =C98+C99+C103 -> 281944.61
A105: Terminal value as % of EV | C105: =C103/C104 -> 0.47690777
A106: Plus: net cash | C106: =$C$20 -> 9885
A107: EQUITY VALUE | C107: =C104+C106 -> 291829.61
A108: DCF VALUE PER SHARE (USD) | C108: =C107/$C$21 -> 175.90694
A109: Implied upside / (downside) vs. current price | C109: =C108/$C$22-1 -> -0.70949922
A110: Implied EV / NTM revenue | C110: =C104/Comps!J17 -> 4.3912003
A111: Implied terminal EV / FY2035E UFCF (x) | C111: =C101/L90 -> 10.122804
A115: BEAR SCENARIO DCF (static snapshot of model outputs for this case; same WACC and fade)
...

Sheet Sensitivity
A1: AMD - DCF Sensitivity Analysis (value per share, USD)
A2: Recomputes the base DCF (DCF tab) for each input pair. Fade-period revenue path held at base; terminal growth and WACC flexed.
A4: TABLE 1: WACC (rows) vs. terminal growth (columns)
B5: WACC \ g | C5: 0.02 | D5: 0.025 | E5: 0.03 | F5: 0.035 | G5: 0.04
B6: =DCF!$C$18+(-0.03) -> 0.10175046 | C6: =(SUMPRODUCT(DCF!$C$33:$L$33,(1+$B6)^(-DCF!$C$34:$L$34))+DCF!$L$30*(1+C$5)/($B6-C$5)*(1+$B6)^(-DCF!$C$42)+DCF!$C$20)/DCF!$C$21 -> 234.86935 | D6: =(SUMPRODUCT(DCF!$C$33:$L$33,(1+$B6)^(-DCF!$C$34:$L$34))+DCF!$L$30*(1+D$5)/($B6-D$5)*(1+$B6)^(-DCF!$C$42)+DCF!$C$20)/DCF!$C$21 -> 243.87311 | E6: =(SUMPRODUCT(DCF!$C$33:$L$33,(1+$B6)^(-DCF!$C$34:$L$34))+DCF!$L$30*(1+E$5)/($B6-E$5)*(1+$B6)^(-DCF!$C$42)+DCF!$C$20)/DCF!$C$21 -> 254.13174 | F6: =(SUMPRODUCT(DCF!$C$33:$L$33,(1+$B6)^(-DCF!$C$34:$L$34))+DCF!$L$30*(1+F$5)/($B6-F$5)*(1+$B6)^(-DCF!$C$42)+DCF!$C$20)/DCF!$C$21 -> 265.92723 | G6: =(SUMPRODUCT(DCF!$C$33:$L$33,(1+$B6)^(-DCF!$C$34:$L$34))+DCF!$L$30*(1+G$5)/($B6-G$5)*(1+$B6)^(-DCF!$C$42)+DCF!$C$20)/DCF!$C$21 -> 279.63291
B7: =DCF!$C$18+(-0.02) -> 0.11175046 | C7: =(SUMPRODUCT(DCF!$C$33:$L$33,(1+$B7)^(-DCF!$C$34:$L$34))+DCF!$L$30*(1+C$5)/($B7-C$5)*(1+$B7)^(-DCF!$C$42)+DCF!$C$20)/DCF!$C$21 -> 207.54013 | D7: =(SUMPRODUCT(DCF!$C$33:$L$33,(1+$B7)^(-DCF!$C$34:$L$34))+DCF!$L$30*(1+D$5)/($B7-D$5)*(1+$B7)^(-DCF!$C$42)+DCF!$C$20)/DCF!$C$21 -> 214.13015 | E7: =(SUMPRODUCT(DCF!$C$33:$L$33,(1+$B7)^(-DCF!$C$34:$L$34))+DCF!$L$30*(1+E$5)/($B7-E$5)*(1+$B7)^(-DCF!$C$42)+DCF!$C$20)/DCF!$C$21 -> 221.52629 | F7: =(SUMPRODUCT(DCF!$C$33:$L$33,(1+$B7)^(-DCF!$C$34:$L$34))+DCF!$L$30*(1+F$5)/($B7-F$5)*(1+$B7)^(-DCF!$C$42)+DCF!$C$20)/DCF!$C$21 -> 229.88609 | G7: =(SUMPRODUCT(DCF!$C$33:$L$33,(1+$B7)^(-DCF!$C$34:$L$34))+DCF!$L$30*(1+G$5)/($B7-G$5)*(1+$B7)^(-DCF!$C$42)+DCF!$C$20)/DCF!$C$21 -> 239.41101
B8: =DCF!$C$18+(-0.01) -> 0.12175046 | C8: =(SUMPRODUCT(DCF!$C$33:$L$33,(1+$B8)^(-DCF!$C$34:$L$34))+DCF!$L$30*(1+C$5)/($B8-C$5)*(1+$B8)^(-DCF!$C$42)+DCF!$C$20)/DCF!$C$21 -> 185.72706 | D8: =(SUMPRODUCT(DCF!$C$33:$L$33,(1+$B8)^(-DCF!$C$34:$L$34))+DCF!$L$30*(1+D$5)/($B8-D$5)*(1+$B8)^(-DCF!$C$42)+DCF!$C$20)/DCF!$C$21 -> 190.67744 | E8: =(SUMPRODUCT(DCF!$C$33:$L$33,(1+$B8)^(-DCF!$C$34:$L$34))+DCF!$L$30*(1+E$5)/($B8-E$5)*(1+$B8)^(-DCF!$C$42)+DCF!$C$20)/DCF!$C$21 -> 196.16737 | F8: =(SUMPRODUCT(DCF!$C$33:$L$33,(1+$B8)^(-DCF!$C$34:$L$34))+DCF!$L$30*(1+F$5)/($B8-F$5)*(1+$B8)^(-DCF!$C$42)+DCF!$C$20)/DCF!$C$21 -> 202.29013 | G8: =(SUMPRODUCT(DCF!$C$33:$L$33,(1+$B8)^(-DCF!$C$34:$L$34))+DCF!$L$30*(1+G$5)/($B8-G$5)*(1+$B8)^(-DCF!$C$42)+DCF!$C$20)/DCF!$C$21 -> 209.16186
B9: =DCF!$C$18+(0) -> 0.13175046 | C9: =(SUMPRODUCT(DCF!$C$33:$L$33,(1+$B9)^(-DCF!$C$34:$L$34))+DCF!$L$30*(1+C$5)/($B9-C$5)*(1+$B9)^(-DCF!$C$42)+DCF!$C$20)/DCF!$C$21 -> 167.93779 | D9: =(SUMPRODUCT(DCF!$C$33:$L$33,(1+$B9)^(-DCF!$C$34:$L$34))+DCF!$L$30*(1+D$5)/($B9-D$5)*(1+$B9)^(-DCF!$C$42)+DCF!$C$20)/DCF!$C$21 -> 171.73577 | E9: =(SUMPRODUCT(DCF!$C$33:$L$33,(1+$B9)^(-DCF!$C$34:$L$34))+DCF!$L$30*(1+E$5)/($B9-E$5)*(1+$B9)^(-DCF!$C$42)+DCF!$C$20)/DCF!$C$21 -> 175.90701 | F9: =(SUMPRODUCT(DCF!$C$33:$L$33,(1+$B9)^(-DCF!$C$34:$L$34))+DCF!$L$30*(1+F$5)/($B9-F$5)*(1+$B9)^(-DCF!$C$42)+DCF!$C$20)/DCF!$C$21 -> 180.50939 | G9: =(SUMPRODUCT(DCF!$C$33:$L$33,(1+$B9)^(-DCF!$C$34:$L$34))+DCF!$L$30*(1+G$5)/($B9-G$5)*(1+$B9)^(-DCF!$C$42)+DCF!$C$20)/DCF!$C$21 -> 185.61339
B10: =DCF!$C$18+(0.01) -> 0.14175046 | C10: =(SUMPRODUCT(DCF!$C$33:$L$33,(1+$B10)^(-DCF!$C$34:$L$34))+DCF!$L$30*(1+C$5)/($B10-C$5)*(1+$B10)^(-DCF!$C$42)+DCF!$C$20)/DCF!$C$21 -> 153.17136 | D10: =(SUMPRODUCT(DCF!$C$33:$L$33,(1+$B10)^(-DCF!$C$34:$L$34))+DCF!$L$30*(1+D$5)/($B10-D$5)*(1+$B10)^(-DCF!$C$42)+DCF!$C$20)/DCF!$C$21 -> 156.13664 | E10: =(SUMPRODUCT(DCF!$C$33:$L$33,(1+$B10)^(-DCF!$C$34:$L$34))+DCF!$L$30*(1+E$5)/($B10-E$5)*(1+$B10)^(-DCF!$C$42)+DCF!$C$20)/DCF!$C$21 -> 159.36727 | F10: =(SUMPRODUCT(DCF!$C$33:$L$33,(1+$B10)^(-DCF!$C$34:$L$34))+DCF!$L$30*(1+F$5)/($B10-F$5)*(1+$B10)^(-DCF!$C$42)+DCF!$C$20)/DCF!$C$21 -> 162.90052 | G10: =(SUMPRODUCT(DCF!$C$33:$L$33,(1+$B10)^(-DCF!$C$34:$L$34))+DCF!$L$30*(1+G$5)/($B10-G$5)*(1+$B10)^(-DCF!$C$42)+DCF!$C$20)/DCF!$C$21 -> 166.78103
B11: =DCF!$C$18+(0.02) -> 0.15175046 | C11: =(SUMPRODUCT(DCF!$C$33:$L$33,(1+$B11)^(-DCF!$C$34:$L$34))+DCF!$L$30*(1+C$5)/($B11-C$5)*(1+$B11)^(-DCF!$C$42)+DCF!$C$20)/DCF!$C$21 -> 140.73167 | D11: =(SUMPRODUCT(DCF!$C$33:$L$33,(1+$B11)^(-DCF!$C$34:$L$34))+DCF!$L$30*(1+D$5)/($B11-D$5)*(1+$B11)^(-DCF!$C$42)+DCF!$C$20)/DCF!$C$21 -> 143.08124 | E11: =(SUMPRODUCT(DCF!$C$33:$L$33,(1+$B11)^(-DCF!$C$34:$L$34))+DCF!$L$30*(1+E$5)/($B11-E$5)*(1+$B11)^(-DCF!$C$42)+DCF!$C$20)/DCF!$C$21 -> 145.6238 | F11: =(SUMPRODUCT(DCF!$C$33:$L$33,(1+$B11)^(-DCF!$C$34:$L$34))+DCF!$L$30*(1+F$5)/($B11-F$5)*(1+$B11)^(-DCF!$C$42)+DCF!$C$20)/DCF!$C$21 -> 148.38413 | G11: =(SUMPRODUCT(DCF!$C$33:$L$33,(1+$B11)^(-DCF!$C$34:$L$34))+DCF!$L$30*(1+G$5)/($B11-G$5)*(1+$B11)^(-DCF!$C$42)+DCF!$C$20)/DCF!$C$21 -> 151.39148
B12: =DCF!$C$18+(0.03) -> 0.16175046 | C12: =(SUMPRODUCT(DCF!$C$33:$L$33,(1+$B12)^(-DCF!$C$34:$L$34))+DCF!$L$30*(1+C$5)/($B12-C$5)*(1+$B12)^(-DCF!$C$42)+DCF!$C$20)/DCF!$C$21 -> 130.11978 | D12: =(SUMPRODUCT(DCF!$C$33:$L$33,(1+$B12)^(-DCF!$C$34:$L$34))+DCF!$L$30*(1+D$5)/($B12-D$5)*(1+$B12)^(-DCF!$C$42)+DCF!$C$20)/DCF!$C$21 -> 132.00517 | E12: =(SUMPRODUCT(DCF!$C$33:$L$33,(1+$B12)^(-DCF!$C$34:$L$34))+DCF!$L$30*(1+E$5)/($B12-E$5)*(1+$B12)^(-DCF!$C$42)+DCF!$C$20)/DCF!$C$21 -> 134.03367 | F12: =(SUMPRODUCT(DCF!$C$33:$L$33,(1+$B12)^(-DCF!$C$34:$L$34))+DCF!$L$30*(1+F$5)/($B12-F$5)*(1+$B12)^(-DCF!$C$42)+DCF!$C$20)/DCF!$C$21 -> 136.22221 | G12: =(SUMPRODUCT(DCF!$C$33:$L$33,(1+$B12)^(-DCF!$C$34:$L$34))+DCF!$L$30*(1+G$5)/($B12-G$5)*(1+$B12)^(-DCF!$C$42)+DCF!$C$20)/DCF!$C$21 -> 138.59051
A15: TABLE 2: WACC (rows) vs. fade-period & terminal UFCF margin (columns); g = base
B16: WACC \ margin | C16: 0.18 | D16: 0.22 | E16: 0.26 | F16: 0.3 | G16: 0.34
B17: =DCF!$C$18+(-0.03) -> 0.10175046 | C17: =(SUMPRODUCT(DCF!$C$33:$G$33,(1+$B17)^(-DCF!$C$34:$G$34))+C$16*SUMPRODUCT(DCF!$H$28:$L$28,(1+$B17)^(-DCF!$H$34:$L$34))+DCF!$L$28*C$16*(1+DCF!$C$19)/($B17-DCF!$C$19)*(1+$B17)^(-DCF!$C$42)+DCF!$C$20)/DCF!$C$21 -> 193.24167 | D17: =(SUMPRODUCT(DCF!$C$33:$G$33,(1+$B17)^(-DCF!$C$34:$G$34))+D$16*SUMPRODUCT(DCF!$H$28:$L$28,(1+$B17)^(-DCF!$H$34:$L$34))+DCF!$L$28*D$16*(1+DCF!$C$19)/($B17-DCF!$C$19)*(1+$B17)^(-DCF!$C$42)+DCF!$C$20)/DCF!$C$21 -> 225.39927 | E17: =(SUMPRODUCT(DCF!$C$33:$G$33,(1+$B17)^(-DCF!$C$34:$G$34))+E$16*SUMPRODUCT(DCF!$H$28:$L$28,(1+$B17)^(-DCF!$H$34:$L$34))+DCF!$L$28*E$16*(1+DCF!$C$19)/($B17-DCF!$C$19)*(1+$B17)^(-DCF!$C$42)+DCF!$C$20)/DCF!$C$21 -> 257.55688 | F17: =(SUMPRODUCT(DCF!$C$33:$G$33,(1+$B17)^(-DCF!$C$34:$G$34))+F$16*SUMPRODUCT(DCF!$H$28:$L$28,(1+$B17)^(-DCF!$H$34:$L$34))+DCF!$L$28*F$16*(1+DCF!$C$19)/($B17-DCF!$C$19)*(1+$B17)^(-DCF!$C$42)+DCF!$C$20)/DCF!$C$21 -> 289.71449 | G17: =(SUMPRODUCT(DCF!$C$33:$G$33,(1+$B17)^(-DCF!$C$34:$G$34))+G$16*SUMPRODUCT(DCF!$H$28:$L$28,(1+$B17)^(-DCF!$H$34:$L$34))+DCF!$L$28*G$16*(1+DCF!$C$19)/($B17-DCF!$C$19)*(1+$B17)^(-DCF!$C$42)+DCF!$C$20)/DCF!$C$21 -> 321.8721
B18: =DCF!$C$18+(-0.02) -> 0.11175046 | C18: =(SUMPRODUCT(DCF!$C$33:$G$33,(1+$B18)^(-DCF!$C$34:$G$34))+C$16*SUMPRODUCT(DCF!$H$28:$L$28,(1+$B18)^(-DCF!$H$34:$L$34))+DCF!$L$28*C$16*(1+DCF!$C$19)/($B18-DCF!$C$19)*(1+$B18)^(-DCF!$C$42)+DCF!$C$20)/DCF!$C$21 -> 170.03272 | D18: =(SUMPRODUCT(DCF!$C$33:$G$33,(1+$B18)^(-DCF!$C$34:$G$34))+D$16*SUMPRODUCT(DCF!$H$28:$L$28,(1+$B18)^(-DCF!$H$34:$L$34))+DCF!$L$28*D$16*(1+DCF!$C$19)/($B18-DCF!$C$19)*(1+$B18)^(-DCF!$C$42)+DCF!$C$20)/DCF!$C$21 -> 197.2278 | E18: =(SUMPRODUCT(DCF!$C$33:$G$33,(1+$B18)^(-DCF!$C$34:$G$34))+E$16*SUMPRODUCT(DCF!$H$28:$L$28,(1+$B18)^(-DCF!$H$34:$L$34))+DCF!$L$28*E$16*(1+DCF!$C$19)/($B18-DCF!$C$19)*(1+$B18)^(-DCF!$C$42)+DCF!$C$20)/DCF!$C$21 -> 224.42287 | F18: =(SUMPRODUCT(DCF!$C$33:$G$33,(1+$B18)^(-DCF!$C$34:$G$34))+F$16*SUMPRODUCT(DCF!$H$28:$L$28,(1+$B18)^(-DCF!$H$34:$L$34))+DCF!$L$28*F$16*(1+DCF!$C$19)/($B18-DCF!$C$19)*(1+$B18)^(-DCF!$C$42)+DCF!$C$20)/DCF!$C$21 -> 251.61795 | G18: =(SUMPRODUCT(DCF!$C$33:$G$33,(1+$B18)^(-DCF!$C$34:$G$34))+G$16*SUMPRODUCT(DCF!$H$28:$L$28,(1+$B18)^(-DCF!$H$34:$L$34))+DCF!$L$28*G$16*(1+DCF!$C$19)/($B18-DCF!$C$19)*(1+$B18)^(-DCF!$C$42)+DCF!$C$20)/DCF!$C$21 -> 278.81302
B19: =DCF!$C$18+(-0.01) -> 0.12175046 | C19: =(SUMPRODUCT(DCF!$C$33:$G$33,(1+$B19)^(-DCF!$C$34:$G$34))+C$16*SUMPRODUCT(DCF!$H$28:$L$28,(1+$B19)^(-DCF!$H$34:$L$34))+DCF!$L$28*C$16*(1+DCF!$C$19)/($B19-DCF!$C$19)*(1+$B19)^(-DCF!$C$42)+DCF!$C$20)/DCF!$C$21 -> 151.93316 | D19: =(SUMPRODUCT(DCF!$C$33:$G$33,(1+$B19)^(-DCF!$C$34:$G$34))+D$16*SUMPRODUCT(DCF!$H$28:$L$28,(1+$B19)^(-DCF!$H$34:$L$34))+DCF!$L$28*D$16*(1+DCF!$C$19)/($B19-DCF!$C$19)*(1+$B19)^(-DCF!$C$42)+DCF!$C$20)/DCF!$C$21 -> 175.29438 | E19: =(SUMPRODUCT(DCF!$C$33:$G$33,(1+$B19)^(-DCF!$C$34:$G$34))+E$16*SUMPRODUCT(DCF!$H$28:$L$28,(1+$B19)^(-DCF!$H$34:$L$34))+DCF!$L$28*E$16*(1+DCF!$C$19)/($B19-DCF!$C$19)*(1+$B19)^(-DCF!$C$42)+DCF!$C$20)/DCF!$C$21 -> 198.6556 | F19: =(SUMPRODUCT(DCF!$C$33:$G$33,(1+$B19)^(-DCF!$C$34:$G$34))+F$16*SUMPRODUCT(DCF!$H$28:$L$28,(1+$B19)^(-DCF!$H$34:$L$34))+DCF!$L$28*F$16*(1+DCF!$C$19)/($B19-DCF!$C$19)*(1+$B19)^(-DCF!$C$42)+DCF!$C$20)/DCF!$C$21 -> 222.01682 | G19: =(SUMPRODUCT(DCF!$C$33:$G$33,(1+$B19)^(-DCF!$C$34:$G$34))+G$16*SUMPRODUCT(DCF!$H$28:$L$28,(1+$B19)^(-DCF!$H$34:$L$34))+DCF!$L$28*G$16*(1+DCF!$C$19)/($B19-DCF!$C$19)*(1+$B19)^(-DCF!$C$42)+DCF!$C$20)/DCF!$C$21 -> 245.37804
B20: =DCF!$C$18+(0) -> 0.13175046 | C20: =(SUMPRODUCT(DCF!$C$33:$G$33,(1+$B20)^(-DCF!$C$34:$G$34))+C$16*SUMPRODUCT(DCF!$H$28:$L$28,(1+$B20)^(-DCF!$H$34:$L$34))+DCF!$L$28*C$16*(1+DCF!$C$19)/($B20-DCF!$C$19)*(1+$B20)^(-DCF!$C$42)+DCF!$C$20)/DCF!$C$21 -> 137.43074 | D20: =(SUMPRODUCT(DCF!$C$33:$G$33,(1+$B20)^(-DCF!$C$34:$G$34))+D$16*SUMPRODUCT(DCF!$H$28:$L$28,(1+$B20)^(-DCF!$H$34:$L$34))+DCF!$L$28*D$16*(1+DCF!$C$19)/($B20-DCF!$C$19)*(1+$B20)^(-DCF!$C$42)+DCF!$C$20)/DCF!$C$21 -> 157.75105 | E20: =(SUMPRODUCT(DCF!$C$33:$G$33,(1+$B20)^(-DCF!$C$34:$G$34))+E$16*SUMPRODUCT(DCF!$H$28:$L$28,(1+$B20)^(-DCF!$H$34:$L$34))+DCF!$L$28*E$16*(1+DCF!$C$19)/($B20-DCF!$C$19)*(1+$B20)^(-DCF!$C$42)+DCF!$C$20)/DCF!$C$21 -> 178.07135 | F20: =(SUMPRODUCT(DCF!$C$33:$G$33,(1+$B20)^(-DCF!$C$34:$G$34))+F$16*SUMPRODUCT(DCF!$H$28:$L$28,(1+$B20)^(-DCF!$H$34:$L$34))+DCF!$L$28*F$16*(1+DCF!$C$19)/($B20-DCF!$C$19)*(1+$B20)^(-DCF!$C$42)+DCF!$C$20)/DCF!$C$21 -> 198.39166 | G20: =(SUMPRODUCT(DCF!$C$33:$G$33,(1+$B20)^(-DCF!$C$34:$G$34))+G$16*SUMPRODUCT(DCF!$H$28:$L$28,(1+$B20)^(-DCF!$H$34:$L$34))+DCF!$L$28*G$16*(1+DCF!$C$19)/($B20-DCF!$C$19)*(1+$B20)^(-DCF!$C$42)+DCF!$C$20)/DCF!$C$21 -> 218.71197
B21: =DCF!$C$18+(0.01) -> 0.14175046 | C21: =(SUMPRODUCT(DCF!$C$33:$G$33,(1+$B21)^(-DCF!$C$34:$G$34))+C$16*SUMPRODUCT(DCF!$H$28:$L$28,(1+$B21)^(-DCF!$H$34:$L$34))+DCF!$L$28*C$16*(1+DCF!$C$19)/($B21-DCF!$C$19)*(1+$B21)^(-DCF!$C$42)+DCF!$C$20)/DCF!$C$21 -> 125.55523 | D21: =(SUMPRODUCT(DCF!$C$33:$G$33,(1+$B21)^(-DCF!$C$34:$G$34))+D$16*SUMPRODUCT(DCF!$H$28:$L$28,(1+$B21)^(-DCF!$H$34:$L$34))+DCF!$L$28*D$16*(1+DCF!$C$19)/($B21-DCF!$C$19)*(1+$B21)^(-DCF!$C$42)+DCF!$C$20)/DCF!$C$21 -> 143.41224 | E21: =(SUMPRODUCT(DCF!$C$33:$G$33,(1+$B21)^(-DCF!$C$34:$G$34))+E$16*SUMPRODUCT(DCF!$H$28:$L$28,(1+$B21)^(-DCF!$H$34:$L$34))+DCF!$L$28*E$16*(1+DCF!$C$19)/($B21-DCF!$C$19)*(1+$B21)^(-DCF!$C$42)+DCF!$C$20)/DCF!$C$21 -> 161.26924 | F21: =(SUMPRODUCT(DCF!$C$33:$G$33,(1+$B21)^(-DCF!$C$34:$G$34))+F$16*SUMPRODUCT(DCF!$H$28:$L$28,(1+$B21)^(-DCF!$H$34:$L$34))+DCF!$L$28*F$16*(1+DCF!$C$19)/($B21-DCF!$C$19)*(1+$B21)^(-DCF!$C$42)+DCF!$C$20)/DCF!$C$21 -> 179.12624 | G21: =(SUMPRODUCT(DCF!$C$33:$G$33,(1+$B21)^(-DCF!$C$34:$G$34))+G$16*SUMPRODUCT(DCF!$H$28:$L$28,(1+$B21)^(-DCF!$H$34:$L$34))+DCF!$L$28*G$16*(1+DCF!$C$19)/($B21-DCF!$C$19)*(1+$B21)^(-DCF!$C$42)+DCF!$C$20)/DCF!$C$21 -> 196.98324
B22: =DCF!$C$18+(0.02) -> 0.15175046 | C22: =(SUMPRODUCT(DCF!$C$33:$G$33,(1+$B22)^(-DCF!$C$34:$G$34))+C$16*SUMPRODUCT(DCF!$H$28:$L$28,(1+$B22)^(-DCF!$H$34:$L$34))+DCF!$L$28*C$16*(1+DCF!$C$19)/($B22-DCF!$C$19)*(1+$B22)^(-DCF!$C$42)+DCF!$C$20)/DCF!$C$21 -> 115.6557 | D22: =(SUMPRODUCT(DCF!$C$33:$G$33,(1+$B22)^(-DCF!$C$34:$G$34))+D$16*SUMPRODUCT(DCF!$H$28:$L$28,(1+$B22)^(-DCF!$H$34:$L$34))+DCF!$L$28*D$16*(1+DCF!$C$19)/($B22-DCF!$C$19)*(1+$B22)^(-DCF!$C$42)+DCF!$C$20)/DCF!$C$21 -> 131.48262 | E22: =(SUMPRODUCT(DCF!$C$33:$G$33,(1+$B22)^(-DCF!$C$34:$G$34))+E$16*SUMPRODUCT(DCF!$H$28:$L$28,(1+$B22)^(-DCF!$H$34:$L$34))+DCF!$L$28*E$16*(1+DCF!$C$19)/($B22-DCF!$C$19)*(1+$B22)^(-DCF!$C$42)+DCF!$C$20)/DCF!$C$21 -> 147.30955 | F22: =(SUMPRODUCT(DCF!$C$33:$G$33,(1+$B22)^(-DCF!$C$34:$G$34))+F$16*SUMPRODUCT(DCF!$H$28:$L$28,(1+$B22)^(-DCF!$H$34:$L$34))+DCF!$L$28*F$16*(1+DCF!$C$19)/($B22-DCF!$C$19)*(1+$B22)^(-DCF!$C$42)+DCF!$C$20)/DCF!$C$21 -> 163.13647 | G22: =(SUMPRODUCT(DCF!$C$33:$G$33,(1+$B22)^(-DCF!$C$34:$G$34))+G$16*SUMPRODUCT(DCF!$H$28:$L$28,(1+$B22)^(-DCF!$H$34:$L$34))+DCF!$L$28*G$16*(1+DCF!$C$19)/($B22-DCF!$C$19)*(1+$B22)^(-DCF!$C$42)+DCF!$C$20)/DCF!$C$21 -> 178.96339
B23: =DCF!$C$18+(0.03) -> 0.16175046 | C23: =(SUMPRODUCT(DCF!$C$33:$G$33,(1+$B23)^(-DCF!$C$34:$G$34))+C$16*SUMPRODUCT(DCF!$H$28:$L$28,(1+$B23)^(-DCF!$H$34:$L$34))+DCF!$L$28*C$16*(1+DCF!$C$19)/($B23-DCF!$C$19)*(1+$B23)^(-DCF!$C$42)+DCF!$C$20)/DCF!$C$21 -> 107.27926 | D23: =(SUMPRODUCT(DCF!$C$33:$G$33,(1+$B23)^(-DCF!$C$34:$G$34))+D$16*SUMPRODUCT(DCF!$H$28:$L$28,(1+$B23)^(-DCF!$H$34:$L$34))+DCF!$L$28*D$16*(1+DCF!$C$19)/($B23-DCF!$C$19)*(1+$B23)^(-DCF!$C$42)+DCF!$C$20)/DCF!$C$21 -> 121.40895 | E23: =(SUMPRODUCT(DCF!$C$33:$G$33,(1+$B23)^(-DCF!$C$34:$G$34))+E$16*SUMPRODUCT(DCF!$H$28:$L$28,(1+$B23)^(-DCF!$H$34:$L$34))+DCF!$L$28*E$16*(1+DCF!$C$19)/($B23-DCF!$C$19)*(1+$B23)^(-DCF!$C$42)+DCF!$C$20)/DCF!$C$21 -> 135.53864 | F23: =(SUMPRODUCT(DCF!$C$33:$G$33,(1+$B23)^(-DCF!$C$34:$G$34))+F$16*SUMPRODUCT(DCF!$H$28:$L$28,(1+$B23)^(-DCF!$H$34:$L$34))+DCF!$L$28*F$16*(1+DCF!$C$19)/($B23-DCF!$C$19)*(1+$B23)^(-DCF!$C$42)+DCF!$C$20)/DCF!$C$21 -> 149.66833 | G23: =(SUMPRODUCT(DCF!$C$33:$G$33,(1+$B23)^(-DCF!$C$34:$G$34))+G$16*SUMPRODUCT(DCF!$H$28:$L$28,(1+$B23)^(-DCF!$H$34:$L$34))+DCF!$L$28*G$16*(1+DCF!$C$19)/($B23-DCF!$C$19)*(1+$B23)^(-DCF!$C$42)+DCF!$C$20)/DCF!$C$21 -> 163.79802
A24: Memo: base fade/terminal UFCF margin = | C24: =DCF!$G$31 -> 0.25573955
A26: TABLE 3: Beta (rows) vs. equity risk premium (columns); g = base; WACC ~ cost of equity (debt <1% of capital)
B27: Beta \ ERP | C27: 0.04 | D27: 0.045 | E27: 0.05 | F27: 0.055 | G27: 0.06
B28: 1.2 | C28: =(SUMPRODUCT(DCF!$C$33:$L$33,(1+(DCF!$C$17*(DCF!$C$5+$B28*C$27)+(1-DCF!$C$17)*DCF!$C$14))^(-DCF!$C$34:$L$34))+DCF!$L$30*(1+DCF!$C$19)/((DCF!$C$17*(DCF!$C$5+$B28*C$27)+(1-DCF!$C$17)*DCF!$C$14)-DCF!$C$19)*(1+(DCF!$C$17*(DCF!$C$5+$B28*C$27)+(1-DCF!$C$17)*DCF!$C$14))^(-DCF!$C$42)+DCF!$C$20)/DCF!$C$21 -> 259.90075 | D28: =(SUMPRODUCT(DCF!$C$33:$L$33,(1+(DCF!$C$17*(DCF!$C$5+$B28*D$27)+(1-DCF!$C$17)*DCF!$C$14))^(-DCF!$C$34:$L$34))+DCF!$L$30*(1+DCF!$C$19)/((DCF!$C$17*(DCF!$C$5+$B28*D$27)+(1-DCF!$C$17)*DCF!$C$14)-DCF!$C$19)*(1+(DCF!$C$17*(DCF!$C$5+$B28*D$27)+(1-DCF!$C$17)*DCF!$C$14))^(-DCF!$C$42)+DCF!$C$20)/DCF!$C$21 -> 238.49489 | E28: =(SUMPRODUCT(DCF!$C$33:$L$33,(1+(DCF!$C$17*(DCF!$C$5+$B28*E$27)+(1-DCF!$C$17)*DCF!$C$14))^(-DCF!$C$34:$L$34))+DCF!$L$30*(1+DCF!$C$19)/((DCF!$C$17*(DCF!$C$5+$B28*E$27)+(1-DCF!$C$17)*DCF!$C$14)-DCF!$C$19)*(1+(DCF!$C$17*(DCF!$C$5+$B28*E$27)+(1-DCF!$C$17)*DCF!$C$14))^(-DCF!$C$42)+DCF!$C$20)/DCF!$C$21 -> 220.26252 | F28: =(SUMPRODUCT(DCF!$C$33:$L$33,(1+(DCF!$C$17*(DCF!$C$5+$B28*F$27)+(1-DCF!$C$17)*DCF!$C$14))^(-DCF!$C$34:$L$34))+DCF!$L$30*(1+DCF!$C$19)/((DCF!$C$17*(DCF!$C$5+$B28*F$27)+(1-DCF!$C$17)*DCF!$C$14)-DCF!$C$19)*(1+(DCF!$C$17*(DCF!$C$5+$B28*F$27)+(1-DCF!$C$17)*DCF!$C$14))^(-DCF!$C$42)+DCF!$C$20)/DCF!$C$21 -> 204.55486 | G28: =(SUMPRODUCT(DCF!$C$33:$L$33,(1+(DCF!$C$17*(DCF!$C$5+$B28*G$27)+(1-DCF!$C$17)*DCF!$C$14))^(-DCF!$C$34:$L$34))+DCF!$L$30*(1+DCF!$C$19)/((DCF!$C$17*(DCF!$C$5+$B28*G$27)+(1-DCF!$C$17)*DCF!$C$14)-DCF!$C$19)*(1+(DCF!$C$17*(DCF!$C$5+$B28*G$27)+(1-DCF!$C$17)*DCF!$C$14))^(-DCF!$C$42)+DCF!$C$20)/DCF!$C$21 -> 190.88815
B29: 1.4 | C29: =(SUMPRODUCT(DCF!$C$33:$L$33,(1+(DCF!$C$17*(DCF!$C$5+$B29*C$27)+(1-DCF!$C$17)*DCF!$C$14))^(-DCF!$C$34:$L$34))+DCF!$L$30*(1+DCF!$C$19)/((DCF!$C$17*(DCF!$C$5+$B29*C$27)+(1-DCF!$C$17)*DCF!$C$14)-DCF!$C$19)*(1+(DCF!$C$17*(DCF!$C$5+$B29*C$27)+(1-DCF!$C$17)*DCF!$C$14))^(-DCF!$C$42)+DCF!$C$20)/DCF!$C$21 -> 232.10095 | D29: =(SUMPRODUCT(DCF!$C$33:$L$33,(1+(DCF!$C$17*(DCF!$C$5+$B29*D$27)+(1-DCF!$C$17)*DCF!$C$14))^(-DCF!$C$34:$L$34))+DCF!$L$30*(1+DCF!$C$19)/((DCF!$C$17*(DCF!$C$5+$B29*D$27)+(1-DCF!$C$17)*DCF!$C$14)-DCF!$C$19)*(1+(DCF!$C$17*(DCF!$C$5+$B29*D$27)+(1-DCF!$C$17)*DCF!$C$14))^(-DCF!$C$42)+DCF!$C$20)/DCF!$C$21 -> 212.12653 | E29: =(SUMPRODUCT(DCF!$C$33:$L$33,(1+(DCF!$C$17*(DCF!$C$5+$B29*E$27)+(1-DCF!$C$17)*DCF!$C$14))^(-DCF!$C$34:$L$34))+DCF!$L$30*(1+DCF!$C$19)/((DCF!$C$17*(DCF!$C$5+$B29*E$27)+(1-DCF!$C$17)*DCF!$C$14)-DCF!$C$19)*(1+(DCF!$C$17*(DCF!$C$5+$B29*E$27)+(1-DCF!$C$17)*DCF!$C$14))^(-DCF!$C$42)+DCF!$C$20)/DCF!$C$21 -> 195.24163 | F29: =(SUMPRODUCT(DCF!$C$33:$L$33,(1+(DCF!$C$17*(DCF!$C$5+$B29*F$27)+(1-DCF!$C$17)*DCF!$C$14))^(-DCF!$C$34:$L$34))+DCF!$L$30*(1+DCF!$C$19)/((DCF!$C$17*(DCF!$C$5+$B29*F$27)+(1-DCF!$C$17)*DCF!$C$14)-DCF!$C$19)*(1+(DCF!$C$17*(DCF!$C$5+$B29*F$27)+(1-DCF!$C$17)*DCF!$C$14))^(-DCF!$C$42)+DCF!$C$20)/DCF!$C$21 -> 180.79009 | G29: =(SUMPRODUCT(DCF!$C$33:$L$33,(1+(DCF!$C$17*(DCF!$C$5+$B29*G$27)+(1-DCF!$C$17)*DCF!$C$14))^(-DCF!$C$34:$L$34))+DCF!$L$30*(1+DCF!$C$19)/((DCF!$C$17*(DCF!$C$5+$B29*G$27)+(1-DCF!$C$17)*DCF!$C$14)-DCF!$C$19)*(1+(DCF!$C$17*(DCF!$C$5+$B29*G$27)+(1-DCF!$C$17)*DCF!$C$14))^(-DCF!$C$42)+DCF!$C$20)/DCF!$C$21 -> 168.28858
B30: 1.6 | C30: =(SUMPRODUCT(DCF!$C$33:$L$33,(1+(DCF!$C$17*(DCF!$C$5+$B30*C$27)+(1-DCF!$C$17)*DCF!$C$14))^(-DCF!$C$34:$L$34))+DCF!$L$30*(1+DCF!$C$19)/((DCF!$C$17*(DCF!$C$5+$B30*C$27)+(1-DCF!$C$17)*DCF!$C$14)-DCF!$C$19)*(1+(DCF!$C$17*(DCF!$C$5+$B30*C$27)+(1-DCF!$C$17)*DCF!$C$14))^(-DCF!$C$42)+DCF!$C$20)/DCF!$C$21 -> 209.54286 | D30: =(SUMPRODUCT(DCF!$C$33:$L$33,(1+(DCF!$C$17*(DCF!$C$5+$B30*D$27)+(1-DCF!$C$17)*DCF!$C$14))^(-DCF!$C$34:$L$34))+DCF!$L$30*(1+DCF!$C$19)/((DCF!$C$17*(DCF!$C$5+$B30*D$27)+(1-DCF!$C$17)*DCF!$C$14)-DCF!$C$19)*(1+(DCF!$C$17*(DCF!$C$5+$B30*D$27)+(1-DCF!$C$17)*DCF!$C$14))^(-DCF!$C$42)+DCF!$C$20)/DCF!$C$21 -> 190.88815 | E30: =(SUMPRODUCT(DCF!$C$33:$L$33,(1+(DCF!$C$17*(DCF!$C$5+$B30*E$27)+(1-DCF!$C$17)*DCF!$C$14))^(-DCF!$C$34:$L$34))+DCF!$L$30*(1+DCF!$C$19)/((DCF!$C$17*(DCF!$C$5+$B30*E$27)+(1-DCF!$C$17)*DCF!$C$14)-DCF!$C$19)*(1+(DCF!$C$17*(DCF!$C$5+$B30*E$27)+(1-DCF!$C$17)*DCF!$C$14))^(-DCF!$C$42)+DCF!$C$20)/DCF!$C$21 -> 175.21702 | F30: =(SUMPRODUCT(DCF!$C$33:$L$33,(1+(DCF!$C$17*(DCF!$C$5+$B30*F$27)+(1-DCF!$C$17)*DCF!$C$14))^(-DCF!$C$34:$L$34))+DCF!$L$30*(1+DCF!$C$19)/((DCF!$C$17*(DCF!$C$5+$B30*F$27)+(1-DCF!$C$17)*DCF!$C$14)-DCF!$C$19)*(1+(DCF!$C$17*(DCF!$C$5+$B30*F$27)+(1-DCF!$C$17)*DCF!$C$14))^(-DCF!$C$42)+DCF!$C$20)/DCF!$C$21 -> 161.87657 | G30: =(SUMPRODUCT(DCF!$C$33:$L$33,(1+(DCF!$C$17*(DCF!$C$5+$B30*G$27)+(1-DCF!$C$17)*DCF!$C$14))^(-DCF!$C$34:$L$34))+DCF!$L$30*(1+DCF!$C$19)/((DCF!$C$17*(DCF!$C$5+$B30*G$27)+(1-DCF!$C$17)*DCF!$C$14)-DCF!$C$19)*(1+(DCF!$C$17*(DCF!$C$5+$B30*G$27)+(1-DCF!$C$17)*DCF!$C$14))^(-DCF!$C$42)+DCF!$C$20)/DCF!$C$21 -> 150.39065
B31: 1.8 | C31: =(SUMPRODUCT(DCF!$C$33:$L$33,(1+(DCF!$C$17*(DCF!$C$5+$B31*C$27)+(1-DCF!$C$17)*DCF!$C$14))^(-DCF!$C$34:$L$34))+DCF!$L$30*(1+DCF!$C$19)/((DCF!$C$17*(DCF!$C$5+$B31*C$27)+(1-DCF!$C$17)*DCF!$C$14)-DCF!$C$19)*(1+(DCF!$C$17*(DCF!$C$5+$B31*C$27)+(1-DCF!$C$17)*DCF!$C$14))^(-DCF!$C$42)+DCF!$C$20)/DCF!$C$21 -> 190.88815 | D31: =(SUMPRODUCT(DCF!$C$33:$L$33,(1+(DCF!$C$17*(DCF!$C$5+$B31*D$27)+(1-DCF!$C$17)*DCF!$C$14))^(-DCF!$C$34:$L$34))+DCF!$L$30*(1+DCF!$C$19)/((DCF!$C$17*(DCF!$C$5+$B31*D$27)+(1-DCF!$C$17)*DCF!$C$14)-DCF!$C$19)*(1+(DCF!$C$17*(DCF!$C$5+$B31*D$27)+(1-DCF!$C$17)*DCF!$C$14))^(-DCF!$C$42)+DCF!$C$20)/DCF!$C$21 -> 173.43319 | E31: =(SUMPRODUCT(DCF!$C$33:$L$33,(1+(DCF!$C$17*(DCF!$C$5+$B31*E$27)+(1-DCF!$C$17)*DCF!$C$14))^(-DCF!$C$34:$L$34))+DCF!$L$30*(1+DCF!$C$19)/((DCF!$C$17*(DCF!$C$5+$B31*E$27)+(1-DCF!$C$17)*DCF!$C$14)-DCF!$C$19)*(1+(DCF!$C$17*(DCF!$C$5+$B31*E$27)+(1-DCF!$C$17)*DCF!$C$14))^(-DCF!$C$42)+DCF!$C$20)/DCF!$C$21 -> 158.84684 | F31: =(SUMPRODUCT(DCF!$C$33:$L$33,(1+(DCF!$C$17*(DCF!$C$5+$B31*F$27)+(1-DCF!$C$17)*DCF!$C$14))^(-DCF!$C$34:$L$34))+DCF!$L$30*(1+DCF!$C$19)/((DCF!$C$17*(DCF!$C$5+$B31*F$27)+(1-DCF!$C$17)*DCF!$C$14)-DCF!$C$19)*(1+(DCF!$C$17*(DCF!$C$5+$B31*F$27)+(1-DCF!$C$17)*DCF!$C$14))^(-DCF!$C$42)+DCF!$C$20)/DCF!$C$21 -> 146.48603 | G31: =(SUMPRODUCT(DCF!$C$33:$L$33,(1+(DCF!$C$17*(DCF!$C$5+$B31*G$27)+(1-DCF!$C$17)*DCF!$C$14))^(-DCF!$C$34:$L$34))+DCF!$L$30*(1+DCF!$C$19)/((DCF!$C$17*(DCF!$C$5+$B31*G$27)+(1-DCF!$C$17)*DCF!$C$14)-DCF!$C$19)*(1+(DCF!$C$17*(DCF!$C$5+$B31*G$27)+(1-DCF!$C$17)*DCF!$C$14))^(-DCF!$C$42)+DCF!$C$20)/DCF!$C$21 -> 135.88561
B32: 2 | C32: =(SUMPRODUCT(DCF!$C$33:$L$33,(1+(DCF!$C$17*(DCF!$C$5+$B32*C$27)+(1-DCF!$C$17)*DCF!$C$14))^(-DCF!$C$34:$L$34))+DCF!$L$30*(1+DCF!$C$19)/((DCF!$C$17*(DCF!$C$5+$B32*C$27)+(1-DCF!$C$17)*DCF!$C$14)-DCF!$C$19)*(1+(DCF!$C$17*(DCF!$C$5+$B32*C$27)+(1-DCF!$C$17)*DCF!$C$14))^(-DCF!$C$42)+DCF!$C$20)/DCF!$C$21 -> 175.21702 | D32: =(SUMPRODUCT(DCF!$C$33:$L$33,(1+(DCF!$C$17*(DCF!$C$5+$B32*D$27)+(1-DCF!$C$17)*DCF!$C$14))^(-DCF!$C$34:$L$34))+DCF!$L$30*(1+DCF!$C$19)/((DCF!$C$17*(DCF!$C$5+$B32*D$27)+(1-DCF!$C$17)*DCF!$C$14)-DCF!$C$19)*(1+(DCF!$C$17*(DCF!$C$5+$B32*D$27)+(1-DCF!$C$17)*DCF!$C$14))^(-DCF!$C$42)+DCF!$C$20)/DCF!$C$21 -> 158.84684 | E32: =(SUMPRODUCT(DCF!$C$33:$L$33,(1+(DCF!$C$17*(DCF!$C$5+$B32*E$27)+(1-DCF!$C$17)*DCF!$C$14))^(-DCF!$C$34:$L$34))+DCF!$L$30*(1+DCF!$C$19)/((DCF!$C$17*(DCF!$C$5+$B32*E$27)+(1-DCF!$C$17)*DCF!$C$14)-DCF!$C$19)*(1+(DCF!$C$17*(DCF!$C$5+$B32*E$27)+(1-DCF!$C$17)*DCF!$C$14))^(-DCF!$C$42)+DCF!$C$20)/DCF!$C$21 -> 145.22846 | F32: =(SUMPRODUCT(DCF!$C$33:$L$33,(1+(DCF!$C$17*(DCF!$C$5+$B32*F$27)+(1-DCF!$C$17)*DCF!$C$14))^(-DCF!$C$34:$L$34))+DCF!$L$30*(1+DCF!$C$19)/((DCF!$C$17*(DCF!$C$5+$B32*F$27)+(1-DCF!$C$17)*DCF!$C$14)-DCF!$C$19)*(1+(DCF!$C$17*(DCF!$C$5+$B32*F$27)+(1-DCF!$C$17)*DCF!$C$14))^(-DCF!$C$42)+DCF!$C$20)/DCF!$C$21 -> 133.73252 | G32: =(SUMPRODUCT(DCF!$C$33:$L$33,(1+(DCF!$C$17*(DCF!$C$5+$B32*G$27)+(1-DCF!$C$17)*DCF!$C$14))^(-DCF!$C$34:$L$34))+DCF!$L$30*(1+DCF!$C$19)/((DCF!$C$17*(DCF!$C$5+$B32*G$27)+(1-DCF!$C$17)*DCF!$C$14)-DCF!$C$19)*(1+(DCF!$C$17*(DCF!$C$5+$B32*G$27)+(1-DCF!$C$17)*DCF!$C$14))^(-DCF!$C$42)+DCF!$C$20)/DCF!$C$21 -> 123.907
B33: 2.2 | C33: =(SUMPRODUCT(DCF!$C$33:$L$33,(1+(DCF!$C$17*(DCF!$C$5+$B33*C$27)+(1-DCF!$C$17)*DCF!$C$14))^(-DCF!$C$34:$L$34))+DCF!$L$30*(1+DCF!$C$19)/((DCF!$C$17*(DCF!$C$5+$B33*C$27)+(1-DCF!$C$17)*DCF!$C$14)-DCF!$C$19)*(1+(DCF!$C$17*(DCF!$C$5+$B33*C$27)+(1-DCF!$C$17)*DCF!$C$14))^(-DCF!$C$42)+DCF!$C$20)/DCF!$C$21 -> 161.87657 | D33: =(SUMPRODUCT(DCF!$C$33:$L$33,(1+(DCF!$C$17*(DCF!$C$5+$B33*D$27)+(1-DCF!$C$17)*DCF!$C$14))^(-DCF!$C$34:$L$34))+DCF!$L$30*(1+DCF!$C$19)/((DCF!$C$17*(DCF!$C$5+$B33*D$27)+(1-DCF!$C$17)*DCF!$C$14)-DCF!$C$19)*(1+(DCF!$C$17*(DCF!$C$5+$B33*D$27)+(1-DCF!$C$17)*DCF!$C$14))^(-DCF!$C$42)+DCF!$C$20)/DCF!$C$21 -> 146.48603 | E33: =(SUMPRODUCT(DCF!$C$33:$L$33,(1+(DCF!$C$17*(DCF!$C$5+$B33*E$27)+(1-DCF!$C$17)*DCF!$C$14))^(-DCF!$C$34:$L$34))+DCF!$L$30*(1+DCF!$C$19)/((DCF!$C$17*(DCF!$C$5+$B33*E$27)+(1-DCF!$C$17)*DCF!$C$14)-DCF!$C$19)*(1+(DCF!$C$17*(DCF!$C$5+$B33*E$27)+(1-DCF!$C$17)*DCF!$C$14))^(-DCF!$C$42)+DCF!$C$20)/DCF!$C$21 -> 133.73252 | F33: =(SUMPRODUCT(DCF!$C$33:$L$33,(1+(DCF!$C$17*(DCF!$C$5+$B33*F$27)+(1-DCF!$C$17)*DCF!$C$14))^(-DCF!$C$34:$L$34))+DCF!$L$30*(1+DCF!$C$19)/((DCF!$C$17*(DCF!$C$5+$B33*F$27)+(1-DCF!$C$17)*DCF!$C$14)-DCF!$C$19)*(1+(DCF!$C$17*(DCF!$C$5+$B33*F$27)+(1-DCF!$C$17)*DCF!$C$14))^(-DCF!$C$42)+DCF!$C$20)/DCF!$C$21 -> 123.0027 | G33: =(SUMPRODUCT(DCF!$C$33:$L$33,(1+(DCF!$C$17*(DCF!$C$5+$B33*G$27)+(1-DCF!$C$17)*DCF!$C$14))^(-DCF!$C$34:$L$34))+DCF!$L$30*(1+DCF!$C$19)/((DCF!$C$17*(DCF!$C$5+$B33*G$27)+(1-DCF!$C$17)*DCF!$C$14)-DCF!$C$19)*(1+(DCF!$C$17*(DCF!$C$5+$B33*G$27)+(1-DCF!$C$17)*DCF!$C$14))^(-DCF!$C$42)+DCF!$C$20)/DCF!$C$21 -> 113.85864
A36: TABLE 4: Comps - EV / NTM revenue multiple applied to AMD NTM revenue
B37: Multiple | C37: Implied value / share (USD) | D37: vs. price
B38: 6 | C38: =(B38*Comps!$J$17+Comps!$G$17-Comps!$F$17)/DCF!$C$21 -> 238.17081 | D38: =C38/DCF!$C$22-1 -> -0.6066738
B39: 8 | C39: =(B39*Comps!$J$17+Comps!$G$17-Comps!$F$17)/DCF!$C$21 -> 315.57495 | D39: =C39/DCF!$C$22-1 -> -0.47884506
B40: 10 | C40: =(B40*Comps!$J$17+Comps!$G$17-Comps!$F$17)/DCF!$C$21 -> 392.97908 | D40: =C40/DCF!$C$22-1 -> -0.35101633
B41: 12 | C41: =(B41*Comps!$J$17+Comps!$G$17-Comps!$F$17)/DCF!$C$21 -> 470.38322 | D41: =C41/DCF!$C$22-1 -> -0.22318759
B42: 14 | C42: =(B42*Comps!$J$17+Comps!$G$17-Comps!$F$17)/DCF!$C$21 -> 547.78735 | D42: =C42/DCF!$C$22-1 -> -0.095358853
B43: 16 | C43: =(B43*Comps!$J$17+Comps!$G$17-Comps!$F$17)/DCF!$C$21 -> 625.19149 | D43: =C43/DCF!$C$22-1 -> 0.032469884
B44: 18 | C44: =(B44*Comps!$J$17+Comps!$G$17-Comps!$F$17)/DCF!$C$21 -> 702.59562 | D44: =C44/DCF!$C$22-1 -> 0.16029862
A46: Multiple implied by current price (EV / NTM revenue) | C46: =Comps!N17 -> 15.237343

Sheet Comps
A1: AMD - Trading Comparables (NVDA, AVGO, INTC, QCOM)
A2: USD millions except per share. Prices/market caps: stock-data get_quote 2026-10-14. Balance sheet & LTM: SEC XBRL (stock-data get_financials), latest reported quarter. NTM revenue for peers = analyst estimates (no consensus feed). Betas: 5y monthly vs S&P 500 (59 months to 2026-09), Blume-adjusted.
A4: Company | B4: Ticker | C4: Latest qtr end | D4: Price (USD) | E4: Market cap | F4: Total debt | G4: Cash + ST inv. | H4: Enterprise value | I4: LTM revenue | J4: NTM revenue (est.) | K4: LTM op. income | L4: LTM net income | M4: EV / LTM rev | N4: EV / NTM rev | O4: EV / LTM EBIT | P4: P/E LTM | Q4: NTM rev growth | R4: LTM op. margin | S4: Raw beta | T4: Blume beta | U4: D/E (market) | V4: Unlevered beta
A5: NVIDIA | B5: NVDA | C5: 2026-07-26 | D5: 228.52 | E5: 5518072.5 | F5: 33366 | G5: 22443 | H5: =E5+F5-G5 -> 5528995.5 | I5: 302969 | J5: 486660 | K5: 197579 | L5: 192879 | M5: =H5/I5 -> 18.249377 | N5: =H5/J5 -> 11.361105 | O5: =IF(K5>0,H5/K5,"n.m.") -> 27.98372 | P5: =IF(L5>0,E5/L5,"n.m.") -> 28.608985 | Q5: =J5/I5-1 -> 0.60630296 | R5: =K5/I5 -> 0.65214263 | S5: 2.23 | T5: =0.67*S5+0.33 -> 1.8241 | U5: =F5/E5 -> 0.0060466766 | V5: =T5/(1+(1-0.15)*U5) -> 1.8147727 | W5: NTM: Q3 FY27 guide 108,000 then +8% q/q (est.); cash excl. marketable securities (not tagged)
A6: Broadcom | B6: AVGO | C6: 2026-08-02 | D6: 357.31 | E6: 1705665.7 | F6: 59419 | G6: 23975 | H6: =E6+F6-G6 -> 1741109.7 | I6: 89104 | J6: 130200 | K6: 42814 | L6: 38265 | M6: =H6/I6 -> 19.540197 | N6: =H6/J6 -> 13.372578 | O6: =IF(K6>0,H6/K6,"n.m.") -> 40.666831 | P6: =IF(L6>0,E6/L6,"n.m.") -> 44.575087 | Q6: =J6/I6-1 -> 0.46121386 | R6: =K6/I6 -> 0.4804947 | S6: 1.485 | T6: =0.67*S6+0.33 -> 1.32495 | U6: =F6/E6 -> 0.034836252 | V6: =T6/(1+(1-0.15)*U6) -> 1.2868455 | W6: NTM: latest qtr 29,591 x4 x1.10 (est.)
A7: Intel | B7: INTC | C7: 2026-06-27 | D7: 102.81 | E7: 540217.8 | F7: 50537 | G7: 29727 | H7: =E7+F7-G7 -> 561027.8 | I7: 57032 | J7: 65800 | K7: -77 | L7: -11289 | M7: =H7/I7 -> 9.8370704 | N7: =H7/J7 -> 8.5262584 | O7: =IF(K7>0,H7/K7,"n.m.") -> n.m. | P7: =IF(L7>0,E7/L7,"n.m.") -> n.m. | Q7: =J7/I7-1 -> 0.15373825 | R7: =K7/I7 -> -0.0013501192 | S7: 2.354 | T7: =0.67*S7+0.33 -> 1.90718 | U7: =F7/E7 -> 0.093549305 | V7: =T7/(1+(1-0.15)*U7) -> 1.7666977 | W7: NTM: latest qtr x4 x1.02 (est.); LTM loss -> P/E n.m.
A8: Qualcomm | B8: QCOM | C8: 2026-06-28 | D8: 176.86 | E8: 188858.1 | F8: 14811 | G8: 8304 | H8: =E8+F8-G8 -> 195365.1 | I8: 44069 | J8: 42747 | K8: 10219 | L8: 9259 | M8: =H8/I8 -> 4.4331639 | N8: =H8/J8 -> 4.5702646 | O8: =IF(K8>0,H8/K8,"n.m.") -> 19.11783 | P8: =IF(L8>0,E8/L8,"n.m.") -> 20.397246 | Q8: =J8/I8-1 -> -0.029998412 | R8: =K8/I8 -> 0.23188636 | S8: 1.751 | T8: =0.67*S8+0.33 -> 1.50317 | U8: =F8/E8 -> 0.07842396 | V8: =T8/(1+(1-0.15)*U8) -> 1.4092302 | W8: NTM: LTM x0.97 (est.); debt = last tagged total (FY2025Q4)
A9: STATISTICAL SUMMARY (peers)
A10: Maximum | E10: =MAX(E5:E8) -> 5518072.5 | M10: =MAX(M5:M8) -> 19.540197 | N10: =MAX(N5:N8) -> 13.372578 | O10: =MAX(O5:O8) -> 40.666831 | P10: =MAX(P5:P8) -> 44.575087 | Q10: =MAX(Q5:Q8) -> 0.60630296 | R10: =MAX(R5:R8) -> 0.65214263 | T10: =MAX(T5:T8) -> 1.90718 | V10: =MAX(V5:V8) -> 1.8147727
A11: 75th percentile | E11: =PERCENTILE(E5:E8,0.75) -> 2658767.4 | M11: =PERCENTILE(M5:M8,0.75) -> 18.572082 | N11: =PERCENTILE(N5:N8,0.75) -> 11.863974 | O11: =PERCENTILE(O5:O8,0.75) -> 34.325276 | P11: =PERCENTILE(P5:P8,0.75) -> 36.592036 | Q11: =PERCENTILE(Q5:Q8,0.75) -> 0.49748614 | R11: =PERCENTILE(R5:R8,0.75) -> 0.52340668 | T11: =PERCENTILE(T5:T8,0.75) -> 1.84487 | V11: =PERCENTILE(V5:V8,0.75) -> 1.7787164
A12: Median | E12: =MEDIAN(E5:E8) -> 1122941.8 | M12: =MEDIAN(M5:M8) -> 14.043224 | N12: =MEDIAN(N5:N8) -> 9.9436818 | O12: =MEDIAN(O5:O8) -> 27.98372 | P12: =MEDIAN(P5:P8) -> 28.608985 | Q12: =MEDIAN(Q5:Q8) -> 0.30747606 | R12: =MEDIAN(R5:R8) -> 0.35619053 | T12: =MEDIAN(T5:T8) -> 1.663635 | V12: =MEDIAN(V5:V8) -> 1.5879639
A13: 25th percentile | E13: =PERCENTILE(E5:E8,0.25) -> 452377.88 | M13: =PERCENTILE(M5:M8,0.25) -> 8.4860938 | N13: =PERCENTILE(N5:N8,0.25) -> 7.5372599 | O13: =PERCENTILE(O5:O8,0.25) -> 23.550775 | P13: =PERCENTILE(P5:P8,0.25) -> 24.503116 | Q13: =PERCENTILE(Q5:Q8,0.25) -> 0.10780409 | R13: =PERCENTILE(R5:R8,0.25) -> 0.17357724 | T13: =PERCENTILE(T5:T8,0.25) -> 1.458615 | V13: =PERCENTILE(V5:V8,0.25) -> 1.378634
A14: Minimum | E14: =MIN(E5:E8) -> 188858.1 | M14: =MIN(M5:M8) -> 4.4331639 | N14: =MIN(N5:N8) -> 4.5702646 | O14: =MIN(O5:O8) -> 19.11783 | P14: =MIN(P5:P8) -> 20.397246 | Q14: =MIN(Q5:Q8) -> -0.029998412 | R14: =MIN(R5:R8) -> -0.0013501192 | T14: =MIN(T5:T8) -> 1.32495 | V14: =MIN(V5:V8) -> 1.2868455
A16: TARGET
A17: Advanced Micro Devices | B17: AMD | C17: 2026-06-27 | D17: ='DCF Inputs'!C28 -> 605.53 | E17: ='DCF Inputs'!C31 -> 988224.96 | F17: ='DCF Inputs'!C34 -> 3226 | G17: ='DCF Inputs'!C32+'DCF Inputs'!C33 -> 13111 | H17: =E17+F17-G17 -> 978339.96 | I17: ='Quarterly Hist'!G6+'Quarterly Hist'!H6+'Quarterly Hist'!I6+'Quarterly Hist'!J6 -> 41305 | J17: =0.25*'Revenue Model'!G47+0.75*'Revenue Model'!H47 -> 64206.73 | K17: ='Quarterly Hist'!G16+'Quarterly Hist'!H16+'Quarterly Hist'!I16+'Quarterly Hist'!J16 -> 6488 | L17: ='Quarterly Hist'!G19+'Quarterly Hist'!H19+'Quarterly Hist'!I19+'Quarterly Hist'!J19 -> 6434 | M17: =H17/I17 -> 23.685751 | N17: =H17/J17 -> 15.237343 | O17: =H17/K17 -> 150.79223 | P17: =E17/L17 -> 153.59418 | Q17: =J17/I17-1 -> 0.55445418 | R17: =K17/I17 -> 0.15707541 | S17: 2.515 | T17: =0.67*S17+0.33 -> 2.01505 | U17: =F17/E17 -> 0.0032644389 | W17: NTM = 25% FY2026E + 75% FY2027E (model base case)
A18: AMD premium / (discount) to peer median EV/NTM revenue | N18: =N17/N12-1 -> 0.53236428
A20: COMPS-IMPLIED VALUE (EV / NTM revenue applied to AMD NTM revenue)
A21: Case | C21: Multiple | D21: AMD NTM revenue | E21: Implied EV | F21: Net cash | G21: Equity value | H21: Diluted shares | I21: Value / share (USD) | J21: vs. price
A22: 25th percentile | C22: =N13 -> 7.5372599 | D22: =J17 -> 64206.73 | E22: =C22*D22 -> 483942.81 | F22: =G17-F17 -> 9885 | G22: =E22+F22 -> 493827.81 | H22: ='DCF Inputs'!C30 -> 1659 | I22: =G22/H22 -> 297.66595 | J22: =I22/D17-1 -> -0.5084208
A23: Median | C23: =N12 -> 9.9436818 | D23: =J17 -> 64206.73 | E23: =C23*D23 -> 638451.29 | F23: =G17-F17 -> 9885 | G23: =E23+F23 -> 648336.29 | H23: ='DCF Inputs'!C30 -> 1659 | I23: =G23/H23 -> 390.79945 | J23: =I23/D17-1 -> -0.35461587
A24: 75th percentile | C24: =N11 -> 11.863974 | D24: =J17 -> 64206.73 | E24: =C24*D24 -> 761746.95 | F24: =G17-F17 -> 9885 | G24: =E24+F24 -> 771631.95 | H24: ='DCF Inputs'!C30 -> 1659 | I24: =G24/H24 -> 465.11871 | J24: =I24/D17-1 -> -0.23188163
A26: Peer selection: NVDA (AI GPU leader, direct DC competitor); AVGO (custom AI ASIC + networking, competes for hyperscaler AI budgets); INTC (x86 CPU rival in server and client); QCOM (Arm PC entrant; large fabless peer). Peer set specified by the user.
A27: Multiple choice: EV/NTM revenue is primary because AMD's GAAP earnings are depressed by acquisition amortization (USD ~2.1bn/yr) and Intel has negative LTM earnings. Median applied with no premium: AMD's faster growth than the median is offset by GAAP operating margin (~16%) far below NVDA/AVGO (48-65%).

Sheet Valuation Summary
A1: AMD - Valuation Summary, Price Target and Rating
A2: USD per share unless stated. 12-month price target. Rating bands: BUY if upside > +15%; SELL if < -10%; otherwise HOLD.
A4: Method | B4: Low | C4: Base | D4: High | E4: Weight | F4: Weighted | G4: Basis for range
A5: DCF (base case) | B5: =Sensitivity!D10 -> 156.13664 | C5: =DCF!C48 -> 175.90701 | D5: =Sensitivity!F8 -> 202.29013 | E5: 0.5 | F5: =C5*E5 -> 87.953507 | G5: WACC +/-1pp and g -/+0.5pp (Sensitivity Table 1)
A6: Trading comps (EV / NTM revenue) | B6: =Comps!I22 -> 297.66595 | C6: =Comps!I23 -> 390.79945 | D6: =Comps!I24 -> 465.11871 | E6: 0.5 | F6: =C6*E6 -> 195.39973 | G6: Peer 25th / median / 75th percentile
A7: Weighted value | B7: =B5*E5+B6*E6 -> 226.9013 | C7: =SUM(F5:F6) -> 283.35323 | D7: =D5*E5+D6*E6 -> 333.70442 | E7: =SUM(E5:E6) -> 1
A9: 12-MONTH PRICE TARGET (rounded to nearest USD 5) | C9: =ROUND(C7/5,0)*5 -> 285
A10: Current price (2026-10-14) | C10: =DCF!$C$22 -> 605.53
A11: Implied upside / (downside) | C11: =C9/C10-1 -> -0.52933794
A12: RATING | C12: =IF(C11>0.15,"BUY",IF(C11<-0.1,"SELL","HOLD")) -> SELL
A13: Implied EV / NTM revenue at target | C13: =(C9*DCF!$C$21-DCF!$C$20)/Comps!J17 -> 7.2099918
A14: Implied P/E on FY2027E GAAP EPS at target | C14: =C9/'Income Statement'!H65 -> 33.403785
A15: Implied P/E on FY2027E approx. non-GAAP EPS at target | C15: =C9/'Income Statement'!H67 -> 25.950798
A16: Current P/E on FY2027E approx. non-GAAP EPS | C16: =C10/'Income Statement'!H67 -> 55.136794
A18: SCENARIO DCF VALUES (static model snapshots, same WACC / fade / terminal growth)
A19: Scenario | B19: Probability | C19: FY2030E revenue | D19: FY2030E UFCF | E19: DCF value / share | F19: vs. price | G19: Prob.-weighted
A20: Bear | B20: 0.25 | C20: =DCF!G118 -> 65405.9 | D20: =DCF!G120 -> 11779.9 | E20: =DCF!C138 -> 70.93319 | F20: =E20/$C$10-1 -> -0.88285768 | G20: =B20*E20 -> 17.733298
A21: Base | B21: 0.5 | C21: =DCF!G88 -> 114511.3 | D21: =DCF!G90 -> 29285.1 | E21: =DCF!C108 -> 175.90694 | F21: =E21/$C$10-1 -> -0.70949922 | G21: =B21*E21 -> 87.95347
A22: Bull | B22: 0.25 | C22: =DCF!G58 -> 157285.6 | D22: =DCF!G60 -> 44813.3 | E22: =DCF!C78 -> 280.0219 | F22: =E22/$C$10-1 -> -0.53755899 | G22: =B22*E22 -> 70.005476
A23: Probability-weighted DCF value | G23: =SUM(G20:G22) -> 175.69224
A25: FOOTBALL FIELD (USD per share)
A26: Range | B26: Low | C26: High | D26: Midpoint
A27: DCF - base case (WACC +/-1pp, g +/-0.5pp) | B27: =B5 -> 156.13664 | C27: =D5 -> 202.29013 | D27: =(B27+C27)/2 -> 179.21339
A28: DCF - full sensitivity grid (Table 1) | B28: =MIN(Sensitivity!C6:G12) -> 130.11978 | C28: =MAX(Sensitivity!C6:G12) -> 279.63291 | D28: =(B28+C28)/2 -> 204.87634
A29: DCF - bear to bull scenarios | B29: =E20 -> 70.93319 | C29: =E22 -> 280.0219 | D29: =(B29+C29)/2 -> 175.47755
A30: Trading comps (25th-75th pct EV/NTM rev) | B30: =B6 -> 297.66595 | C30: =D6 -> 465.11871 | D30: =(B30+C30)/2 -> 381.39233
A31: 52-week trading range | B31: 188.22 | C31: 658.52 | D31: =(B31+C31)/2 -> 423.37
A32: Price target | B32: =C9 -> 285 | C32: =C9 -> 285 | D32: =(B32+C32)/2 -> 285
A33: Current price | B33: =C10 -> 605.53 | C33: =C10 -> 605.53 | D33: =(B33+C33)/2 -> 605.53
A35: Reverse DCF check: see Sensitivity Table 1/3 - the current price is not reached anywhere in the WACC 10-16% / g 2-4% grid under base-case cash flows.

Sheet Quarterly Hist
A1: AMD - Quarterly History (8 quarters)
A2: USD millions. SEC XBRL via stock-data get_financials (Q4 values derived as FY - 9M). Segment data from 10-Qs / earnings releases.
A4: USD millions | C4: Q3 FY24 | D4: Q4 FY24 | E4: Q1 FY25 | F4: Q2 FY25 | G4: Q3 FY25 | H4: Q4 FY25 | I4: Q1 FY26 | J4: Q2 FY26
A5: Period end | C5: 2024-09-28 | D5: 2024-12-28 | E5: 2025-03-29 | F5: 2025-06-28 | G5: 2025-09-27 | H5: 2025-12-27 | I5: 2026-03-28 | J5: 2026-06-27
A6: Revenue | C6: 6819 | D6: 7658 | E6: 7438 | F6: 7685 | G6: 9246 | H6: 10270 | I6: 10253 | J6: 11536
A7: Data Center | C7: 3549 | D7: 3859 | E7: 3674 | F7: 3240 | G7: 4341 | H7: 5380 | I7: 5775 | J7: 6718
A8: Client | C8: 1881 | D8: 2313 | E8: 2294 | F8: 2499 | G8: 2750 | H8: 3097 | I8: 2885 | J8: 3062
A9: Gaming | C9: 462 | D9: 563 | E9: 647 | F9: 1122 | G9: 1298 | H9: 843 | I9: 720 | J9: 779
A10: Embedded | C10: 927 | D10: 923 | E10: 823 | F10: 824 | G10: 857 | H10: 950 | I10: 873 | J10: 977
A11: Cost of revenue (incl. amortization) | C11: 3400 | D11: 3776 | E11: 3702 | F11: 4626 | G11: 4466 | H11: 4693 | I11: 4837 | J11: 5333
A12: Gross profit | C12: =C6-C11 -> 3419 | D12: =D6-D11 -> 3882 | E12: =E6-E11 -> 3736 | F12: =F6-F11 -> 3059 | G12: =G6-G11 -> 4780 | H12: =H6-H11 -> 5577 | I12: =I6-I11 -> 5416 | J12: =J6-J11 -> 6203
A13: Research & development | C13: 1636 | D13: 1712 | E13: 1728 | F13: 1894 | G13: 2139 | H13: 2330 | I13: 2397 | J13: 2528
A14: SG&A / MG&A | C14: 707 | D14: 781 | E14: 886 | F14: 991 | G14: 1069 | H14: 1198 | I14: 1253 | J14: 1401
A15: Total operating expenses (XBRL, incl. amortization) | C15: 2695 | D15: 3011 | E15: 2930 | F15: 3193 | G15: 3510 | H15: 3825 | I15: 3940 | J15: 4213
A16: Operating income | C16: 724 | D16: 871 | E16: 806 | F16: -134 | G16: 1270 | H16: 1752 | I16: 1476 | J16: 1990
A17: Pre-tax income | C17: 737 | D17: 889 | E17: 825 | F17: -74 | G17: 1315 | H17: 2074 | I17: 1604 | J17: 2551
A18: Income tax | C18: -27 | D18: 419 | E18: 123 | F18: -834 | G18: 153 | H18: 455 | I18: 238 | J18: 252
A19: Net income | C19: 771 | D19: 482 | E19: 709 | F19: 872 | G19: 1243 | H19: 1511 | I19: 1383 | J19: 2297
A20: Diluted EPS (USD) | C20: 0.47 | E20: 0.44 | F20: 0.54 | G20: 0.75 | H20: 0.92 | I20: 0.84 | J20: 1.38
A21: Diluted shares (M) | C21: 1636 | E21: 1626 | F21: 1630 | G21: 1641 | I21: 1650 | J21: 1659
A22: Operating cash flow | C22: 628 | D22: 1299 | E22: 939 | F22: 2011 | G22: 2159 | H22: 2600 | I22: 2955 | J22: 2366
A23: Capex | C23: 132 | D23: 208 | E23: 212 | F23: 282 | G23: 258 | H23: 222 | I23: 389 | J23: 808
A24: Free cash flow (OCF - capex) | C24: =C22-C23 -> 496 | D24: =D22-D23 -> 1091 | E24: =E22-E23 -> 727 | F24: =F22-F23 -> 1729 | G24: =G22-G23 -> 1901 | H24: =H22-H23 -> 2378 | I24: =I22-I23 -> 2566 | J24: =J22-J23 -> 1558
A25: Stock-based compensation | C25: 351 | D25: 339 | E25: 364 | F25: 369 | G25: 419 | H25: 486 | I25: 487 | J25: 503
A26: Share repurchases | C26: 250 | D26: 256 | E26: 749 | F26: 478 | G26: 89 | H26: 0 | I26: 221 | J26: 0
A27: Cash and equivalents | C27: 3897 | D27: 3787 | E27: 6049 | F27: 4442 | G27: 4808 | H27: 5539 | I27: 5585 | J27: 5086
A28: Short-term investments | C28: 647 | D28: 1345 | E28: 1261 | F28: 1425 | G28: 2435 | H28: 5013 | I28: 6762 | J28: 8025
A29: Inventories | C29: 5374 | D29: 5734 | E29: 6416 | F29: 6677 | G29: 7313 | H29: 7920 | I29: 8045 | J29: 8468
A30: Total assets | C30: 69636 | D30: 69226 | E30: 71550 | F30: 74820 | G30: 76891 | H30: 76926 | I30: 79642 | J30: 84464
A31: Total debt (current + long-term) | C31: 1720 | D31: 1721 | E31: 3217 | F31: 3218 | G31: 3220 | H31: 3222 | I31: 3224 | J31: 3226
A32: Stockholders' equity | C32: 56985 | D32: 57568 | E32: 57881 | F32: 59665 | G32: 60790 | H32: 62999 | I32: 64462 | J32: 67224
A34: Ratios
A35: Gross margin % (GAAP) | C35: =C12/C6 -> 0.50139317 | D35: =D12/D6 -> 0.50692087 | E35: =E12/E6 -> 0.50228556 | F35: =F12/F6 -> 0.39804815 | G35: =G12/G6 -> 0.51698032 | H35: =H12/H6 -> 0.54303797 | I35: =I12/I6 -> 0.52823564 | J35: =J12/J6 -> 0.53770804
A36: Operating margin % (GAAP) | C36: =C16/C6 -> 0.10617393 | D36: =D16/D6 -> 0.11373727 | E36: =E16/E6 -> 0.10836246 | F36: =F16/F6 -> -0.017436565 | G36: =G16/G6 -> 0.13735669 | H36: =H16/H6 -> 0.17059396 | I36: =I16/I6 -> 0.14395787 | J36: =J16/J6 -> 0.17250347
A37: Revenue YoY % | G37: =G6/C6-1 -> 0.35591729 | H37: =H6/D6-1 -> 0.34108122 | I37: =I6/E6-1 -> 0.37846195 | J37: =J6/F6-1 -> 0.50110605
A38: Data Center YoY % | G38: =G7/C7-1 -> 0.22316145 | H38: =H7/D7-1 -> 0.39414356 | I38: =I7/E7-1 -> 0.57185629 | J38: =J7/F7-1 -> 1.0734568
A39: Segment sum check (should be 0) | C39: =C7+C8+C9+C10-C6 -> 0 | D39: =D7+D8+D9+D10-D6 -> 0 | E39: =E7+E8+E9+E10-E6 -> 0 | F39: =F7+F8+F9+F10-F6 -> 0 | G39: =G7+G8+G9+G10-G6 -> 0 | H39: =H7+H8+H9+H10-H6 -> 0 | I39: =I7+I8+I9+I10-I6 -> 0 | J39: =J7+J8+J9+J10-J6 -> 0
A41: FY2026E bridge (calibration of annual projection)
A42: H1 FY2026 actual revenue | C42: =I6+J6 -> 21789
A43: Q3 FY2026 guidance midpoint (2026-08-05) | C43: 13000
A44: Implied Q4 FY2026E revenue in model | C44: ='Revenue Model'!G47-C42-C43 -> 14686.5
A45: Implied Q4 QoQ growth % | C45: =C44/C43-1 -> 0.12973077

Sheet Checks
A1: AMD - Model Integrity Checks
A4: USD millions | C4: FY2022A | D4: FY2023A | E4: FY2024A | F4: FY2025A | G4: FY2026E | H4: FY2027E | I4: FY2028E | J4: FY2029E | K4: FY2030E
A5: Balance sheet balances (|A - L - E| < 0.5) | C5: =ABS('Balance Sheet'!C49)<0.5 -> TRUE | D5: =ABS('Balance Sheet'!D49)<0.5 -> TRUE | E5: =ABS('Balance Sheet'!E49)<0.5 -> TRUE | F5: =ABS('Balance Sheet'!F49)<0.5 -> TRUE | G5: =ABS('Balance Sheet'!G49)<0.5 -> TRUE | H5: =ABS('Balance Sheet'!H49)<0.5 -> TRUE | I5: =ABS('Balance Sheet'!I49)<0.5 -> TRUE | J5: =ABS('Balance Sheet'!J49)<0.5 -> TRUE | K5: =ABS('Balance Sheet'!K49)<0.5 -> TRUE
A6: CF ending cash = BS cash (projections) | G6: =ABS('Cash Flow'!G45-'Balance Sheet'!G14)<0.5 -> TRUE | H6: =ABS('Cash Flow'!H45-'Balance Sheet'!H14)<0.5 -> TRUE | I6: =ABS('Cash Flow'!I45-'Balance Sheet'!I14)<0.5 -> TRUE | J6: =ABS('Cash Flow'!J45-'Balance Sheet'!J14)<0.5 -> TRUE | K6: =ABS('Cash Flow'!K45-'Balance Sheet'!K14)<0.5 -> TRUE
A7: Revenue: product = geography | C7: =ABS('Revenue Model'!C47-'Revenue Model'!C74)<0.5 -> TRUE | D7: =ABS('Revenue Model'!D47-'Revenue Model'!D74)<0.5 -> TRUE | E7: =ABS('Revenue Model'!E47-'Revenue Model'!E74)<0.5 -> TRUE | F7: =ABS('Revenue Model'!F47-'Revenue Model'!F74)<0.5 -> TRUE | G7: =ABS('Revenue Model'!G47-'Revenue Model'!G74)<0.5 -> TRUE | H7: =ABS('Revenue Model'!H47-'Revenue Model'!H74)<0.5 -> TRUE | I7: =ABS('Revenue Model'!I47-'Revenue Model'!I74)<0.5 -> TRUE | J7: =ABS('Revenue Model'!J47-'Revenue Model'!J74)<0.5 -> TRUE | K7: =ABS('Revenue Model'!K47-'Revenue Model'!K74)<0.5 -> TRUE
A8: Revenue: Revenue Model = Income Statement | C8: =ABS('Revenue Model'!C47-'Income Statement'!C10)<0.5 -> TRUE | D8: =ABS('Revenue Model'!D47-'Income Statement'!D10)<0.5 -> TRUE | E8: =ABS('Revenue Model'!E47-'Income Statement'!E10)<0.5 -> TRUE | F8: =ABS('Revenue Model'!F47-'Income Statement'!F10)<0.5 -> TRUE | G8: =ABS('Revenue Model'!G47-'Income Statement'!G10)<0.5 -> TRUE | H8: =ABS('Revenue Model'!H47-'Income Statement'!H10)<0.5 -> TRUE | I8: =ABS('Revenue Model'!I47-'Income Statement'!I10)<0.5 -> TRUE | J8: =ABS('Revenue Model'!J47-'Income Statement'!J10)<0.5 -> TRUE | K8: =ABS('Revenue Model'!K47-'Income Statement'!K10)<0.5 -> TRUE
A9: Geographic shares sum to 100% | C9: =ABS('Revenue Model'!C87-1)<0.0001 -> TRUE | D9: =ABS('Revenue Model'!D87-1)<0.0001 -> TRUE | E9: =ABS('Revenue Model'!E87-1)<0.0001 -> TRUE | F9: =ABS('Revenue Model'!F87-1)<0.0001 -> TRUE | G9: =ABS('Revenue Model'!G87-1)<0.0001 -> TRUE | H9: =ABS('Revenue Model'!H87-1)<0.0001 -> TRUE | I9: =ABS('Revenue Model'!I87-1)<0.0001 -> TRUE | J9: =ABS('Revenue Model'!J87-1)<0.0001 -> TRUE | K9: =ABS('Revenue Model'!K87-1)<0.0001 -> TRUE
A11: Historical tie-outs to reported figures
A12: Revenue (reported) | C12: 23601 | D12: 22680 | E12: 25785 | F12: 34639
A13: ties? | C13: =ABS('Income Statement'!C10-C12)<0.5 -> TRUE | D13: =ABS('Income Statement'!D10-D12)<0.5 -> TRUE | E13: =ABS('Income Statement'!E10-E12)<0.5 -> TRUE | F13: =ABS('Income Statement'!F10-F12)<0.5 -> TRUE
A14: Gross profit (reported) | C14: 10603 | D14: 10460 | E14: 12725 | F14: 17152
A15: ties? | C15: =ABS('Income Statement'!C18-C14)<0.5 -> TRUE | D15: =ABS('Income Statement'!D18-D14)<0.5 -> TRUE | E15: =ABS('Income Statement'!E18-E14)<0.5 -> TRUE | F15: =ABS('Income Statement'!F18-F14)<0.5 -> TRUE
A16: Operating income (reported) | C16: 1264 | D16: 401 | E16: 1900 | F16: 3694
A17: ties? | C17: =ABS('Income Statement'!C32-C16)<0.5 -> TRUE | D17: =ABS('Income Statement'!D32-D16)<0.5 -> TRUE | E17: =ABS('Income Statement'!E32-E16)<0.5 -> TRUE | F17: =ABS('Income Statement'!F32-F16)<0.5 -> TRUE
A18: Net income (reported) | C18: 1320 | D18: 854 | E18: 1641 | F18: 4335
A19: ties? | C19: =ABS('Income Statement'!C56-C18)<0.5 -> TRUE | D19: =ABS('Income Statement'!D56-D18)<0.5 -> TRUE | E19: =ABS('Income Statement'!E56-E18)<0.5 -> TRUE | F19: =ABS('Income Statement'!F56-F18)<0.5 -> TRUE
A20: Diluted EPS (reported) | C20: 0.84 | D20: 0.53 | E20: 1 | F20: 2.65
A21: ties? | C21: =ABS('Income Statement'!C65-C20)<0.006 -> TRUE | D21: =ABS('Income Statement'!D65-D20)<0.006 -> TRUE | E21: =ABS('Income Statement'!E65-E20)<0.006 -> TRUE | F21: =ABS('Income Statement'!F65-F20)<0.006 -> TRUE
A22: Operating cash flow (reported) | C22: 3565 | D22: 1667 | E22: 3041 | F22: 7709
A23: ties? | C23: =ABS('Cash Flow'!C21-C22)<0.5 -> TRUE | D23: =ABS('Cash Flow'!D21-D22)<0.5 -> TRUE | E23: =ABS('Cash Flow'!E21-E22)<0.5 -> TRUE | F23: =ABS('Cash Flow'!F21-F22)<0.5 -> TRUE
A24: Investing cash flow (reported) | C24: 1999 | D24: -1423 | E24: -1101 | F24: -5533
A25: ties? | C25: =ABS('Cash Flow'!C29-C24)<0.5 -> TRUE | D25: =ABS('Cash Flow'!D29-D24)<0.5 -> TRUE | E25: =ABS('Cash Flow'!E29-E24)<0.5 -> TRUE | F25: =ABS('Cash Flow'!F29-F24)<0.5 -> TRUE
A26: Financing cash flow (reported) | C26: -3264 | D26: -1146 | E26: -2062 | F26: -431
A27: ties? | C27: =ABS('Cash Flow'!C41-C26)<0.5 -> TRUE | D27: =ABS('Cash Flow'!D41-D26)<0.5 -> TRUE | E27: =ABS('Cash Flow'!E41-E26)<0.5 -> TRUE | F27: =ABS('Cash Flow'!F41-F26)<0.5 -> TRUE
A28: Total assets (reported) | C28: 67580 | D28: 67885 | E28: 69226 | F28: 76926
A29: ties? | C29: =ABS('Balance Sheet'!C26-C28)<0.5 -> TRUE | D29: =ABS('Balance Sheet'!D26-D28)<0.5 -> TRUE | E29: =ABS('Balance Sheet'!E26-E28)<0.5 -> TRUE | F29: =ABS('Balance Sheet'!F26-F28)<0.5 -> TRUE
A30: Stockholders' equity (reported) | C30: 54750 | D30: 55892 | E30: 57568 | F30: 62999
A31: ties? | C31: =ABS('Balance Sheet'!C47-C30)<0.5 -> TRUE | D31: =ABS('Balance Sheet'!D47-D30)<0.5 -> TRUE | E31: =ABS('Balance Sheet'!E47-E30)<0.5 -> TRUE | F31: =ABS('Balance Sheet'!F47-F30)<0.5 -> TRUE
A32: Total current assets (reported) | C32: 15019 | D32: 16768 | E32: 19049 | F32: 26947
A33: ties? | C33: =ABS('Balance Sheet'!C19-C32)<0.5 -> TRUE | D33: =ABS('Balance Sheet'!D19-D32)<0.5 -> TRUE | E33: =ABS('Balance Sheet'!E19-E32)<0.5 -> TRUE | F33: =ABS('Balance Sheet'!F19-F32)<0.5 -> TRUE
A34: Total current liabilities (reported) | C34: 6369 | D34: 6689 | E34: 7281 | F34: 9455
A35: ties? | C35: =ABS('Balance Sheet'!C33-C34)<0.5 -> TRUE | D35: =ABS('Balance Sheet'!D33-D34)<0.5 -> TRUE | E35: =ABS('Balance Sheet'!E33-E34)<0.5 -> TRUE | F35: =ABS('Balance Sheet'!F33-F34)<0.5 -> TRUE
A36: Data Center segment revenue (reported) | C36: 6043 | D36: 6496 | E36: 12579 | F36: 16635
A37: ties? | C37: =ABS('Revenue Model'!C12-C36)<0.5 -> TRUE | D37: =ABS('Revenue Model'!D12-D36)<0.5 -> TRUE | E37: =ABS('Revenue Model'!E12-E36)<0.5 -> TRUE | F37: =ABS('Revenue Model'!F12-F36)<0.5 -> TRUE
A38: Client segment revenue (reported) | C38: 6201 | D38: 4651 | E38: 7054 | F38: 10640
A39: ties? | C39: =ABS('Revenue Model'!C21-C38)<0.5 -> TRUE | D39: =ABS('Revenue Model'!D21-D38)<0.5 -> TRUE | E39: =ABS('Revenue Model'!E21-E38)<0.5 -> TRUE | F39: =ABS('Revenue Model'!F21-F38)<0.5 -> TRUE
A40: Gaming segment revenue (reported) | C40: 6805 | D40: 6212 | E40: 2595 | F40: 3910
A41: ties? | C41: =ABS('Revenue Model'!C30-C40)<0.5 -> TRUE | D41: =ABS('Revenue Model'!D30-D40)<0.5 -> TRUE | E41: =ABS('Revenue Model'!E30-E40)<0.5 -> TRUE | F41: =ABS('Revenue Model'!F30-F40)<0.5 -> TRUE
A42: Embedded segment revenue (reported) | C42: 4552 | D42: 5321 | E42: 3557 | F42: 3454
A43: ties? | C43: =ABS('Revenue Model'!C39-C42)<0.5 -> TRUE | D43: =ABS('Revenue Model'!D39-D42)<0.5 -> TRUE | E43: =ABS('Revenue Model'!E39-E42)<0.5 -> TRUE | F43: =ABS('Revenue Model'!F39-F42)<0.5 -> TRUE
A45: Quarterly segment sums tie to revenue | C45: =SUMPRODUCT(ABS('Quarterly Hist'!C39:J39))<0.5 -> TRUE
A47: ALL CHECKS PASS | C47: =IF(COUNTIF(C5:K46,FALSE())=0,"OK","ERROR") -> OK
