Workbook

Sheet Quarterly IS
A1: Microsoft Corporation (MSFT): Quarterly Income Statement
A2: USD millions except per-share data. Fiscal year ends June 30. A = actual, E = estimate. Model updated 2026-10-14 for the FY2026Q4 print (10-K filed 2026-07-29); FY2027Q1 is the next quarter to report.
A4: Fiscal quarter | B4: FY2024Q4 | C4: FY2025Q1 | D4: FY2025Q2 | E4: FY2025Q3 | F4: FY2025Q4 | G4: FY2026Q1 | H4: FY2026Q2 | I4: FY2026Q3 | J4: FY2026Q4 | K4: FY2027Q1 | L4: FY2027Q2 | M4: FY2027Q3 | N4: FY2027Q4
A5: Actual / Estimate | B5: A | C5: A | D5: A | E5: A | F5: A | G5: A | H5: A | I5: A | J5: A | K5: E | L5: E | M5: E | N5: E
A6: Period end | B6: 2024-06-30 | C6: 2024-09-30 | D6: 2024-12-31 | E6: 2025-03-31 | F6: 2025-06-30 | G6: 2025-09-30 | H6: 2025-12-31 | I6: 2026-03-31 | J6: 2026-06-30 | K6: 2026-09-30 | L6: 2026-12-31 | M6: 2027-03-31 | N6: 2027-06-30
A8: Revenue ($mm) | B8: 64727 | C8: 65585 | D8: 69632 | E8: 70066 | F8: 76441 | G8: 77673 | H8: 81273 | I8: 82886 | J8: 90007 | K8: =G8*(1+Assumptions!$B$5) -> 86993.76 | L8: =H8*(1+Assumptions!$B$5) -> 91025.76 | M8: =I8*(1+Assumptions!$B$5) -> 92832.32 | N8: =J8*(1+Assumptions!$B$5) -> 100807.84
A9: Cost of revenue ($mm) | B9: 19684 | C9: 20099 | D9: 21799 | E9: 21919 | F9: 24014 | G9: 24043 | H9: 25978 | I9: 26828 | J9: 29525 | K9: =K8-K10 -> 27857.219 | L9: =L8-L10 -> 29391.38 | M9: =M8-M10 -> 30050.175 | N9: =N8-N10 -> 32632.645
A10: Gross profit ($mm) | B10: =B8-B9 -> 45043 | C10: =C8-C9 -> 45486 | D10: =D8-D9 -> 47833 | E10: =E8-E9 -> 48147 | F10: =F8-F9 -> 52427 | G10: =G8-G9 -> 53630 | H10: =H8-H9 -> 55295 | I10: =I8-I9 -> 56058 | J10: =J8-J9 -> 60482 | K10: =K8*K11 -> 59136.541 | L10: =L8*L11 -> 61634.38 | M10: =M8*M11 -> 62782.145 | N10: =N8*N11 -> 68175.195
A11: Gross margin % | B11: =IF(B8=0,0,B10/B8) -> 0.69589198 | C11: =IF(C8=0,0,C10/C8) -> 0.69354273 | D11: =IF(D8=0,0,D10/D8) -> 0.68693991 | E11: =IF(E8=0,0,E10/E8) -> 0.68716639 | F11: =IF(F8=0,0,F10/F8) -> 0.68584922 | G11: =IF(G8=0,0,G10/G8) -> 0.69045872 | H11: =IF(H8=0,0,H10/H8) -> 0.68036125 | I11: =IF(I8=0,0,I10/I8) -> 0.67632652 | J11: =IF(J8=0,0,J10/J8) -> 0.67196996 | K11: =AVERAGE(G11:J11) -> 0.67977911 | L11: =AVERAGE(H11:K11) -> 0.67710921 | M11: =AVERAGE(I11:L11) -> 0.6762962 | N11: =AVERAGE(J11:M11) -> 0.67628862
A12: Operating expenses ($mm) | B12: 17118 | C12: 14934 | D12: 16180 | E12: 16147 | F12: 18104 | G12: 15669 | H12: 17020 | I12: 17660 | J12: 19879 | K12: =G12*(1+Assumptions!$B$6) -> 16609.14 | L12: =H12*(1+Assumptions!$B$6) -> 18041.2 | M12: =I12*(1+Assumptions!$B$6) -> 18719.6 | N12: =J12*(1+Assumptions!$B$6) -> 21071.74
A13: Operating income ($mm) | B13: =B10-B12 -> 27925 | C13: =C10-C12 -> 30552 | D13: =D10-D12 -> 31653 | E13: =E10-E12 -> 32000 | F13: =F10-F12 -> 34323 | G13: =G10-G12 -> 37961 | H13: =H10-H12 -> 38275 | I13: =I10-I12 -> 38398 | ... N13: =N10-N12 -> 47103.455
A14: Operating margin % | B14: =IF(B8=0,0,B13/B8) -> 0.43142738 | C14: =IF(C8=0,0,C13/C8) -> 0.46583823 | D14: =IF(D8=0,0,D13/D8) -> 0.45457548 | E14: =IF(E8=0,0,E13/E8) -> 0.45671224 | F14: =IF(F8=0,0,F13/F8) -> 0.44901296 | G14: =IF(G8=0,0,G13/G8) -> 0.48872839 | H14: =IF(H8=0,0,H13/H8) -> 0.47094361 | I14: =IF(I8=0,0,I13/I8) -> 0.46326279 | ... N14: =IF(N8=0,0,N13/N8) -> 0.46725984
A15: Other income (expense), net ($mm) | B15: -675 | C15: -283 | D15: -2288 | E15: -623 | F15: -1707 | G15: -3660 | H15: 9971 | I15: 942 | J15: 3444 | K15: =Assumptions!$B$9 -> 0 | L15: =Assumptions!$B$9 -> 0 | M15: =Assumptions!$B$9 -> 0 | N15: =Assumptions!$B$9 -> 0
A16: Pretax income ($mm) | B16: =B13+B15 -> 27250 | C16: =C13+C15 -> 30269 | D16: =D13+D15 -> 29365 | E16: =E13+E15 -> 31377 | F16: =F13+F15 -> 32616 | G16: =G13+G15 -> 34301 | H16: =H13+H15 -> 48246 | I16: =I13+I15 -> 39340 | ... N16: =N13+N15 -> 47103.455
A17: Income tax ($mm) | B17: 5214 | C17: 5602 | D17: 5257 | E17: 5553 | F17: 5383 | G17: 6554 | H17: 9788 | I17: 7562 | J17: 8281 | K17: =K16*K18 -> 7654.9322 | L17: =L16*L18 -> 7846.7725 | M17: =M16*M18 -> 7931.2582 | N17: =N16*N18 -> 8478.6219
A18: Effective tax rate % | B18: =IF(B16=0,0,B17/B16) -> 0.19133945 | C18: =IF(C16=0,0,C17/C16) -> 0.18507384 | D18: =IF(D16=0,0,D17/D16) -> 0.17902265 | E18: =IF(E16=0,0,E17/E16) -> 0.17697677 | F18: =IF(F16=0,0,F17/F16) -> 0.1650417 | G18: =IF(G16=0,0,G17/G16) -> 0.19107315 | H18: =IF(H16=0,0,H17/H16) -> 0.20287692 | I18: =IF(I16=0,0,I17/I16) -> 0.19222166 | J18: =IF(J16=0,0,J17/J16) -> 0.18800372 | K18: =Assumptions!$B$7 -> 0.18 | L18: =Assumptions!$B$7 -> 0.18 | M18: =Assumptions!$B$7 -> 0.18 | N18: =Assumptions!$B$7 -> 0.18
A19: Net income ($mm) | B19: =B16-B17 -> 22036 | C19: =C16-C17 -> 24667 | D19: =D16-D17 -> 24108 | E19: =E16-E17 -> 25824 | F19: =F16-F17 -> 27233 | G19: =G16-G17 -> 27747 | H19: =H16-H17 -> 38458 | I19: =I16-I17 -> 31778 | ... N19: =N16-N17 -> 38624.833
A20: Diluted shares (mm) | B20: 7469 | C20: 7470 | D20: 7468 | E20: 7461 | F20: 7465 | G20: 7466 | H20: 7460 | I20: 7445 | J20: 7441 | K20: =J20*(1-Assumptions!$B$8) -> 7418.677 | L20: =K20*(1-Assumptions!$B$8) -> 7396.421 | M20: =L20*(1-Assumptions!$B$8) -> 7374.2317 | N20: =M20*(1-Assumptions!$B$8) -> 7352.109
A21: Diluted EPS ($) | B21: =IF(B20=0,0,B19/B20) -> 2.950328 | C21: =IF(C20=0,0,C19/C20) -> 3.3021419 | D21: =IF(D20=0,0,D19/D20) -> 3.2281735 | E21: =IF(E20=0,0,E19/E20) -> 3.4611982 | F21: =IF(F20=0,0,F19/F20) -> 3.6480911 | G21: =IF(G20=0,0,G19/G20) -> 3.7164479 | H21: =IF(H20=0,0,H19/H20) -> 5.1552279 | I21: =IF(I20=0,0,I19/I20) -> 4.268368 | ... N21: =IF(N20=0,0,N19/N20) -> 5.2535719
A22: Revenue growth YoY % | F22: =IF(B8=0,0,F8/B8-1) -> 0.18097548 | G22: =IF(C8=0,0,G8/C8-1) -> 0.18431044 | H22: =IF(D8=0,0,H8/D8-1) -> 0.16717888 | I22: =IF(E8=0,0,I8/E8-1) -> 0.18297034 | J22: =IF(F8=0,0,J8/F8-1) -> 0.17747021 | K22: =IF(G8=0,0,K8/G8-1) -> 0.12 | L22: =IF(H8=0,0,L8/H8-1) -> 0.12 | M22: =IF(I8=0,0,M8/I8-1) -> 0.12 | N22: =IF(J8=0,0,N8/J8-1) -> 0.12
A24: Source: stock-data MCP get_financials (SEC XBRL, us-gaap tags), pulled 2026-10-13; FY2026Q4 actuals pulled 2026-10-14 from the FY2026 10-K (filed 2026-07-29). FY Q4 (June quarter) values are annual minus Q1-Q3 (tool-derived). FY2026Q4 other income = pretax 44,047 - operating income 40,603. FY2026Q4 diluted shares (7,441) derived as 4 x FY2026 weighted diluted shares (7,453) - sum of Q1-Q3; not separately reported in XBRL.
A25: Estimates: revenue = same qtr LY x (1+12%); GM = trailing-4Q avg; opex = same qtr LY x (1+6%); tax 18.0%; other income 0; diluted shares = prior qtr x (1-0.3%). See Assumptions tab.

Sheet Annual Summary
A1: MSFT Annual Summary (fiscal years ending June 30)
A2: USD millions except per share. Built from the Quarterly IS tab; FY2026 = 4 actual quarters; FY2027E = 4 estimate quarters.
A4: Fiscal year | B4: FY2025 | C4: FY2026 | D4: FY2027
A5: Actual / Estimate | B5: A | C5: A | D5: E
A6: Composition | B6: 4A | C6: 4A | D6: 4E
A8: Revenue ($mm) | B8: =SUM('Quarterly IS'!C8:F8) -> 281724 | C8: =SUM('Quarterly IS'!G8:J8) -> 331839 | D8: =SUM('Quarterly IS'!K8:N8) -> 371659.68
A9: Cost of revenue ($mm) | B9: =SUM('Quarterly IS'!C9:F9) -> 87831 | C9: =SUM('Quarterly IS'!G9:J9) -> 106374 | D9: =SUM('Quarterly IS'!K9:N9) -> 119931.42
A10: Gross profit ($mm) | B10: =SUM('Quarterly IS'!C10:F10) -> 193893 | C10: =SUM('Quarterly IS'!G10:J10) -> 225465 | D10: =SUM('Quarterly IS'!K10:N10) -> 251728.26
A11: Gross margin % | B11: =IF(B8=0,0,B10/B8) -> 0.68823742 | C11: =IF(C8=0,0,C10/C8) -> 0.67944093 | D11: =IF(D8=0,0,D10/D8) -> 0.6773085
A12: Operating expenses ($mm) | B12: =SUM('Quarterly IS'!C12:F12) -> 65365 | C12: =SUM('Quarterly IS'!G12:J12) -> 70228 | D12: =SUM('Quarterly IS'!K12:N12) -> 74441.68
A13: Operating income ($mm) | B13: =SUM('Quarterly IS'!C13:F13) -> 128528 | C13: =SUM('Quarterly IS'!G13:J13) -> 155237 | D13: =SUM('Quarterly IS'!K13:N13) -> 177286.58
A14: Operating margin % | B14: =IF(B8=0,0,B13/B8) -> 0.45621956 | C14: =IF(C8=0,0,C13/C8) -> 0.46780818 | D14: =IF(D8=0,0,D13/D8) -> 0.47701322
A15: Other income (expense), net ($mm) | B15: =SUM('Quarterly IS'!C15:F15) -> -4901 | C15: =SUM('Quarterly IS'!G15:J15) -> 10697 | D15: =SUM('Quarterly IS'!K15:N15) -> 0
A16: Pretax income ($mm) | B16: =SUM('Quarterly IS'!C16:F16) -> 123627 | C16: =SUM('Quarterly IS'!G16:J16) -> 165934 | D16: =SUM('Quarterly IS'!K16:N16) -> 177286.58
A17: Income tax ($mm) | B17: =SUM('Quarterly IS'!C17:F17) -> 21795 | C17: =SUM('Quarterly IS'!G17:J17) -> 32185 | D17: =SUM('Quarterly IS'!K17:N17) -> 31911.585
A18: Effective tax rate % | B18: =IF(B16=0,0,B17/B16) -> 0.17629644 | C18: =IF(C16=0,0,C17/C16) -> 0.19396266 | D18: =IF(D16=0,0,D17/D16) -> 0.18
A19: Net income ($mm) | B19: =SUM('Quarterly IS'!C19:F19) -> 101832 | C19: =SUM('Quarterly IS'!G19:J19) -> 133749 | D19: =SUM('Quarterly IS'!K19:N19) -> 145375
A20: Diluted shares (mm, avg of quarters) | B20: =AVERAGE('Quarterly IS'!C20:F20) -> 7466 | C20: =AVERAGE('Quarterly IS'!G20:J20) -> 7453 | D20: =AVERAGE('Quarterly IS'!K20:N20) -> 7385.3597
A21: Diluted EPS ($, NI / avg shares) | B21: =IF(B20=0,0,B19/B20) -> 13.639432 | C21: =IF(C20=0,0,C19/C20) -> 17.945659 | D21: =IF(D20=0,0,D19/D20) -> 19.684214
A22: Revenue growth vs. prior FY % | C22: =IF(B8=0,0,C8/B8-1) -> 0.17788687 | D22: =IF(C8=0,0,D8/C8-1) -> 0.12
A24: Annual diluted EPS = annual net income / average of the four quarterly diluted share counts, so it can differ slightly from the sum of quarterly EPS and from reported annual EPS.

Sheet Valuation
A1: MSFT Valuation: NTM EPS x P/E
A2: NTM = the next four quarters after the last actual (FY2026Q4), i.e. FY2027Q1E-FY2027Q4E. Rolled forward 2026-10-14.
A4: Quarter | B4: Diluted EPS ($)
A5: ='Quarterly IS'!K4 -> FY2027Q1 | B5: ='Quarterly IS'!K21 -> 4.7006318
A6: ='Quarterly IS'!L4 -> FY2027Q2 | B6: ='Quarterly IS'!L21 -> 4.8329331
A7: ='Quarterly IS'!M4 -> FY2027Q3 | B7: ='Quarterly IS'!M21 -> 4.899668
A8: ='Quarterly IS'!N4 -> FY2027Q4 | B8: ='Quarterly IS'!N21 -> 5.2535719
A10: NTM diluted EPS ($) | B10: =SUM(B5:B8) -> 19.686805
A11: Target P/E (x) | B11: =Assumptions!$B$10 -> 30
A12: Target price ($) | B12: =B10*B11 -> 590.60414
A14: Prior target price ($, model dated late July 2026) | B14: 567.58431
A15: Prior NTM diluted EPS ($) | B15: 18.919477
A16: Change in target price % | B16: =IF(B14=0,0,B12/B14-1) -> 0.040557553
A17: Share price ($, stock-data get_quote, 2026-10-14) | B17: 543.45
A18: Upside / (downside) to target % | B18: =IF(B17=0,0,B12/B17-1) -> 0.086768136
A19: Implied P/E on NTM EPS at current price (x) | B19: =IF(B10=0,0,B17/B10) -> 27.604784

Sheet Assumptions
A1: MSFT Quarterly Model: Estimate Assumptions
A2: Blue = hardcoded input; black = formula; green = link to another sheet. Yellow cells are the key levers; edit them to change the estimates.
A4: Assumption | B4: Value | C4: Basis
A5: Revenue growth vs. same quarter last year | B5: 0.12 | C5: Estimate rule: revenue = same quarter last year x 1.12
A6: Opex growth vs. same quarter last year | B6: 0.06 | C6: Estimate rule: operating expenses = same quarter last year x 1.06
A7: Tax rate (estimates) | B7: 0.18 | C7: Estimate rule: tax rate 18.0%
A8: Diluted share reduction per quarter | B8: 0.003 | C8: Estimate rule: diluted shares = latest actual minus 0.3% per quarter (compounded)
A9: Other income (expense), net - estimates ($mm) | B9: 0 | C9: Modeling default (not in spec): non-operating items assumed zero in estimate quarters
A10: Target P/E multiple on NTM EPS (x) | B10: 30 | C10: Valuation rule: NTM EPS x 30 = target price
A11: Gross margin method | B11: Trailing-4-quarter average | C11: Each estimate quarter's GM = average GM of the 4 preceding quarters (rolls forward through estimates)
A13: Update log
A14: 2026-10-14: FY2026Q4 actuals entered (10-K filed 2026-07-29); NTM window rolled to FY2027Q1-Q4; estimate rules unchanged. See Est vs Actual tab.

Sheet Est vs Actual
A1: MSFT FY2026Q4 (quarter ended 2026-06-30): prior estimate vs. reported actual
A2: Prior estimate = values from the model before this update (hardcoded, blue). Actual = link to Quarterly IS column J (green). Filing: Form 10-K filed 2026-07-29; earnings 8-K (Item 2.02) filed 2026-07-29.
A4: Line item | B4: Prior estimate | C4: Actual | D4: Delta | E4: Delta %
A5: Revenue ($mm) | B5: 85613.92 | C5: ='Quarterly IS'!J8 -> 90007 | D5: =C5-B5 -> 4393.08 | E5: =IF(B5=0,"n/m",C5/B5-1) -> 0.051312684
A6: Cost of revenue ($mm) | B6: 27118.301 | C6: ='Quarterly IS'!J9 -> 29525 | D6: =C6-B6 -> 2406.699 | E6: =IF(B6=0,"n/m",C6/B6-1) -> 0.088748147
A7: Gross profit ($mm) | B7: 58495.619 | C7: ='Quarterly IS'!J10 -> 60482 | D7: =C7-B7 -> 1986.381 | E7: =IF(B7=0,"n/m",C7/B7-1) -> 0.033957774
A8: Gross margin % | B8: 0.68324893 | C8: ='Quarterly IS'!J11 -> 0.67196996 | D8: =C8-B8 -> -0.011278969 | E8: n/m (see Delta, pts)
A9: Operating expenses ($mm) | B9: 19190.24 | C9: ='Quarterly IS'!J12 -> 19879 | D9: =C9-B9 -> 688.76 | E9: =IF(B9=0,"n/m",C9/B9-1) -> 0.035891161
A10: Operating income ($mm) | B10: 39305.379 | C10: ='Quarterly IS'!J13 -> 40603 | D10: =C10-B10 -> 1297.621 | E10: =IF(B10=0,"n/m",C10/B10-1) -> 0.033013828
A11: Operating margin % | B11: 0.45910033 | C11: ='Quarterly IS'!J14 -> 0.45110936 | D11: =C11-B11 -> -0.0079909723 | E11: n/m (see Delta, pts)
A12: Other income (expense), net ($mm) | B12: 0 | C12: ='Quarterly IS'!J15 -> 3444 | D12: =C12-B12 -> 3444 | E12: =IF(B12=0,"n/m",C12/B12-1) -> n/m
A13: Pretax income ($mm) | B13: 39305.379 | C13: ='Quarterly IS'!J16 -> 44047 | D13: =C13-B13 -> 4741.621 | E13: =IF(B13=0,"n/m",C13/B13-1) -> 0.12063542
A14: Income tax ($mm) | B14: 7074.9682 | C14: ='Quarterly IS'!J17 -> 8281 | D14: =C14-B14 -> 1206.0318 | E14: =IF(B14=0,"n/m",C14/B14-1) -> 0.17046462
A15: Effective tax rate % | B15: 0.18 | C15: ='Quarterly IS'!J18 -> 0.18800372 | D15: =C15-B15 -> 0.0080037233 | E15: n/m (see Delta, pts)
A16: Net income ($mm) | B16: 32230.411 | C16: ='Quarterly IS'!J19 -> 35766 | D16: =C16-B16 -> 3535.5893 | E16: =IF(B16=0,"n/m",C16/B16-1) -> 0.10969731
A17: Diluted shares (mm) | B17: 7422.665 | C17: ='Quarterly IS'!J20 -> 7441 | D17: =C17-B17 -> 18.335 | E17: =IF(B17=0,"n/m",C17/B17-1) -> 0.0024701371
A18: Diluted EPS ($) | B18: 4.3421616 | C18: ='Quarterly IS'!J21 -> 4.806612 | D18: =C18-B18 -> 0.46445044 | E18: =IF(B18=0,"n/m",C18/B18-1) -> 0.10696296
A21: Estimate revisions (old model vs. updated model)
A22: Item | B22: Old | C22: New | D22: Change | E22: Change %
A23: FY2027Q1E revenue ($mm) | B23: 86993.76 | C23: ='Quarterly IS'!K8 -> 86993.76 | D23: =C23-B23 -> 0 | E23: =IF(B23=0,"n/m",C23/B23-1) -> 0
A24: FY2027Q1E diluted EPS ($) | B24: 4.7394234 | C24: ='Quarterly IS'!K21 -> 4.7006318 | D24: =C24-B24 -> -0.038791636 | E24: =IF(B24=0,"n/m",C24/B24-1) -> -0.0081848851
A25: FY2026 revenue ($mm) (old = 3A+1E) | B25: 327445.92 | C25: ='Annual Summary'!C8 -> 331839 | D25: =C25-B25 -> 4393.08 | E25: =IF(B25=0,"n/m",C25/B25-1) -> 0.0134162
A26: FY2026 diluted EPS ($) (old = 3A+1E) | B26: 17.482027 | C26: ='Annual Summary'!C21 -> 17.945659 | D26: =C26-B26 -> 0.4636329 | E26: =IF(B26=0,"n/m",C26/B26-1) -> 0.026520547
A27: FY2027E revenue ($mm) | B27: 366739.43 | C27: ='Annual Summary'!D8 -> 371659.68 | D27: =C27-B27 -> 4920.2496 | E27: =IF(B27=0,"n/m",C27/B27-1) -> 0.0134162
A28: FY2027E diluted EPS ($) | B28: 19.611047 | C28: ='Annual Summary'!D21 -> 19.684214 | D28: =C28-B28 -> 0.073166842 | E28: =IF(B28=0,"n/m",C28/B28-1) -> 0.0037308994
A29: NTM diluted EPS ($) | B29: 18.919477 | C29: =Valuation!B10 -> 19.686805 | D29: =C29-B29 -> 0.7673277 | E29: =IF(B29=0,"n/m",C29/B29-1) -> 0.040557553
A30: Target price ($) | B30: 567.58431 | C30: =Valuation!B12 -> 590.60414 | D30: =C30-B30 -> 23.019831 | E30: =IF(B30=0,"n/m",C30/B30-1) -> 0.040557553
A32: Estimate rules on the Assumptions tab were left unchanged; the roll-forward reflects only the new FY2026Q4 actual base (GM trailing average, FY2027Q4 revenue/opex base, share-count base) and the NTM window shift.
