Workbook

Sheet DCF
A1: Microsoft Corporation (MSFT) - DCF Model
A2: Ticker: MSFT | Valuation date: 2026-10-14 | Fiscal year end: June 30 | USD millions except per-share
A4: Case selector (1=Bear, 2=Base, 3=Bull) | B4: 2 | C4: =CHOOSE(B4,"Bear case","Base case","Bull case") -> Base case
A6: MARKET DATA & KEY INPUTS
A7: Current share price ($) | B7: 533.69
A8: Diluted shares (M) | B8: 7453
A9: Market capitalisation ($M) | B9: =B7*B8 -> 3977591.6
A10: Cash + short-term investments ($M) | B10: 76843
A11: Total debt ($M) | B11: 40294
A12: Net debt / (net cash) ($M) | B12: =B11-B10 -> -36549
A13: Tax rate (cash/operating) | B13: 0.19
A14: Change in NWC (% of change in revenue) | B14: 0.05
A15: Base WACC (from WACC sheet) | B15: =WACC!B29 -> 0.10658549
A16: Peer median EV/LTM EBITDA (from Comps sheet) | B16: =Comps!J34 -> 17.074188
A17: FY2026A diluted EPS ($) | B17: 17.95
A19: SCENARIO ASSUMPTIONS
A20: BEAR CASE ASSUMPTIONS
A21: Assumption | E21: FY2027E | F21: FY2028E | G21: FY2029E | H21: FY2030E | I21: FY2031E | J21: FY2032E | K21: FY2033E | L21: FY2034E | M21: FY2035E | N21: FY2036E
A22: Revenue growth (%) | E22: 0.12 | F22: 0.1 | G22: 0.09 | H22: 0.08 | I22: 0.07 | J22: 0.06 | K22: 0.05 | L22: 0.045 | M22: 0.04 | N22: 0.035
A23: EBIT margin (%) | E23: 0.44 | F23: 0.435 | G23: 0.43 | H23: 0.425 | I23: 0.42 | J23: 0.415 | K23: 0.41 | L23: 0.41 | M23: 0.41 | N23: 0.41
A24: D&A (% of revenue) | E24: 0.14 | F24: 0.15 | G24: 0.155 | H24: 0.16 | I24: 0.16 | J24: 0.16 | K24: 0.155 | L24: 0.15 | M24: 0.145 | N24: 0.14
A25: CapEx (% of revenue) | E25: 0.38 | F25: 0.34 | G25: 0.29 | H25: 0.26 | I25: 0.23 | J25: 0.21 | K25: 0.195 | L25: 0.18 | M25: 0.17 | N25: 0.165
A26: WACC adjustment vs. base (pp) | E26: 0.005
A27: Terminal growth rate (%) | E27: 0.025
A29: BASE CASE ASSUMPTIONS
A30: Assumption | E30: FY2027E | F30: FY2028E | G30: FY2029E | H30: FY2030E | I30: FY2031E | J30: FY2032E | K30: FY2033E | L30: FY2034E | M30: FY2035E | N30: FY2036E
A31: Revenue growth (%) | E31: 0.16 | F31: 0.15 | G31: 0.13 | H31: 0.12 | I31: 0.11 | J31: 0.1 | K31: 0.08 | L31: 0.07 | M31: 0.06 | N31: 0.05
A32: EBIT margin (%) | E32: 0.46 | F32: 0.465 | G32: 0.47 | H32: 0.47 | I32: 0.47 | J32: 0.47 | K32: 0.465 | L32: 0.46 | M32: 0.46 | N32: 0.46
A33: D&A (% of revenue) | E33: 0.14 | F33: 0.15 | G33: 0.155 | H33: 0.16 | I33: 0.16 | J33: 0.16 | K33: 0.155 | L33: 0.15 | M33: 0.145 | N33: 0.14
A34: CapEx (% of revenue) | E34: 0.36 | F34: 0.32 | G34: 0.27 | H34: 0.24 | I34: 0.22 | J34: 0.2 | K34: 0.185 | L34: 0.17 | M34: 0.16 | N34: 0.155
A35: WACC adjustment vs. base (pp) | E35: 0
A36: Terminal growth rate (%) | E36: 0.03
A38: BULL CASE ASSUMPTIONS
A39: Assumption | E39: FY2027E | F39: FY2028E | G39: FY2029E | H39: FY2030E | I39: FY2031E | J39: FY2032E | K39: FY2033E | L39: FY2034E | M39: FY2035E | N39: FY2036E
A40: Revenue growth (%) | E40: 0.19 | F40: 0.18 | G40: 0.16 | H40: 0.15 | I40: 0.13 | J40: 0.12 | K40: 0.1 | L40: 0.09 | M40: 0.07 | N40: 0.06
A41: EBIT margin (%) | E41: 0.47 | F41: 0.475 | G41: 0.48 | H41: 0.485 | I41: 0.49 | J41: 0.49 | K41: 0.49 | L41: 0.49 | M41: 0.49 | N41: 0.49
A42: D&A (% of revenue) | E42: 0.14 | F42: 0.15 | G42: 0.155 | H42: 0.16 | I42: 0.16 | J42: 0.16 | K42: 0.155 | L42: 0.15 | M42: 0.145 | N42: 0.14
A43: CapEx (% of revenue) | E43: 0.34 | F43: 0.29 | G43: 0.24 | H43: 0.21 | I43: 0.19 | J43: 0.175 | K43: 0.16 | L43: 0.15 | M43: 0.145 | N43: 0.14
A44: WACC adjustment vs. base (pp) | E44: -0.005
A45: Terminal growth rate (%) | E45: 0.035
A47: SELECTED CASE (feeds model)
A48: Assumption | E48: FY2027E | F48: FY2028E | G48: FY2029E | H48: FY2030E | I48: FY2031E | J48: FY2032E | K48: FY2033E | L48: FY2034E | M48: FY2035E | N48: FY2036E
A49: Revenue growth (%) | E49: =CHOOSE($B$4,E22,E31,E40) -> 0.16 | F49: =CHOOSE($B$4,F22,F31,F40) -> 0.15 | G49: =CHOOSE($B$4,G22,G31,G40) -> 0.13 | H49: =CHOOSE($B$4,H22,H31,H40) -> 0.12 | I49: =CHOOSE($B$4,I22,I31,I40) -> 0.11 | J49: =CHOOSE($B$4,J22,J31,J40) -> 0.1 | K49: =CHOOSE($B$4,K22,K31,K40) -> 0.08 | L49: =CHOOSE($B$4,L22,L31,L40) -> 0.07 | ... N49: =CHOOSE($B$4,N22,N31,N40) -> 0.05
A50: EBIT margin (%) | E50: =CHOOSE($B$4,E23,E32,E41) -> 0.46 | F50: =CHOOSE($B$4,F23,F32,F41) -> 0.465 | G50: =CHOOSE($B$4,G23,G32,G41) -> 0.47 | H50: =CHOOSE($B$4,H23,H32,H41) -> 0.47 | I50: =CHOOSE($B$4,I23,I32,I41) -> 0.47 | J50: =CHOOSE($B$4,J23,J32,J41) -> 0.47 | K50: =CHOOSE($B$4,K23,K32,K41) -> 0.465 | L50: =CHOOSE($B$4,L23,L32,L41) -> 0.46 | ... N50: =CHOOSE($B$4,N23,N32,N41) -> 0.46
A51: D&A (% of revenue) | E51: =CHOOSE($B$4,E24,E33,E42) -> 0.14 | F51: =CHOOSE($B$4,F24,F33,F42) -> 0.15 | G51: =CHOOSE($B$4,G24,G33,G42) -> 0.155 | H51: =CHOOSE($B$4,H24,H33,H42) -> 0.16 | I51: =CHOOSE($B$4,I24,I33,I42) -> 0.16 | J51: =CHOOSE($B$4,J24,J33,J42) -> 0.16 | K51: =CHOOSE($B$4,K24,K33,K42) -> 0.155 | L51: =CHOOSE($B$4,L24,L33,L42) -> 0.15 | ... N51: =CHOOSE($B$4,N24,N33,N42) -> 0.14
A52: CapEx (% of revenue) | E52: =CHOOSE($B$4,E25,E34,E43) -> 0.36 | F52: =CHOOSE($B$4,F25,F34,F43) -> 0.32 | G52: =CHOOSE($B$4,G25,G34,G43) -> 0.27 | H52: =CHOOSE($B$4,H25,H34,H43) -> 0.24 | I52: =CHOOSE($B$4,I25,I34,I43) -> 0.22 | J52: =CHOOSE($B$4,J25,J34,J43) -> 0.2 | K52: =CHOOSE($B$4,K25,K34,K43) -> 0.185 | L52: =CHOOSE($B$4,L25,L34,L43) -> 0.17 | ... N52: =CHOOSE($B$4,N25,N34,N43) -> 0.155
A53: Selected WACC (base + adjustment) | E53: =$B$15+CHOOSE($B$4,E26,E35,E44) -> 0.10658549
A54: Terminal growth rate (%) | E54: =CHOOSE($B$4,E27,E36,E45) -> 0.03
A56: HISTORICAL & PROJECTED FREE CASH FLOW ($M)
A57: Fiscal year | B57: FY2024A | C57: FY2025A | D57: FY2026A | E57: FY2027E | F57: FY2028E | G57: FY2029E | H57: FY2030E | I57: FY2031E | J57: FY2032E | K57: FY2033E | L57: FY2034E | M57: FY2035E | N57: FY2036E
A58: Revenue | B58: 245122 | C58: 281724 | D58: 331839 | E58: =D58*(1+E49) -> 384933.24 | F58: =E58*(1+F49) -> 442673.23 | G58: =F58*(1+G49) -> 500220.75 | H58: =G58*(1+H49) -> 560247.23 | I58: =H58*(1+I49) -> 621874.43 | J58: =I58*(1+J49) -> 684061.87 | K58: =J58*(1+K49) -> 738786.82 | L58: =K58*(1+L49) -> 790501.9 | ... N58: =M58*(1+N49) -> 879828.62
A59: % growth | B59: =B58/211915-1 -> 0.15669962 | C59: =C58/B58-1 -> 0.14932156 | D59: =D58/C58-1 -> 0.17788687 | E59: =E58/D58-1 -> 0.16 | F59: =F58/E58-1 -> 0.15 | G59: =G58/F58-1 -> 0.13 | H59: =H58/G58-1 -> 0.12 | I59: =I58/H58-1 -> 0.11 | J59: =J58/I58-1 -> 0.1 | ... N59: =N58/M58-1 -> 0.05
A60: EBIT (operating income) | B60: 109433 | C60: 128528 | D60: 155237 | E60: =E58*E50 -> 177069.29 | F60: =F58*F50 -> 205843.05 | G60: =G58*G50 -> 235103.75 | H60: =H58*H50 -> 263316.2 | I60: =I58*I50 -> 292280.98 | J60: =J58*J50 -> 321509.08 | K60: =K58*K50 -> 343535.87 | L60: =L58*L50 -> 363630.87 | ... N60: =N58*N50 -> 404721.16
A61: % margin | B61: =B60/B58 -> 0.446443 | C61: =C60/C58 -> 0.45621956 | D61: =D60/D58 -> 0.46780818 | E61: =E60/E58 -> 0.46 | F61: =F60/F58 -> 0.465 | G61: =G60/G58 -> 0.47 | H61: =H60/H58 -> 0.47 | I61: =I60/I58 -> 0.47 | ... N61: =N60/N58 -> 0.46
A62: (-) Taxes on EBIT | E62: =E60*$B$13 -> 33643.165 | F62: =F60*$B$13 -> 39110.18 | G62: =G60*$B$13 -> 44669.713 | H62: =H60*$B$13 -> 50030.078 | I62: =I60*$B$13 -> 55533.387 | J62: =J60*$B$13 -> 61086.725 | K62: =K60*$B$13 -> 65271.816 | L62: =L60*$B$13 -> 69089.866 | ... N62: =N60*$B$13 -> 76897.021
A63: NOPAT | E63: =E60-E62 -> 143426.13 | F63: =F60-F62 -> 166732.87 | G63: =G60-G62 -> 190434.04 | H63: =H60-H62 -> 213286.12 | I63: =I60-I62 -> 236747.6 | J63: =J60-J62 -> 260422.36 | K63: =K60-K62 -> 278264.06 | L63: =L60-L62 -> 294541.01 | ... N63: =N60-N62 -> 327824.14
A64: (+) D&A | B64: 22287 | C64: 34153 | D64: 39000 | E64: =E58*E51 -> 53890.654 | F64: =F58*F51 -> 66400.984 | G64: =G58*G51 -> 77534.216 | H64: =H58*H51 -> 89639.558 | I64: =I58*I51 -> 99499.909 | J64: =J58*J51 -> 109449.9 | K64: =K58*K51 -> 114511.96 | L64: =L58*L51 -> 118575.29 | ... N64: =N58*N51 -> 123176.01
A65: % of revenue | B65: =B64/B58 -> 0.090922071 | C65: =C64/C58 -> 0.12122858 | D65: =D64/D58 -> 0.11752687 | E65: =E64/E58 -> 0.14 | F65: =F64/F58 -> 0.15 | G65: =G64/G58 -> 0.155 | H65: =H64/H58 -> 0.16 | I65: =I64/I58 -> 0.16 | ... N65: =N64/N58 -> 0.14
A66: (-) CapEx | B66: 44477 | C66: 64551 | D66: 115948 | E66: =E58*E52 -> 138575.97 | F66: =F58*F52 -> 141655.43 | G66: =G58*G52 -> 135059.6 | H66: =H58*H52 -> 134459.34 | I66: =I58*I52 -> 136812.37 | J66: =J58*J52 -> 136812.37 | K66: =K58*K52 -> 136675.56 | L66: =L58*L52 -> 134385.32 | ... N66: =N58*N52 -> 136373.44
A67: % of revenue | B67: =B66/B58 -> 0.18144842 | C67: =C66/C58 -> 0.22912851 | D67: =D66/D58 -> 0.34941041 | E67: =E66/E58 -> 0.36 | F67: =F66/F58 -> 0.32 | G67: =G66/G58 -> 0.27 | H67: =H66/H58 -> 0.24 | I67: =I66/I58 -> 0.22 | ... N67: =N66/N58 -> 0.155
A68: (-) Increase in NWC | E68: =(E58-D58)*$B$14 -> 2654.712 | F68: =(F58-E58)*$B$14 -> 2886.9993 | G68: =(G58-F58)*$B$14 -> 2877.376 | H68: =(H58-G58)*$B$14 -> 3001.3245 | I68: =(I58-H58)*$B$14 -> 3081.3598 | J68: =(J58-I58)*$B$14 -> 3109.3722 | K68: =(K58-J58)*$B$14 -> 2736.2475 | L68: =(L58-K58)*$B$14 -> 2585.7539 | ... N68: =(N58-M58)*$B$14 -> 2094.83
A69: Unlevered free cash flow | E69: =E63+E64-E66-E68 -> 56086.1 | F69: =F63+F64-F66-F68 -> 88591.423 | G69: =G63+G64-G66-G68 -> 130031.28 | H69: =H63+H64-H66-H68 -> 165465.02 | I69: =I63+I64-I66-I68 -> 196353.77 | J69: =J63+J64-J66-J68 -> 229950.51 | K69: =K63+K64-K66-K68 -> 253364.2 | L69: =L63+L64-L66-L68 -> 276145.22 | ... N69: =N63+N64-N66-N68 -> 312531.88
A70: Memo: operating cash flow (reported) | B70: 118548 | C70: 136162 | D70: 182935
A71: Memo: reported FCF (OCF - CapEx) | B71: =B70-B66 -> 74071 | C71: =C70-C66 -> 71611 | D71: =D70-D66 -> 66987
A72: EBITDA (EBIT + D&A) | B72: =B60+B64 -> 131720 | C72: =C60+C64 -> 162681 | D72: =D60+D64 -> 194237 | E72: =E60+E64 -> 230959.94 | F72: =F60+F64 -> 272244.03 | G72: =G60+G64 -> 312637.97 | H72: =H60+H64 -> 352955.76 | I72: =I60+I64 -> 391780.89 | ... N72: =N60+N64 -> 527897.17
A74: DISCOUNTING (mid-year convention)
E75: FY2027E | F75: FY2028E | G75: FY2029E | H75: FY2030E | I75: FY2031E | J75: FY2032E | K75: FY2033E | L75: FY2034E | M75: FY2035E | N75: FY2036E
A76: Discount period (years) | E76: =0.5 -> 0.5 | F76: =E76+1 -> 1.5 | G76: =F76+1 -> 2.5 | H76: =G76+1 -> 3.5 | I76: =H76+1 -> 4.5 | J76: =I76+1 -> 5.5 | K76: =J76+1 -> 6.5 | L76: =K76+1 -> 7.5 | M76: =L76+1 -> 8.5 | N76: =M76+1 -> 9.5
A77: Discount factor | E77: =1/(1+$E$53)^E76 -> 0.95062124 | F77: =1/(1+$E$53)^F76 -> 0.85905811 | G77: =1/(1+$E$53)^G76 -> 0.77631428 | H77: =1/(1+$E$53)^H76 -> 0.70154027 | I77: =1/(1+$E$53)^I76 -> 0.63396843 | J77: =1/(1+$E$53)^J76 -> 0.57290506 | K77: =1/(1+$E$53)^K76 -> 0.51772328 | L77: =1/(1+$E$53)^L76 -> 0.46785656 | ... N77: =1/(1+$E$53)^N76 -> 0.38206986
A78: PV of unlevered FCF | E78: =E69*E77 -> 53316.638 | F78: =F69*F77 -> 76105.181 | G78: =G69*G77 -> 100945.14 | H78: =H69*H77 -> 116080.37 | I78: =I69*I77 -> 124482.09 | J78: =J69*J77 -> 131739.81 | K78: =K69*K77 -> 131172.55 | L78: =L69*L77 -> 129196.35 | ... N78: =N69*N77 -> 119409.01
A80: TERMINAL VALUE
A81: Terminal-year FCF x (1+g) | B81: =N69*(1+E54) -> 321907.84
A82: Terminal value - perpetuity growth | B82: =B81/(E53-E54) -> 4203248.5
A83: PV of terminal value | B83: =B82*N77 -> 1605934.6
A84: Implied terminal EV / EBITDA (FY2036) | B84: =B82/N72 -> 7.9622486
A85: Cross-check: TV at peer median EV/EBITDA | B85: =N72*B16 -> 9013415.5
A86: Cross-check: PV of exit-multiple TV | B86: =B85*N77 -> 3443754.4
A88: VALUATION SUMMARY
A89: Sum of PV of FCF (FY2027-FY2036) | B89: =SUM(E78:N78) -> 1108132.1
A90: PV of terminal value | B90: =B83 -> 1605934.6
A91: Enterprise value | B91: =B89+B90 -> 2714066.6
A92: Terminal value as % of EV | B92: =B90/B91 -> 0.59170786
A93: (-) Net debt / (+) net cash | B93: =-B12 -> 36549
A94: Equity value | B94: =B91+B93 -> 2750615.6
A95: Diluted shares (M) | B95: =B8 -> 7453
A96: IMPLIED VALUE PER SHARE ($) | B96: =B94/B95 -> 369.06154
A97: Current share price ($) | B97: =B7 -> 533.69
A98: Implied upside / (downside) | B98: =B96/B97-1 -> -0.30847208
A99: DCF-implied EV / FY2026A EBITDA | B99: =B91/D72 -> 13.972964
A100: Peer median EV / LTM EBITDA | B100: =B16 -> 17.074188
A101: DCF multiple premium / (discount) to peers | B101: =B99/B100-1 -> -0.18163229
A102: DCF-implied P/E on FY2026A EPS | B102: =B96/B17 -> 20.560531
A103: Cross-check: value/share using exit multiple TV ($) | B103: =(B89+B86-B12)/B8 -> 615.64946
A104: Market-implied EV / FY2026A EBITDA | B104: =(B9+B12)/D72 -> 20.289865
A106: SCENARIO SUMMARY - all three cases calculated simultaneously
A107: Line | E107: FY2027E | F107: FY2028E | G107: FY2029E | H107: FY2030E | I107: FY2031E | J107: FY2032E | K107: FY2033E | L107: FY2034E | M107: FY2035E | N107: FY2036E
A108: Bear: revenue | E108: =$D$58*(1+E22) -> 371659.68 | F108: =E108*(1+F22) -> 408825.65 | G108: =F108*(1+G22) -> 445619.96 | H108: =G108*(1+H22) -> 481269.55 | I108: =H108*(1+I22) -> 514958.42 | J108: =I108*(1+J22) -> 545855.93 | K108: =J108*(1+K22) -> 573148.72 | L108: =K108*(1+L22) -> 598940.42 | M108: =L108*(1+M22) -> 622898.03 | N108: =M108*(1+N22) -> 644699.46
A109: Bear: unlevered FCF | E109: =E108*E23*(1-$B$13)+E108*E24-E108*E25-(E108-$D$58)*$B$14 -> 41270.153 | F109: =F108*F23*(1-$B$13)+F108*F24-F108*F25-(F108-E108)*$B$14 -> 64514.546 | G109: =G108*G23*(1-$B$13)+G108*G24-G108*G25-(G108-F108)*$B$14 -> 93211.021 | H109: =H108*H23*(1-$B$13)+H108*H24-H108*H25-(H108-G108)*$B$14 -> 115767.61 | I109: =I108*I23*(1-$B$13)+I108*I24-I108*I25-(I108-H108)*$B$14 -> 137457.32 | J109: =J108*J23*(1-$B$13)+J108*J24-J108*J25-(J108-I108)*$B$14 -> 154651.8 | K109: =K108*K23*(1-$B$13)+K108*K24-K108*K25-(K108-J108)*$B$14 -> 166052.1 | L109: =L108*L23*(1-$B$13)+L108*L24-L108*L25-(L108-K108)*$B$14 -> 179650.31 | M109: =M108*M23*(1-$B$13)+M108*M24-M108*M25-(M108-L108)*$B$14 -> 190094.1 | N109: =N108*N23*(1-$B$13)+N108*N24-N108*N25-(N108-M108)*$B$14 -> 196897.13
A110: Bear: discount factor | E110: =1/(1+$B$15+$E$26)^E$76 -> 0.94848085 | F110: =1/(1+$B$15+$E$26)^F$76 -> 0.85326847 | G110: =1/(1+$B$15+$E$26)^G$76 -> 0.7676139 | H110: =1/(1+$B$15+$E$26)^H$76 -> 0.69055768 | I110: =1/(1+$B$15+$E$26)^I$76 -> 0.62123668 | J110: =1/(1+$B$15+$E$26)^J$76 -> 0.55887441 | K110: =1/(1+$B$15+$E$26)^K$76 -> 0.50277231 | L110: =1/(1+$B$15+$E$26)^L$76 -> 0.45230198 | ... N110: =1/(1+$B$15+$E$26)^N$76 -> 0.36605197
A111: Base: revenue | E111: =$D$58*(1+E31) -> 384933.24 | F111: =E111*(1+F31) -> 442673.23 | G111: =F111*(1+G31) -> 500220.75 | H111: =G111*(1+H31) -> 560247.23 | I111: =H111*(1+I31) -> 621874.43 | J111: =I111*(1+J31) -> 684061.87 | K111: =J111*(1+K31) -> 738786.82 | L111: =K111*(1+L31) -> 790501.9 | M111: =L111*(1+M31) -> 837932.02 | N111: =M111*(1+N31) -> 879828.62
...

Sheet WACC
A1: MSFT - Weighted Average Cost of Capital
A3: COST OF EQUITY (CAPM)
A4: Risk-free rate (10Y UST, 2026-10-13) | B4: 0.0521
A5: Beta (5Y monthly vs S&P 500, raw) | B5: =Beta!H4 -> 1.1017697
A6: Equity risk premium | B6: 0.05
A7: Cost of equity | B7: =B4+B5*B6 -> 0.10718849
A9: COST OF DEBT
A10: Credit rating | B10: AAA
A11: Spread over 10Y UST | B11: 0.006
A12: Pre-tax cost of debt | B12: =B4+B11 -> 0.0581
A13: Tax rate | B13: =DCF!B13 -> 0.19
A14: After-tax cost of debt | B14: =B12*(1-B13) -> 0.047061
A15: Memo: FY2026 interest expense / avg. debt | B15: =C15/AVERAGE(43151,DCF!B11) -> 0.073126011 | C15: 3051
A17: CAPITAL STRUCTURE (market values)
A18: Share price ($) | B18: =DCF!B7 -> 533.69
A19: Diluted shares (M) | B19: =DCF!B8 -> 7453
A20: Market capitalisation ($M) | B20: =B18*B19 -> 3977591.6
A21: Total debt ($M) | B21: =DCF!B11 -> 40294
A22: Cash + ST investments ($M) | B22: =DCF!B10 -> 76843
A23: Net debt / (net cash) ($M) | B23: =B21-B22 -> -36549
A24: Total capital (E + D) ($M) | B24: =B20+B21 -> 4017885.6
A26: WACC | B26: Weight | C26: Cost | D26: Contribution
A27: Equity | B27: =B20/B24 -> 0.98997134 | C27: =B7 -> 0.10718849 | D27: =B27*C27 -> 0.10611353
A28: Debt (gross) | B28: =B21/B24 -> 0.010028658 | C28: =B14 -> 0.047061 | D28: =B28*C28 -> 0.00047195867
A29: WEIGHTED AVERAGE COST OF CAPITAL | B29: =D27+D28 -> 0.10658549
A31: Gross debt weights used (MSFT is net cash); lease liabilities excluded from debt and from the equity bridge for consistency.

Sheet Beta
A1: MSFT 5-year beta vs. S&P 500 - monthly total-return (MSFT adj. close) vs. index price returns
A3: Month-end | B3: MSFT adj. close | C3: S&P 500 close | D3: MSFT return | E3: S&P 500 return
A4: 2021-09 | B4: 270.57 | C4: 4307.54 | G4: Beta (SLOPE, raw) | H4: =SLOPE(D5:D64,E5:E64) -> 1.1017697
A5: 2021-10 | B5: 318.26 | C5: 4605.38 | D5: =B5/B4-1 -> 0.17625753 | E5: =C5/C4-1 -> 0.069143873 | G5: Observations (monthly returns) | H5: =COUNT(D5:D64) -> 60
A6: 2021-11 | B6: 317.86 | C6: 4567 | D6: =B6/B5-1 -> -0.001256834 | E6: =C6/C5-1 -> -0.0083337314 | G6: R-squared | H6: =RSQ(D5:D64,E5:E64) -> 0.39755815
A7: 2021-12 | B7: 323.37 | C7: 4766.18 | D7: =B7/B6-1 -> 0.017334676 | E7: =C7/C6-1 -> 0.043612875 | G7: Blume-adjusted beta (memo) | H7: =0.67*H4+0.33 -> 1.0681857
A8: 2022-01 | B8: 299 | C8: 4515.55 | D8: =B8/B7-1 -> -0.075362588 | E8: =C8/C7-1 -> -0.052585089 | G8: Window: 2021-09 to 2026-09 month-end closes (60 complete months; partial Oct-2026 excluded)
A9: 2022-02 | B9: 287.88 | C9: 4373.94 | D9: =B9/B8-1 -> -0.037190635 | E9: =C9/C8-1 -> -0.031360521
A10: 2022-03 | B10: 297.05 | C10: 4530.41 | D10: =B10/B9-1 -> 0.03185355 | E10: =C10/C9-1 -> 0.035773239
A11: 2022-04 | B11: 267.38 | C11: 4131.93 | D11: =B11/B10-1 -> -0.099882175 | E11: =C11/C10-1 -> -0.087956719
A12: 2022-05 | B12: 262.55 | C12: 4132.15 | D12: =B12/B11-1 -> -0.018064178 | E12: =C12/C11-1 -> 5.3243884e-05
A13: 2022-06 | B13: 248.02 | C13: 3785.38 | D13: =B13/B12-1 -> -0.05534184 | E13: =C13/C12-1 -> -0.083919993
A14: 2022-07 | B14: 271.11 | C14: 4130.29 | D14: =B14/B13-1 -> 0.093097331 | E14: =C14/C13-1 -> 0.091116348
A15: 2022-08 | B15: 253.04 | C15: 3955 | D15: =B15/B14-1 -> -0.066651913 | E15: =C15/C14-1 -> -0.042440119
A16: 2022-09 | B16: 225.39 | C16: 3585.62 | D16: =B16/B15-1 -> -0.10927126 | E16: =C16/C15-1 -> -0.093395702
A17: 2022-10 | B17: 224.65 | C17: 3871.98 | D17: =B17/B16-1 -> -0.003283198 | E17: =C17/C16-1 -> 0.079863455
A18: 2022-11 | B18: 247.61 | C18: 4080.11 | D18: =B18/B17-1 -> 0.10220343 | E18: =C18/C17-1 -> 0.05375286
A19: 2022-12 | B19: 232.74 | C19: 3839.5 | D19: =B19/B18-1 -> -0.060054117 | E19: =C19/C18-1 -> -0.058971449
A20: 2023-01 | B20: 240.5 | C20: 4076.6 | D20: =B20/B19-1 -> 0.033341927 | E20: =C20/C19-1 -> 0.061752832
... A64: 2026-09 | B64: 512.9 | C64: 7651.54 | D64: =B64/B63-1 -> 0.011058763 | E64: =C64/C63-1 -> -0.0045016094

Sheet Comps
A1: TECHNOLOGY MEGA-CAP - COMPARABLE COMPANY ANALYSIS
A2: Microsoft (MSFT) vs. Alphabet (GOOGL) • Amazon (AMZN) • Meta (META) • Apple (AAPL) • Oracle (ORCL)
A3: As of 2026-10-14 (prices) | LTM to latest reported quarter | USD millions except per-share and ratios
A5: OPERATING METRICS (LTM)
A6: Company | B6: Ticker | C6: LTM end | D6: Revenue | E6: Revenue prior LTM | F6: Rev growth | G6: Gross profit | H6: Gross margin | I6: EBIT | J6: EBIT margin | K6: D&A | L6: EBITDA | M6: EBITDA margin | N6: Net income
A7: Microsoft (target) | B7: MSFT | C7: 2026-06-30 | D7: 331839 | E7: 281724 | F7: =D7/E7-1 -> 0.17788687 | G7: 225465 | H7: =IF(ISNUMBER(G7),G7/D7,"n/a") -> 0.67944093 | I7: 155237 | J7: =I7/D7 -> 0.46780818 | K7: 39000 | L7: =I7+K7 -> 194237 | M7: =L7/D7 -> 0.58533506 | N7: 133749
A9: Alphabet | B9: GOOGL | C9: 2026-06-30 | D9: 445867 | E9: 371399 | F9: =D9/E9-1 -> 0.20050673 | G9: 271517 | H9: =IF(ISNUMBER(G9),G9/D9,"n/a") -> 0.60896411 | I9: 147628 | J9: =I9/D9 -> 0.33110322 | K9: 25086 | L9: =I9+K9 -> 172714 | M9: =L9/D9 -> 0.38736664 | N9: 244205
A10: Amazon | B10: AMZN | C10: 2026-06-30 | D10: 775680 | E10: 670038 | F10: =D10/E10-1 -> 0.15766568 | G10: 393810 | H10: =IF(ISNUMBER(G10),G10/D10,"n/a") -> 0.50769647 | I10: 93712 | J10: =I10/D10 -> 0.12081271 | K10: 75200 | L10: =I10+K10 -> 168912 | M10: =L10/D10 -> 0.2177599 | N10: 135281
A11: Meta Platforms | B11: META | C11: 2026-06-30 | D11: 228247 | E11: 178804 | F11: =D11/E11-1 -> 0.27652066 | G11: 186587 | H11: =IF(ISNUMBER(G11),G11/D11,"n/a") -> 0.81747843 | I11: 86927 | J11: =I11/D11 -> 0.38084619 | K11: 22729 | L11: =I11+K11 -> 109656 | M11: =L11/D11 -> 0.48042691 | N11: 68098
A12: Apple | B12: AAPL | C12: 2026-06-27 | D12: 466823 | E12: 408625 | F12: =D12/E12-1 -> 0.14242398 | G12: 227123 | H12: =IF(ISNUMBER(G12),G12/D12,"n/a") -> 0.48652916 | I12: 154859 | J12: =I12/D12 -> 0.33172958 | K12: 13100 | L12: =I12+K12 -> 167959 | M12: =L12/D12 -> 0.35979161 | N12: 128930
A13: Oracle | B13: ORCL | C13: 2026-08-31 | D13: 71777 | E13: 59018 | F13: =D13/E13-1 -> 0.21618828 | G13: n/a | H13: =IF(ISNUMBER(G13),G13/D13,"n/a") -> n/a | I13: 23056 | J13: =I13/D13 -> 0.3212171 | K13: 10881 | L13: =I13+K13 -> 33937 | M13: =L13/D13 -> 0.47281162 | N13: 18920
A15: Peer Maximum | F15: =MAX(F9:F13) -> 0.27652066 | H15: =MAX(H9:H13) -> 0.81747843 | J15: =MAX(J9:J13) -> 0.38084619 | M15: =MAX(M9:M13) -> 0.48042691
A16: Peer 75th Percentile | F16: =QUARTILE(F9:F13,3) -> 0.21618828 | H16: =QUARTILE(H9:H13,3) -> 0.66109269 | J16: =QUARTILE(J9:J13,3) -> 0.33172958 | M16: =QUARTILE(M9:M13,3) -> 0.47281162
A17: Peer Median | F17: =MEDIAN(F9:F13) -> 0.20050673 | H17: =MEDIAN(H9:H13) -> 0.55833029 | J17: =MEDIAN(J9:J13) -> 0.33110322 | M17: =MEDIAN(M9:M13) -> 0.38736664
A18: Peer 25th Percentile | F18: =QUARTILE(F9:F13,1) -> 0.15766568 | H18: =QUARTILE(H9:H13,1) -> 0.50240464 | J18: =QUARTILE(J9:J13,1) -> 0.3212171 | M18: =QUARTILE(M9:M13,1) -> 0.35979161
A19: Peer Minimum | F19: =MIN(F9:F13) -> 0.14242398 | H19: =MIN(H9:H13) -> 0.48652916 | J19: =MIN(J9:J13) -> 0.12081271 | M19: =MIN(M9:M13) -> 0.2177599
A22: VALUATION MULTIPLES
A23: Company | B23: Ticker | C23: Share price | D23: Diluted shares (M) | E23: Market cap | F23: Cash + ST inv. | G23: Total debt | H23: Enterprise value | I23: EV / Revenue | J23: EV / EBITDA | K23: EV / EBIT | L23: P / E | M23: FCF note
A24: =A7 -> Microsoft (target) | B24: =B7 -> MSFT | C24: 533.69 | D24: 7425.5 | E24: =C24*D24 -> 3962915.1 | F24: 76843 | G24: 40294 | H24: =E24-F24+G24 -> 3926366.1 | I24: =H24/D7 -> 11.832142 | J24: =H24/L7 -> 20.214306 | K24: =H24/I7 -> 25.292721 | L24: =E24/N7 -> 29.629493
A26: =A9 -> Alphabet | B26: =B9 -> GOOGL | C26: 347.64 | D26: 12229.9 | E26: =C26*D26 -> 4251602.4 | F26: 242474 | G26: 100164 | H26: =E26-F26+G26 -> 4109292.4 | I26: =H26/D9 -> 9.2164086 | J26: =H26/L9 -> 23.792469 | K26: =H26/I9 -> 27.835454 | L26: =E26/N9 -> 17.409973 | M26: P/E distorted by investment gains
A27: =A10 -> Amazon | B27: =B10 -> AMZN | C27: 254.08 | D27: 10786.3 | E27: =C27*D27 -> 2740583.1 | F27: 122988 | G27: 132224 | H27: =E27-F27+G27 -> 2749819.1 | I27: =H27/D10 -> 3.5450432 | J27: =H27/L10 -> 16.279596 | K27: =H27/I10 -> 29.343298 | L27: =E27/N10 -> 20.258448 | M27: P/E depressed by equity-investment gains
A28: =A11 -> Meta Platforms | B28: =B11 -> META | C28: 737.54 | D28: 2547.5 | E28: =C28*D28 -> 1878883.1 | F28: 90260 | G28: 83664 | H28: =E28-F28+G28 -> 1872287.1 | I28: =H28/D11 -> 8.2028993 | J28: =H28/L11 -> 17.074188 | K28: =H28/I11 -> 21.538615 | L28: =E28/N11 -> 27.590871 | M28: Q3-25 one-off tax charge
A29: =A12 -> Apple | B29: =B12 -> AAPL | C29: 342.96 | D29: 14594.2 | E29: =C29*D29 -> 5005226.8 | F29: 62399 | G29: 82347 | H29: =E29-F29+G29 -> 5025174.8 | I29: =H29/D12 -> 10.764626 | J29: =H29/L12 -> 29.919057 | K29: =H29/I12 -> 32.450002 | L29: =E29/N12 -> 38.821274
A30: =A13 -> Oracle | B30: =B13 -> ORCL | C30: 130.55 | D30: 3031.5 | E30: =C30*D30 -> 395762.33 | F30: 37077 | G30: 125337 | H30: =E30-F30+G30 -> 484022.33 | I30: =H30/D13 -> 6.7434182 | J30: =H30/L13 -> 14.262378 | K30: =H30/I13 -> 20.993335 | L30: =E30/N13 -> 20.91767
A32: Peer Maximum | I32: =MAX(I26:I30) -> 10.764626 | J32: =MAX(J26:J30) -> 29.919057 | K32: =MAX(K26:K30) -> 32.450002 | L32: =MAX(L26:L30) -> 38.821274
A33: Peer 75th Percentile | I33: =QUARTILE(I26:I30,3) -> 9.2164086 | J33: =QUARTILE(J26:J30,3) -> 23.792469 | K33: =QUARTILE(K26:K30,3) -> 29.343298 | L33: =QUARTILE(L26:L30,3) -> 27.590871
A34: Peer Median | I34: =MEDIAN(I26:I30) -> 8.2028993 | J34: =MEDIAN(J26:J30) -> 17.074188 | K34: =MEDIAN(K26:K30) -> 27.835454 | L34: =MEDIAN(L26:L30) -> 20.91767
A35: Peer 25th Percentile | I35: =QUARTILE(I26:I30,1) -> 6.7434182 | J35: =QUARTILE(J26:J30,1) -> 16.279596 | K35: =QUARTILE(K26:K30,1) -> 21.538615 | L35: =QUARTILE(L26:L30,1) -> 20.258448
A36: Peer Minimum | I36: =MIN(I26:I30) -> 3.5450432 | J36: =MIN(J26:J30) -> 14.262378 | K36: =MIN(K26:K30) -> 20.993335 | L36: =MIN(L26:L30) -> 17.409973
A38: MSFT EV/EBITDA premium/(discount) to peer median | J38: =J24/J34-1 -> 0.18391023
A39: MSFT P/E premium/(discount) to peer median | L39: =L24/L34-1 -> 0.4164815
A40: Peer median LTM revenue growth | F40: =F17 -> 0.20050673
A41: Peer median EBITDA margin | M41: =M17 -> 0.38736664
A44: NOTES & METHODOLOGY
A45: Data: SEC XBRL standardized financials via stock-data MCP (get_financials); prices/market caps via stock-data get_quote (Yahoo, close 2026-10-14).
A46: LTM = sum of last four reported quarters; prior LTM = the four quarters before. Fiscal year ends differ (AAPL Sep, ORCL May, MSFT Jun, others Dec).
A47: EBITDA = Operating income (EBIT) + D&A from the cash flow statement. GOOGL LTM D&A is an estimate (see cell comment).
A48: EV = market cap - cash & current marketable securities + total debt (operating and finance lease liabilities excluded for all companies).
A49: P/E for GOOGL, AMZN is depressed by large unrealized equity-investment gains in 2026; META LTM includes a one-off tax charge. Use EV/EBITDA and EV/EBIT as the primary multiples.
A50: Statistics are calculated over the five peers only (MSFT excluded).
