Workbook

Sheet Assumptions
A1: Microsoft Corp. (MSFT) - Projection Assumptions
A2: USD millions unless stated; fiscal years end June 30
A4: Fiscal year | B4: FY2023A | C4: FY2024A | D4: FY2025A | E4: FY2026A | F4: FY2027E | G4: FY2028E | H4: FY2029E | I4: FY2030E | J4: FY2031E
A5: Operating drivers (projection years)
A6: Revenue growth (%) | F6: 0.15 | G6: 0.14 | H6: 0.13 | I6: 0.12 | J6: 0.11
A7: Cost of revenue (% of revenue) | F7: 0.32 | G7: 0.32 | H7: 0.32 | I7: 0.32 | J7: 0.32
A8: Research & development (% of revenue) | F8: 0.105 | G8: 0.105 | H8: 0.105 | I8: 0.105 | J8: 0.105
A9: Sales, marketing, G&A (% of revenue) | F9: 0.1 | G9: 0.1 | H9: 0.1 | I9: 0.1 | J9: 0.1
A10: Interest rate on beginning debt (%) | F10: 0.05 | G10: 0.05 | H10: 0.05 | I10: 0.05 | J10: 0.05
A11: Other income, net ($mm) | F11: 3000 | G11: 3000 | H11: 3000 | I11: 3000 | J11: 3000
A12: Effective tax rate (%) | F12: 0.19 | G12: 0.19 | H12: 0.19 | I12: 0.19 | J12: 0.19
A13: Receivable days (DSO, on revenue) | F13: 89 | G13: 89 | H13: 89 | I13: 89 | J13: 89
A14: Inventory days (DIO, on cost of revenue) | F14: 5 | G14: 5 | H14: 5 | I14: 5 | J14: 5
A15: Payable days (DPO, on cost of revenue) | F15: 145 | G15: 145 | H15: 145 | I15: 145 | J15: 145
A16: Stock-based comp (% of revenue) | F16: 0.037 | G16: 0.037 | H16: 0.037 | I16: 0.037 | J16: 0.037
A17: Capital expenditures (% of revenue) | F17: 0.33 | G17: 0.31 | H17: 0.29 | I17: 0.27 | J17: 0.25
... A21: Net debt issuance / (repayment) ($mm) | F21: -5000 | G21: -5000 | H21: -5000 | I21: -5000 | J21: -5000
A23: Blue = hard-coded input; black = formula; green = link to another sheet. Historical columns are left blank on this tab; history lives on the statements.

Sheet IS
A1: Microsoft Corp. (MSFT) - Income Statement
A2: USD millions unless stated; fiscal years end June 30
A4: Fiscal year | B4: FY2023A | C4: FY2024A | D4: FY2025A | E4: FY2026A | F4: FY2027E | G4: FY2028E | H4: FY2029E | I4: FY2030E | J4: FY2031E
A6: Revenue | B6: 211915 | C6: 245122 | D6: 281724 | E6: 331839 | F6: =E6*(1+Assumptions!F6) | G6: =F6*(1+Assumptions!G6) | H6: =G6*(1+Assumptions!H6) | I6: =H6*(1+Assumptions!I6) | J6: =I6*(1+Assumptions!J6)
A7: Cost of revenue | B7: 65863 | C7: 74114 | D7: 87831 | E7: 106374 | F7: =F6*Assumptions!F7 | G7: =G6*Assumptions!G7 | H7: =H6*Assumptions!H7 | I7: =I6*Assumptions!I7 | J7: =J6*Assumptions!J7
A8: Gross profit | B8: =B6-B7 | C8: =C6-C7 | D8: =D6-D7 | E8: =E6-E7 | F8: =F6-F7 | G8: =G6-G7 | H8: =H6-H7 | I8: =I6-I7 | J8: =J6-J7
A9: Research & development | B9: 27195 | C9: 29510 | D9: 32488 | E9: 35562 | F9: =F6*Assumptions!F8 | G9: =G6*Assumptions!G8 | H9: =H6*Assumptions!H8 | I9: =I6*Assumptions!I8 | J9: =J6*Assumptions!J8
A10: Sales & marketing, general & administrative | B10: 30334 | C10: 32065 | D10: 32877 | E10: 34666 | F10: =F6*Assumptions!F9 | G10: =G6*Assumptions!G9 | H10: =H6*Assumptions!H9 | I10: =I6*Assumptions!I9 | J10: =J6*Assumptions!J9
A11: Operating income | B11: =B8-B9-B10 | C11: =C8-C9-C10 | D11: =D8-D9-D10 | E11: =E8-E9-E10 | F11: =F8-F9-F10 | G11: =G8-G9-G10 | H11: =H8-H9-H10 | I11: =I8-I9-I10 | J11: =J8-J9-J10
A12: Interest expense | B12: 1968 | C12: 2935 | D12: 2385 | E12: 3051 | F12: =(BS!E21+BS!E24)*Assumptions!F10 | G12: =(BS!F21+BS!F24)*Assumptions!G10 | H12: =(BS!G21+BS!G24)*Assumptions!H10 | I12: =(BS!H21+BS!H24)*Assumptions!I10 | J12: =(BS!I21+BS!I24)*Assumptions!J10
A13: Other income (expense), net | B13: 2756 | C13: 1289 | D13: -2516 | E13: 13748 | F13: =Assumptions!F11 | G13: =Assumptions!G11 | H13: =Assumptions!H11 | I13: =Assumptions!I11 | J13: =Assumptions!J11
A14: Income before income taxes | B14: =B11-B12+B13 | C14: =C11-C12+C13 | D14: =D11-D12+D13 | E14: =E11-E12+E13 | F14: =F11-F12+F13 | G14: =G11-G12+G13 | H14: =H11-H12+H13 | I14: =I11-I12+I13 | J14: =J11-J12+J13
A15: Provision for income taxes | B15: 16950 | C15: 19651 | D15: 21795 | E15: 32185 | F15: =F14*Assumptions!F12 | G15: =G14*Assumptions!G12 | H15: =H14*Assumptions!H12 | I15: =I14*Assumptions!I12 | J15: =J14*Assumptions!J12
A16: Net income | B16: =B14-B15 | C16: =C14-C15 | D16: =D14-D15 | E16: =E14-E15 | F16: =F14-F15 | G16: =G14-G15 | H16: =H14-H15 | I16: =I14-I15 | J16: =J14-J15
A17: Memo:
A18: Gross margin (%) | B18: =IF(B6=0,0,B8/B6) | C18: =IF(C6=0,0,C8/C6) | D18: =IF(D6=0,0,D8/D6) | E18: =IF(E6=0,0,E8/E6) | F18: =IF(F6=0,0,F8/F6) | G18: =IF(G6=0,0,G8/G6) | H18: =IF(H6=0,0,H8/H6) | I18: =IF(I6=0,0,I8/I6) | J18: =IF(J6=0,0,J8/J6)
A19: Operating margin (%) | B19: =IF(B6=0,0,B11/B6) | C19: =IF(C6=0,0,C11/C6) | D19: =IF(D6=0,0,D11/D6) | E19: =IF(E6=0,0,E11/E6) | F19: =IF(F6=0,0,F11/F6) | G19: =IF(G6=0,0,G11/G6) | H19: =IF(H6=0,0,H11/H6) | I19: =IF(I6=0,0,I11/I6) | J19: =IF(J6=0,0,J11/J6)
A20: Revenue growth (%) | C20: =IF(B6=0,0,C6/B6-1) | D20: =IF(C6=0,0,D6/C6-1) | E20: =IF(D6=0,0,E6/D6-1) | F20: =IF(E6=0,0,F6/E6-1) | G20: =IF(F6=0,0,G6/F6-1) | H20: =IF(G6=0,0,H6/G6-1) | I20: =IF(H6=0,0,I6/H6-1) | J20: =IF(I6=0,0,J6/I6-1)
A22: Diluted weighted-average shares (mm) | B22: 7472 | C22: 7469 | D22: 7465 | E22: 7453 | F22: =E22 | G22: =F22 | H22: =G22 | I22: =H22 | J22: =I22
A23: Diluted EPS ($) | B23: =IF(B22=0,0,B16/B22) | C23: =IF(C22=0,0,C16/C22) | D23: =IF(D22=0,0,D16/D22) | E23: =IF(E22=0,0,E16/E22) | F23: =IF(F22=0,0,F16/F22) | G23: =IF(G22=0,0,G16/G22) | H23: =IF(H22=0,0,H16/H22) | I23: =IF(I22=0,0,I16/I22) | J23: =IF(J22=0,0,J16/J22)
A25: Source (historicals): Microsoft Form 10-K filings, SEC XBRL company facts (via stock-data get_financials). SG&A = total operating expenses less R&D; other income, net = pretax income less operating income plus interest expense. D&A is embedded in cost of revenue and operating expenses.

Sheet BS
A1: Microsoft Corp. (MSFT) - Balance Sheet
A2: USD millions unless stated; fiscal years end June 30
A4: Fiscal year | B4: FY2023A | C4: FY2024A | D4: FY2025A | E4: FY2026A | F4: FY2027E | G4: FY2028E | H4: FY2029E | I4: FY2030E | J4: FY2031E
A5: Assets
A6: Cash and cash equivalents | B6: 34704 | C6: 18315 | D6: 30242 | E6: 20935 | F6: =CFS!F28 | G6: =CFS!G28 | H6: =CFS!H28 | I6: =CFS!I28 | J6: =CFS!J28
A7: Short-term investments | B7: 76558 | C7: 57228 | D7: 64323 | E7: 55908 | F7: =E7 | G7: =F7 | H7: =G7 | I7: =H7 | J7: =I7
A8: Accounts receivable, net | B8: 48688 | C8: 56924 | D8: 69905 | E8: 80876 | F8: =IS!F6*Assumptions!F13/365 | G8: =IS!G6*Assumptions!G13/365 | H8: =IS!H6*Assumptions!H13/365 | I8: =IS!I6*Assumptions!I13/365 | J8: =IS!J6*Assumptions!J13/365
A9: Inventories | B9: 2500 | C9: 1246 | D9: 938 | E9: 1397 | F9: =IS!F7*Assumptions!F14/365 | G9: =IS!G7*Assumptions!G14/365 | H9: =IS!H7*Assumptions!H14/365 | I9: =IS!I7*Assumptions!I14/365 | J9: =IS!J7*Assumptions!J14/365
A10: Other current assets | B10: =B11-SUM(B6:B9) | C10: =C11-SUM(C6:C9) | D10: =D11-SUM(D6:D9) | E10: =E11-SUM(E6:E9) | F10: =E10 | G10: =F10 | H10: =G10 | I10: =H10 | J10: =I10
A11: Total current assets | B11: 184257 | C11: 159734 | D11: 191131 | E11: 207710 | F11: =SUM(F6:F10) | G11: =SUM(G6:G10) | H11: =SUM(H6:H10) | I11: =SUM(I6:I10) | J11: =SUM(J6:J10)
A12: Property and equipment, net | B12: 95641 | C12: 135591 | D12: 204966 | E12: 313076 | F12: =Schedules!F10 | G12: =Schedules!G10 | H12: =Schedules!H10 | I12: =Schedules!I10 | J12: =Schedules!J10
A13: Goodwill | B13: 67886 | C13: 119220 | D13: 119509 | E13: 119651 | F13: =E13 | G13: =F13 | H13: =G13 | I13: =H13 | J13: =I13
A14: Intangible assets, net | B14: 9366 | C14: 27597 | D14: 22604 | E14: 18609 | F14: =E14 | G14: =F14 | H14: =G14 | I14: =H14 | J14: =I14
A15: Other long-term assets | B15: =B16-B11-SUM(B12:B14) | C15: =C16-C11-SUM(C12:C14) | D15: =D16-D11-SUM(D12:D14) | E15: =E16-E11-SUM(E12:E14) | F15: =E15 | G15: =F15 | H15: =G15 | I15: =H15 | J15: =I15
A16: Total assets | B16: 411976 | C16: 512163 | D16: 619003 | E16: 758376 | F16: =F11+SUM(F12:F15) | G16: =G11+SUM(G12:G15) | H16: =H11+SUM(H12:H15) | I16: =I11+SUM(I12:I15) | J16: =J11+SUM(J12:J15)
A17: Liabilities
A18: Accounts payable | B18: 18095 | C18: 21996 | D18: 27724 | E18: 42416 | F18: =IS!F7*Assumptions!F15/365 | G18: =IS!G7*Assumptions!G15/365 | H18: =IS!H7*Assumptions!H15/365 | I18: =IS!I7*Assumptions!I15/365 | J18: =IS!J7*Assumptions!J15/365
A19: Other current liabilities | B19: =B22-B18-B21 | C19: =C22-C18-C21 | D19: =D22-D18-D21 | E19: =E22-E18-E21 | F19: =E19 | G19: =F19 | H19: =G19 | I19: =H19 | J19: =I19
A21: Current portion of long-term debt | B21: 5247 | C21: 2249 | D21: 2999 | E21: 9227 | F21: =Schedules!F16 | G21: =Schedules!G16 | H21: =Schedules!H16 | I21: =Schedules!I16 | J21: =Schedules!J16
A22: Total current liabilities | B22: 104149 | C22: 125286 | D22: 141218 | E22: 168825 | F22: =SUM(F18:F21) | G22: =SUM(G18:G21) | H22: =SUM(H18:H21) | I22: =SUM(I18:I21) | J22: =SUM(J18:J21)
A24: Long-term debt | B24: 41990 | C24: 42688 | D24: 40152 | E24: 31067 | F24: =Schedules!F17 | G24: =Schedules!G17 | H24: =Schedules!H17 | I24: =Schedules!I17 | J24: =Schedules!J17
A25: Other long-term liabilities | B25: =B26-B22-B24 | C25: =C26-C22-C24 | D25: =D26-D22-D24 | E25: =E26-E22-E24 | F25: =E25 | G25: =F25 | H25: =G25 | I25: =H25 | J25: =I25
A26: Total liabilities | B26: 205753 | C26: 243686 | D26: 275524 | E26: 315989 | F26: =F22+F24+F25 | G26: =G22+G24+G25 | H26: =H22+H24+H25 | I26: =I22+I24+I25 | J26: =J22+J24+J25
A27: Stockholders' equity
A28: Retained earnings & other equity | B28: 206223 | C28: 268477 | D28: 343479 | E28: 442387 | F28: =E28+IS!F16+CFS!F8+CFS!F19+CFS!F20 | G28: =F28+IS!G16+CFS!G8+CFS!G19+CFS!G20 | H28: =G28+IS!H16+CFS!H8+CFS!H19+CFS!H20 | I28: =H28+IS!I16+CFS!I8+CFS!I19+CFS!I20 | J28: =I28+IS!J16+CFS!J8+CFS!J19+CFS!J20
A29: Total stockholders' equity | B29: =B28 | C29: =C28 | D29: =D28 | E29: =E28 | F29: =F28 | G29: =G28 | H29: =H28 | I29: =I28 | J29: =J28
A30: Total liabilities and stockholders' equity | B30: =B26+B29 | C30: =C26+C29 | D30: =D26+D29 | E30: =E26+E29 | F30: =F26+F29 | G30: =G26+G29 | H30: =H26+H29 | I30: =I26+I29 | J30: =J26+J29
A32: Checks: total assets less total liabilities & equity | B32: =ROUND(B16-B30,3) | C32: =ROUND(C16-C30,3) | D32: =ROUND(D16-D30,3) | E32: =ROUND(E16-E30,3) | F32: =ROUND(F16-F30,3) | G32: =ROUND(G16-G30,3) | H32: =ROUND(H16-H30,3) | I32: =ROUND(I16-I30,3) | J32: =ROUND(J16-J30,3)
A34: Source (historicals): Microsoft Form 10-K filings, SEC XBRL (via stock-data get_financials). Historical 'other' lines are reported totals less reported components. Equity is carried in one line because the data source reports total stockholders' equity only.

Sheet Schedules
A1: Microsoft Corp. (MSFT) - Supporting Schedules
A2: USD millions unless stated; fiscal years end June 30
A4: Fiscal year | B4: FY2023A | C4: FY2024A | D4: FY2025A | E4: FY2026A | F4: FY2027E | G4: FY2028E | H4: FY2029E | I4: FY2030E | J4: FY2031E
A6: PP&E roll-forward
A7: Beginning net PP&E | F7: =E10 | G7: =F10 | H7: =G10 | I7: =H10 | J7: =I10
A8: Capital expenditures | B8: 28107 | C8: 44477 | D8: 64551 | E8: 115948 | F8: =IS!F6*Assumptions!F17 | G8: =IS!G6*Assumptions!G17 | H8: =IS!H6*Assumptions!H17 | I8: =IS!I6*Assumptions!I17 | J8: =IS!J6*Assumptions!J17
A9: Depreciation & amortization | F9: =F7*Assumptions!F18 | G9: =G7*Assumptions!G18 | H9: =H7*Assumptions!H18 | I9: =I7*Assumptions!I18 | J9: =J7*Assumptions!J18
A10: Ending net PP&E | B10: =BS!B12 | C10: =BS!C12 | D10: =BS!D12 | E10: =BS!E12 | F10: =F7+F8-F9 | G10: =G7+G8-G9 | H10: =H7+H8-H9 | I10: =I7+I8-I9 | J10: =J7+J8-J9
A13: Debt schedule
A14: Beginning total debt | F14: =E18 | G14: =F18 | H14: =G18 | I14: =H18 | J14: =I18
A15: Net issuance / (repayment) | F15: =Assumptions!F21 | G15: =Assumptions!G21 | H15: =Assumptions!H21 | I15: =Assumptions!I21 | J15: =Assumptions!J21
A16: Current portion of long-term debt | B16: =BS!B21 | C16: =BS!C21 | D16: =BS!D21 | E16: =BS!E21 | F16: =E16 | G16: =F16 | H16: =G16 | I16: =H16 | J16: =I16
A17: Long-term debt | B17: =BS!B24 | C17: =BS!C24 | D17: =BS!D24 | E17: =BS!E24 | F17: =E17+F15 | G17: =F17+G15 | H17: =G17+H15 | I17: =H17+I15 | J17: =I17+J15
A18: Ending total debt | B18: =B16+B17 | C18: =C16+C17 | D18: =D16+D17 | E18: =E16+E17 | F18: =F16+F17 | G18: =G16+G17 | H18: =H16+H17 | I18: =I16+I17 | J18: =J16+J17
A20: Historical D&A is not reported by the data source and is left blank. Projected D&A is not broken out of cost of revenue / operating expenses on the IS; it drives PP&E and the cash flow add-back. Current portion of debt is held flat; net issuance flows through long-term debt.

Sheet CFS
A1: Microsoft Corp. (MSFT) - Cash Flow Statement
A2: USD millions unless stated; fiscal years end June 30
A4: Fiscal year | B4: FY2023A | C4: FY2024A | D4: FY2025A | E4: FY2026A | F4: FY2027E | G4: FY2028E | H4: FY2029E | I4: FY2030E | J4: FY2031E
A5: Operating activities
A6: Net income | B6: =IS!B16 | C6: =IS!C16 | D6: =IS!D16 | E6: =IS!E16 | F6: =IS!F16 | G6: =IS!G16 | H6: =IS!H16 | I6: =IS!I16 | J6: =IS!J16
A7: Depreciation & amortization | F7: =Schedules!F9 | G7: =Schedules!G9 | H7: =Schedules!H9 | I7: =Schedules!I9 | J7: =Schedules!J9
A8: Stock-based compensation | B8: 9611 | C8: 10734 | D8: 11974 | E8: 12405 | F8: =IS!F6*Assumptions!F16 | G8: =IS!G6*Assumptions!G16 | H8: =IS!H6*Assumptions!H16 | I8: =IS!I6*Assumptions!I16 | J8: =IS!J6*Assumptions!J16
A9: (Increase) / decrease in receivables | F9: =BS!E8-BS!F8 | G9: =BS!F8-BS!G8 | H9: =BS!G8-BS!H8 | I9: =BS!H8-BS!I8 | J9: =BS!I8-BS!J8
A10: (Increase) / decrease in inventories | F10: =BS!E9-BS!F9 | G10: =BS!F9-BS!G9 | H10: =BS!G9-BS!H9 | I10: =BS!H9-BS!I9 | J10: =BS!I9-BS!J9
A11: Increase / (decrease) in payables | F11: =BS!F18-BS!E18 | G11: =BS!G18-BS!F18 | H11: =BS!H18-BS!G18 | I11: =BS!I18-BS!H18 | J11: =BS!J18-BS!I18
A12: Other operating items, net | B12: =B13-SUM(B6:B11) | C12: =C13-SUM(C6:C11) | D12: =D13-SUM(D6:D11) | E12: =E13-SUM(E6:E11) | F12: 0 | G12: 0 | H12: 0 | I12: 0 | J12: 0
A13: Cash from operating activities | B13: 87582 | C13: 118548 | D13: 136162 | E13: 182935 | F13: =SUM(F6:F12) | G13: =SUM(G6:G12) | H13: =SUM(H6:H12) | I13: =SUM(I6:I12) | J13: =SUM(J6:J12)
A14: Investing activities
A15: Capital expenditures | B15: =-Schedules!B8 | C15: =-Schedules!C8 | D15: =-Schedules!D8 | E15: =-Schedules!E8 | F15: =-Schedules!F8 | G15: =-Schedules!G8 | H15: =-Schedules!H8 | I15: =-Schedules!I8 | J15: =-Schedules!J8
A16: Other investing, net | B16: =B17-B15 | C16: =C17-C15 | D16: =D17-D15 | E16: =E17-E15 | F16: 0 | G16: 0 | H16: 0 | I16: 0 | J16: 0
A17: Cash from investing activities | B17: -22680 | C17: -96970 | D17: -72599 | E17: -139500 | F17: =SUM(F15:F16) | G17: =SUM(G15:G16) | H17: =SUM(H15:H16) | I17: =SUM(I15:I16) | J17: =SUM(J15:J16)
A18: Financing activities
A19: Dividends paid | B19: -19800 | C19: -21771 | D19: -24082 | E19: -26445 | F19: =-IS!F16*Assumptions!F19 | G19: =-IS!G16*Assumptions!G19 | H19: =-IS!H16*Assumptions!H19 | I19: =-IS!I16*Assumptions!I19 | J19: =-IS!J16*Assumptions!J19
A20: Share repurchases | B20: -22245 | C20: -17254 | D20: -18420 | E20: -22271 | F20: =-Assumptions!F20 | G20: =-Assumptions!G20 | H20: =-Assumptions!H20 | I20: =-Assumptions!I20 | J20: =-Assumptions!J20
A21: Debt issuance / (repayment) | F21: =Schedules!F18-Schedules!E18 | G21: =Schedules!G18-Schedules!F18 | H21: =Schedules!H18-Schedules!G18 | I21: =Schedules!I18-Schedules!H18 | J21: =Schedules!J18-Schedules!I18
A22: Other financing, net | B22: =B23-SUM(B19:B21) | C22: =C23-SUM(C19:C21) | D22: =D23-SUM(D19:D21) | E22: =E23-SUM(E19:E21) | F22: 0 | G22: 0 | H22: 0 | I22: 0 | J22: 0
A23: Cash from financing activities | B23: -43935 | C23: -37757 | D23: -51699 | E23: -52546 | F23: =SUM(F19:F22) | G23: =SUM(G19:G22) | H23: =SUM(H19:H22) | I23: =SUM(I19:I22) | J23: =SUM(J19:J22)
A24: Effect of FX & other | B24: =B28-B27-B13-B17-B23 | C24: =C28-C27-C13-C17-C23 | D24: =D28-D27-D13-D17-D23 | E24: =E28-E27-E13-E17-E23 | F24: 0 | G24: 0 | H24: 0 | I24: 0 | J24: 0
A25: Net change in cash | B25: =B13+B17+B23+B24 | C25: =C13+C17+C23+C24 | D25: =D13+D17+D23+D24 | E25: =E13+E17+E23+E24 | F25: =F13+F17+F23+F24 | G25: =G13+G17+G23+G24 | H25: =H13+H17+H23+H24 | I25: =I13+I17+I23+I24 | J25: =J13+J17+J23+J24
A27: Beginning cash | B27: 13931 | C27: =B28 | D27: =C28 | E27: =D28 | F27: =E28 | G27: =F28 | H27: =G28 | I27: =H28 | J27: =I28
A28: Ending cash | B28: =BS!B6 | C28: =BS!C6 | D28: =BS!D6 | E28: =BS!E6 | F28: =F27+F25 | G28: =G27+G25 | H28: =H27+H25 | I28: =I27+I25 | J28: =J27+J25
A30: Source (historicals): Microsoft Form 10-K filings, SEC XBRL (via stock-data get_financials). Historical subtotals are reported; 'other' lines are reported subtotals less reported components; FY2023 beginning cash is FY2022 reported cash. Historical D&A and working-capital detail are not reported by the data source.

Sheet Valuation
A1: Microsoft Corp. (MSFT) - Valuation Snapshot
A2: USD millions unless stated
A4: Share price ($) | B4: 543.45
A5: Diluted shares (mm) | B5: =IS!E22
A6: Market capitalization | B6: =B4*B5
A7: Total debt (FY2026A) | B7: =BS!E21+BS!E24
A8: Cash & short-term investments (FY2026A) | B8: =BS!E6+BS!E7
A9: Net debt / (net cash) | B9: =B7-B8
A10: Enterprise value | B10: =B6+B9
A12: Revenue FY2026A | B12: =IS!E6
A13: Revenue FY2027E | B13: =IS!F6
A14: EV / Revenue FY2026A | B14: =IF(B12=0,0,B10/B12)
A15: EV / Revenue FY2027E | B15: =IF(B13=0,0,B10/B13)
A17: Share price: stock-data get_quote, MSFT, fetched 2026-10-14 03:54 UTC. Diluted shares: weighted-average diluted shares from the latest Form 10-K (SEC XBRL via stock-data get_financials).
