Workbook

Sheet Assumptions
A1: Microsoft Corp. (MSFT) - Projection Assumptions
A2: USD millions unless stated; fiscal years end June 30
A4: Fiscal year | B4: FY2023A | C4: FY2024A | D4: FY2025A | E4: FY2026A | F4: FY2027E | G4: FY2028E | H4: FY2029E | I4: FY2030E | J4: FY2031E
A5: Operating drivers (projection years)
A6: Revenue growth (%) | F6: 0.15 | G6: 0.14 | H6: 0.13 | I6: 0.12 | J6: 0.11
A7: Cost of revenue (% of revenue) | F7: 0.32 | G7: 0.32 | H7: 0.32 | I7: 0.32 | J7: 0.32
A8: Research & development (% of revenue) | F8: 0.105 | G8: 0.105 | H8: 0.105 | I8: 0.105 | J8: 0.105
A9: Sales, marketing, G&A (% of revenue) | F9: 0.1 | G9: 0.1 | H9: 0.1 | I9: 0.1 | J9: 0.1
A10: Interest rate on beginning debt (%) | F10: 0.05 | G10: 0.05 | H10: 0.05 | I10: 0.05 | J10: 0.05
A11: Other income, net ($mm) | F11: 3000 | G11: 3000 | H11: 3000 | I11: 3000 | J11: 3000
A12: Effective tax rate (%) | F12: 0.19 | G12: 0.19 | H12: 0.19 | I12: 0.19 | J12: 0.19
A13: Receivable days (DSO, on revenue) | F13: 89 | G13: 89 | H13: 89 | I13: 89 | J13: 89
A14: Inventory days (DIO, on cost of revenue) | F14: 5 | G14: 5 | H14: 5 | I14: 5 | J14: 5
A15: Payable days (DPO, on cost of revenue) | F15: 145 | G15: 145 | H15: 145 | I15: 145 | J15: 145
A16: Stock-based comp (% of revenue) | F16: 0.037 | G16: 0.037 | H16: 0.037 | I16: 0.037 | J16: 0.037
A17: Capital expenditures (% of revenue) | F17: 0.33 | G17: 0.31 | H17: 0.29 | I17: 0.27 | J17: 0.25
... A21: Net debt issuance / (repayment) ($mm) | F21: -5000 | G21: -5000 | H21: -5000 | I21: -5000 | J21: -5000
A23: Blue = hard-coded input; black = formula; green = link to another sheet. Historical columns are left blank on this tab; history lives on the statements.

Sheet IS
A1: Microsoft Corp. (MSFT) - Income Statement
A2: USD millions unless stated; fiscal years end June 30
A4: Fiscal year | B4: FY2023A | C4: FY2024A | D4: FY2025A | E4: FY2026A | F4: FY2027E | G4: FY2028E | H4: FY2029E | I4: FY2030E | J4: FY2031E
A6: Revenue | B6: 211915 | C6: 245122 | D6: 304262 | E6: 331839 | F6: =E6*(1+Assumptions!F6) -> 381614.85 | G6: =F6*(1+Assumptions!G6) -> 435040.93 | H6: 491596.25 | I6: =H6*(1+Assumptions!I6) -> 550587.8 | J6: =I6*(1+Assumptions!J6) -> 611152.46
A7: Cost of revenue | B7: 65863 | C7: 74114 | D7: 87831 | E7: 106374 | F7: =F6*Assumptions!F7 -> 122116.75 | G7: =G6*Assumptions!G7 -> 139213.1 | H7: =H6*Assumptions!H7 -> 157310.8 | I7: =I6*Assumptions!I7 -> 176188.1 | J7: =J6*Assumptions!J7 -> 195568.79
A8: Gross profit | B8: =B6-B7 -> 146052 | C8: =C6-C7 -> 171008 | D8: =D6-D7 -> 216431 | E8: =E6-E7 -> 225465 | F8: =F6-F7 -> 259498.1 | G8: =G6-G7 -> 295827.83 | H8: =H6-H7 -> 334285.45 | I8: =I6-I7 -> 374399.7 | J8: =J6-J7 -> 415583.67
A9: Research & development | B9: 27195 | C9: 29510 | D9: 32488 | E9: 35562 | F9: =F6*Assumptions!F8 -> 40069.559 | G9: =G6*Assumptions!G8 -> 45679.298 | H9: =H6*Assumptions!H8 -> 51617.606 | I9: =I6*Assumptions!I8 -> 57811.719 | J9: =J6*Assumptions!J8 -> 64171.008
A10: Sales & marketing, general & administrative | B10: 30334 | C10: 32065 | D10: 32877 | E10: 34666 | F10: =F6*Assumptions!F9 -> 38161.485 | G10: =G6*Assumptions!G9 -> 43504.093 | H10: =H6*Assumptions!H9 -> 49159.625 | I10: =I6*Assumptions!I9 -> 55058.78 | J10: =J6*Assumptions!J9 -> 61115.246
A11: Operating income | B11: =B8-B9-B10 -> 88523 | C11: =C8-C9-C10 -> 109433 | D11: =D8-D9-D10 -> 151066 | E11: =E8-E9-E10 -> 155237 | F11: =F8-F9-F10 -> 181267.05 | G11: =G8-G9-G10 -> 206644.44 | H11: =H8-H9-H10 -> 233508.22 | I11: =I8-I9-I10 -> 261529.2 | J11: =J8-J9-J10 -> 290297.42
A12: Interest expense | B12: 1968 | C12: 2935 | D12: 2385 | E12: 3051 | F12: =(BS!E21+BS!E24)*Assumptions!F10 -> 2014.7 | G12: =(BS!F21+BS!F24)*Assumptions!G10 -> 1764.7 | H12: =(BS!G21+BS!G24)*Assumptions!H10 -> 1514.7 | I12: =(BS!H21+BS!H24)*Assumptions!I10 -> 1264.7 | J12: =(BS!I21+BS!I24)*Assumptions!J10 -> 1014.7
A13: Other income (expense), net | B13: 2756 | C13: 1289 | D13: -2516 | E13: 13748 | F13: =Assumptions!F11 -> 3000 | G13: =Assumptions!G11 -> 3000 | H13: =Assumptions!H11 -> 3000 | I13: =Assumptions!I11 -> 3000 | J13: =Assumptions!J11 -> 3000
A14: Income before income taxes | B14: =B11-B12+B13 -> 89311 | C14: =C11-C12+C13 -> 107787 | D14: =D11-D12+D13 -> 146165 | E14: =E11-E12+E13 -> 165934 | F14: =F11-F12+F13 -> 182252.35 | G14: =G11-G12+G13 -> 207879.74 | H14: =H11-H12+H13 -> 234993.52 | I14: =I11-I12+I13 -> 263264.5 | J14: =J11-J12+J13 -> 292282.72
A15: Provision for income taxes | B15: 16950 | C15: 19651 | D15: 21795 | E15: 32185 | F15: =F14*Assumptions!F12 -> 34627.947 | G15: =G14*Assumptions!G12 -> 39497.151 | H15: =H14*Assumptions!H12 -> 44648.769 | I15: =I14*Assumptions!I12 -> 50020.256 | J15: =J14*Assumptions!J12 -> 55533.716
A16: Net income | B16: =B14-B15 -> 72361 | C16: =C14-C15 -> 88136 | D16: =D14-D15 -> 124370 | E16: =E14-E15 -> 133749 | F16: =F14-F15 -> 147624.41 | G16: =G14-G15 -> 168382.59 | H16: =H14-H15 -> 190344.75 | I16: =I14-I15 -> 213244.25 | J16: =J14-J15 -> 236749
A17: Memo:
A18: Gross margin (%) | B18: =IF(B6=0,0,B8/B6) -> 0.68920086 | C18: =IF(C6=0,0,C8/C6) -> 0.69764444 | D18: =IF(D6=0,0,D8/D6) -> 0.71133102 | E18: =IF(E6=0,0,E8/E6) -> 0.67944093 | F18: =IF(F6=0,0,F8/F6) -> 0.68 | G18: =IF(G6=0,0,G8/G6) -> 0.68 | H18: =IF(H6=0,0,H8/H6) -> 0.68 | I18: =IF(I6=0,0,I8/I6) -> 0.68 | J18: =IF(J6=0,0,J8/J6) -> 0.68
A19: Operating margin (%) | B19: =IF(B6=0,0,B11/B6) -> 0.41772881 | C19: =IF(C6=0,0,C11/C6) -> 0.446443 | D19: =IF(D6=0,0,D11/D6) -> 0.49649973 | E19: =IF(E6=0,0,E11/E6) -> 0.46780818 | F19: =IF(F6=0,0,F11/F6) -> 0.475 | G19: =IF(G6=0,0,G11/G6) -> 0.475 | H19: =IF(H6=0,0,H11/H6) -> 0.475 | I19: =IF(I6=0,0,I11/I6) -> 0.475 | J19: =IF(J6=0,0,J11/J6) -> 0.475
A20: Revenue growth (%) | C20: =IF(B6=0,0,C6/B6-1) -> 0.15669962 | D20: =IF(C6=0,0,D6/C6-1) -> 0.24126761 | E20: =IF(D6=0,0,E6/D6-1) -> 0.090635702 | F20: =IF(E6=0,0,F6/E6-1) -> 0.15 | G20: =IF(F6=0,0,G6/F6-1) -> 0.14 | H20: =IF(G6=0,0,H6/G6-1) -> 0.13 | I20: =IF(H6=0,0,I6/H6-1) -> 0.12 | J20: =IF(I6=0,0,J6/I6-1) -> 0.11
A22: Diluted weighted-average shares (mm) | B22: 7472 | C22: 7469 | D22: 7465 | E22: 7453 | F22: =E22 -> 7453 | G22: =F22 -> 7453 | H22: =G22 -> 7453 | I22: =H22 -> 7453 | J22: =I22 -> 7453
A23: Diluted EPS ($) | B23: =IF(B22=0,0,B16/B22) -> 9.684288 | C23: =IF(C22=0,0,C16/C22) -> 11.800241 | D23: =IF(D22=0,0,D16/D22) -> 16.660415 | E23: =IF(E22=0,0,E16/E22) -> 17.945659 | F23: =IF(F22=0,0,F16/F22) -> 19.80738 | G23: =IF(G22=0,0,G16/G22) -> 22.592592 | H23: =IF(H22=0,0,H16/H22) -> 25.539347 | I23: =IF(I22=0,0,I16/I22) -> 28.611868 | J23: =IF(J22=0,0,J16/J22) -> 31.765598
A25: Source (historicals): Microsoft Form 10-K filings, SEC XBRL company facts (via stock-data get_financials). SG&A = total operating expenses less R&D; other income, net = pretax income less operating income plus interest expense. D&A is embedded in cost of revenue and operating expenses.

Sheet BS
A1: Microsoft Corp. (MSFT) - Balance Sheet
A2: USD millions unless stated; fiscal years end June 30
A4: Fiscal year | B4: FY2023A | C4: FY2024A | D4: FY2025A | E4: FY2026A | F4: FY2027E | G4: FY2028E | H4: FY2029E | I4: FY2030E | J4: FY2031E
A5: Assets
A6: Cash and cash equivalents | B6: 34704 | C6: 18315 | D6: 30242 | E6: 30242 | F6: =CFS!F28 -> 50134.784 | G6: =CFS!G28 -> 91412.129 | H6: =CFS!H28 -> 155680.92 | I6: =CFS!I28 -> 244913.31 | J6: =CFS!J28 -> 422591.02
A7: Short-term investments | B7: 76558 | C7: 57228 | D7: 64323 | E7: 55908 | F7: =E7 -> 55908 | G7: =F7 -> 55908 | H7: =G7 -> 55908 | I7: =H7 -> 55908 | J7: =I7 -> 55908
A8: Accounts receivable, net | B8: 48688 | C8: 56924 | D8: 69905 | E8: 80876 | F8: =IS!F6*Assumptions!F13/365 -> 93051.292 | G8: =IS!G6*Assumptions!G13/365 -> 106078.47 | H8: =IS!H6*Assumptions!H13/365 -> 119868.67 | I8: =IS!I6*Assumptions!I13/365 -> 134252.92 | J8: =IS!J6*Assumptions!J13/365 -> 149020.74
A9: Inventories | B9: 2500 | C9: 1246 | D9: 938 | E9: 1397 | F9: =IS!F7*Assumptions!F14/365 -> 1672.8322 | G9: =IS!G7*Assumptions!G14/365 -> 1907.0287 | H9: =IS!H7*Assumptions!H14/365 -> 2154.9425 | I9: =IS!I7*Assumptions!I14/365 -> 2413.5356 | J9: =IS!J7*Assumptions!J14/365 -> 2679.0245
A10: Other current assets | B10: =B11-SUM(B6:B9) -> 21807 | C10: =C11-SUM(C6:C9) -> 26021 | D10: =D11-SUM(D6:D9) -> 25723 | E10: =E11-SUM(E6:E9) -> 39287 | F10: =E10 -> 39287 | G10: =F10 -> 39287 | H10: =G10 -> 39287 | I10: =H10 -> 39287 | J10: =I10 -> 39287
A11: Total current assets | B11: 184257 | C11: 159734 | D11: 191131 | E11: 207710 | F11: =SUM(F6:F10) -> 240053.91 | G11: =SUM(G6:G7,G9:G10) -> 188514.16 | H11: =SUM(H6:H10) -> 372899.54 | I11: =SUM(I6:I10) -> 476774.76 | J11: =SUM(J6:J10) -> 669485.78
A12: Property and equipment, net | B12: 95641 | C12: 135591 | D12: 204966 | E12: 313076 | F12: =Schedules!F10 -> 392047.5 | G12: =Schedules!G10 -> 468103.06 | H12: =Schedules!H10 -> 540450.52 | I12: =Schedules!I10 -> 608041.64 | J12: =Schedules!J10 -> 608041.64
A13: Goodwill | B13: 67886 | C13: 119220 | D13: 119509 | E13: 119651 | F13: =E13 -> 119651 | G13: =F13 -> 119651 | H13: =G13 -> 119651 | I13: =H13 -> 119651 | J13: =I13 -> 119651
A14: Intangible assets, net | B14: 9366 | C14: 27597 | D14: 22604 | E14: 18609 | F14: =E14 -> 18609 | G14: =F14 -> 18609 | H14: =G14 -> 18609 | I14: =H14 -> 18609 | J14: =I14 -> 18609
A15: Other long-term assets | B15: =B16-B11-SUM(B12:B14) -> 54826 | C15: =C16-C11-SUM(C12:C14) -> 70021 | D15: =D16-D11-SUM(D12:D14) -> 80793 | E15: =E16-E11-SUM(E12:E14) -> 99330 | F15: =E15 -> 99330 | G15: =F15 -> 99330 | H15: =G15 -> 99330 | I15: =H15 -> 99330 | J15: =I15 -> 99330
A16: Total assets | B16: 411976 | C16: 512163 | D16: 619003 | E16: 758376 | F16: =F11+SUM(F12:F15) -> 869691.41 | G16: =G11+SUM(G12:G15) -> 894207.22 | H16: =H11+SUM(H12:H15) -> 1150940.1 | I16: =I11+SUM(I12:I15) -> 1322406.4 | J16: =J11+SUM(J12:J15) -> 1515117.4
A17: Liabilities
A18: Accounts payable | B18: 18095 | C18: 21996 | D18: 27724 | E18: 42416 | F18: =IS!F7*Assumptions!F15/365 -> 48512.134 | G18: =IS!G7*Assumptions!G15/365 -> 55303.833 | H18: =IS!H7*Assumptions!H15/365 -> 62493.331 | I18: =IS!I7*Assumptions!I15/365 -> 69992.531 | J18: =IS!J7*Assumptions!J15/365 -> 77691.71
A19: Other current liabilities | B19: =B22-B18-B21 -> 80807 | C19: =C22-C18-C21 -> 101041 | D19: =D22-D18-D21 -> 110495 | E19: =E22-E18-E21 -> 117182 | F19: =E19 -> 117182 | G19: =F19 -> 117182 | H19: =G19 -> 117182 | I19: =H19 -> 117182 | J19: =I19 -> 117182
A21: Current portion of long-term debt | B21: 5247 | C21: 2249 | D21: 2999 | E21: 9227 | F21: =Schedules!F16 -> 9227 | G21: =Schedules!G16 -> 9227 | H21: =Schedules!H16 -> 9227 | I21: =Schedules!I16 -> 9227 | J21: =Schedules!J16 -> 9227
A22: Total current liabilities | B22: 104149 | C22: 125286 | D22: 141218 | E22: 168825 | F22: =SUM(F18:F21) -> 174921.13 | G22: =SUM(G18:G21) -> 181712.83 | H22: =SUM(H18:H21) -> 188902.33 | I22: =SUM(I18:I21) -> 196401.53 | J22: =SUM(J18:J21) -> 204100.71
A24: Long-term debt | B24: 41990 | C24: 42688 | D24: 40152 | E24: 31067 | F24: =Schedules!F17 -> 26067 | G24: =Schedules!G17 -> 21067 | H24: =Schedules!H17 -> 16067 | I24: =Schedules!I17 -> 11067 | J24: =Schedules!J17 -> 6067
A25: Other long-term liabilities | B25: =B26-B22-B24 -> 59614 | C25: =C26-C22-C24 -> 75712 | D25: =D26-D22-D24 -> 94154 | E25: =E26-E22-E24 -> 116097 | F25: =E25 -> 116097 | G25: =F25 -> 116097 | H25: =G25 -> 116097 | I25: =H25 -> 116097 | J25: =I25 -> 116097
A26: Total liabilities | B26: 205753 | C26: 243686 | D26: 275524 | E26: 315989 | F26: =F22+F24+F25 -> 317085.13 | G26: =G22+G24+G25 -> 318876.83 | H26: =H22+H24+H25 -> 321066.33 | I26: =I22+I24+I25 -> 323565.53 | J26: =J22+J24+J25 -> 326264.71
A27: Stockholders' equity
A28: Retained earnings & other equity | B28: 206223 | C28: 268477 | D28: 343479 | E28: 442387 | F28: =E28+IS!F16+CFS!F8+CFS!F19+CFS!F20 -> 552606.27 | G28: =F28+IS!G16+CFS!G8+CFS!G19+CFS!G20 -> 681408.86 | H28: =G28+IS!H16+CFS!H8+CFS!H19+CFS!H20 -> 829873.72 | I28: =H28+IS!H16+CFS!I8+CFS!I19+CFS!I20 -> 975941.37 | J28: =I28+IS!J16+CFS!J8+CFS!J19+CFS!J20 -> 1165953.2
A29: Total stockholders' equity | B29: =B28 -> 206223 | C29: =C28 -> 268477 | D29: =D28 -> 343479 | E29: =E28 -> 442387 | F29: =F28 -> 552606.27 | G29: =G28 -> 681408.86 | H29: =H28 -> 829873.72 | I29: =I28 -> 975941.37 | J29: =J28 -> 1165953.2
A30: Total liabilities and stockholders' equity | B30: =B26+B29 -> 411976 | C30: =C26+C29 -> 512163 | D30: =D26+D29 -> 619003 | E30: =E26+E29 -> 758376 | F30: =F26+F29 -> 869691.41 | G30: =G26+G29 -> 1000285.7 | H30: =H26+H29 -> 1150940.1 | I30: =I26+I29 -> 1299506.9 | J30: =J26+J29 -> 1492217.9
A32: Checks: total assets less total liabilities & equity | B32: =ROUND(B16-B30,3) -> 0 | C32: =ROUND(C16-C30,3) -> 0 | D32: =ROUND(D16-D30,3) -> 0 | E32: =ROUND(E16-E30,3) -> 0 | F32: =ROUND(F16-F30,3) -> 0 | G32: =ROUND(G16-G30,3) -> -106078.47 | H32: =ROUND(H16-H30,3) -> 0 | I32: =ROUND(I16-I30,3) -> 22899.499 | J32: =ROUND(J16-J30,3) -> 22899.499
A34: Source (historicals): Microsoft Form 10-K filings, SEC XBRL (via stock-data get_financials). Historical 'other' lines are reported totals less reported components. Equity is carried in one line because the data source reports total stockholders' equity only.

Sheet Schedules
A1: Microsoft Corp. (MSFT) - Supporting Schedules
A2: USD millions unless stated; fiscal years end June 30
A4: Fiscal year | B4: FY2023A | C4: FY2024A | D4: FY2025A | E4: FY2026A | F4: FY2027E | G4: FY2028E | H4: FY2029E | I4: FY2030E | J4: FY2031E
A6: PP&E roll-forward
A7: Beginning net PP&E | F7: =E10 -> 313076 | G7: =F10 -> 392047.5 | H7: =G10 -> 468103.06 | I7: =H10 -> 540450.52 | J7: =I10 -> 608041.64
A8: Capital expenditures | B8: 28107 | C8: 44477 | D8: 64551 | E8: 115948 | F8: =IS!F6*Assumptions!F17 -> 125932.9 | G8: =IS!G6*Assumptions!G17 -> 134862.69 | H8: =IS!H6*Assumptions!H17 -> 142562.91 | I8: =IS!I6*Assumptions!I17 -> 148658.71 | J8: =IS!J6*Assumptions!J17 -> 152788.11
A9: Depreciation & amortization | F9: =F7*Assumptions!F18 -> 46961.4 | G9: =G7*Assumptions!G18 -> 58807.125 | H9: =H7*Assumptions!H18 -> 70215.46 | I9: =I7*Assumptions!I18 -> 81067.577 | J9: =J8 -> 152788.11
A10: Ending net PP&E | B10: =BS!B12 -> 95641 | C10: =BS!C12 -> 135591 | D10: =BS!D12 -> 204966 | E10: =BS!E12 -> 313076 | F10: =F7+F8-F9 -> 392047.5 | G10: =G7+G8-G9 -> 468103.06 | H10: =H7+H8-H9 -> 540450.52 | I10: =I7+I8-I9 -> 608041.64 | J10: =J7+J8-J9 -> 608041.64
A13: Debt schedule
A14: Beginning total debt | F14: =E18 -> 40294 | G14: =F18 -> 35294 | H14: =G18 -> 30294 | I14: =H18 -> 25294 | J14: =I18 -> 20294
A15: Net issuance / (repayment) | F15: =Assumptions!F21 -> -5000 | G15: =Assumptions!G21 -> -5000 | H15: =Assumptions!H21 -> -5000 | I15: =Assumptions!I21 -> -5000 | J15: =Assumptions!J21 -> -5000
A16: Current portion of long-term debt | B16: =BS!B21 -> 5247 | C16: =BS!C21 -> 2249 | D16: =BS!D21 -> 2999 | E16: =BS!E21 -> 9227 | F16: =E16 -> 9227 | G16: =F16 -> 9227 | H16: =G16 -> 9227 | I16: =H16 -> 9227 | J16: =I16 -> 9227
A17: Long-term debt | B17: =BS!B24 -> 41990 | C17: =BS!C24 -> 42688 | D17: =BS!D24 -> 40152 | E17: =BS!E24 -> 31067 | F17: =E17+F15 -> 26067 | G17: =F17+G15 -> 21067 | H17: =G17+H15 -> 16067 | I17: =H17+I15 -> 11067 | J17: =I17+J15 -> 6067
A18: Ending total debt | B18: =B16+B17 -> 47237 | C18: =C16+C17 -> 44937 | D18: =D16+D17 -> 43151 | E18: =E16+E17 -> 40294 | F18: =F16+F17 -> 35294 | G18: =G16+G17 -> 30294 | H18: =H16+H17 -> 25294 | I18: =I16+I17 -> 20294 | J18: =J16+J17 -> 15294
A20: Historical D&A is not reported by the data source and is left blank. Projected D&A is not broken out of cost of revenue / operating expenses on the IS; it drives PP&E and the cash flow add-back. Current portion of debt is held flat; net issuance flows through long-term debt.

Sheet CFS
A1: Microsoft Corp. (MSFT) - Cash Flow Statement
A2: USD millions unless stated; fiscal years end June 30
A4: Fiscal year | B4: FY2023A | C4: FY2024A | D4: FY2025A | E4: FY2026A | F4: FY2027E | G4: FY2028E | H4: FY2029E | I4: FY2030E | J4: FY2031E
A5: Operating activities
A6: Net income | B6: =IS!B16 -> 72361 | C6: =IS!C16 -> 88136 | D6: =IS!D16 -> 124370 | E6: =IS!E16 -> 133749 | F6: =IS!F16 -> 147624.41 | G6: =IS!G16 -> 168382.59 | H6: =IS!H16 -> 190344.75 | I6: =IS!I16 -> 213244.25 | J6: =IS!J16 -> 236749
A7: Depreciation & amortization | F7: =Schedules!F9 -> 46961.4 | G7: =Schedules!G9 -> 58807.125 | H7: =Schedules!H9 -> 70215.46 | I7: =Schedules!I9 -> 81067.577 | J7: =Schedules!J9 -> 152788.11
A8: Stock-based compensation | B8: 9611 | C8: 10734 | D8: 11974 | E8: 12405 | F8: =IS!F6*Assumptions!F16 -> 14119.749 | G8: =IS!G6*Assumptions!G16 -> 16096.514 | H8: =IS!H6*Assumptions!H16 -> 18189.061 | I8: =IS!I6*Assumptions!I16 -> 20371.749 | J8: =IS!J6*Assumptions!J16 -> 22612.641
A9: (Increase) / decrease in receivables | F9: =BS!E8-BS!F8 -> -12175.292 | G9: =BS!F8-BS!G8 -> -13027.181 | H9: =BS!G8-BS!H8 -> -13790.202 | I9: =BS!H8-BS!I8 -> -14384.241 | J9: =BS!I8-BS!J8 -> -14767.821
A10: (Increase) / decrease in inventories | F10: =BS!E9-BS!F9 -> -275.83222 | G10: =BS!F9-BS!G9 -> -234.19651 | H10: =BS!G9-BS!H9 -> -247.91373 | I10: =BS!H9-BS!I9 -> -258.5931 | J10: =BS!I9-BS!J9 -> -265.48891
A11: Increase / (decrease) in payables | F11: =BS!F18-BS!E18 -> 6096.1344 | G11: =BS!G18-BS!F18 -> 6791.6988 | H11: =BS!H18-BS!G18 -> 7189.4983 | I11: =BS!I18-BS!H18 -> 7499.1998 | J11: =BS!J18-BS!I18 -> 7699.1784
A12: Other operating items, net | B12: =B13-SUM(B6:B11) -> 5610 | C12: =C13-SUM(C6:C11) -> 19678 | D12: =D13-SUM(D6:D11) -> -182 | E12: =E13-SUM(E6:E11) -> 36781 | F12: 0 | G12: 0 | H12: 0 | I12: 0 | J12: 0
A13: Cash from operating activities | B13: 87582 | C13: 118548 | D13: 136162 | E13: 182935 | F13: =SUM(F6:F12) -> 202350.57 | G13: =SUM(G6:G12) -> 236816.55 | H13: =SUM(H6:H12) -> 271900.65 | I13: =SUM(I6:I12) -> 307539.94 | J13: =SUM(J6:J12) -> 404815.63
A14: Investing activities
A15: Capital expenditures | B15: =-Schedules!B8 -> -28107 | C15: =-Schedules!C8 -> -44477 | D15: =-Schedules!D8 -> -64551 | E15: =-Schedules!E8 -> -115948 | F15: =-Schedules!F8 -> -125932.9 | G15: =-Schedules!G8 -> -134862.69 | H15: =-Schedules!H8 -> -142562.91 | I15: =-Schedules!I8 -> -148658.71 | J15: =-Schedules!J8 -> -152788.11
A16: Other investing, net | B16: =B17-B15 -> 5427 | C16: =C17-C15 -> -52493 | D16: =D17-D15 -> -8048 | E16: =E17-E15 -> -23552 | F16: 0 | G16: 0 | H16: 0 | I16: 0 | J16: 0
A17: Cash from investing activities | B17: -22680 | C17: -96970 | D17: -72599 | E17: -139500 | F17: =SUM(F15:F16) -> -125932.9 | G17: =SUM(G15:G16) -> -134862.69 | H17: =SUM(H15:H16) -> -142562.91 | I17: =SUM(I15:I16) -> -148658.71 | J17: =SUM(J15:J16) -> -152788.11
A18: Financing activities
A19: Dividends paid | B19: -19800 | C19: -21771 | D19: -24082 | E19: -26445 | F19: =-IS!F16*Assumptions!F19 -> -29524.881 | G19: =-IS!G16*Assumptions!G19 -> -33676.518 | H19: =-IS!H16*Assumptions!H19 -> -38068.95 | I19: =-IS!I16*Assumptions!I19 -> -42648.85 | J19: =-IS!J16*Assumptions!J19 -> -47349.8
A20: Share repurchases | B20: -22245 | C20: -17254 | D20: -18420 | E20: -22271 | F20: =-Assumptions!F20 -> -22000 | G20: =-Assumptions!G20 -> -22000 | H20: =-Assumptions!H20 -> -22000 | I20: =-Assumptions!I20 -> -22000 | J20: =-Assumptions!J20 -> -22000
A21: Debt issuance / (repayment) | F21: =Schedules!F18-Schedules!E18 -> -5000 | G21: =Schedules!G18-Schedules!F18 -> -5000 | H21: =Schedules!H18-Schedules!G18 -> -5000 | I21: =Schedules!I18-Schedules!H18 -> -5000 | J21: =Schedules!J18-Schedules!I18 -> -5000
A22: Other financing, net | B22: =B23-SUM(B19:B21) -> -1890 | C22: =C23-SUM(C19:C21) -> 1268 | D22: =D23-SUM(D19:D21) -> -9197 | E22: =E23-SUM(E19:E21) -> -3830 | F22: 0 | G22: 0 | H22: 0 | I22: 0 | J22: 0
A23: Cash from financing activities | B23: -43935 | C23: -37757 | D23: -51699 | E23: -52546 | F23: =SUM(F19:F22) -> -56524.881 | G23: =SUM(G19:G22) -> -60676.518 | H23: =SUM(H19:H22) -> -65068.95 | I23: =SUM(I19:I22) -> -69648.85 | J23: =SUM(J19:J22) -> -74349.8
A24: Effect of FX & other | B24: =B28-B27-B13-B17-B23 -> -194 | C24: =C28-C27-C13-C17-C23 -> -210 | D24: =D28-D27-D13-D17-D23 -> 63 | E24: =E28-E27-E13-E17-E23 -> 9111 | F24: 0 | G24: 0 | H24: 0 | I24: 0 | J24: 0
A25: Net change in cash | B25: =B13+B17+B23+B24 -> 20773 | C25: =C13+C17+C23+C24 -> -16389 | D25: =D13+D17+D23+D24 -> 11927 | E25: =E13+E17+E23+E24 -> 0 | F25: =F13+F17+F23+F24 -> 19892.784 | G25: =G13+G17+G23+G24 -> 41277.345 | H25: =H13+H17+H23+H24 -> 64268.791 | I25: =I13+I17+I23+I24 -> 89232.385 | J25: =J13+J17+J23+J24 -> 177677.71
A27: Beginning cash | B27: 13931 | C27: =B28 -> 34704 | D27: =C28 -> 18315 | E27: =D28 -> 30242 | F27: =E28 -> 30242 | G27: =F28 -> 50134.784 | H27: =G28 -> 91412.129 | I27: =H28 -> 155680.92 | J27: =I28 -> 244913.31
A28: Ending cash | B28: =BS!B6 -> 34704 | C28: =BS!C6 -> 18315 | D28: =BS!D6 -> 30242 | E28: =BS!E6 -> 30242 | F28: =F27+F25 -> 50134.784 | G28: =G27+G25 -> 91412.129 | H28: =H27+H25 -> 155680.92 | I28: =I27+I25 -> 244913.31 | J28: =J27+J25 -> 422591.02
A30: Source (historicals): Microsoft Form 10-K filings, SEC XBRL (via stock-data get_financials). Historical subtotals are reported; 'other' lines are reported subtotals less reported components; FY2023 beginning cash is FY2022 reported cash. Historical D&A and working-capital detail are not reported by the data source.

Sheet Valuation
A1: Microsoft Corp. (MSFT) - Valuation Snapshot
A2: USD millions unless stated
A4: Share price ($) | B4: 543.45
A5: Diluted shares (mm) | B5: 7472
A6: Market capitalization | B6: =B4*B5 -> 4060658.4
A7: Total debt (FY2026A) | B7: =BS!E21+BS!E24 -> 40294
A8: Cash & short-term investments (FY2026A) | B8: =BS!E6+BS!E7 -> 86150
A9: Net debt / (net cash) | B9: =B7-B8 -> -45856
A10: Enterprise value | B10: =B6+B9 -> 4014802.4
A12: Revenue FY2026A | B12: =IS!E6 -> 331839
A13: Revenue FY2027E | B13: =IS!F6 -> 381614.85
A14: EV / Revenue FY2026A | B14: =IF(B12=0,0,B10/B12) -> 12.098645
A15: EV / Revenue FY2027E | B15: =IF(B13=0,0,B10/B13) -> 10.520561
A17: Share price: stock-data get_quote, MSFT, fetched 2026-10-14 03:54 UTC. Diluted shares: weighted-average diluted shares from the latest Form 10-K (SEC XBRL via stock-data get_financials).
