Workbook

Sheet Cover
A1: Three-Statement Financial Model
A3: Company name | B3: Microsoft Corporation
A4: Ticker | B4: MSFT
A5: Fiscal year end | B5: June 30
A6: Currency / units | B6: USD millions (per-share values in USD)
A7: Model date | B7: 2026-10-14
A8: Prepared by | B8: Claude (financial-analysis:3-statement-model)
A9: Data sources | B9: Form 10-K FY2026 (filed 2026-07-29), 10-K FY2025 (filed 2025-07-30), 10-K FY2024 (filed 2024-07-30) via SEC EDGAR XBRL R-pages; stock-data get_financials cross-check
A11: Legend
A12: Blue font: hard-coded inputs (historicals and assumptions)
A13: Black font: formulas
A14: Green font: links to other sheets
A15: Columns: FY2023A to FY2026A = historical actuals (FYE June 30); FY2027E to FY2031E = projections
A16: Tabs: Assumptions, IS, BS, CFS, Schedules, Checks
A18: Mapping notes
A19: IS: D&A (depreciation + intangible amortization per 10-K notes) is shown on its own line and removed from cost of revenue, so EBIT = reported operating income.
A20: IS: SG&A = Sales and marketing + General and administrative. Other income/(expense) is split into interest income, interest expense and the residual.
A21: BS: Other current assets as reported; Other long-term assets = operating lease ROU + equity & other investments + other long-term assets.
A22: BS: Accrued & other current liabilities = accrued compensation + short-term income taxes + short-term unearned revenue + other current liabilities.
A23: BS: Deferred taxes & other LT liabilities = LT income taxes + LT unearned revenue + deferred income taxes + operating lease liabilities + other LT liabilities.
... A26: CFS FY2024A-FY2026A use the FY2026 10-K presentation; FY2023A uses the FY2025 10-K presentation (the FY2026 10-K reclassified equity-method losses within operating adjustments; CFO total unaffected).

Sheet Assumptions
A1: Assumptions
A2: Units: USD millions unless stated. Historical columns show implied ratios (formulas); projection columns are inputs (blue).
A4: Fiscal year | B4: FY2023A | C4: FY2024A | D4: FY2025A | E4: FY2026A | F4: FY2027E | G4: FY2028E | H4: FY2029E | I4: FY2030E | J4: FY2031E
A6: Income statement
A7: Revenue growth (%) | C7: =IS!C6/IS!B6-1 -> 0.15669962 | D7: =IS!D6/IS!C6-1 -> 0.14932156 | E7: =IS!E6/IS!D6-1 -> 0.17788687 | F7: 0.16 | G7: 0.14 | H7: 0.12 | I7: 0.11 | J7: 0.1
A8: Cost of revenue (% of revenue) | B8: =IS!B7/IS!B6 -> 0.24709435 | C8: =IS!C7/IS!C6 -> 0.22076354 | D8: =IS!D7/IS!D6 -> 0.21237452 | E8: =IS!E7/IS!E6 -> 0.20303219 | F8: 0.205 | G8: 0.205 | H8: 0.205 | I8: 0.205 | J8: 0.205
A9: SG&A (% of revenue) | B9: =IS!B9/IS!B6 -> 0.1431423 | C9: =IS!C9/IS!C6 -> 0.13081241 | D9: =IS!D9/IS!D6 -> 0.11669932 | E9: =IS!E9/IS!E6 -> 0.10446632 | F9: 0.102 | G9: 0.1 | H9: 0.098 | I9: 0.097 | J9: 0.096
A10: R&D (% of revenue) | B10: =IS!B10/IS!B6 -> 0.12832975 | C10: =IS!C10/IS!C6 -> 0.12038903 | D10: =IS!D10/IS!D6 -> 0.11531854 | E10: =IS!E10/IS!E6 -> 0.10716643 | F10: 0.105 | G10: 0.105 | H10: 0.105 | I10: 0.105 | J10: 0.105
A11: Other operating expense (% of revenue) | B11: =IS!B11/IS!B6 -> 0 | C11: =IS!C11/IS!C6 -> 0 | D11: =IS!D11/IS!D6 -> 0 | E11: =IS!E11/IS!E6 -> 0 | F11: 0 | G11: 0 | H11: 0 | I11: 0 | J11: 0
A12: Interest rate on debt (%) | C12: =IS!C15/AVERAGE(BS!B22+BS!B24,BS!C22+BS!C24) -> 0.059372693 | D12: =IS!D15/AVERAGE(BS!C22+BS!C24,BS!D22+BS!D24) -> 0.050326542 | E12: =IS!E15/AVERAGE(BS!D22+BS!D24,BS!E22+BS!E24) -> 0.073126011 | F12: 0.07 | G12: 0.07 | H12: 0.07 | I12: 0.07 | J12: 0.07
A13: Interest income rate on cash (%) | C13: =IS!C16/(BS!B7+BS!B8) -> 0.028374467 | D13: =IS!D16/(BS!C7+BS!C8) -> 0.035039646 | E13: =IS!E16/(BS!D7+BS!D8) -> 0.034907207 | F13: 0.035 | G13: 0.035 | H13: 0.035 | I13: 0.035 | J13: 0.035
A14: Effective tax rate (%) | B14: =IS!B19/IS!B18 -> 0.18978625 | C14: =IS!C19/IS!C18 -> 0.18231327 | D14: =IS!D19/IS!D18 -> 0.17629644 | E14: =IS!E19/IS!E18 -> 0.19396266 | F14: 0.19 | G14: 0.19 | H14: 0.19 | I14: 0.19 | J14: 0.19
A15: Diluted shares outstanding | B15: =IS!B24 -> 7472 | C15: =IS!C24 -> 7469 | D15: =IS!D24 -> 7465 | E15: =IS!E24 -> 7453 | F15: 7440 | G15: 7425 | H15: 7410 | I15: 7395 | J15: 7380
A17: Working capital
A18: Days sales outstanding (DSO) | B18: =BS!B9/IS!B6*365 -> 83.859661 | C18: =BS!C9/IS!C6*365 -> 84.762934 | D18: =BS!D9/IS!D6*365 -> 90.568517 | E18: =BS!E9/IS!E6*365 -> 88.958019 | F18: 89 | G18: 89 | H18: 89 | I18: 89 | J18: 89
A19: Days inventory outstanding (DIO) | B19: =BS!B10/IS!B7*365 -> 17.426427 | C19: =BS!C10/IS!C7*365 -> 8.4042946 | D19: =BS!D10/IS!D7*365 -> 5.7222844 | E19: =BS!E10/IS!E7*365 -> 7.5682756 | F19: 7.5 | G19: 7.5 | H19: 7.5 | I19: 7.5 | J19: 7.5
A20: Days payable outstanding (DPO) | B20: =BS!B20/IS!B7*365 -> 126.13248 | C20: =BS!C20/IS!C7*365 -> 148.36345 | D20: =BS!D20/IS!D7*365 -> 169.13072 | E20: =BS!E20/IS!E7*365 -> 229.78953 | F20: 220 | G20: 210 | H20: 200 | I20: 190 | J20: 180
A21: Other current assets (% of revenue) | B21: =BS!B11/IS!B6 -> 0.10290447 | C21: =BS!C11/IS!C6 -> 0.1061553 | D21: =BS!D11/IS!D6 -> 0.091305675 | E21: =BS!E11/IS!E6 -> 0.14643848 | F21: 0.146 | G21: 0.146 | H21: 0.146 | I21: 0.146 | J21: 0.146
A22: Accrued & other current liabilities (% of revenue) | B22: =BS!B21/IS!B6 -> 0.38131798 | C22: =BS!C21/IS!C6 -> 0.38490221 | D22: =BS!D21/IS!D6 -> 0.39221011 | E22: =BS!E21/IS!E6 -> 0.35312908 | F22: 0.353 | G22: 0.353 | H22: 0.353 | I22: 0.353 | J22: 0.353
A24: Capex and D&A
A25: Capital expenditures (% of revenue) | B25: =-CFS!B20/IS!B6 -> 0.13263337 | C25: =-CFS!C20/IS!C6 -> 0.18144842 | D25: =-CFS!D20/IS!D6 -> 0.22912851 | E25: =-CFS!E20/IS!E6 -> 0.34941041 | F25: 0.35 | G25: 0.33 | H25: 0.3 | I25: 0.28 | J25: 0.26
A26: Depreciation (% of beginning PP&E) | C26: =Schedules!C9/Schedules!C7 -> 0.15892766 | D26: =Schedules!D9/Schedules!D7 -> 0.16225266 | E26: =Schedules!E9/Schedules!E7 -> 0.16734483 | F26: 0.17 | G26: 0.17 | H26: 0.17 | I26: 0.17 | J26: 0.17
A27: Amortization of intangibles | B27: =Schedules!B12 -> 2500 | C27: =Schedules!C12 -> 4800 | D27: =Schedules!D12 -> 6000 | E27: =Schedules!E12 -> 4700 | F27: 3097 | G27: 2141 | H27: 1944 | I27: 1477 | J27: 1128
A29: Financing and capital return
A30: Debt issuance / (repayment) | B30: =CFS!B27+CFS!B28 -> -2750 | C30: =CFS!C27+CFS!C28 -> 575 | D30: =CFS!D27+CFS!D28 -> -8962 | E30: =CFS!E27+CFS!E28 -> -3000 | F30: -9227 | G30: 0 | H30: -2001 | I30: 0 | J30: -500
A31: Dividend payout ratio (%) | B31: =-CFS!B29/IS!B20 -> 0.27362806 | C31: =-CFS!C29/IS!C20 -> 0.24701598 | D31: =-CFS!D29/IS!D20 -> 0.23648755 | E31: =-CFS!E29/IS!E20 -> 0.1977211 | F31: 0.2 | G31: 0.2 | H31: 0.2 | I31: 0.2 | J31: 0.2
A32: Share repurchases | B32: =-CFS!B30 -> 22245 | C32: =-CFS!C30 -> 17254 | D32: =-CFS!D30 -> 18420 | E32: =-CFS!E30 -> 22271 | F32: 24000 | G32: 25000 | H32: 26000 | I32: 27000 | J32: 28000
A33: Minimum cash balance | F33: 15000 | G33: 15000 | H33: 15000 | I33: 15000 | J33: 15000
A35: Other assumptions
A36: Stock-based compensation (% of revenue) | B36: =CFS!B9/IS!B6 -> 0.04535309 | C36: =CFS!C9/IS!C6 -> 0.043790439 | D36: =CFS!D9/IS!D6 -> 0.042502591 | E36: =CFS!E9/IS!E6 -> 0.037382586 | F36: 0.037 | G36: 0.037 | H36: 0.037 | I36: 0.037 | J36: 0.037
A37: Proceeds from stock issuance | B37: =CFS!B31 -> 1866 | C37: =CFS!C31 -> 2002 | D37: =CFS!D31 -> 2056 | E37: =CFS!E31 -> 2009 | F37: 2000 | G37: 2000 | H37: 2000 | I37: 2000 | J37: 2000
A38: Other income / (expense), net excl. interest | B38: =IS!B17 -> -238 | C38: =IS!C17 -> -1868 | D38: =IS!D17 -> -5163 | E38: =IS!E17 -> 10447 | F38: 0 | G38: 0 | H38: 0 | I38: 0 | J38: 0
A39: Current portion of debt at year end (next-year maturities) | B39: =BS!B22 -> 5247 | C39: =BS!C22 -> 8942 | D39: =BS!D22 -> 2999 | E39: =BS!E22 -> 9227 | F39: 0 | G39: 2001 | H39: 0 | I39: 500 | J39: 0

Sheet IS
A1: Income Statement
A2: Units: USD millions unless stated (per-share in USD; shares in millions)
A4: Fiscal year | B4: FY2023A | C4: FY2024A | D4: FY2025A | E4: FY2026A | F4: FY2027E | G4: FY2028E | H4: FY2029E | I4: FY2030E | J4: FY2031E
A6: Revenue | B6: 211915 | C6: 245122 | D6: 281724 | E6: 331839 | F6: =E6*(1+Assumptions!F7) -> 384933.24 | G6: =F6*(1+Assumptions!G7) -> 438823.89 | H6: =G6*(1+Assumptions!H7) -> 491482.76 | I6: =H6*(1+Assumptions!I7) -> 545545.86 | J6: =I6*(1+Assumptions!J7) -> 600100.45
A7: Cost of revenue | B7: =IS!B38-Schedules!B14 -> 52363 | C7: =IS!C38-Schedules!C14 -> 54114 | D7: =IS!D38-Schedules!D14 -> 59831 | E7: =IS!E38-Schedules!E14 -> 67374 | F7: =F6*Assumptions!F8 -> 78911.314 | G7: =G6*Assumptions!G8 -> 89958.898 | H7: =H6*Assumptions!H8 -> 100753.97 | I7: =I6*Assumptions!I8 -> 111836.9 | J7: =J6*Assumptions!J8 -> 123020.59
A8: Gross profit | B8: =B6-B7 -> 159552 | C8: =C6-C7 -> 191008 | D8: =D6-D7 -> 221893 | E8: =E6-E7 -> 264465 | F8: =F6-F7 -> 306021.93 | G8: =G6-G7 -> 348865 | H8: =H6-H7 -> 390728.79 | I8: =I6-I7 -> 433708.96 | J8: =J6-J7 -> 477079.86
A9: Selling, general & administrative | B9: 30334 | C9: 32065 | D9: 32877 | E9: 34666 | F9: =F6*Assumptions!F9 -> 39263.19 | G9: =G6*Assumptions!G9 -> 43882.389 | H9: =H6*Assumptions!H9 -> 48165.311 | I9: =I6*Assumptions!I9 -> 52917.949 | J9: =J6*Assumptions!J9 -> 57609.643
A10: Research & development | B10: 27195 | C10: 29510 | D10: 32488 | E10: 35562 | F10: =F6*Assumptions!F10 -> 40417.99 | G10: =G6*Assumptions!G10 -> 46076.509 | H10: =H6*Assumptions!H10 -> 51605.69 | I10: =I6*Assumptions!I10 -> 57282.316 | J10: =J6*Assumptions!J10 -> 63010.547
A11: Other operating expenses | B11: 0 | C11: 0 | D11: 0 | E11: 0 | F11: =F6*Assumptions!F11 -> 0 | G11: =G6*Assumptions!G11 -> 0 | H11: =H6*Assumptions!H11 -> 0 | I11: =I6*Assumptions!I11 -> 0 | J11: =J6*Assumptions!J11 -> 0
A12: EBITDA | B12: =B8-B9-B10-B11 -> 102023 | C12: =C8-C9-C10-C11 -> 129433 | D12: =D8-D9-D10-D11 -> 156528 | E12: =E8-E9-E10-E11 -> 194237 | F12: =F8-F9-F10-F11 -> 226340.75 | G12: =G8-G9-G10-G11 -> 258906.1 | H12: =H8-H9-H10-H11 -> 290957.79 | I12: =I8-I9-I10-I11 -> 323508.7 | J12: =J8-J9-J10-J11 -> 356459.67
A13: Depreciation & amortization | B13: =Schedules!B14 -> 13500 | C13: =Schedules!C14 -> 20000 | D13: =Schedules!D14 -> 28000 | E13: =Schedules!E14 -> 39000 | F13: =Schedules!F14 -> 56319.92 | G13: =Schedules!G14 -> 69219.551 | H13: =Schedules!H14 -> 82237.218 | I13: =Schedules!I14 -> 93185.992 | J13: =Schedules!J14 -> 103214.45
A14: Operating income (EBIT) | B14: =B12-B13 -> 88523 | C14: =C12-C13 -> 109433 | D14: =D12-D13 -> 128528 | E14: =E12-E13 -> 155237 | F14: =F12-F13 -> 170020.83 | G14: =G12-G13 -> 189686.55 | H14: =H12-H13 -> 208720.58 | I14: =I12-I13 -> 230322.71 | J14: =J12-J13 -> 253245.22
A15: Interest expense | B15: 1968 | C15: 2935 | D15: 2385 | E15: 3051 | F15: =Schedules!F35 -> 2497.635 | G15: =Schedules!G35 -> 2174.69 | H15: =Schedules!H35 -> 2104.655 | I15: =Schedules!I35 -> 2034.62 | J15: =Schedules!J35 -> 2017.12
A16: Interest income | B16: 2994 | C16: 3157 | D16: 2647 | E16: 3301 | F16: =Schedules!F38 -> 2689.505 | G16: =Schedules!G38 -> 3317.3318 | H16: =Schedules!H38 -> 4832.2562 | I16: =Schedules!I38 -> 7117.1825 | J16: =Schedules!J38 -> 10230.453
A17: Other income / (expense), net | B17: -238 | C17: -1868 | D17: -5163 | E17: 10447 | F17: =Assumptions!F38 -> 0 | G17: =Assumptions!G38 -> 0 | H17: =Assumptions!H38 -> 0 | I17: =Assumptions!I38 -> 0 | J17: =Assumptions!J38 -> 0
A18: Pre-tax income | B18: =B14-B15+B16+B17 -> 89311 | C18: =C14-C15+C16+C17 -> 107787 | D18: =D14-D15+D16+D17 -> 123627 | E18: =E14-E15+E16+E17 -> 165934 | F18: =F14-F15+F16+F17 -> 170212.7 | G18: =G14-G15+G16+G17 -> 190829.19 | H18: =H14-H15+H16+H17 -> 211448.18 | I18: =I14-I15+I16+I17 -> 235405.27 | J18: =J14-J15+J16+J17 -> 261458.56
A19: Income tax expense | B19: 16950 | C19: 19651 | D19: 21795 | E19: 32185 | F19: =F18*Assumptions!F14 -> 32340.412 | G19: =G18*Assumptions!G14 -> 36257.546 | H19: =H18*Assumptions!H14 -> 40175.154 | I19: =I18*Assumptions!I14 -> 44727.001 | J19: =J18*Assumptions!J14 -> 49677.125
A20: Net income | B20: =B18-B19 -> 72361 | C20: =C18-C19 -> 88136 | D20: =D18-D19 -> 101832 | E20: =E18-E19 -> 133749 | F20: =F18-F19 -> 137872.28 | G20: =G18-G19 -> 154571.64 | H20: =H18-H19 -> 171273.02 | I20: =I18-I19 -> 190678.27 | J20: =J18-J19 -> 211781.43
A22: Per share
A23: Basic shares outstanding | B23: 7446 | C23: 7431 | D23: 7433 | E23: 7429 | F23: =F24-(E24-E23) -> 7416 | G23: =G24-(F24-F23) -> 7401 | H23: =H24-(G24-G23) -> 7386 | I23: =I24-(H24-H23) -> 7371 | J23: =J24-(I24-I23) -> 7356
A24: Diluted shares outstanding | B24: 7472 | C24: 7469 | D24: 7465 | E24: 7453 | F24: =Assumptions!F15 -> 7440 | G24: =Assumptions!G15 -> 7425 | H24: =Assumptions!H15 -> 7410 | I24: =Assumptions!I15 -> 7395 | J24: =Assumptions!J15 -> 7380
A25: Basic EPS | B25: =B20/B23 -> 9.7181037 | C25: =C20/C23 -> 11.860584 | D25: =D20/D23 -> 13.699987 | E25: =E20/E23 -> 18.003634 | F25: =F20/F23 -> 18.591192 | G25: =G20/G23 -> 20.885237 | H25: =H20/H23 -> 23.188874 | I25: =I20/I23 -> 25.868711 | J25: =J20/J23 -> 28.790298
A26: Diluted EPS | B26: =B20/B24 -> 9.684288 | C26: =C20/C24 -> 11.800241 | D26: =D20/D24 -> 13.641259 | E26: =E20/E24 -> 17.945659 | F26: =F20/F24 -> 18.531221 | G26: =G20/G24 -> 20.81773 | H26: =H20/H24 -> 23.113768 | I26: =I20/I24 -> 25.784756 | J26: =J20/J24 -> 28.696671
A27: Dividends per share | B27: 2.72 | C27: 3 | D27: 3.32 | E27: 3.64 | F27: =-CFS!F29/F23 -> 3.7182385 | G27: =-CFS!G29/G23 -> 4.1770475 | H27: =-CFS!H29/H23 -> 4.6377748 | I27: =-CFS!I29/I23 -> 5.1737422 | J27: =-CFS!J29/J23 -> 5.7580595
A29: Margins and growth
A30: Revenue growth (%) | C30: =C6/B6-1 -> 0.15669962 | D30: =D6/C6-1 -> 0.14932156 | E30: =E6/D6-1 -> 0.17788687 | F30: =F6/E6-1 -> 0.16 | G30: =G6/F6-1 -> 0.14 | H30: =H6/G6-1 -> 0.12 | I30: =I6/H6-1 -> 0.11 | J30: =J6/I6-1 -> 0.1
A31: Gross margin (%) | B31: =B8/B6 -> 0.75290565 | C31: =C8/C6 -> 0.77923646 | D31: =D8/D6 -> 0.78762548 | E31: =E8/E6 -> 0.79696781 | F31: =F8/F6 -> 0.795 | G31: =G8/G6 -> 0.795 | H31: =H8/H6 -> 0.795 | I31: =I8/I6 -> 0.795 | J31: =J8/J6 -> 0.795
A32: EBITDA margin (%) | B32: =B12/B6 -> 0.48143359 | C32: =C12/C6 -> 0.52803502 | D32: =D12/D6 -> 0.55560762 | E32: =E12/E6 -> 0.58533506 | F32: =F12/F6 -> 0.588 | G32: =G12/G6 -> 0.59 | H32: =H12/H6 -> 0.592 | I32: =I12/I6 -> 0.593 | J32: =J12/J6 -> 0.594
A33: Operating margin (%) | B33: =B14/B6 -> 0.41772881 | C33: =C14/C6 -> 0.446443 | D33: =D14/D6 -> 0.45621956 | E33: =E14/E6 -> 0.46780818 | F33: =F14/F6 -> 0.44168912 | G33: =G14/G6 -> 0.43226121 | H33: =H14/H6 -> 0.42467527 | I33: =I14/I6 -> 0.42218761 | J33: =J14/J6 -> 0.42200472
A34: Net margin (%) | B34: =B20/B6 -> 0.34146238 | C34: =C20/C6 -> 0.35955973 | D34: =D20/D6 -> 0.36146015 | E34: =E20/E6 -> 0.40305389 | F34: =F20/F6 -> 0.35817193 | G34: =G20/G6 -> 0.35224071 | H34: =H20/H6 -> 0.34848226 | I34: =I20/I6 -> 0.34951831 | J34: =J20/J6 -> 0.35290997
A35: Effective tax rate (%) | B35: =B19/B18 -> 0.18978625 | C35: =C19/C18 -> 0.18231327 | D35: =D19/D18 -> 0.17629644 | E35: =E19/E18 -> 0.19396266 | F35: =F19/F18 -> 0.19 | G35: =G19/G18 -> 0.19 | H35: =H19/H18 -> 0.19 | I35: =I19/I18 -> 0.19 | J35: =J19/J18 -> 0.19
A37: Memo: reported figures (10-K) and reconciliation
A38: Cost of revenue as reported (incl. D&A) | B38: 65863 | C38: 74114 | D38: 87831 | E38: 106374
A39: Gross margin as reported | B39: =B6-B38 -> 146052 | C39: =C6-C38 -> 171008 | D39: =D6-D38 -> 193893 | E39: =E6-E38 -> 225465
A40: Operating income as reported | B40: 88523 | C40: 109433 | D40: 128528 | E40: 155237
A41: Net income as reported | B41: 72361 | C41: 88136 | D41: 101832 | E41: 133749
A42: Diluted EPS as reported | B42: 9.68 | C42: 11.8 | D42: 13.64 | E42: 17.95
A43: Check: model EBIT less reported operating income | B43: =B14-B40 -> 0 | C43: =C14-C40 -> 0 | D43: =D14-D40 -> 0 | E43: =E14-E40 -> 0
A44: Check: model net income less reported net income | B44: =B20-B41 -> 0 | C44: =C20-C41 -> 0 | D44: =D20-D41 -> 0 | E44: =E20-E41 -> 0

Sheet BS
A1: Balance Sheet
A2: Units: USD millions unless stated (per-share in USD; shares in millions)
A4: Fiscal year | B4: FY2023A | C4: FY2024A | D4: FY2025A | E4: FY2026A | F4: FY2027E | G4: FY2028E | H4: FY2029E | I4: FY2030E | J4: FY2031E
A6: Assets
A7: Cash and cash equivalents | B7: 34704 | C7: 18315 | D7: 30242 | E7: 20935 | F7: =CFS!F38 -> 38872.908 | G7: =CFS!G38 -> 82156.462 | H7: =CFS!H38 -> 147440.07 | I7: =CFS!I38 -> 236390.67 | J7: =CFS!J38 -> 348919.73
A8: Short-term investments | B8: 76558 | C8: 57228 | D8: 64323 | E8: 55908 | F8: =E8-CFS!F22 -> 55908 | G8: =F8-CFS!G22 -> 55908 | H8: =G8-CFS!H22 -> 55908 | I8: =H8-CFS!I22 -> 55908 | J8: =I8-CFS!J22 -> 55908
A9: Accounts receivable, net | B9: 48688 | C9: 56924 | D9: 69905 | E9: 80876 | F9: =Schedules!F17 -> 93860.434 | G9: =Schedules!G17 -> 107000.89 | H9: =Schedules!H17 -> 119841 | I9: =Schedules!I17 -> 133023.51 | J9: =Schedules!J17 -> 146325.86
A10: Inventories | B10: 2500 | C10: 1246 | D10: 938 | E10: 1397 | F10: =Schedules!F18 -> 1621.4654 | G10: =Schedules!G18 -> 1848.4705 | H10: =Schedules!H18 -> 2070.287 | I10: =Schedules!I18 -> 2298.0185 | J10: =Schedules!J18 -> 2527.8204
A11: Prepaid expenses & other current assets | B11: 21807 | C11: 26021 | D11: 25723 | E11: 48594 | F11: =Schedules!F19 -> 56200.253 | G11: =Schedules!G19 -> 64068.288 | H11: =Schedules!H19 -> 71756.483 | I11: =Schedules!I19 -> 79649.696 | J11: =Schedules!J19 -> 87614.666
A12: Total current assets | B12: =SUM(B7:B11) -> 184257 | C12: =SUM(C7:C11) -> 159734 | D12: =SUM(D7:D11) -> 191131 | E12: =SUM(E7:E11) -> 207710 | F12: =SUM(F7:F11) -> 246463.06 | G12: =SUM(G7:G11) -> 310982.12 | H12: =SUM(H7:H11) -> 397015.84 | I12: =SUM(I7:I11) -> 507269.9 | J12: =SUM(J7:J11) -> 641296.08
A13: Property, plant & equipment, net | B13: 95641 | C13: 135591 | D13: 204966 | E13: 313076 | F13: =Schedules!F10 -> 394579.71 | G13: =Schedules!G10 -> 472313.05 | H13: =Schedules!H10 -> 539464.66 | I13: =Schedules!I10 -> 600508.51 | J13: =Schedules!J10 -> 654448.18
A14: Goodwill | B14: 67886 | C14: 119220 | D14: 119509 | E14: 119651 | F14: =E14 -> 119651 | G14: =F14 -> 119651 | H14: =G14 -> 119651 | I14: =H14 -> 119651 | J14: =I14 -> 119651
A15: Intangible assets, net | B15: 9366 | C15: 27597 | D15: 22604 | E15: 18609 | F15: =Schedules!F13 -> 15512 | G15: =Schedules!G13 -> 13371 | H15: =Schedules!H13 -> 11427 | I15: =Schedules!I13 -> 9950 | J15: =Schedules!J13 -> 8822
A16: Other long-term assets | B16: 54826 | C16: 70021 | D16: 80793 | E16: 99330 | F16: =E16 -> 99330 | G16: =F16 -> 99330 | H16: =G16 -> 99330 | I16: =H16 -> 99330 | J16: =I16 -> 99330
A17: Total assets | B17: =B12+SUM(B13:B16) -> 411976 | C17: =C12+SUM(C13:C16) -> 512163 | D17: =D12+SUM(D13:D16) -> 619003 | E17: =E12+SUM(E13:E16) -> 758376 | F17: =F12+SUM(F13:F16) -> 875535.77 | G17: =G12+SUM(G13:G16) -> 1015647.2 | H17: =H12+SUM(H13:H16) -> 1166888.5 | I17: =I12+SUM(I13:I16) -> 1336709.4 | J17: =J12+SUM(J13:J16) -> 1523547.3
A19: Liabilities
A20: Accounts payable | B20: 18095 | C20: 21996 | D20: 27724 | E20: 42416 | F20: =Schedules!F20 -> 47562.984 | G20: =Schedules!G20 -> 51757.174 | H20: =Schedules!H20 -> 55207.653 | I20: =Schedules!I20 -> 58216.47 | J20: =Schedules!J20 -> 60667.689
A21: Accrued expenses & other current liabilities | B21: 80807 | C21: 94348 | D21: 110495 | E21: 117182 | F21: =Schedules!F21 -> 135881.43 | G21: =Schedules!G21 -> 154904.83 | H21: =Schedules!H21 -> 173493.41 | I21: =Schedules!I21 -> 192577.69 | J21: =Schedules!J21 -> 211835.46
A22: Short-term debt & current portion of long-term debt | B22: 5247 | C22: 8942 | D22: 2999 | E22: 9227 | F22: =MIN(Assumptions!F39,Schedules!F32) -> 0 | G22: =MIN(Assumptions!G39,Schedules!G32) -> 2001 | H22: =MIN(Assumptions!H39,Schedules!H32) -> 0 | I22: =MIN(Assumptions!I39,Schedules!I32) -> 500 | J22: =MIN(Assumptions!J39,Schedules!J32) -> 0
A23: Total current liabilities | B23: =SUM(B20:B22) -> 104149 | C23: =SUM(C20:C22) -> 125286 | D23: =SUM(D20:D22) -> 141218 | E23: =SUM(E20:E22) -> 168825 | F23: =SUM(F20:F22) -> 183444.42 | G23: =SUM(G20:G22) -> 208663.01 | H23: =SUM(H20:H22) -> 228701.07 | I23: =SUM(I20:I22) -> 251294.16 | J23: =SUM(J20:J22) -> 272503.15
A24: Long-term debt | B24: 41990 | C24: 42688 | D24: 40152 | E24: 31067 | F24: =Schedules!F32-F22 -> 31067 | G24: =Schedules!G32-G22 -> 29066 | H24: =Schedules!H32-H22 -> 29066 | I24: =Schedules!I32-I22 -> 28566 | J24: =Schedules!J32-J22 -> 28566
A25: Deferred taxes & other long-term liabilities | B25: 59614 | C25: 75712 | D25: 94154 | E25: 116097 | F25: =E25 -> 116097 | G25: =F25 -> 116097 | H25: =G25 -> 116097 | I25: =H25 -> 116097 | J25: =I25 -> 116097
A26: Total liabilities | B26: =B23+B24+B25 -> 205753 | C26: =C23+C24+C25 -> 243686 | D26: =D23+D24+D25 -> 275524 | E26: =E23+E24+E25 -> 315989 | F26: =F23+F24+F25 -> 330608.42 | G26: =G23+G24+G25 -> 353826.01 | H26: =H23+H24+H25 -> 373864.07 | I26: =I23+I24+I25 -> 395957.16 | J26: =J23+J24+J25 -> 417166.15
A28: Stockholders' equity
A29: Common stock & additional paid-in capital | B29: 93718 | C29: 100923 | D29: 109095 | E29: 117406 | F29: =E29+CFS!F9+CFS!F31 -> 133648.53 | G29: =F29+CFS!G9+CFS!G31 -> 151885.01 | H29: =G29+CFS!H9+CFS!H31 -> 172069.88 | I29: =H29+CFS!I9+CFS!I31 -> 194255.07 | J29: =I29+CFS!J9+CFS!J31 -> 218458.79
A30: Retained earnings | B30: 118848 | C30: 173144 | D30: 237731 | E30: 328265 | F30: =E30+IS!F20+CFS!F29+CFS!F30 -> 414562.83 | G30: =F30+IS!G20+CFS!G29+CFS!G30 -> 513220.14 | H30: =G30+IS!H20+CFS!H29+CFS!H30 -> 624238.56 | I30: =H30+IS!I20+CFS!I29+CFS!I30 -> 749781.17 | J30: =I30+IS!J20+CFS!J29+CFS!J30 -> 891206.32
A31: Accumulated other comprehensive income / (loss) | B31: -6343 | C31: -5590 | D31: -3347 | E31: -3284 | F31: =E31 -> -3284 | G31: =F31 -> -3284 | H31: =G31 -> -3284 | I31: =H31 -> -3284 | J31: =I31 -> -3284
A32: Treasury stock | B32: 0 | C32: 0 | D32: 0 | E32: 0 | F32: =E32 -> 0 | G32: =F32 -> 0 | H32: =G32 -> 0 | I32: =H32 -> 0 | J32: =I32 -> 0
A33: Total stockholders' equity | B33: =SUM(B29:B32) -> 206223 | C33: =SUM(C29:C32) -> 268477 | D33: =SUM(D29:D32) -> 343479 | E33: =SUM(E29:E32) -> 442387 | F33: =SUM(F29:F32) -> 544927.36 | G33: =SUM(G29:G32) -> 661821.15 | H33: =SUM(H29:H32) -> 793024.44 | I33: =SUM(I29:I32) -> 940752.25 | J33: =SUM(J29:J32) -> 1106381.1
A34: Total liabilities & stockholders' equity | B34: =B26+B33 -> 411976 | C34: =C26+C33 -> 512163 | D34: =D26+D33 -> 619003 | E34: =E26+E33 -> 758376 | F34: =F26+F33 -> 875535.77 | G34: =G26+G33 -> 1015647.2 | H34: =H26+H33 -> 1166888.5 | I34: =I26+I33 -> 1336709.4 | J34: =J26+J33 -> 1523547.3

Sheet CFS
A1: Cash Flow Statement
A2: Units: USD millions unless stated (per-share in USD; shares in millions)
A4: Fiscal year | B4: FY2023A | C4: FY2024A | D4: FY2025A | E4: FY2026A | F4: FY2027E | G4: FY2028E | H4: FY2029E | I4: FY2030E | J4: FY2031E
A6: Operating activities
A7: Net income | B7: =IS!B20 -> 72361 | C7: =IS!C20 -> 88136 | D7: =IS!D20 -> 101832 | E7: =IS!E20 -> 133749 | F7: =IS!F20 -> 137872.28 | G7: =IS!G20 -> 154571.64 | H7: =IS!H20 -> 171273.02 | I7: =IS!I20 -> 190678.27 | J7: =IS!J20 -> 211781.43
A8: Depreciation & amortization | B8: =IS!B13 -> 13500 | C8: =IS!C13 -> 20000 | D8: =IS!D13 -> 28000 | E8: =IS!E13 -> 39000 | F8: =IS!F13 -> 56319.92 | G8: =IS!G13 -> 69219.551 | H8: =IS!H13 -> 82237.218 | I8: =IS!I13 -> 93185.992 | J8: =IS!J13 -> 103214.45
A9: Stock-based compensation | B9: 9611 | C9: 10734 | D9: 11974 | E9: 12405 | F9: =IS!F6*Assumptions!F36 -> 14242.53 | G9: =IS!G6*Assumptions!G36 -> 16236.484 | H9: =IS!H6*Assumptions!H36 -> 18184.862 | I9: =IS!I6*Assumptions!I36 -> 20185.197 | J9: =IS!J6*Assumptions!J36 -> 22203.717
A10: Deferred taxes | B10: -6059 | C10: -4738 | D10: -7056 | E10: 14189 | F10: 0 | G10: 0 | H10: 0 | I10: 0 | J10: 0
A11: (Increase) / decrease in accounts receivable | B11: -4087 | C11: -7191 | D11: -10581 | E11: -12737 | F11: =BS!E9-BS!F9 -> -12984.434 | G11: =BS!F9-BS!G9 -> -13140.461 | H11: =BS!G9-BS!H9 -> -12840.107 | I11: =BS!H9-BS!I9 -> -13182.51 | J11: =BS!I9-BS!J9 -> -13302.351
A12: (Increase) / decrease in inventories | B12: 1242 | C12: 1284 | D12: 309 | E12: -461 | F12: =BS!E10-BS!F10 -> -224.46536 | G12: =BS!F10-BS!G10 -> -227.00515 | H12: =BS!G10-BS!H10 -> -221.81646 | I12: =BS!H10-BS!I10 -> -227.73157 | J12: =BS!I10-BS!J10 -> -229.80185
A13: (Increase) / decrease in other current assets | B13: -1991 | C13: -1648 | D13: -3044 | E13: -2627 | F13: =BS!E11-BS!F11 -> -7606.253 | G13: =BS!F11-BS!G11 -> -7868.0354 | H13: =BS!G11-BS!H11 -> -7688.1946 | I13: =BS!H11-BS!I11 -> -7893.2131 | J13: =BS!I11-BS!J11 -> -7964.9696
A14: Increase / (decrease) in accounts payable | B14: -2721 | C14: 3545 | D14: 569 | E14: 5268 | F14: =BS!F20-BS!E20 -> 5146.9839 | G14: =BS!G20-BS!F20 -> 4194.1904 | H14: =BS!H20-BS!G20 -> 3450.4783 | I14: =BS!I20-BS!H20 -> 3008.8171 | J14: =BS!J20-BS!I20 -> 2451.2198
A15: Increase / (decrease) in accrued & other current liabilities | B15: 7449 | C15: 11902 | D15: 11322 | E15: 14333 | F15: =BS!F21-BS!E21 -> 18699.434 | G15: =BS!G21-BS!F21 -> 19023.401 | H15: =BS!H21-BS!G21 -> 18588.58 | I15: =BS!I21-BS!H21 -> 19084.276 | J15: =BS!J21-BS!I21 -> 19257.769
A16: Other operating activities | B16: -1723 | C16: -3476 | D16: 2837 | E16: -20184 | F16: 0 | G16: 0 | H16: 0 | I16: 0 | J16: 0
A17: Cash flow from operating activities | B17: =SUM(B7:B16) -> 87582 | C17: =SUM(C7:C16) -> 118548 | D17: =SUM(D7:D16) -> 136162 | E17: =SUM(E7:E16) -> 182935 | F17: =SUM(F7:F16) -> 211466 | G17: =SUM(G7:G16) -> 242009.77 | H17: =SUM(H7:H16) -> 272984.04 | I17: =SUM(I7:I16) -> 304839.09 | J17: =SUM(J7:J16) -> 337411.46
A19: Investing activities
A20: Capital expenditures | B20: -28107 | C20: -44477 | D20: -64551 | E20: -115948 | F20: =-Schedules!F8 -> -134726.63 | G20: =-Schedules!G8 -> -144811.88 | H20: =-Schedules!H8 -> -147444.83 | I20: =-Schedules!I8 -> -152752.84 | J20: =-Schedules!J8 -> -156026.12
A21: Acquisitions, net of cash acquired | B21: -1670 | C21: -69132 | D21: -5978 | E21: -1743 | F21: 0 | G21: 0 | H21: 0 | I21: 0 | J21: 0
A22: Purchases / sales of investments, net | B22: 10213 | C22: 17937 | D22: -4387 | E22: -1948 | F22: 0 | G22: 0 | H22: 0 | I22: 0 | J22: 0
A23: Other investing activities | B23: -3116 | C23: -1298 | D23: 2317 | E23: -19861 | F23: 0 | G23: 0 | H23: 0 | I23: 0 | J23: 0
A24: Cash flow from investing activities | B24: =SUM(B20:B23) -> -22680 | C24: =SUM(C20:C23) -> -96970 | D24: =SUM(D20:D23) -> -72599 | E24: =SUM(E20:E23) -> -139500 | F24: =SUM(F20:F23) -> -134726.63 | G24: =SUM(G20:G23) -> -144811.88 | H24: =SUM(H20:H23) -> -147444.83 | I24: =SUM(I20:I23) -> -152752.84 | J24: =SUM(J20:J23) -> -156026.12
A26: Financing activities
A27: Debt issuance | B27: 0 | C27: 29645 | D27: 0 | E27: 0 | F27: =Schedules!F30 -> 0 | G27: =Schedules!G30 -> 0 | H27: =Schedules!H30 -> 0 | I27: =Schedules!I30 -> 0 | J27: =Schedules!J30 -> 0
A28: Debt repayment | B28: -2750 | C28: -29070 | D28: -8962 | E28: -3000 | F28: =Schedules!F31 -> -9227 | G28: =Schedules!G31 -> 0 | H28: =Schedules!H31 -> -2001 | I28: =Schedules!I31 -> 0 | J28: =Schedules!J31 -> -500
A29: Dividends paid | B29: -19800 | C29: -21771 | D29: -24082 | E29: -26445 | F29: =-IS!F20*Assumptions!F31 -> -27574.457 | G29: =-IS!G20*Assumptions!G31 -> -30914.328 | H29: =-IS!H20*Assumptions!H31 -> -34254.605 | I29: =-IS!I20*Assumptions!I31 -> -38135.653 | J29: =-IS!J20*Assumptions!J31 -> -42356.286
A30: Share repurchases | B30: -22245 | C30: -17254 | D30: -18420 | E30: -22271 | F30: =-Assumptions!F32 -> -24000 | G30: =-Assumptions!G32 -> -25000 | H30: =-Assumptions!H32 -> -26000 | I30: =-Assumptions!I32 -> -27000 | J30: =-Assumptions!J32 -> -28000
A31: Proceeds from stock issuance | B31: 1866 | C31: 2002 | D31: 2056 | E31: 2009 | F31: =Assumptions!F37 -> 2000 | G31: =Assumptions!G37 -> 2000 | H31: =Assumptions!H37 -> 2000 | I31: =Assumptions!I37 -> 2000 | J31: =Assumptions!J37 -> 2000
A32: Other financing activities | B32: -1006 | C32: -1309 | D32: -2291 | E32: -2839 | F32: 0 | G32: 0 | H32: 0 | I32: 0 | J32: 0
A33: Cash flow from financing activities | B33: =SUM(B27:B32) -> -43935 | C33: =SUM(C27:C32) -> -37757 | D33: =SUM(D27:D32) -> -51699 | E33: =SUM(E27:E32) -> -52546 | F33: =SUM(F27:F32) -> -58801.457 | G33: =SUM(G27:G32) -> -53914.328 | H33: =SUM(H27:H32) -> -60255.605 | I33: =SUM(I27:I32) -> -63135.653 | J33: =SUM(J27:J32) -> -68856.286
A35: Effect of exchange rates on cash | B35: -194 | C35: -210 | D35: 63 | E35: -196 | F35: 0 | G35: 0 | H35: 0 | I35: 0 | J35: 0
A36: Net change in cash | B36: =B17+B24+B33+B35 -> 20773 | C36: =C17+C24+C33+C35 -> -16389 | D36: =D17+D24+D33+D35 -> 11927 | E36: =E17+E24+E33+E35 -> -9307 | F36: =F17+F24+F33+F35 -> 17937.908 | G36: =G17+G24+G33+G35 -> 43283.554 | H36: =H17+H24+H33+H35 -> 65283.611 | I36: =I17+I24+I33+I35 -> 88950.598 | J36: =J17+J24+J33+J35 -> 112529.06
A37: Beginning cash balance | B37: 13931 | C37: =B38 -> 34704 | D37: =C38 -> 18315 | E37: =D38 -> 30242 | F37: =E38 -> 20935 | G37: =F38 -> 38872.908 | H37: =G38 -> 82156.462 | I37: =H38 -> 147440.07 | J37: =I38 -> 236390.67
A38: Ending cash balance | B38: =B37+B36 -> 34704 | C38: =C37+C36 -> 18315 | D38: =D37+D36 -> 30242 | E38: =E37+E36 -> 20935 | F38: =F37+F36 -> 38872.908 | G38: =G37+G36 -> 82156.462 | H38: =H37+H36 -> 147440.07 | I38: =I37+I36 -> 236390.67 | J38: =J37+J36 -> 348919.73
A40: Memo: reported figures (10-K)
A41: Net cash from operations as reported | B41: 87582 | C41: 118548 | D41: 136162 | E41: 182935
A42: Check: model CFO less reported CFO | B42: =B17-B41 -> 0 | C42: =C17-C41 -> 0 | D42: =D17-D41 -> 0 | E42: =E17-E41 -> 0

Sheet Schedules
A1: Supporting Schedules
A2: Units: USD millions unless stated (per-share in USD; shares in millions)
A4: Fiscal year | B4: FY2023A | C4: FY2024A | D4: FY2025A | E4: FY2026A | F4: FY2027E | G4: FY2028E | H4: FY2029E | I4: FY2030E | J4: FY2031E
A6: D&A / PP&E schedule
A7: Beginning PP&E, net | B7: 74398 | C7: =B10 -> 95641 | D7: =C10 -> 135591 | E7: =D10 -> 204966 | F7: =E10 -> 313076 | G7: =F10 -> 394579.71 | H7: =G10 -> 472313.05 | I7: =H10 -> 539464.66 | J7: =I10 -> 600508.51
A8: Capital expenditures | B8: =-CFS!B20 -> 28107 | C8: =-CFS!C20 -> 44477 | D8: =-CFS!D20 -> 64551 | E8: =-CFS!E20 -> 115948 | F8: =IS!F6*Assumptions!F25 -> 134726.63 | G8: =IS!G6*Assumptions!G25 -> 144811.88 | H8: =IS!H6*Assumptions!H25 -> 147444.83 | I8: =IS!I6*Assumptions!I25 -> 152752.84 | J8: =IS!J6*Assumptions!J25 -> 156026.12
A9: Depreciation | B9: 11000 | C9: 15200 | D9: 22000 | E9: 34300 | F9: =F7*Assumptions!F26 -> 53222.92 | G9: =G7*Assumptions!G26 -> 67078.551 | H9: =H7*Assumptions!H26 -> 80293.218 | I9: =I7*Assumptions!I26 -> 91708.992 | J9: =J7*Assumptions!J26 -> 102086.45
A10: Ending PP&E, net | B10: =BS!B13 -> 95641 | C10: =BS!C13 -> 135591 | D10: =BS!D13 -> 204966 | E10: =BS!E13 -> 313076 | F10: =F7+F8-F9 -> 394579.71 | G10: =G7+G8-G9 -> 472313.05 | H10: =H7+H8-H9 -> 539464.66 | I10: =I7+I8-I9 -> 600508.51 | J10: =J7+J8-J9 -> 654448.18
A11: Beginning intangible assets, net | B11: 11298 | C11: =B13 -> 9366 | D11: =C13 -> 27597 | E11: =D13 -> 22604 | F11: =E13 -> 18609 | G11: =F13 -> 15512 | H11: =G13 -> 13371 | I11: =H13 -> 11427 | J11: =I13 -> 9950
A12: Amortization | B12: 2500 | C12: 4800 | D12: 6000 | E12: 4700 | F12: =MIN(F11,Assumptions!F27) -> 3097 | G12: =MIN(G11,Assumptions!G27) -> 2141 | H12: =MIN(H11,Assumptions!H27) -> 1944 | I12: =MIN(I11,Assumptions!I27) -> 1477 | J12: =MIN(J11,Assumptions!J27) -> 1128
A13: Ending intangible assets, net | B13: =BS!B15 -> 9366 | C13: =BS!C15 -> 27597 | D13: =BS!D15 -> 22604 | E13: =BS!E15 -> 18609 | F13: =F11-F12 -> 15512 | G13: =G11-G12 -> 13371 | H13: =H11-H12 -> 11427 | I13: =I11-I12 -> 9950 | J13: =J11-J12 -> 8822
A14: Total D&A | B14: =B9+B12 -> 13500 | C14: =C9+C12 -> 20000 | D14: =D9+D12 -> 28000 | E14: =E9+E12 -> 39000 | F14: =F9+F12 -> 56319.92 | G14: =G9+G12 -> 69219.551 | H14: =H9+H12 -> 82237.218 | I14: =I9+I12 -> 93185.992 | J14: =J9+J12 -> 103214.45
A16: Working capital schedule
A17: Accounts receivable | B17: =BS!B9 -> 48688 | C17: =BS!C9 -> 56924 | D17: =BS!D9 -> 69905 | E17: =BS!E9 -> 80876 | F17: =IS!F6*Assumptions!F18/365 -> 93860.434 | G17: =IS!G6*Assumptions!G18/365 -> 107000.89 | H17: =IS!H6*Assumptions!H18/365 -> 119841 | I17: =IS!I6*Assumptions!I18/365 -> 133023.51 | J17: =IS!J6*Assumptions!J18/365 -> 146325.86
A18: Inventories | B18: =BS!B10 -> 2500 | C18: =BS!C10 -> 1246 | D18: =BS!D10 -> 938 | E18: =BS!E10 -> 1397 | F18: =IS!F7*Assumptions!F19/365 -> 1621.4654 | G18: =IS!G7*Assumptions!G19/365 -> 1848.4705 | H18: =IS!H7*Assumptions!H19/365 -> 2070.287 | I18: =IS!I7*Assumptions!I19/365 -> 2298.0185 | J18: =IS!J7*Assumptions!J19/365 -> 2527.8204
A19: Other current assets | B19: =BS!B11 -> 21807 | C19: =BS!C11 -> 26021 | D19: =BS!D11 -> 25723 | E19: =BS!E11 -> 48594 | F19: =IS!F6*Assumptions!F21 -> 56200.253 | G19: =IS!G6*Assumptions!G21 -> 64068.288 | H19: =IS!H6*Assumptions!H21 -> 71756.483 | I19: =IS!I6*Assumptions!I21 -> 79649.696 | J19: =IS!J6*Assumptions!J21 -> 87614.666
A20: Accounts payable | B20: =BS!B20 -> 18095 | C20: =BS!C20 -> 21996 | D20: =BS!D20 -> 27724 | E20: =BS!E20 -> 42416 | F20: =IS!F7*Assumptions!F20/365 -> 47562.984 | G20: =IS!G7*Assumptions!G20/365 -> 51757.174 | H20: =IS!H7*Assumptions!H20/365 -> 55207.653 | I20: =IS!I7*Assumptions!I20/365 -> 58216.47 | J20: =IS!J7*Assumptions!J20/365 -> 60667.689
A21: Accrued & other current liabilities | B21: =BS!B21 -> 80807 | C21: =BS!C21 -> 94348 | D21: =BS!D21 -> 110495 | E21: =BS!E21 -> 117182 | F21: =IS!F6*Assumptions!F22 -> 135881.43 | G21: =IS!G6*Assumptions!G22 -> 154904.83 | H21: =IS!H6*Assumptions!H22 -> 173493.41 | I21: =IS!I6*Assumptions!I22 -> 192577.69 | J21: =IS!J6*Assumptions!J22 -> 211835.46
A22: Net working capital | B22: =B17+B18+B19-B20-B21 -> -25907 | C22: =C17+C18+C19-C20-C21 -> -32153 | D22: =D17+D18+D19-D20-D21 -> -41653 | E22: =E17+E18+E19-E20-E21 -> -28731 | F22: =F17+F18+F19-F20-F21 -> -31762.265 | G22: =G17+G18+G19-G20-G21 -> -33744.355 | H22: =H17+H18+H19-H20-H21 -> -35033.295 | I22: =I17+I18+I19-I20-I21 -> -35822.933 | J22: =J17+J18+J19-J20-J21 -> -36034.799
A23: (Increase) / decrease in net working capital | C23: =B22-C22 -> 6246 | D23: =C22-D22 -> 9500 | E23: =D22-E22 -> -12922 | F23: =E22-F22 -> 3031.2654 | G23: =F22-G22 -> 1982.0898 | H23: =G22-H22 -> 1288.94 | I23: =H22-I22 -> 789.63775 | J23: =I22-J22 -> 211.8661
A24: DSO (days) | B24: =B17/IS!B6*365 -> 83.859661 | C24: =C17/IS!C6*365 -> 84.762934 | D24: =D17/IS!D6*365 -> 90.568517 | E24: =E17/IS!E6*365 -> 88.958019 | F24: =F17/IS!F6*365 -> 89 | G24: =G17/IS!G6*365 -> 89 | H24: =H17/IS!H6*365 -> 89 | I24: =I17/IS!I6*365 -> 89 | J24: =J17/IS!J6*365 -> 89
A25: DIO (days) | B25: =B18/IS!B7*365 -> 17.426427 | C25: =C18/IS!C7*365 -> 8.4042946 | D25: =D18/IS!D7*365 -> 5.7222844 | E25: =E18/IS!E7*365 -> 7.5682756 | F25: =F18/IS!F7*365 -> 7.5 | G25: =G18/IS!G7*365 -> 7.5 | H25: =H18/IS!H7*365 -> 7.5 | I25: =I18/IS!I7*365 -> 7.5 | J25: =J18/IS!J7*365 -> 7.5
A26: DPO (days) | B26: =B20/IS!B7*365 -> 126.13248 | C26: =C20/IS!C7*365 -> 148.36345 | D26: =D20/IS!D7*365 -> 169.13072 | E26: =E20/IS!E7*365 -> 229.78953 | F26: =F20/IS!F7*365 -> 220 | G26: =G20/IS!G7*365 -> 210 | H26: =H20/IS!H7*365 -> 200 | I26: =I20/IS!I7*365 -> 190 | J26: =J20/IS!J7*365 -> 180
A28: Debt schedule
A29: Beginning debt balance | B29: 49781 | C29: =B32 -> 47237 | D29: =C32 -> 51630 | E29: =D32 -> 43151 | F29: =E32 -> 40294 | G29: =F32 -> 31067 | H29: =G32 -> 31067 | I29: =H32 -> 29066 | J29: =I32 -> 29066
A30: Issuance | B30: =CFS!B27 -> 0 | C30: =CFS!C27 -> 29645 | D30: =CFS!D27 -> 0 | E30: =CFS!E27 -> 0 | F30: =MAX(Assumptions!F30,0) -> 0 | G30: =MAX(Assumptions!G30,0) -> 0 | H30: =MAX(Assumptions!H30,0) -> 0 | I30: =MAX(Assumptions!I30,0) -> 0 | J30: =MAX(Assumptions!J30,0) -> 0
A31: Repayment | B31: =CFS!B28 -> -2750 | C31: =CFS!C28 -> -29070 | D31: =CFS!D28 -> -8962 | E31: =CFS!E28 -> -3000 | F31: =MIN(Assumptions!F30,0) -> -9227 | G31: =MIN(Assumptions!G30,0) -> 0 | H31: =MIN(Assumptions!H30,0) -> -2001 | I31: =MIN(Assumptions!I30,0) -> 0 | J31: =MIN(Assumptions!J30,0) -> -500
A32: Ending debt balance | B32: =BS!B22+BS!B24 -> 47237 | C32: =BS!C22+BS!C24 -> 51630 | D32: =BS!D22+BS!D24 -> 43151 | E32: =BS!E22+BS!E24 -> 40294 | F32: =F29+F30+F31 -> 31067 | G32: =G29+G30+G31 -> 31067 | H32: =H29+H30+H31 -> 29066 | I32: =I29+I30+I31 -> 29066 | J32: =J29+J30+J31 -> 28566
A33: Average debt balance | B33: =AVERAGE(B29,B32) -> 48509 | C33: =AVERAGE(C29,C32) -> 49433.5 | D33: =AVERAGE(D29,D32) -> 47390.5 | E33: =AVERAGE(E29,E32) -> 41722.5 | F33: =AVERAGE(F29,F32) -> 35680.5 | G33: =AVERAGE(G29,G32) -> 31067 | H33: =AVERAGE(H29,H32) -> 30066.5 | I33: =AVERAGE(I29,I32) -> 29066 | J33: =AVERAGE(J29,J32) -> 28816
A34: Interest rate (%) | B34: =IFERROR(B35/B33,0) -> 0.040569791 | C34: =IFERROR(C35/C33,0) -> 0.059372693 | D34: =IFERROR(D35/D33,0) -> 0.050326542 | E34: =IFERROR(E35/E33,0) -> 0.073126011 | F34: =Assumptions!F12 -> 0.07 | G34: =Assumptions!G12 -> 0.07 | H34: =Assumptions!H12 -> 0.07 | I34: =Assumptions!I12 -> 0.07 | J34: =Assumptions!J12 -> 0.07
A35: Interest expense | B35: =IS!B15 -> 1968 | C35: =IS!C15 -> 2935 | D35: =IS!D15 -> 2385 | E35: =IS!E15 -> 3051 | F35: =F33*F34 -> 2497.635 | G35: =G33*G34 -> 2174.69 | H35: =H33*H34 -> 2104.655 | I35: =I33*I34 -> 2034.62 | J35: =J33*J34 -> 2017.12
A36: Cash + ST investments, beginning of year (basis for interest income) | B36: 104757 | C36: =BS!B7+BS!B8 -> 111262 | D36: =BS!C7+BS!C8 -> 75543 | E36: =BS!D7+BS!D8 -> 94565 | F36: =BS!E7+BS!E8 -> 76843 | G36: =BS!F7+BS!F8 -> 94780.908 | H36: =BS!G7+BS!G8 -> 138064.46 | I36: =BS!H7+BS!H8 -> 203348.07 | J36: =BS!I7+BS!I8 -> 292298.67
A37: Interest income rate (%) | B37: =IFERROR(B38/B36,0) -> 0.028580429 | C37: =IFERROR(C38/C36,0) -> 0.028374467 | D37: =IFERROR(D38/D36,0) -> 0.035039646 | E37: =IFERROR(E38/E36,0) -> 0.034907207 | F37: =Assumptions!F13 -> 0.035 | G37: =Assumptions!G13 -> 0.035 | H37: =Assumptions!H13 -> 0.035 | I37: =Assumptions!I13 -> 0.035 | J37: =Assumptions!J13 -> 0.035
A38: Interest income | B38: =IS!B16 -> 2994 | C38: =IS!C16 -> 3157 | D38: =IS!D16 -> 2647 | E38: =IS!E16 -> 3301 | F38: =F36*F37 -> 2689.505 | G38: =G36*G37 -> 3317.3318 | H38: =H36*H37 -> 4832.2562 | I38: =I36*I37 -> 7117.1825 | J38: =J36*J37 -> 10230.453

Sheet Checks
A1: Model Checks
A2: Units: USD millions unless stated (per-share in USD; shares in millions)
A4: Fiscal year | B4: FY2023A | C4: FY2024A | D4: FY2025A | E4: FY2026A | F4: FY2027E | G4: FY2028E | H4: FY2029E | I4: FY2030E | J4: FY2031E
A6: Balance check: total assets less total liabilities & equity (should be 0) | B6: =ROUND(BS!B17-BS!B34,3) -> 0 | C6: =ROUND(BS!C17-BS!C34,3) -> 0 | D6: =ROUND(BS!D17-BS!D34,3) -> 0 | E6: =ROUND(BS!E17-BS!E34,3) -> 0 | F6: =ROUND(BS!F17-BS!F34,3) -> 0 | G6: =ROUND(BS!G17-BS!G34,3) -> 0 | H6: =ROUND(BS!H17-BS!H34,3) -> 0 | I6: =ROUND(BS!I17-BS!I34,3) -> 0 | J6: =ROUND(BS!J17-BS!J34,3) -> 0
A7: Cash tie-out: CFS ending cash less BS cash (should be 0) | B7: =ROUND(CFS!B38-BS!B7,3) -> 0 | C7: =ROUND(CFS!C38-BS!C7,3) -> 0 | D7: =ROUND(CFS!D38-BS!D7,3) -> 0 | E7: =ROUND(CFS!E38-BS!E7,3) -> 0 | F7: =ROUND(CFS!F38-BS!F7,3) -> 0 | G7: =ROUND(CFS!G38-BS!G7,3) -> 0 | H7: =ROUND(CFS!H38-BS!H7,3) -> 0 | I7: =ROUND(CFS!I38-BS!I7,3) -> 0 | J7: =ROUND(CFS!J38-BS!J7,3) -> 0
A8: Ending cash at or above minimum cash balance (1 = yes) | B8: =IF(BS!B7>=IF(ISNUMBER(Assumptions!B33),Assumptions!B33,0),1,0) -> 1 | C8: =IF(BS!C7>=IF(ISNUMBER(Assumptions!C33),Assumptions!C33,0),1,0) -> 1 | D8: =IF(BS!D7>=IF(ISNUMBER(Assumptions!D33),Assumptions!D33,0),1,0) -> 1 | E8: =IF(BS!E7>=IF(ISNUMBER(Assumptions!E33),Assumptions!E33,0),1,0) -> 1 | F8: =IF(BS!F7>=IF(ISNUMBER(Assumptions!F33),Assumptions!F33,0),1,0) -> 1 | G8: =IF(BS!G7>=IF(ISNUMBER(Assumptions!G33),Assumptions!G33,0),1,0) -> 1 | H8: =IF(BS!H7>=IF(ISNUMBER(Assumptions!H33),Assumptions!H33,0),1,0) -> 1 | I8: =IF(BS!I7>=IF(ISNUMBER(Assumptions!I33),Assumptions!I33,0),1,0) -> 1 | J8: =IF(BS!J7>=IF(ISNUMBER(Assumptions!J33),Assumptions!J33,0),1,0) -> 1
A9: Net income: IS vs CFS (should be 0) | B9: =ROUND(IS!B20-CFS!B7,3) -> 0 | C9: =ROUND(IS!C20-CFS!C7,3) -> 0 | D9: =ROUND(IS!D20-CFS!D7,3) -> 0 | E9: =ROUND(IS!E20-CFS!E7,3) -> 0 | F9: =ROUND(IS!F20-CFS!F7,3) -> 0 | G9: =ROUND(IS!G20-CFS!G7,3) -> 0 | H9: =ROUND(IS!H20-CFS!H7,3) -> 0 | I9: =ROUND(IS!I20-CFS!I7,3) -> 0 | J9: =ROUND(IS!J20-CFS!J7,3) -> 0
A11: All checks pass (1 = yes) | B11: =IF(AND(B6=0,B7=0,B8=1,B9=0),1,0) -> 1 | C11: =IF(AND(C6=0,C7=0,C8=1,C9=0),1,0) -> 1 | D11: =IF(AND(D6=0,D7=0,D8=1,D9=0),1,0) -> 1 | E11: =IF(AND(E6=0,E7=0,E8=1,E9=0),1,0) -> 1 | F11: =IF(AND(F6=0,F7=0,F8=1,F9=0),1,0) -> 1 | G11: =IF(AND(G6=0,G7=0,G8=1,G9=0),1,0) -> 1 | H11: =IF(AND(H6=0,H7=0,H8=1,H9=0),1,0) -> 1 | I11: =IF(AND(I6=0,I7=0,I8=1,I9=0),1,0) -> 1 | J11: =IF(AND(J6=0,J7=0,J8=1,J9=0),1,0) -> 1
A12: Model-wide: all periods pass (1 = yes) | B12: =MIN(B11:J11) -> 1
