Workbook

Sheet Quarterly IS
A1: Microsoft Corporation (MSFT): Quarterly Income Statement
A2: USD millions except per-share data. Fiscal year ends June 30. A = actual, E = estimate. Model updated 2026-10-14 for the FY2026Q4 print (8-K filed 2026-07-29).
A4: Fiscal quarter | B4: FY2024Q4 | C4: FY2025Q1 | D4: FY2025Q2 | E4: FY2025Q3 | F4: FY2025Q4 | G4: FY2026Q1 | H4: FY2026Q2 | I4: FY2026Q3 | J4: FY2026Q4 | K4: FY2027Q1 | L4: FY2027Q2 | M4: FY2027Q3 | N4: FY2027Q4
A5: Actual / Estimate | B5: A | C5: A | D5: A | E5: A | F5: A | G5: A | H5: A | I5: A | J5: A | K5: E | L5: E | M5: E | N5: E
A6: Period end | B6: 2024-06-30 | C6: 2024-09-30 | D6: 2024-12-31 | E6: 2025-03-31 | F6: 2025-06-30 | G6: 2025-09-30 | H6: 2025-12-31 | I6: 2026-03-31 | J6: 2026-06-30 | K6: 2026-09-30 | L6: 2026-12-31 | M6: 2027-03-31 | N6: 2027-06-30
A8: Revenue ($mm) | B8: 64727 | C8: 65585 | D8: 69632 | E8: 70066 | F8: 76441 | G8: 77673 | H8: 81273 | I8: 82886 | J8: 90007 | K8: =G8*(1+Assumptions!$B$5) -> 90411.372 | L8: =H8*(1+Assumptions!$B$5) -> 94601.772 | M8: =I8*(1+Assumptions!$B$5) -> 96479.304 | N8: =J8*(1+Assumptions!$B$5) -> 104768.15
A9: Cost of revenue ($mm) | B9: 19684 | C9: 20099 | D9: 21799 | E9: 21919 | F9: 24014 | G9: 24043 | H9: 25978 | I9: 26828 | J9: 29525 | K9: =K8-K10 -> 29657.646 | L9: =L8-L10 -> 31032.223 | M9: =M8-M10 -> 31648.11 | N9: =N8-N10 -> 34367.1
A10: Gross profit ($mm) | B10: =B8-B9 -> 45043 | C10: =C8-C9 -> 45486 | D10: =D8-D9 -> 47833 | E10: =E8-E9 -> 48147 | F10: =F8-F9 -> 52427 | G10: =G8-G9 -> 53630 | H10: =H8-H9 -> 55295 | I10: =I8-I9 -> 56058 | J10: =J8-J9 -> 60482 | K10: =K8*K11 -> 60753.726 | L10: =L8*L11 -> 63569.549 | M10: =M8*M11 -> 64831.194 | N10: =N8*N11 -> 70401.048
A11: Gross margin % | B11: =IF(B8=0,0,B10/B8) -> 0.69589198 | C11: =IF(C8=0,0,C10/C8) -> 0.69354273 | D11: =IF(D8=0,0,D10/D8) -> 0.68693991 | E11: =IF(E8=0,0,E10/E8) -> 0.68716639 | F11: =IF(F8=0,0,F10/F8) -> 0.68584922 | G11: =IF(G8=0,0,G10/G8) -> 0.69045872 | H11: =IF(H8=0,0,H10/H8) -> 0.68036125 | I11: =IF(I8=0,0,I10/I8) -> 0.67632652 | J11: =IF(J8=0,0,J10/J8) -> 0.67196996 | K11: =Assumptions!$B$11 -> 0.67196996 | L11: =Assumptions!$B$11 -> 0.67196996 | M11: =Assumptions!$B$11 -> 0.67196996 | N11: =Assumptions!$B$11 -> 0.67196996
A12: Operating expenses ($mm) | B12: 17118 | C12: 14934 | D12: 16180 | E12: 16147 | F12: 18104 | G12: 15669 | H12: 17020 | I12: 17660 | J12: 19879 | K12: =G12*(1+Assumptions!$B$6) -> 17235.9 | L12: =H12*(1+Assumptions!$B$6) -> 18722 | M12: =I12*(1+Assumptions!$B$6) -> 19426 | N12: =J12*(1+Assumptions!$B$6) -> 21866.9
A13: Operating income ($mm) | B13: =B10-B12 -> 27925 | C13: =C10-C12 -> 30552 | D13: =D10-D12 -> 31653 | E13: =E10-E12 -> 32000 | F13: =F10-F12 -> 34323 | G13: =G10-G12 -> 37961 | H13: =H10-H12 -> 38275 | I13: =I10-I12 -> 38398 | ... N13: =N10-N12 -> 48534.148
A14: Operating margin % | B14: =IF(B8=0,0,B13/B8) -> 0.43142738 | C14: =IF(C8=0,0,C13/C8) -> 0.46583823 | D14: =IF(D8=0,0,D13/D8) -> 0.45457548 | E14: =IF(E8=0,0,E13/E8) -> 0.45671224 | F14: =IF(F8=0,0,F13/F8) -> 0.44901296 | G14: =IF(G8=0,0,G13/G8) -> 0.48872839 | H14: =IF(H8=0,0,H13/H8) -> 0.47094361 | I14: =IF(I8=0,0,I13/I8) -> 0.46326279 | ... N14: =IF(N8=0,0,N13/N8) -> 0.4632529
A15: Other income (expense), net ($mm) | B15: -675 | C15: -283 | D15: -2288 | E15: -623 | F15: -1707 | G15: -3660 | H15: 9971 | I15: 942 | J15: 3444 | K15: =Assumptions!$B$9 -> 0 | L15: =Assumptions!$B$9 -> 0 | M15: =Assumptions!$B$9 -> 0 | N15: =Assumptions!$B$9 -> 0
A16: Pretax income ($mm) | B16: =B13+B15 -> 27250 | C16: =C13+C15 -> 30269 | D16: =D13+D15 -> 29365 | E16: =E13+E15 -> 31377 | F16: =F13+F15 -> 32616 | G16: =G13+G15 -> 34301 | H16: =H13+H15 -> 48246 | I16: =I13+I15 -> 39340 | ... N16: =N13+N15 -> 48534.148
A17: Income tax ($mm) | B17: 5214 | C17: 5602 | D17: 5257 | E17: 5553 | F17: 5383 | G17: 6554 | H17: 9788 | I17: 7562 | J17: 8281 | K17: =K16*K18 -> 8268.3869 | L17: =L16*L18 -> 8521.0343 | M17: =M16*M18 -> 8626.9868 | N17: =N16*N18 -> 9221.4881
A18: Effective tax rate % | B18: =IF(B16=0,0,B17/B16) -> 0.19133945 | C18: =IF(C16=0,0,C17/C16) -> 0.18507384 | D18: =IF(D16=0,0,D17/D16) -> 0.17902265 | E18: =IF(E16=0,0,E17/E16) -> 0.17697677 | F18: =IF(F16=0,0,F17/F16) -> 0.1650417 | G18: =IF(G16=0,0,G17/G16) -> 0.19107315 | H18: =IF(H16=0,0,H17/H16) -> 0.20287692 | I18: =IF(I16=0,0,I17/I16) -> 0.19222166 | J18: =IF(J16=0,0,J17/J16) -> 0.18800372 | K18: =Assumptions!$B$7 -> 0.19 | L18: =Assumptions!$B$7 -> 0.19 | M18: =Assumptions!$B$7 -> 0.19 | N18: =Assumptions!$B$7 -> 0.19
A19: Net income ($mm) | B19: =B16-B17 -> 22036 | C19: =C16-C17 -> 24667 | D19: =D16-D17 -> 24108 | E19: =E16-E17 -> 25824 | F19: =F16-F17 -> 27233 | G19: =G16-G17 -> 27747 | H19: =H16-H17 -> 38458 | I19: =I16-I17 -> 31778 | ... N19: =N16-N17 -> 39312.66
A20: Diluted shares (mm) | B20: 7469 | C20: 7470 | D20: 7468 | E20: 7461 | F20: 7465 | G20: 7466 | H20: 7460 | I20: 7445 | J20: 7443 | K20: =J20*(1-Assumptions!$B$8) -> 7420.671 | L20: =K20*(1-Assumptions!$B$8) -> 7398.409 | M20: =L20*(1-Assumptions!$B$8) -> 7376.2138 | N20: =M20*(1-Assumptions!$B$8) -> 7354.0851
A21: Diluted EPS ($) | B21: =IF(B20=0,0,B19/B20) -> 2.950328 | C21: =IF(C20=0,0,C19/C20) -> 3.3021419 | D21: =IF(D20=0,0,D19/D20) -> 3.2281735 | E21: =IF(E20=0,0,E19/E20) -> 3.4611982 | F21: =IF(F20=0,0,F19/F20) -> 3.6480911 | G21: =IF(G20=0,0,G19/G20) -> 3.7164479 | H21: =IF(H20=0,0,H19/H20) -> 5.1552279 | I21: =IF(I20=0,0,I19/I20) -> 4.268368 | ... N21: =IF(N20=0,0,N19/N20) -> 5.3456901
A22: Revenue growth YoY % | F22: =IF(B8=0,0,F8/B8-1) -> 0.18097548 | G22: =IF(C8=0,0,G8/C8-1) -> 0.18431044 | H22: =IF(D8=0,0,H8/D8-1) -> 0.16717888 | I22: =IF(E8=0,0,I8/E8-1) -> 0.18297034 | J22: =IF(F8=0,0,J8/F8-1) -> 0.17747021 | K22: =IF(G8=0,0,K8/G8-1) -> 0.164 | L22: =IF(H8=0,0,L8/H8-1) -> 0.164 | M22: =IF(I8=0,0,M8/I8-1) -> 0.164 | N22: =IF(J8=0,0,N8/J8-1) -> 0.164
A24: Source: FY2024Q4-FY2026Q3 from stock-data MCP get_financials (SEC XBRL), pulled 2026-10-13. FY2026Q4 actuals from Microsoft 8-K Exhibit 99.1 (filed 2026-07-29, quarter ended 2026-06-30), sec.gov/Archives/edgar/data/789019/000119312526323632/msft-ex99_1.htm; opex = R&D 9,997 + S&M 7,595 + G&A 2,287.
A25: Estimates (rev. 2026-10-14): revenue = same qtr LY x (1+16.4%, FY27Q1 guide midpoint); GM = FY2026Q4 actual held flat; opex = same qtr LY x (1+10%); tax 19.0%; other income 0; diluted shares = prior qtr x (1-0.3%). See Assumptions tab.
A26: Prior-estimate vs actual comparison and estimate revisions are on the "Est vs Actual" tab.

Sheet Est vs Actual
A1: MSFT FY2026Q4 (quarter ended 2026-06-30): prior estimate vs reported actual
A2: Prior estimate = pre-print model values (hardcoded, blue). Actual = link to Quarterly IS column J. Reported in 8-K Exhibit 99.1 filed 2026-07-29. USD millions except per share.
A4: Metric | B4: Prior estimate | C4: Actual | D4: Delta | E4: Delta %
A5: Revenue ($mm) | B5: 85613.92 | C5: ='Quarterly IS'!J8 -> 90007 | D5: =C5-B5 -> 4393.08 | E5: =IF(B5=0,"n/m",C5/B5-1) -> 0.051312684
A6: Gross profit ($mm) | B6: 58495.619 | C6: ='Quarterly IS'!J10 -> 60482 | D6: =C6-B6 -> 1986.381 | E6: =IF(B6=0,"n/m",C6/B6-1) -> 0.033957774
A7: Gross margin % | B7: 0.683244 | C7: ='Quarterly IS'!J11 -> 0.67196996 | D7: =C7-B7 -> -0.011274042 | E7: n/a (see delta, pts)
A8: Operating expenses ($mm) | B8: 19190.24 | C8: ='Quarterly IS'!J12 -> 19879 | D8: =C8-B8 -> 688.76 | E8: =IF(B8=0,"n/m",C8/B8-1) -> 0.035891161
A9: Operating income ($mm) | B9: 39305.379 | C9: ='Quarterly IS'!J13 -> 40603 | D9: =C9-B9 -> 1297.621 | E9: =IF(B9=0,"n/m",C9/B9-1) -> 0.033013827
A10: Operating margin % | B10: 0.459105 | C10: ='Quarterly IS'!J14 -> 0.45110936 | D10: =C10-B10 -> -0.0079956418 | E10: n/a (see delta, pts)
A11: Other income (expense), net ($mm) | B11: 0 | C11: ='Quarterly IS'!J15 -> 3444 | D11: =C11-B11 -> 3444 | E11: =IF(B11=0,"n/m",C11/B11-1) -> n/m
A12: Effective tax rate % | B12: 0.18 | C12: ='Quarterly IS'!J18 -> 0.18800372 | D12: =C12-B12 -> 0.0080037233 | E12: n/a (see delta, pts)
A13: Net income ($mm) | B13: 32230.411 | C13: ='Quarterly IS'!J19 -> 35766 | D13: =C13-B13 -> 3535.5893 | E13: =IF(B13=0,"n/m",C13/B13-1) -> 0.10969731
A14: Diluted shares (mm) | B14: 7422.665 | C14: ='Quarterly IS'!J20 -> 7443 | D14: =C14-B14 -> 20.335 | E14: =IF(B14=0,"n/m",C14/B14-1) -> 0.0027395821
A15: Diluted EPS ($) | B15: 4.342162 | C15: ='Quarterly IS'!J21 -> 4.8053204 | D15: =C15-B15 -> 0.46315844 | E15: =IF(B15=0,"n/m",C15/B15-1) -> 0.1066654
A16: Margin/tax-rate deltas are shown in percentage points in the Delta column.
A18: Estimate revisions (roll-forward)
A19: Metric | B19: Prior estimate | C19: New estimate | D19: Change | E19: Change %
A20: FY2027Q1E revenue ($mm) | B20: 86993.76 | C20: ='Quarterly IS'!K8 -> 90411.372 | D20: =C20-B20 -> 3417.612 | E20: =IF(B20=0,"n/m",C20/B20-1) -> 0.039285714
A21: FY2027Q1E diluted EPS ($) | B21: 4.739423 | C21: ='Quarterly IS'!K21 -> 4.7501687 | D21: =C21-B21 -> 0.010745674 | E21: =IF(B21=0,"n/m",C21/B21-1) -> 0.0022672959
A22: FY2027E revenue ($mm) | B22: 366739.43 | C22: ='Annual Summary'!D8 -> 386260.6 | D22: =C22-B22 -> 19521.166 | E22: =IF(B22=0,"n/m",C22/B22-1) -> 0.053228979
A23: FY2027E operating margin % | B23: 0.480429 | C23: ='Annual Summary'!D14 -> 0.47197337 | D23: =C23-B23 -> -0.0084556268 | E23: n/a (pts)
A24: FY2027E diluted EPS ($) | B24: 19.611047 | C24: ='Annual Summary'!D21 -> 19.989161 | D24: =C24-B24 -> 0.37811365 | E24: =IF(B24=0,"n/m",C24/B24-1) -> 0.019280646
A25: NTM diluted EPS ($) | B25: 18.919477 | C25: =Valuation!B10 -> 19.991958 | D25: =C25-B25 -> 1.0724808 | E25: =IF(B25=0,"n/m",C25/B25-1) -> 0.056686599
A26: Target price ($) | B26: 567.58431 | C26: =Valuation!B12 -> 599.75873 | D26: =C26-B26 -> 32.174421 | E26: =IF(B26=0,"n/m",C26/B26-1) -> 0.056686593
A27: Prior NTM = FY2026Q4E-FY2027Q3E; new NTM = FY2027Q1E-FY2027Q4E. Prior FY2027E used the old assumptions (12% growth, 6% opex growth, 18% tax, trailing-avg GM).
A29: Guidance and context (FY2026Q4 call, 2026-07-29)
A30: FY2027Q1 revenue guide $89.85-90.95bn (+16-17%); Intelligent Cloud $40.95-41.25bn; P&BP $36.7-37.0bn; Azure +45% cc; Q1 capex ~$50bn; CY2026 capex ~$175bn (was ~$190bn).
A31: Q4 GAAP EPS $4.81 includes ~$0.27 net discrete benefit (incl. $3.2bn Anthropic investment gain, lower VRP cost, partly offset by severance and Xbox impairment). Non-GAAP EPS (ex-OpenAI) $4.74 vs ~$4.24 consensus.
A32: Segment revenue Q4: P&BP $37,847mm (+14.3%), Intelligent Cloud $39,306mm (+31.6%), More Personal Computing $12,854mm (-4.5%).

Sheet Annual Summary
A1: MSFT Annual Summary (fiscal years ending June 30)
A2: USD millions except per share. Built from the Quarterly IS tab; FY2026 = 4 actual quarters; FY2027E = 4 estimate quarters.
A4: Fiscal year | B4: FY2025 | C4: FY2026 | D4: FY2027
A5: Actual / Estimate | B5: A | C5: A | D5: E
A6: Composition | B6: 4A | C6: 4A | D6: 4E
A8: Revenue ($mm) | B8: =SUM('Quarterly IS'!C8:F8) -> 281724 | C8: =SUM('Quarterly IS'!G8:J8) -> 331839 | D8: =SUM('Quarterly IS'!K8:N8) -> 386260.6
A9: Cost of revenue ($mm) | B9: =SUM('Quarterly IS'!C9:F9) -> 87831 | C9: =SUM('Quarterly IS'!G9:J9) -> 106374 | D9: =SUM('Quarterly IS'!K9:N9) -> 126705.08
A10: Gross profit ($mm) | B10: =SUM('Quarterly IS'!C10:F10) -> 193893 | C10: =SUM('Quarterly IS'!G10:J10) -> 225465 | D10: =SUM('Quarterly IS'!K10:N10) -> 259555.52
A11: Gross margin % | B11: =IF(B8=0,0,B10/B8) -> 0.68823742 | C11: =IF(C8=0,0,C10/C8) -> 0.67944093 | D11: =IF(D8=0,0,D10/D8) -> 0.67196996
A12: Operating expenses ($mm) | B12: =SUM('Quarterly IS'!C12:F12) -> 65365 | C12: =SUM('Quarterly IS'!G12:J12) -> 70228 | D12: =SUM('Quarterly IS'!K12:N12) -> 77250.8
A13: Operating income ($mm) | B13: =SUM('Quarterly IS'!C13:F13) -> 128528 | C13: =SUM('Quarterly IS'!G13:J13) -> 155237 | D13: =SUM('Quarterly IS'!K13:N13) -> 182304.72
A14: Operating margin % | B14: =IF(B8=0,0,B13/B8) -> 0.45621956 | C14: =IF(C8=0,0,C13/C8) -> 0.46780818 | D14: =IF(D8=0,0,D13/D8) -> 0.47197337
A15: Other income (expense), net ($mm) | B15: =SUM('Quarterly IS'!C15:F15) -> -4901 | C15: =SUM('Quarterly IS'!G15:J15) -> 10697 | D15: =SUM('Quarterly IS'!K15:N15) -> 0
A16: Pretax income ($mm) | B16: =SUM('Quarterly IS'!C16:F16) -> 123627 | C16: =SUM('Quarterly IS'!G16:J16) -> 165934 | D16: =SUM('Quarterly IS'!K16:N16) -> 182304.72
A17: Income tax ($mm) | B17: =SUM('Quarterly IS'!C17:F17) -> 21795 | C17: =SUM('Quarterly IS'!G17:J17) -> 32185 | D17: =SUM('Quarterly IS'!K17:N17) -> 34637.896
A18: Effective tax rate % | B18: =IF(B16=0,0,B17/B16) -> 0.17629644 | C18: =IF(C16=0,0,C17/C16) -> 0.19396266 | D18: =IF(D16=0,0,D17/D16) -> 0.19
A19: Net income ($mm) | B19: =SUM('Quarterly IS'!C19:F19) -> 101832 | C19: =SUM('Quarterly IS'!G19:J19) -> 133749 | D19: =SUM('Quarterly IS'!K19:N19) -> 147666.82
A20: Diluted shares (mm, avg of quarters) | B20: =AVERAGE('Quarterly IS'!C20:F20) -> 7466 | C20: =AVERAGE('Quarterly IS'!G20:J20) -> 7453.5 | D20: =AVERAGE('Quarterly IS'!K20:N20) -> 7387.3447
A21: Diluted EPS ($, NI / avg shares) | B21: =IF(B20=0,0,B19/B20) -> 13.639432 | C21: =IF(C20=0,0,C19/C20) -> 17.944456 | D21: =IF(D20=0,0,D19/D20) -> 19.989161
A22: Revenue growth vs. prior FY % | C22: =IF(B8=0,0,C8/B8-1) -> 0.17788687 | D22: =IF(C8=0,0,D8/C8-1) -> 0.164
A24: Annual diluted EPS = annual net income / average of the four quarterly diluted share counts, so it can differ slightly from the sum of quarterly EPS and from reported annual EPS.

Sheet Valuation
A1: MSFT Valuation: NTM EPS x P/E
A2: NTM = the next four quarters after the last actual (FY2026Q4), i.e. FY2027Q1E-FY2027Q4E. Rolled forward 2026-10-14 after the FY2026Q4 print.
A4: Quarter | B4: Diluted EPS ($)
A5: ='Quarterly IS'!K4 -> FY2027Q1 | B5: ='Quarterly IS'!K21 -> 4.7501687
A6: ='Quarterly IS'!L4 -> FY2027Q2 | B6: ='Quarterly IS'!L21 -> 4.9100441
A7: ='Quarterly IS'!M4 -> FY2027Q3 | B7: ='Quarterly IS'!M21 -> 4.9860549
A8: ='Quarterly IS'!N4 -> FY2027Q4 | B8: ='Quarterly IS'!N21 -> 5.3456901
A10: NTM diluted EPS ($) | B10: =SUM(B5:B8) -> 19.991958
A11: Target P/E (x) | B11: =Assumptions!$B$10 -> 30
A12: Target price ($) | B12: =B10*B11 -> 599.75873
A14: Prior target price ($, pre-FY26Q4 model) | B14: 567.58
A15: Change in target price % | B15: =IF(B14=0,0,B12/B14-1) -> 0.056694623
A16: Share price ($), close 2026-10-12 | B16: 541.15
A17: Upside / (downside) to target % | B17: =IF(B16=0,0,B12/B16-1) -> 0.10830405
A18: Implied P/E on NTM EPS at current price (x) | B18: =IF(B10=0,0,B16/B10) -> 27.068384
A20: Price source: Investing.com MSFT quote page (close 2026-10-12), not verified against a second source.

Sheet Assumptions
A1: MSFT Quarterly Model: Estimate Assumptions
A2: Blue = hardcoded input; black = formula; green = link to another sheet. Yellow cells are the key levers; edit them to change the estimates.
A4: Assumption | B4: Value | C4: Basis | D4: Prior value (pre-FY26Q4 print) | E4: Change rationale
A5: Revenue growth vs. same quarter last year | B5: 0.164 | C5: Estimate rule: revenue = same quarter last year x 1.164 | D5: 0.12 | E5: FY27Q1 guide $89.85-90.95bn (midpoint $90.4bn) = +16.4% YoY vs FY26Q1 $77,673mm; FY26Q4 actual grew +17.7%. Applied to all FY27 quarters (no deceleration assumed).
A6: Opex growth vs. same quarter last year | B6: 0.1 | C6: Estimate rule: operating expenses = same quarter last year x 1.10 | D6: 0.06 | E6: FY26Q4 opex +9.8% YoY and FY26Q3 +9.4% (FY26 full year +7.4%); 6% no longer matches run-rate.
A7: Tax rate (estimates) | B7: 0.19 | C7: Estimate rule: tax rate 19.0% | D7: 0.18 | E7: FY26 effective rate 19.4%, FY26Q4 18.8%; 18% looked light.
A8: Diluted share reduction per quarter | B8: 0.003 | C8: Estimate rule: diluted shares = latest actual minus 0.3% per quarter (compounded) | D8: 0.003 | E8: Unchanged (FY26Q4 diluted shares 7,443mm vs 7,445mm in Q3).
A9: Other income (expense), net - estimates ($mm) | B9: 0 | C9: Modeling default (not in spec): non-operating items assumed zero in estimate quarters | D9: 0 | E9: Unchanged; FY26 other income was +$10.7bn but driven by volatile investment marks (OpenAI, Anthropic gain).
A10: Target P/E multiple on NTM EPS (x) | B10: 30 | C10: Valuation rule: NTM EPS x 30 = target price | D10: 30 | E10: Unchanged multiple; NTM window rolled forward to FY2027Q1-Q4.
A11: Gross margin method | B11: ='Quarterly IS'!J11 -> 0.67196996 | C11: Gross margin for each estimate quarter = latest actual quarter (FY2026Q4) GM held flat. Edit to a hardcoded % to override. | D11: Trailing-4-quarter average | E11: GM fell four straight quarters (69.0% -> 68.0% -> 67.6% -> 67.2%) on AI infrastructure costs; trailing average would have lifted FY27Q1 GM back to ~68%.
A12: Gross margin method | B12: Latest actual quarter, held flat
