Workbook

Sheet Comps
A1: LARGE-CAP TECHNOLOGY - COMPARABLE COMPANY ANALYSIS (TARGET: MICROSOFT)
A2: Microsoft (MSFT) vs. Alphabet (GOOGL) • Amazon (AMZN) • Meta Platforms (META) • Apple (AAPL) • Oracle (ORCL)
A3: Prices as of 2026-10-14 close | LTM aligned to each company's latest reported quarter | All figures in USD millions except per-share amounts and ratios | Statistics computed on the 5 peers (MSFT excluded)
A5: OPERATING STATISTICS & FINANCIAL METRICS (LTM)
A6: Company | B6: Ticker | C6: LTM Qtr End | D6: LTM Revenue | E6: Prior-Yr LTM Revenue | F6: Revenue Growth (YoY) % | G6: LTM EBIT | H6: EBIT Margin % | I6: LTM D&A | J6: LTM EBITDA | K6: EBITDA Margin % | L6: LTM Net Income | M6: Net Margin %
A7: Microsoft Corporation (target) | B7: MSFT | C7: 2026-06-30 | D7: =LTM_Build!$I$4 -> 331839 | E7: =LTM_Build!$I$5 -> 281724 | F7: =D7/E7-1 -> 0.17788687 | G7: =LTM_Build!$I$6 -> 155237 | H7: =G7/D7 -> 0.46780818 | I7: =LTM_Build!$I$7 -> 38534 | J7: =G7+I7 -> 193771 | K7: =J7/D7 -> 0.58393076 | L7: =LTM_Build!$I$8 -> 133749 | M7: =L7/D7 -> 0.40305389
A8: Alphabet Inc. | B8: GOOGL | C8: 2026-06-30 | D8: =LTM_Build!$I$10 -> 445866 | E8: =LTM_Build!$I$11 -> 371399 | F8: =D8/E8-1 -> 0.20050404 | G8: =LTM_Build!$I$12 -> 147628 | H8: =G8/D8 -> 0.33110396 | I8: =LTM_Build!$I$13 -> 25237 | J8: =G8+I8 -> 172865 | K8: =J8/D8 -> 0.38770617 | L8: =LTM_Build!$I$14 -> 244205 | M8: =L8/D8 -> 0.5477094
A9: Amazon.com, Inc. | B9: AMZN | C9: 2026-06-30 | D9: =LTM_Build!$I$16 -> 775680 | E9: =LTM_Build!$I$17 -> 670038 | F9: =D9/E9-1 -> 0.15766568 | G9: =LTM_Build!$I$18 -> 93712 | H9: =G9/D9 -> 0.12081271 | I9: =LTM_Build!$I$19 -> 75200 | J9: =G9+I9 -> 168912 | K9: =J9/D9 -> 0.2177599 | L9: =LTM_Build!$I$20 -> 135281 | M9: =L9/D9 -> 0.1744031
A10: Meta Platforms, Inc. | B10: META | C10: 2026-06-30 | D10: =LTM_Build!$I$22 -> 228247 | E10: =LTM_Build!$I$23 -> 178804 | F10: =D10/E10-1 -> 0.27652066 | G10: =LTM_Build!$I$24 -> 86926 | H10: =G10/D10 -> 0.38084181 | I10: =LTM_Build!$I$25 -> 22729 | J10: =G10+I10 -> 109655 | K10: =J10/D10 -> 0.48042252 | L10: =LTM_Build!$I$26 -> 68098 | M10: =L10/D10 -> 0.29835222
A11: Apple Inc. | B11: AAPL | C11: 2026-06-27 | D11: =LTM_Build!$I$28 -> 466823 | E11: =LTM_Build!$I$29 -> 408625 | F11: =D11/E11-1 -> 0.14242398 | G11: =LTM_Build!$I$30 -> 154859 | H11: =G11/D11 -> 0.33172958 | I11: =LTM_Build!$I$31 -> 13100 | J11: =G11+I11 -> 167959 | K11: =J11/D11 -> 0.35979161 | L11: =LTM_Build!$I$32 -> 128930 | M11: =L11/D11 -> 0.27618605
A12: Oracle Corporation | B12: ORCL | C12: 2026-08-31 | D12: =LTM_Build!$I$34 -> 71776 | E12: =LTM_Build!$I$35 -> 59018 | F12: =D12/E12-1 -> 0.21617134 | G12: =LTM_Build!$I$36 -> 23057 | H12: =G12/D12 -> 0.32123551 | I12: =LTM_Build!$I$37 -> 10881 | J12: =G12+I12 -> 33938 | K12: =J12/D12 -> 0.47283214 | L12: =LTM_Build!$I$38 -> 18920 | M12: =L12/D12 -> 0.26359786
A14: Peer Maximum | F14: =MAX(F8:F12) -> 0.27652066 | H14: =MAX(H8:H12) -> 0.38084181 | K14: =MAX(K8:K12) -> 0.48042252 | M14: =MAX(M8:M12) -> 0.5477094
A15: Peer 75th Percentile | F15: =QUARTILE(F8:F12,3) -> 0.21617134 | H15: =QUARTILE(H8:H12,3) -> 0.33172958 | K15: =QUARTILE(K8:K12,3) -> 0.47283214 | M15: =QUARTILE(M8:M12,3) -> 0.29835222
A16: Peer Median | F16: =MEDIAN(F8:F12) -> 0.20050404 | H16: =MEDIAN(H8:H12) -> 0.33110396 | K16: =MEDIAN(K8:K12) -> 0.38770617 | M16: =MEDIAN(M8:M12) -> 0.27618605
A17: Peer 25th Percentile | F17: =QUARTILE(F8:F12,1) -> 0.15766568 | H17: =QUARTILE(H8:H12,1) -> 0.32123551 | K17: =QUARTILE(K8:K12,1) -> 0.35979161 | M17: =QUARTILE(M8:M12,1) -> 0.26359786
A18: Peer Minimum | F18: =MIN(F8:F12) -> 0.14242398 | H18: =MIN(H8:H12) -> 0.12081271 | K18: =MIN(K8:K12) -> 0.2177599 | M18: =MIN(M8:M12) -> 0.1744031
A20: VALUATION MULTIPLES
A21: Company | B21: Ticker | C21: Share Price (USD) | D21: Diluted Shares (mm) | E21: Market Cap | F21: Total Debt | G21: Cash & ST Investments | H21: Enterprise Value | I21: EV / LTM Revenue | J21: EV / LTM EBITDA | K21: P/E (LTM GAAP) | L21: EV / LTM EBIT | M21: LTM Diluted EPS (USD)
A22: Microsoft Corporation (target) | B22: MSFT | C22: 533.69 | D22: 7443 | E22: =C22*D22 -> 3972254.7 | F22: 40294 | G22: 76843 | H22: =E22+F22-G22 -> 3935705.7 | I22: =H22/D7 -> 11.860287 | J22: =H22/J7 -> 20.311118 | K22: =E22/L7 -> 29.699322 | L22: =H22/G7 -> 25.352884 | M22: =L7/D22 -> 17.96977
A23: Alphabet Inc. | B23: GOOGL | C23: 347.64 | D23: 12306 | E23: =C23*D23 -> 4278057.8 | F23: 98165 | G23: 242474 | H23: =E23+F23-G23 -> 4133748.8 | I23: =H23/D8 -> 9.2712807 | J23: =H23/J8 -> 23.913163 | K23: =E23/L8 -> 17.518306 | L23: =H23/G8 -> 28.001117 | M23: =L8/D23 -> 19.844385
A24: Amazon.com, Inc. | B24: AMZN | C24: 254.08 | D24: 10903 | E24: =C24*D24 -> 2770234.2 | F24: 128894 | G24: 122988 | H24: =E24+F24-G24 -> 2776140.2 | I24: =H24/D9 -> 3.5789762 | J24: =H24/J9 -> 16.435423 | K24: =E24/L9 -> 20.47763 | L24: =H24/G9 -> 29.62417 | M24: =L9/D24 -> 12.407686
A25: Meta Platforms, Inc. | B25: META | C25: 737.54 | D25: 2566 | E25: =C25*D25 -> 1892527.6 | F25: 83664 | G25: 90260 | H25: =E25+F25-G25 -> 1885931.6 | I25: =H25/D10 -> 8.2626788 | J25: =H25/J10 -> 17.198775 | K25: =E25/L10 -> 27.791237 | L25: =H25/G10 -> 21.695829 | M25: =L10/D25 -> 26.538581
A26: Apple Inc. | B26: AAPL | C26: 342.96 | D26: 14714.7 | E26: =C26*D26 -> 5046553.5 | F26: 84344 | G26: 146517 | H26: =E26+F26-G26 -> 4984380.5 | I26: =H26/D11 -> 10.677239 | J26: =H26/J11 -> 29.676174 | K26: =E26/L11 -> 39.14181 | L26: =H26/G11 -> 32.186573 | M26: =L11/D26 -> 8.7619863
A27: Oracle Corporation | B27: ORCL | C27: 130.55 | D27: 3000 | E27: =C27*D27 -> 391650 | F27: 125337 | G27: 37077 | H27: =E27+F27-G27 -> 479910 | I27: =H27/D12 -> 6.6862182 | J27: =H27/J12 -> 14.140786 | K27: =E27/L12 -> 20.700317 | L27: =H27/G12 -> 20.814069 | M27: =L12/D27 -> 6.3066667
A29: Peer Maximum | I29: =MAX(I23:I27) -> 10.677239 | J29: =MAX(J23:J27) -> 29.676174 | K29: =MAX(K23:K27) -> 39.14181 | L29: =MAX(L23:L27) -> 32.186573
A30: Peer 75th Percentile | I30: =QUARTILE(I23:I27,3) -> 9.2712807 | J30: =QUARTILE(J23:J27,3) -> 23.913163 | K30: =QUARTILE(K23:K27,3) -> 27.791237 | L30: =QUARTILE(L23:L27,3) -> 29.62417
A31: Peer Median | I31: =MEDIAN(I23:I27) -> 8.2626788 | J31: =MEDIAN(J23:J27) -> 17.198775 | K31: =MEDIAN(K23:K27) -> 20.700317 | L31: =MEDIAN(L23:L27) -> 28.001117
A32: Peer 25th Percentile | I32: =QUARTILE(I23:I27,1) -> 6.6862182 | J32: =QUARTILE(J23:J27,1) -> 16.435423 | K32: =QUARTILE(K23:K27,1) -> 20.47763 | L32: =QUARTILE(L23:L27,1) -> 21.695829
A33: Peer Minimum | I33: =MIN(I23:I27) -> 3.5789762 | J33: =MIN(J23:J27) -> 14.140786 | K33: =MIN(K23:K27) -> 17.518306 | L33: =MIN(L23:L27) -> 20.814069
A34: MSFT premium / (discount) to peer median | I34: =I22/I31-1 -> 0.43540455 | J34: =J22/J31-1 -> 0.18096309 | K34: =K22/K31-1 -> 0.43472789 | L34: =L22/L31-1 -> -0.09457596
A36: IMPLIED MSFT VALUE AT PEER MULTIPLES (USD per share)
A37: Multiple | B37: MSFT LTM Metric | C37: Peer 25th | D37: Peer Median | E37: Peer 75th | F37: Implied Price @25th | G37: Implied Price @Median | H37: Implied Price @75th | I37: Current Price | J37: Upside/(Down) @Median
A38: EV / LTM Revenue | B38: =D7 -> 331839 | C38: =I32 -> 6.6862182 | D38: =I31 -> 8.2626788 | E38: =I30 -> 9.2712807 | F38: =(C38*B38-$F$22+$G$22)/$D$22 -> 303.00913 | G38: =(D38*B38-$F$22+$G$22)/$D$22 -> 373.29411 | H38: =(E38*B38-$F$22+$G$22)/$D$22 -> 418.26166 | I38: =$C$22 -> 533.69 | J38: =G38/I38-1 -> -0.30054131
A39: EV / LTM EBITDA | B39: =J7 -> 193771 | C39: =J32 -> 16.435423 | D39: =J31 -> 17.198775 | E39: =J30 -> 23.913163 | F39: =(C39*B39-$F$22+$G$22)/$D$22 -> 432.7902 | G39: =(D39*B39-$F$22+$G$22)/$D$22 -> 452.66328 | H39: =(E39*B39-$F$22+$G$22)/$D$22 -> 627.46559 | I39: =$C$22 -> 533.69 | J39: =G39/I39-1 -> -0.15182357
A40: P/E (LTM GAAP) | B40: =L7 -> 133749 | C40: =K32 -> 20.47763 | D40: =K31 -> 20.700317 | E40: =K30 -> 27.791237 | F40: =C40*B40/$D$22 -> 367.9783 | G40: =D40*B40/$D$22 -> 371.97994 | H40: =E40*B40/$D$22 -> 499.40214 | I40: =$C$22 -> 533.69 | J40: =G40/I40-1 -> -0.30300372

Sheet LTM_Build
A1: LTM BUILD - LTM = Last fiscal year - Prior-year YTD + Current YTD (USD millions)
A3: Ticker | B3: Metric | C3: Last FY period | D3: Last FY value | E3: Prior-year YTD period | F3: Less: prior-year YTD | G3: Current YTD period | H3: Plus: current YTD | I3: LTM | J3: Source
A4: MSFT | B4: Revenue | C4: FY26 (Jun-26) | D4: 331839 | E4: n/a (FY end) | F4: 0 | G4: n/a (FY end) | H4: 0 | I4: =D4-F4+H4 -> 331839 | J4: SEC XBRL companyconcept us-gaap:RevenueFromContractWithCustomerExcludingAssessedTax (https://data.sec.gov/api/xbrl/companyconcept/CIK0000789019/us-gaap/RevenueFromContractWithCustomerExcludingAssessedTax.json); filings: MSFT 8-K Ex.99.1 filed 2026-07-29 (FY26 Q4 release); FY26 10-K filed 2026-07-29
A5: MSFT | B5: Revenue - prior-year LTM | C5: FY25 (Jun-25) | D5: 281724 | E5: n/a | F5: 0 | G5: n/a | H5: 0 | I5: =D5-F5+H5 -> 281724 | J5: SEC XBRL companyconcept us-gaap:RevenueFromContractWithCustomerExcludingAssessedTax (https://data.sec.gov/api/xbrl/companyconcept/CIK0000789019/us-gaap/RevenueFromContractWithCustomerExcludingAssessedTax.json); filings: MSFT 8-K Ex.99.1 filed 2026-07-29 (FY26 Q4 release); FY26 10-K filed 2026-07-29
A6: MSFT | B6: Operating income (EBIT) | C6: FY26 (Jun-26) | D6: 155237 | E6: n/a (FY end) | F6: 0 | G6: n/a (FY end) | H6: 0 | I6: =D6-F6+H6 -> 155237 | J6: SEC XBRL us-gaap:OperatingIncomeLoss, FY ended 2026-06-30, MSFT 10-K filed 2026-07-29
A7: MSFT | B7: D&A (cash flow statement) | C7: FY26 (Jun-26) | D7: 38534 | E7: n/a (FY end) | F7: 0 | G7: n/a (FY end) | H7: 0 | I7: =D7-F7+H7 -> 38534 | J7: MSFT 8-K Ex.99.1 filed 2026-07-29, cash flow statement line 'Depreciation, amortization, and other' FY26 = 38,534 (FY25 = 29,433). Includes minor other non-cash items.
A8: MSFT | B8: Net income (to parent) | C8: FY26 (Jun-26) | D8: 133749 | E8: n/a (FY end) | F8: 0 | G8: n/a (FY end) | H8: 0 | I8: =D8-F8+H8 -> 133749 | J8: SEC XBRL companyconcept us-gaap:NetIncomeLoss (https://data.sec.gov/api/xbrl/companyconcept/CIK0000789019/us-gaap/NetIncomeLoss.json); filings: MSFT 8-K Ex.99.1 filed 2026-07-29 (FY26 Q4 release); FY26 10-K filed 2026-07-29
A10: GOOGL | B10: Revenue | C10: FY25 (Dec-25) | D10: 402836 | E10: 6M to Jun-25 | F10: 186662 | G10: 6M to Jun-26 | H10: 229692 | I10: =D10-F10+H10 -> 445866 | J10: SEC XBRL us-gaap:Revenues (GOOGL 10-K filed 2026-02-05; 10-Qs filed 2025-07-24, 2026-07-23)
A11: GOOGL | B11: Revenue - prior-year LTM | C11: FY24 (Dec-24) | D11: 350018 | E11: 6M to Jun-24 | F11: 165281 | G11: 6M to Jun-25 | H11: 186662 | I11: =D11-F11+H11 -> 371399 | J11: SEC XBRL us-gaap:Revenues / RevenueFromContract... (GOOGL 10-K filed 2025-02-05; 10-Qs 2024-07-24, 2025-07-24)
A12: GOOGL | B12: Operating income (EBIT) | C12: FY25 (Dec-25) | D12: 129039 | E12: 6M to Jun-25 | F12: 61877 | G12: 6M to Jun-26 | H12: 80466 | I12: =D12-F12+H12 -> 147628 | J12: SEC XBRL companyconcept us-gaap:OperatingIncomeLoss (https://data.sec.gov/api/xbrl/companyconcept/CIK0001652044/us-gaap/OperatingIncomeLoss.json); filings: GOOGL 8-K Ex.99.1 filed 2026-07-22 (Q2'26 release); 10-Q filed 2026-07-23
A13: GOOGL | B13: D&A (cash flow statement) | C13: FY25 (Dec-25) | D13: 21136 | E13: 6M to Jun-25 | F13: 9485 | G13: 6M to Jun-26 | H13: 13586 | I13: =D13-F13+H13 -> 25237 | J13: SEC XBRL us-gaap:Depreciation (depreciation of property & equipment; Alphabet does not present intangible amortization separately on the cash flow statement)
A14: GOOGL | B14: Net income (to parent) | C14: FY25 (Dec-25) | D14: 132170 | E14: 6M to Jun-25 | F14: 62736 | G14: 6M to Jun-26 | H14: 174771 | I14: =D14-F14+H14 -> 244205 | J14: SEC XBRL companyconcept us-gaap:NetIncomeLoss (https://data.sec.gov/api/xbrl/companyconcept/CIK0001652044/us-gaap/NetIncomeLoss.json); filings: GOOGL 8-K Ex.99.1 filed 2026-07-22 (Q2'26 release); 10-Q filed 2026-07-23
A16: AMZN | B16: Revenue | C16: FY25 (Dec-25) | D16: 716924 | E16: 6M to Jun-25 | F16: 323369 | G16: 6M to Jun-26 | H16: 382125 | I16: =D16-F16+H16 -> 775680 | J16: SEC XBRL companyconcept us-gaap:RevenueFromContractWithCustomerExcludingAssessedTax (https://data.sec.gov/api/xbrl/companyconcept/CIK0001018724/us-gaap/RevenueFromContractWithCustomerExcludingAssessedTax.json); filings: AMZN 8-K Ex.99.1 filed 2026-07-30 (Q2'26 release); 10-Q filed 2026-07-31
A17: AMZN | B17: Revenue - prior-year LTM | C17: FY24 (Dec-24) | D17: 637959 | E17: 6M to Jun-24 | F17: 291290 | G17: 6M to Jun-25 | H17: 323369 | I17: =D17-F17+H17 -> 670038 | J17: SEC XBRL companyconcept us-gaap:RevenueFromContractWithCustomerExcludingAssessedTax (https://data.sec.gov/api/xbrl/companyconcept/CIK0001018724/us-gaap/RevenueFromContractWithCustomerExcludingAssessedTax.json); filings: AMZN 8-K Ex.99.1 filed 2026-07-30 (Q2'26 release); 10-Q filed 2026-07-31
... A38: ORCL | B38: Net income (to parent) | C38: FY26 (May-26) | D38: 17087 | E38: 3M to Aug-25 | F38: 2927 | G38: 3M to Aug-26 | H38: 4760 | I38: =D38-F38+H38 -> 18920 | J38: SEC XBRL companyconcept us-gaap:NetIncomeLoss (https://data.sec.gov/api/xbrl/companyconcept/CIK0001341439/us-gaap/NetIncomeLoss.json); filings: ORCL 8-K Ex.99.1 filed 2026-09-10 (Q1 FY27 release); 10-Q filed 2026-09-11

Sheet Notes
A1: NOTES & METHODOLOGY
A3: Purpose: trading comparables for Microsoft (MSFT) for investment committee valuation review. Peer group as specified: GOOGL, AMZN, META, AAPL, ORCL.
A4: Statistics (Max / 75th / Median / 25th / Min) are computed over the five peers only; MSFT is shown for comparison and excluded from the ranges.
A6: DATA SOURCES
A7: - Financials: SEC EDGAR XBRL company-concept API (data.sec.gov) and each company's latest 8-K Exhibit 99.1 earnings release (see cell comments and LTM_Build column J).
A8: - Share prices: daily closes for 2026-10-14 from stockanalysis.com price history pages (ORCL 2026-10-13 close of 143.20 cross-checked on financialcontent.com).
A9: - No institutional data feed (FactSet / S&P / Daloopa / Bloomberg) was available in this session; figures were not cross-checked against a second vendor.
A11: PERIODS
A12: - LTM is aligned to each company's latest reported quarter: MSFT 2026-06-30 (FY26), GOOGL / AMZN / META 2026-06-30, AAPL 2026-06-27, ORCL 2026-08-31.
A13: - LTM = last fiscal year - prior-year YTD + current YTD (see LTM_Build). Revenue growth = LTM vs. the LTM period one year earlier.
A14: - Fiscal year ends differ (Jun / Dec / Sep / May); LTM quarter ends span 2026-06-27 to 2026-08-31.
A16: DEFINITIONS
... A29: COLOR CONVENTION: blue font = hard-coded input (every input has a cell comment with its source); black font = formula.
